Workbook

Sheet Master
A1: PUBLIC MUTUAL — FUND MASTER | Data: MFR February 2026 | 111 Qualified / 171 Total Funds
A2: FUND DETAILS | K2: SCREENING | N2: ANNUALISED RETURNS vs BENCHMARK (MFR FEB 2026) | AC2: ALPHA EFFICIENCY (Alpha / VF) | AH2: ASSET ALLOCATION (%) | AN2: GEOGRAPHICAL BREAKDOWN (%) | AZ2: SECTOR BREAKDOWN (%) | BK2: TOP 5 | BL2: META | BP2: ATH MOMENTUM
A3: Fund Name | B3: Abbr | C3: Series | D3: Fund Type | E3: Geography | F3: Objective | G3: Risk Level | H3: Distribution | I3: Size (RM M) | J3: Launch | K3: Status | L3: Beat (%) | M3: Periods | N3: YTD Fund (%) | O3: YTD Bench (%) | P3: YTD Alpha (%) | Q3: 1Y Fund (%) | R3: 1Y Bench (%) | S3: 1Y Alpha (%) | T3: 3Y Fund (%) | U3: 3Y Bench (%) | V3: 3Y Alpha (%) | W3: 5Y Fund (%) | X3: 5Y Bench (%) | Y3: 5Y Alpha (%) | Z3: 10Y Fund (%) | AA3: 10Y Bench (%) | AB3: 10Y Alpha (%) | AC3: AE YTD | AD3: AE 1Y | AE3: AE 3Y | AF3: AE 5Y | AG3: AE 10Y | AH3: Dom. Equity (%) | AI3: For. Equity (%) | AJ3: FI / Sukuk (%) | AK3: Money Mkt (%) | AL3: Deposits (%) | AM3: Alloc Other (%) | AN3: USA (%) | AO3: Taiwan (%) | AP3: Korea (%) | AQ3: Japan (%) | AR3: France (%) | AS3: Germany (%) | AT3: China (%) | AU3: Singapore (%) | AV3: Netherlands (%) | AW3: Indonesia (%) | AX3: Australia (%) | AY3: Geo Other (%) | AZ3: Industrial (%) | BA3: Technology (%) | BB3: Financial (%) | BC3: Comms (%) | BD3: Cons. Disc. (%) | BE3: Cons. Staples (%) | BF3: Utilities (%) | BG3: Energy (%) | BH3: Materials (%) | BI3: Real Estate (%) | BJ3: Sector Other (%) | BK3: Top 5 Holdings | BL3: VF | BM3: VC | BN3: Lipper Class | BO3: Benchmark | BP3: ATH NAV | BQ3: ATH Date | BR3: Cur NAV | BS3: Drawdown (%) | BT3: Days from ATH
A4: PUBLIC ISLAMIC SELECT TREASURES FUND | B4: PISTF | C4: Shariah | D4: Equity | E4: Malaysia | F4: Capital Growth | G4: 5 | H4: Incidental | I4: 1262.73 | J4: 26.02.2008 | K4: Qualified | L4: 100 | M4: 5/5 | N4: 5.86 | O4: 1.2 | P4: 4.66 | Q4: 18.31 | R4: 0.31 | S4: 18 | T4: 9.42 | U4: 1.36 | V4: 8.06 | W4: 2.81 | X4: -2.46 | Y4: 5.27 | Z4: 5.52 | AA4: 0.84 | AB4: 4.68 | AC4: =IF(OR(P4="",BL4="",BL4=0),"",P4/BL4) | AD4: =IF(OR(S4="",BL4="",BL4=0),"",S4/BL4) | AE4: =IF(OR(V4="",BL4="",BL4=0),"",V4/BL4) | AF4: =IF(OR(Y4="",BL4="",BL4=0),"",Y4/BL4) | AG4: =IF(OR(AB4="",BL4="",BL4=0),"",AB4/BL4) | AH4: 74.7 | AI4: 20.4 | AK4: 4.9 | AN4: 7 | AO4: 6.4 | AP4: 2.8 | AQ4: 4.2 | AZ4: 37.3 | BA4: 7.2 | BB4: 15.7 | BC4: 8.5 | BE4: 20.9 | BK4: TIME dotCom Berhad | KPJ Healthcare Berhad | Frontken Corporation Berhad | Vitrox Corporation Berhad | Farm Fresh Berhad | BL4: 9.1 | BM4: Moderate | BN4: Equity Malaysia Domestic | BP4: 0.4796 | BQ4: 2026-03-18 | BR4: 0.4702 | BS4: -1.96 | BT4: 19
A5: PUBLIC ISLAMIC EMERGING OPPORTUNITIES FUND | B5: PIEMOF | C5: Shariah | D5: Equity | E5: Malaysia | F5: Capital Growth | G5: 5 | H5: Incidental | I5: 104.43 | J5: 30.03.2016 | K5: Qualified | L5: 100 | M5: 4/4 | N5: 8.87 | O5: 1.14 | P5: 7.73 | Q5: 19.49 | R5: 0.73 | S5: 18.76 | T5: 8.86 | U5: 1.66 | V5: 7.2 | W5: 2.76 | X5: -1.83 | Y5: 4.59 | AC5: =IF(OR(P5="",BL5="",BL5=0),"",P5/BL5) | AD5: =IF(OR(S5="",BL5="",BL5=0),"",S5/BL5) | AE5: =IF(OR(V5="",BL5="",BL5=0),"",V5/BL5) | AF5: =IF(OR(Y5="",BL5="",BL5=0),"",Y5/BL5) | AG5: =IF(OR(AB5="",BL5="",BL5=0),"",AB5/BL5) | AH5: 71.8 | AI5: 21 | AK5: 7.2 | AN5: 7.1 | AO5: 5.7 | AP5: 3 | AQ5: 5.2 | AZ5: 35.1 | BB5: 11.6 | BD5: 5.1 | BE5: 21.7 | BG5: 7.5 | BK5: Spritzer Berhad | Gas Malaysia Berhad | Malayan Cement Berhad | Kinik Company | Shibaura Mechatronics Corporation | BL5: 8.5 | BM5: Moderate | BN5: Equity Malaysia Domestic | BP5: 0.3976 | BQ5: 2026-02-26 | BR5: 0.3703 | BS5: -6.87 | BT5: 39
A6: PUBLIC ASIA ITTIKAL FUND | B6: PAIF | C6: Shariah | D6: Equity | E6: Malaysia | F6: Capital Growth | G6: 5 | H6: Incidental | I6: 5179.3 | J6: 22.08.2006 | K6: Qualified | L6: 100 | M6: 5/5 | N6: 24.96 | O6: 16.63 | P6: 8.33 | Q6: 55.72 | R6: 32.88 | S6: 22.84 | T6: 22.06 | U6: 14.92 | V6: 7.14 | W6: 5.12 | X6: 2.91 | Y6: 2.21 | Z6: 9.82 | AA6: 7.79 | AB6: 2.03 | AC6: =IF(OR(P6="",BL6="",BL6=0),"",P6/BL6) | AD6: =IF(OR(S6="",BL6="",BL6=0),"",S6/BL6) | AE6: =IF(OR(V6="",BL6="",BL6=0),"",V6/BL6) | AF6: =IF(OR(Y6="",BL6="",BL6=0),"",Y6/BL6) | AG6: =IF(OR(AB6="",BL6="",BL6=0),"",AB6/BL6) | AI6: 94.6 | AK6: 5.4 | AN6: 3.4 | AO6: 30.6 | AP6: 41.4 | AQ6: 11.4 | AT6: 7.8 | AZ6: 26.8 | BA6: 54.7 | BC6: 13.1 | BK6: Samsung Electronics Company Limited | SK Hynix Incorporated | Taiwan Semiconductor Manufacturing Company Limited | HD Hyundai Electric Company Limited | Delta Electronics Incorporated | BL6: 19.5 | BM6: Very High | BN6: Equity Asia Pacific Asia | BO6: ThebenchmarkforPAIFisacompositeof30%KualaLumpurSyariahIndex(prior to 1 November 2007), 30% FTSE Bursa Malaysia EMAS Shariah Index (1 November 2007 to 29 April 2011), 30% FTSE Bursa Malaysia Hijrah Shariah Index (30April2011to29April2013),15%FTSEBursaMalaysiaHijrahShariahIndex (w.e.f. 30 April 2013), 15% customised indexbyS&P Dow Jones Indices, LLC based on top 20 constituents bymarket capitalisation of the S&P BMIShariah JapanIndex(w.e.f.30April2013)and70%DowJonesIslamicMarketAsiaEx- JapanIndexSM(priorto1January2009),70%S&PShariahBMIAsiaEx-Japan Index (w.e.f. 1 January 2009). UnderlyingindexdataaresourcedfromS&PDowJonesIndices,LLCandLipper and expressed in Ringgit terms. | BP6: 0.6503 | BQ6: 2026-02-26 | BR6: 0.5851 | BS6: -10.03 | BT6: 39
A7: PUBLIC SMALLCAP FUND | B7: P SmallCap | C7: Conventional | D7: Equity | E7: Malaysia | F7: Capital Growth | G7: 5 | H7: Incidental | I7: 1448.19 | J7: 13.06.2000 | K7: Qualified | L7: 100 | M7: 5/5 | N7: 3.52 | O7: -0.06 | P7: 3.58 | Q7: 16.01 | R7: -0.97 | S7: 16.98 | T7: 7.49 | U7: 0.7 | V7: 6.79 | W7: 4.37 | X7: -0.76 | Y7: 5.13 | Z7: 5.68 | AA7: 0.42 | AB7: 5.26 | AC7: =IF(OR(P7="",BL7="",BL7=0),"",P7/BL7) | AD7: =IF(OR(S7="",BL7="",BL7=0),"",S7/BL7) | AE7: =IF(OR(V7="",BL7="",BL7=0),"",V7/BL7) | AF7: =IF(OR(Y7="",BL7="",BL7=0),"",Y7/BL7) | AG7: =IF(OR(AB7="",BL7="",BL7=0),"",AB7/BL7) | AH7: 76.7 | AI7: 17.1 | AK7: 6.2 | AN7: 13 | AQ7: 4.1 | AZ7: 23.4 | BB7: 34.3 | BC7: 19.5 | BE7: 7 | BJ7: 5.7 | BK7: TIME dotCom Berhad | IGB Real Estate Investment Trust | Hong Leong Industries Berhad | Malaysian Pacific Industries Berhad | IGB Berhad | BL7: 7.8 | BM7: Moderate | BN7: Equity Malaysia Domestic 30% of the fund’s NAV | BP7: 1.1524 | BQ7: 2026-01-23 | BR7: 1.0475 | BS7: -9.1 | BT7: 73
A8: PUBLIC REGIONAL SECTOR FUND | B8: PRSEC | C8: Conventional | D8: Equity | E8: Malaysia | F8: Capital Growth | G8: 5 | H8: Incidental | I8: 571.04 | J8: 21.03.2006 | K8: Qualified | L8: 100 | M8: 5/5 | N8: 19.9 | O8: 10.69 | P8: 9.21 | Q8: 39.14 | R8: 26.12 | S8: 13.02 | T8: 20.85 | U8: 14.17 | V8: 6.68 | W8: 4.71 | X8: 2.39 | Y8: 2.32 | Z8: 8.53 | AA8: 7.39 | AB8: 1.14 | AC8: =IF(OR(P8="",BL8="",BL8=0),"",P8/BL8) | AD8: =IF(OR(S8="",BL8="",BL8=0),"",S8/BL8) | AE8: =IF(OR(V8="",BL8="",BL8=0),"",V8/BL8) | AF8: =IF(OR(Y8="",BL8="",BL8=0),"",Y8/BL8) | AG8: =IF(OR(AB8="",BL8="",BL8=0),"",AB8/BL8) | AH8: 1 | AI8: 93.2 | AK8: 5.8 | AO8: 30.2 | AP8: 36.2 | AQ8: 9.8 | AT8: 10.4 | AU8: 3.3 | AZ8: 20.2 | BA8: 51.2 | BB8: 8.7 | BC8: 14.1 | BK8: Samsung Electronics Company Limited | Taiwan Semiconductor Manufacturing Company Limited | SK Hynix Incorporated | HD Hyundai Electric Company Limited | Tencent Holdings Limited | BL8: 17 | BM8: Very High | BN8: Equity Asia Pacific Asia | BP8: 0.3772 | BQ8: 2026-02-26 | BR8: 0.3445 | BS8: -8.67 | BT8: 39
A9: PUBLIC ASIA PACIFIC FOCUS FUND | B9: PAPFF | C9: Conventional | D9: Equity | E9: Asia Pacific | F9: Capital Growth | G9: 5 | H9: Incidental | I9: 120.99 | J9: 30.11.2021 | K9: Qualified | L9: 100 | M9: 3/3 | N9: 19.16 | O9: 9.35 | P9: 9.81 | Q9: 43.85 | R9: 24.76 | S9: 19.09 | T9: 22.92 | U9: 16.43 | V9: 6.49 | AC9: =IF(OR(P9="",BL9="",BL9=0),"",P9/BL9) | AD9: =IF(OR(S9="",BL9="",BL9=0),"",S9/BL9) | AE9: =IF(OR(V9="",BL9="",BL9=0),"",V9/BL9) | AF9: =IF(OR(Y9="",BL9="",BL9=0),"",Y9/BL9) | AG9: =IF(OR(AB9="",BL9="",BL9=0),"",AB9/BL9) | AH9: 1 | AI9: 93.5 | AK9: 5.5 | AN9: 9.4 | AO9: 26.8 | AP9: 39.9 | AQ9: 8.7 | AT9: 8.7 | AZ9: 23 | BA9: 54.3 | BB9: 2.2 | BC9: 15 | BK9: Samsung Electronics Company Limited | SK Hynix Incorporated | Taiwan Semiconductor Manufacturing Company Limited | HD Hyundai Electric Company Limited | Alibaba Group Holding Limited - W | BL9: 18.5 | BM9: Very High | BN9: Equity Asia Pacific Asia | BO9: ThebenchmarkforPAPFFisacompositeof80%customisedindexbyS&PDow JonesIndices,LLCbasedonthetop30constituentsoftheS&PBMIAsiaEx-Japan Index, 10% Tokyo Stock Price Index (TOPIX) and 10% 3-Month Kuala Lumpur Interbank Offered Rate (KLIBOR). UnderlyingindexdataaresourcedfromS&PDowJonesIndices,LLC,Lipperand Bank Negara Malaysia and expressed in Ringgit terms. | BP9: 0.3651 | BQ9: 2026-02-26 | BR9: 0.3276 | BS9: -10.27 | BT9: 39
A10: PUBLIC STRATEGIC SMALLCAP FUND | B10: PSSCF | C10: Conventional | D10: Equity | E10: Malaysia | F10: Capital Growth | G10: 5 | H10: Incidental | I10: 455.28 | J10: 20.03.2012 | K10: Qualified | L10: 100 | M10: 5/5 | N10: 0.59 | O10: -0.06 | P10: 0.65 | Q10: 15.84 | R10: -0.97 | S10: 16.81 | T10: 6.7 | U10: 0.7 | V10: 6 | W10: 2.02 | X10: -0.76 | Y10: 2.78 | Z10: 4.05 | AA10: 0.42 | AB10: 3.63 | AC10: =IF(OR(P10="",BL10="",BL10=0),"",P10/BL10) | AD10: =IF(OR(S10="",BL10="",BL10=0),"",S10/BL10) | AE10: =IF(OR(V10="",BL10="",BL10=0),"",V10/BL10) | AF10: =IF(OR(Y10="",BL10="",BL10=0),"",Y10/BL10) | AG10: =IF(OR(AB10="",BL10="",BL10=0),"",AB10/BL10) | AH10: 76.7 | AI10: 18.4 | AK10: 4.9 | AN10: 14.1 | AQ10: 4.3 | AZ10: 39.3 | BB10: 14.3 | BC10: 14.5 | BE10: 14.5 | BJ10: 5.4 | BK10: Spritzer Berhad | Kelington Group Berhad | Meta Platforms Incorporated | Malaysian Pacific Industries Berhad | Alphabet Incorporated - Class A | BL10: 11.5 | BM10: High | BN10: Equity Malaysia Domestic 30% of the fund’s NAV | BO10: Index data are sourced from Lipper. | BP10: 0.4893 | BQ10: 2024-05-23 | BR10: 0.4036 | BS10: -17.51 | BT10: 683
A11: PUBLIC ISLAMIC ASIA DIVIDEND FUND | B11: PIADF | C11: Shariah | D11: Equity | E11: Asia | F11: Income | G11: 5 | H11: Annual | I11: 1686.97 | J11: 03.04.2007 | K11: Qualified | L11: 100 | M11: 5/5 | N11: 17.79 | O11: 14.96 | P11: 2.83 | Q11: 34.98 | R11: 30.36 | S11: 4.62 | T11: 18.53 | U11: 13.61 | V11: 4.92 | W11: 3.33 | X11: 2.84 | Y11: 0.49 | Z11: 8.41 | AA11: 6.94 | AB11: 1.47 | AC11: =IF(OR(P11="",BL11="",BL11=0),"",P11/BL11) | AD11: =IF(OR(S11="",BL11="",BL11=0),"",S11/BL11) | AE11: =IF(OR(V11="",BL11="",BL11=0),"",V11/BL11) | AF11: =IF(OR(Y11="",BL11="",BL11=0),"",Y11/BL11) | AG11: =IF(OR(AB11="",BL11="",BL11=0),"",AB11/BL11) | AH11: 1.8 | AI11: 84.6 | AK11: 13.6 | AN11: 4 | AO11: 20.4 | AP11: 39.7 | AT11: 12.1 | AX11: 3.6 | AZ11: 20.2 | BA11: 36.9 | BC11: 25.1 | BE11: 1.5 | BH11: 1.8 | BK11: Samsung Electronics Company Limited | SK Hynix Incorporated | Taiwan Semiconductor Manufacturing Company Limited | Alibaba Group Holding Limited - W | Hanwha Aerospace Company Limited | BL11: 14.9 | BM11: Very High | BN11: Equity Asia Pacific Asia | BP11: 0.5329 | BQ11: 2026-02-26 | BR11: 0.4982 | BS11: -6.51 | BT11: 39
A12: PUBLIC ISLAMIC SAVINGS FUND | B12: PISVF | C12: Shariah | D12: Equity | E12: Malaysia | F12: Income | G12: 4 | H12: Semi-Annual | I12: 486.59 | J12: 15.12.2011 | K12: Qualified | L12: 100 | M12: 5/5 | N12: 1.97 | O12: 0.96 | P12: 1.01 | Q12: 14.18 | R12: 6.76 | S12: 7.42 | T12: 9.01 | U12: 4.19 | V12: 4.82 | W12: 2.39 | X12: -0.72 | Y12: 3.11 | Z12: 4.64 | AA12: 0.35 | AB12: 4.29 | AC12: =IF(OR(P12="",BL12="",BL12=0),"",P12/BL12) | AD12: =IF(OR(S12="",BL12="",BL12=0),"",S12/BL12) | AE12: =IF(OR(V12="",BL12="",BL12=0),"",V12/BL12) | AF12: =IF(OR(Y12="",BL12="",BL12=0),"",Y12/BL12) | AG12: =IF(OR(AB12="",BL12="",BL12=0),"",AB12/BL12) | AH12: 76.5 | AI12: 17.3 | AK12: 6.2 | AN12: 8.9 | AO12: 2 | AP12: 6.4 | AZ12: 26.8 | BB12: 12.3 | BC12: 13.9 | BE12: 9.8 | BF12: 10.3 | BK12: Tenaga Nasional Berhad | Telekom Malaysia Berhad | Press Metal Aluminium Holdings Berhad | HD Hyundai Electric Company Limited | Malayan Cement Berhad | BL12: 9.2 | BM12: Moderate | BN12: Equity Malaysia Domestic | BP12: 0.4053 | BQ12: 2024-07-15 | BR12: 0.381 | BS12: -6 | BT12: 630
A13: PB GREATER CHINA A-SHARES FUND | B13: PBGCASF | C13: Conventional | D13: Equity | E13: Greater China | F13: Capital Growth | G13: 5 | H13: Incidental | I13: 543.83 | J13: 10.03.2020 | K13: Qualified | L13: 100 | M13: 4/4 | N13: -0.15 | O13: -1.59 | P13: 1.44 | Q13: 28.45 | R13: 4.87 | S13: 23.58 | T13: 11.29 | U13: 6.63 | V13: 4.66 | W13: 0.01 | X13: -0.97 | Y13: 0.97 | AC13: =IF(OR(P13="",BL13="",BL13=0),"",P13/BL13) | AD13: =IF(OR(S13="",BL13="",BL13=0),"",S13/BL13) | AE13: =IF(OR(V13="",BL13="",BL13=0),"",V13/BL13) | AF13: =IF(OR(Y13="",BL13="",BL13=0),"",Y13/BL13) | AG13: =IF(OR(AB13="",BL13="",BL13=0),"",AB13/BL13) | AI13: 90.5 | AK13: 9.5 | AN13: 2.3 | AO13: 24.9 | AT13: 63.3 | AZ13: 6.7 | BA13: 34.8 | BC13: 17.1 | BE13: 10 | BH13: 16 | BK13: Taiwan Semiconductor Manufacturing Company Limited | Zijin Mining Group Company Limited - A Shares (HKS) | Wanhua Chemical Group Company Limited - A Shares (HKS) | Kinik Company | NAURA Technology Group Company Limited - A Shares (HKS) | BL13: 19.3 | BM13: Very High | BN13: Equity Greater China Greater China | BO13: ThebenchmarkforPBGCASFisacompositeof50%S&PChinaA50Index,25% Hang Seng China Enterprises Index(HSCEI), 15% S&P Taiwan LargeCapIndex and 10% 3-Month Kuala Lumpur Interbank Offered Rate (KLIBOR). UnderlyingindexdataaresourcedfromLipper,S&PDowJonesIndices,LLCand Bank Negara Malaysia and expressed in Ringgit terms. | BP13: 0.3848 | BQ13: 2021-02-18 | BR13: 0.3143 | BS13: -18.32 | BT13: 1873
A14: PUBLIC ISLAMIC TREASURES GROWTH FUND | B14: PITGF | C14: Shariah | D14: Equity | E14: Malaysia | F14: Capital Growth | G14: 5 | H14: Incidental | I14: 283.97 | J14: 19.07.2011 | K14: Qualified | L14: 100 | M14: 5/5 | N14: 9.12 | O14: 1.14 | P14: 7.98 | Q14: 14.9 | R14: 0.73 | S14: 14.17 | T14: 6.06 | U14: 1.66 | V14: 4.4 | W14: 0.18 | X14: -1.83 | Y14: 2.01 | Z14: 3.87 | AA14: 1.18 | AB14: 2.69 | AC14: =IF(OR(P14="",BL14="",BL14=0),"",P14/BL14) | AD14: =IF(OR(S14="",BL14="",BL14=0),"",S14/BL14) | AE14: =IF(OR(V14="",BL14="",BL14=0),"",V14/BL14) | AF14: =IF(OR(Y14="",BL14="",BL14=0),"",Y14/BL14) | AG14: =IF(OR(AB14="",BL14="",BL14=0),"",AB14/BL14) | AH14: 76.8 | AI14: 18.7 | AK14: 4.5 | AN14: 7.6 | AO14: 5.8 | AQ14: 5.3 | AZ14: 34.1 | BB14: 12.4 | BC14: 8.2 | BE14: 18.9 | BJ14: 6.6 | BK14: Vitrox Corporation Berhad | TIME dotCom Berhad | QL Resources Berhad | Malaysian Pacific Industries Berhad | Bursa Malaysia Berhad | BL14: 9 | BM14: Moderate | BN14: Equity Malaysia Domestic | BO14: The benchmark for PITGF is a composite of 90% FTSE Bursa Malaysia EMAS Shariah Index (prior to 30 April 2013), 90% FTSE Bursa Malaysia Small Cap ShariahIndex(FBMSSC)(30April2013to29April2015),90%customisedindex byFTSEbasedontheconstituentswithmarketcapitalisationbelowRM6.0billion withintheFTSE BursaMalaysia EMAS ShariahIndex(w.e.f. 30April 2015)and 10% 3-Month Islamic Interbank Money Market (IIMM) rate. Underlying index data are sourced from FTSE International Limited, Lipper and Bank Negara Malaysia. | BP14: 0.4043 | BQ14: 2021-04-26 | BR14: 0.3611 | BS14: -10.69 | BT14: 1806
A15: PUBLIC SELECT TREASURES EQUITY FUND | B15: PSTEF | C15: Conventional | D15: Equity | E15: Malaysia | F15: Capital Growth | G15: 5 | H15: Incidental | I15: 415.66 | J15: 22.07.2015 | K15: Qualified | L15: 100 | M15: 5/5 | N15: 6.19 | O15: 3.11 | P15: 3.08 | Q15: 17.13 | R15: 4.05 | S15: 13.08 | T15: 10.41 | U15: 7.06 | V15: 3.35 | W15: 3.18 | X15: 2.05 | Y15: 1.13 | Z15: 7.48 | AA15: 2.78 | AB15: 4.7 | AC15: =IF(OR(P15="",BL15="",BL15=0),"",P15/BL15) | AD15: =IF(OR(S15="",BL15="",BL15=0),"",S15/BL15) | AE15: =IF(OR(V15="",BL15="",BL15=0),"",V15/BL15) | AF15: =IF(OR(Y15="",BL15="",BL15=0),"",Y15/BL15) | AG15: =IF(OR(AB15="",BL15="",BL15=0),"",AB15/BL15) | AH15: 74.2 | AI15: 22.5 | AK15: 3.3 | AN15: 4.9 | AO15: 14.2 | AS15: 3.4 | AZ15: 37.3 | BA15: 7.3 | BB15: 31.1 | BC15: 5 | BE15: 12.2 | BK15: Hon.Precision Incorporated | Kinik Company | IGB Real Estate Investment Trust | TIME dotCom Berhad | HEICO Corporation | BL15: 9.1 | BM15: Moderate | BN15: Equity Malaysia Domestic 25% of the fund’s NAV | BP15: 0.4539 | BQ15: 2026-02-25 | BR15: 0.421 | BS15: -7.25 | BT15: 40
A16: PUBLIC DIVIDEND SELECT FUND | B16: PDSF | C16: Conventional | D16: Equity | E16: Malaysia | F16: Income | G16: 4 | H16: Semi-Annual | I16: 866.73 | J16: 03.05.2005 | K16: Qualified | L16: 100 | M16: 5/5 | N16: 2.68 | O16: 2.48 | P16: 0.2 | Q16: 9.19 | R16: 7.73 | S16: 1.46 | T16: 9.59 | U16: 6.31 | V16: 3.28 | W16: 4.72 | X16: 2.09 | Y16: 2.63 | Z16: 3.59 | AA16: 1.31 | AB16: 2.28 | AC16: =IF(OR(P16="",BL16="",BL16=0),"",P16/BL16) | AD16: =IF(OR(S16="",BL16="",BL16=0),"",S16/BL16) | AE16: =IF(OR(V16="",BL16="",BL16=0),"",V16/BL16) | AF16: =IF(OR(Y16="",BL16="",BL16=0),"",Y16/BL16) | AG16: =IF(OR(AB16="",BL16="",BL16=0),"",AB16/BL16) | AH16: 76.3 | AI16: 17.9 | AK16: 5.8 | AN16: 12.5 | AR16: 5.4 | AZ16: 7.3 | BB16: 47.5 | BC16: 9.3 | BD16: 13.3 | BF16: 8.4 | BK16: Public Bank Berhad | Malayan Banking Berhad | CIMB Group Holdings Berhad | IGB Real Estate Investment Trust | Tenaga Nasional Berhad | BL16: 6.7 | BM16: Low | BN16: Equity Malaysia Income Domestic 30% of the fund’s NAV | BP16: 0.3542 | BQ16: 2007-10-31 | BR16: 0.2908 | BS16: -17.9 | BT16: 6732
A17: PUBLIC FOCUS SELECT FUND | B17: PFSF | C17: Conventional | D17: Equity | E17: United States | F17: Capital Growth | G17: 5 | H17: Incidental | I17: 491.8 | J17: 25.11.2004 | K17: Qualified | L17: 100 | M17: 5/5 | N17: 4.79 | O17: 4.4 | P17: 0.39 | Q17: 15.42 | R17: 5.44 | S17: 9.98 | T17: 12.56 | U17: 9.29 | V17: 3.27 | W17: 5.35 | X17: 2.56 | Y17: 2.79 | Z17: 5.43 | AA17: 3.19 | AB17: 2.24 | AC17: =IF(OR(P17="",BL17="",BL17=0),"",P17/BL17) | AD17: =IF(OR(S17="",BL17="",BL17=0),"",S17/BL17) | AE17: =IF(OR(V17="",BL17="",BL17=0),"",V17/BL17) | AF17: =IF(OR(Y17="",BL17="",BL17=0),"",Y17/BL17) | AG17: =IF(OR(AB17="",BL17="",BL17=0),"",AB17/BL17) | AH17: 74.9 | AI17: 22.4 | AK17: 2.7 | AN17: 5.4 | AO17: 15.3 | AS17: 1.7 | AZ17: 30.5 | BA17: 8.1 | BB17: 33.1 | BC17: 5.5 | BE17: 14.5 | BK17: Hon.Precision Incorporated | Kinik Company | QL Resources Berhad | LPI Capital Berhad | TIME dotCom Berhad | BL17: 7.7 | BM17: Low | BN17: Equity Malaysia Domestic 30% of the fund’s NAV | BO17: Kuala Lumpur Composite Index (prior to 30 April 2008). FTSE Bursa Malaysia Mid 70 Index (w.e.f. 30 April 2008). Underlying index data are sourced from Lipper. | BP17: 0.4139 | BQ17: 2026-02-26 | BR17: 0.3866 | BS17: -6.6 | BT17: 39
A18: PUBLIC FAR-EAST PROPERTY & RESORTS FUND | B18: PFEPRF | C18: Conventional | D18: Equity | E18: Asia Pacific | F18: Capital Growth | G18: 5 | H18: Annual | I18: 199.9 | J18: 10.07.2007 | K18: Qualified | L18: 100 | M18: 5/5 | N18: 9.04 | O18: 8.32 | P18: 0.72 | Q18: 15.68 | R18: 14.99 | S18: 0.69 | T18: 8.69 | U18: 5.7 | V18: 2.99 | W18: 4.05 | X18: 0.83 | Y18: 3.22 | Z18: 3.3 | AA18: 1.26 | AB18: 2.04 | AC18: =IF(OR(P18="",BL18="",BL18=0),"",P18/BL18) | AD18: =IF(OR(S18="",BL18="",BL18=0),"",S18/BL18) | AE18: =IF(OR(V18="",BL18="",BL18=0),"",V18/BL18) | AF18: =IF(OR(Y18="",BL18="",BL18=0),"",Y18/BL18) | AG18: =IF(OR(AB18="",BL18="",BL18=0),"",AB18/BL18) | AH18: 26.2 | AI18: 63.6 | AK18: 10.2 | AQ18: 20.4 | AT18: 7 | AU18: 2.3 | AX18: 18.3 | BI18: 89.8 | BK18: Sun Hung Kai Properties Limited | Goodman Group | China Resources Land Limited | IGB Real Estate Investment Trust | Mitsubishi Estate Company Limited | BL18: 9.5 | BM18: Moderate | BN18: Equity Sector Real Asia | BP18: 0.3479 | BQ18: 2013-05-20 | BR18: 0.2669 | BS18: -23.28 | BT18: 4704
A19: PUBLIC EMERGING OPPORTUNITIES FUND | B19: PEMOF | C19: Conventional | D19: Equity | E19: Malaysia | F19: Capital Growth | G19: 5 | H19: Incidental | I19: 151.06 | J19: 30.03.2016 | K19: Qualified | L19: 100 | M19: 4/4 | N19: 6.11 | O19: 2.66 | P19: 3.45 | Q19: 9.84 | R19: 0.58 | S19: 9.26 | T19: 9.06 | U19: 6.19 | V19: 2.87 | W19: 1.97 | X19: 1.73 | Y19: 0.24 | AC19: =IF(OR(P19="",BL19="",BL19=0),"",P19/BL19) | AD19: =IF(OR(S19="",BL19="",BL19=0),"",S19/BL19) | AE19: =IF(OR(V19="",BL19="",BL19=0),"",V19/BL19) | AF19: =IF(OR(Y19="",BL19="",BL19=0),"",Y19/BL19) | AG19: =IF(OR(AB19="",BL19="",BL19=0),"",AB19/BL19) | AH19: 74.3 | AI19: 22.8 | AK19: 2.9 | AN19: 5.3 | AO19: 14.7 | AS19: 2.8 | AZ19: 44.8 | BA19: 7.7 | BB19: 25.9 | BE19: 8.3 | BG19: 4.7 | BK19: Kelington Group Berhad | Hon.Precision Incorporated | Kinik Company | Sunway Real Estate Investment Trust | IGB Real Estate Investment Trust | BL19: 10.6 | BM19: High | BN19: Equity Malaysia Domestic 25% of the fund’s NAV | BP19: 0.5405 | BQ19: 2024-07-15 | BR19: 0.4885 | BS19: -9.62 | BT19: 630
A20: PB CHINA PACIFIC EQUITY FUND | B20: PBCPEF | C20: Conventional | D20: Equity | E20: Greater China | F20: Capital Growth | G20: 5 | H20: Incidental | I20: 241.62 | J20: 23.10.2007 | K20: Qualified | L20: 100 | M20: 5/5 | N20: 15.47 | O20: 7.97 | P20: 7.5 | Q20: 20.01 | R20: 19.44 | S20: 0.57 | T20: 13.31 | U20: 10.71 | V20: 2.6 | W20: -0.75 | X20: -1.53 | Y20: 0.78 | Z20: 8.03 | AA20: 6.82 | AB20: 1.21 | AC20: =IF(OR(P20="",BL20="",BL20=0),"",P20/BL20) | AD20: =IF(OR(S20="",BL20="",BL20=0),"",S20/BL20) | AE20: =IF(OR(V20="",BL20="",BL20=0),"",V20/BL20) | AF20: =IF(OR(Y20="",BL20="",BL20=0),"",Y20/BL20) | AG20: =IF(OR(AB20="",BL20="",BL20=0),"",AB20/BL20) | AI20: 86.9 | AK20: 13.1 | AN20: 4 | AO20: 30.8 | AP20: 21.7 | AQ20: 7.1 | AT20: 23.3 | AZ20: 17.9 | BA20: 49 | BB20: 4.3 | BC20: 13.5 | BD20: 2.2 | BK20: Samsung Electronics Company Limited | SK Hynix Incorporated | Taiwan Semiconductor Manufacturing Company Limited | Alibaba Group Holding Limited - W | Semiconductor Manufacturing International Corporation | BL20: 18 | BM20: Very High | BN20: Equity Asia Pacific Greater China | BO20: ThebenchmarkforPBCPEFisacompositeof70%HangSengChinaEnterprises Index (HSCEI) and 30% Hang Seng Index (HSI) (prior to 1 January 2009). MSCI Zhong Hua Index (1 January 2009 to 29 April 2015). 80%MSCIZhongHuaIndex(30April2015to29April2021),80%S&PChina& HongKongLargeMidCapIndex(30April 2021to28December2025),60%S&P China&HongKongLargeMidCapIndex(w.e.f.29December2025),10%KOSPI50 Index (30 April 2015 to 29 April 2016), 10% MSCI Korea Large Cap Index (30April2016to29April2021),10%S&PKoreaLargeCapIndex(30April2021to 28December2025),15%S&PKoreaLargeCapIndex(w.e.f.29December2025), 10% FTSE TWSE Taiwan50Index(30April 2015 to29 April 2016), 10% MSCI Taiwan Large Cap Index (30 April 2016 to 29 April 2021), 10% S&P Taiwan LargeCapIndex(30April2021to28December2025),15%S&PTaiwanLargeCap Index(w.e.f.29December2025)and10%3-MonthKualaLumpurInterbankOffered Rate (KLIBOR) (w.e.f. 29 December 2025). UnderlyingindexdataaresourcedfromS&PDowJonesIndices,LLC,Lipperand Bank Negara Malaysia and expressed in Ringgit terms. | BP20: 0.5343 | BQ20: 2021-02-17 | BR20: 0.3943 | BS20: -26.2 | BT20: 1874
A21: PUBLIC ADVANTAGE GROWTH EQUITY FUND | B21: PAVGEF | C21: Conventional | D21: Equity | E21: Malaysia | F21: Capital Growth | G21: 5 | H21: Incidental | I21: 19.45 | J21: 08.09.2015 | K21: Qualified | L21: 100 | M21: 5/5 | N21: 2.32 | O21: 2.17 | P21: 0.15 | Q21: 12.36 | R21: 9.01 | S21: 3.35 | T21: 7.62 | U21: 5.69 | V21: 1.93 | W21: 2.27 | X21: 1.7 | Y21: 0.57 | Z21: 4.51 | AA21: 0.37 | AB21: 4.14 | AC21: =IF(OR(P21="",BL21="",BL21=0),"",P21/BL21) | AD21: =IF(OR(S21="",BL21="",BL21=0),"",S21/BL21) | AE21: =IF(OR(V21="",BL21="",BL21=0),"",V21/BL21) | AF21: =IF(OR(Y21="",BL21="",BL21=0),"",Y21/BL21) | AG21: =IF(OR(AB21="",BL21="",BL21=0),"",AB21/BL21) | AH21: 76.8 | AI21: 12.4 | AK21: 10.8 | AN21: 5.5 | AO21: 3.6 | AT21: 3.3 | AZ21: 19.3 | BB21: 27.5 | BC21: 17.1 | BF21: 10.5 | BH21: 6.9 | BK21: Malayan Banking Berhad | Tenaga Nasional Berhad | UWC Berhad | Press Metal Aluminium Holdings Berhad | Telekom Malaysia Berhad | BL21: 11 | BM21: High | BN21: Equity Malaysia Domestic 25% of the fund’s NAV | BP21: 0.3454 | BQ21: 2026-01-27 | BR21: 0.3273 | BS21: -5.24 | BT21: 69
A22: PUBLIC ISLAMIC SECTOR SELECT FUND | B22: PISSF | C22: Shariah | D22: Equity | E22: Malaysia | F22: Capital Growth | G22: 4 | H22: Incidental | I22: 112.13 | J22: 13.11.2007 | K22: Qualified | L22: 100 | M22: 5/5 | N22: 2.62 | O22: 1 | P22: 1.62 | Q22: 7.07 | R22: 7.06 | S22: 0.01 | T22: 5.13 | U22: 4.2 | V22: 0.93 | W22: 1.73 | X22: -1.2 | Y22: 2.93 | Z22: 1.55 | AA22: -0.03 | AB22: 1.58 | AC22: =IF(OR(P22="",BL22="",BL22=0),"",P22/BL22) | AD22: =IF(OR(S22="",BL22="",BL22=0),"",S22/BL22) | AE22: =IF(OR(V22="",BL22="",BL22=0),"",V22/BL22) | AF22: =IF(OR(Y22="",BL22="",BL22=0),"",Y22/BL22) | AG22: =IF(OR(AB22="",BL22="",BL22=0),"",AB22/BL22) | AH22: 77 | AI22: 21.1 | AK22: 1.9 | AN22: 8.9 | AO22: 6.9 | AR22: 5.3 | AZ22: 26.9 | BC22: 23.7 | BE22: 16.3 | BF22: 10.2 | BG22: 8.6 | BK22: Tenaga Nasional Berhad | Sunway Construction Group Berhad | Telekom Malaysia Berhad | Gamuda Berhad | Malayan Cement Berhad | BL22: 8 | BM22: Moderate | BN22: Equity Malaysia Domestic | BO22: Index data are sourced from Lipper. | BP22: 0.3302 | BQ22: 2013-11-19 | BR22: 0.2763 | BS22: -16.32 | BT22: 4521
A23: PUBLIC ISLAMIC OPPORTUNITIES FUND | B23: PIOF | C23: Shariah | D23: Equity | E23: Malaysia | F23: Capital Growth | G23: 5 | H23: Incidental | I23: 1090.72 | J23: 28.06.2005 | K23: Qualified | L23: 100 | M23: 5/5 | N23: 1.51 | O23: -1.51 | P23: 3.02 | Q23: 1.63 | R23: -0.19 | S23: 1.82 | T23: 2.22 | U23: 1.3 | V23: 0.92 | W23: -0.79 | X23: -1 | Y23: 0.21 | Z23: 5.32 | AA23: 0.25 | AB23: 5.07 | AC23: =IF(OR(P23="",BL23="",BL23=0),"",P23/BL23) | AD23: =IF(OR(S23="",BL23="",BL23=0),"",S23/BL23) | AE23: =IF(OR(V23="",BL23="",BL23=0),"",V23/BL23) | AF23: =IF(OR(Y23="",BL23="",BL23=0),"",Y23/BL23) | AG23: =IF(OR(AB23="",BL23="",BL23=0),"",AB23/BL23) | AH23: 69.9 | AI23: 18.9 | AK23: 11.2 | AN23: 6.2 | AO23: 5.5 | AP23: 7.2 | AZ23: 39.9 | BA23: 14.5 | BB23: 11.4 | BC23: 5.6 | BD23: 6.9 | BK23: Kelington Group Berhad | Frontken Corporation Berhad | Taiwan Semiconductor Manufacturing Company Limited | Uchi Technologies Berhad | HD Hyundai Electric Company Limited | BL23: 11.1 | BM23: High | BN23: Equity Malaysia Domestic | BO23: Kuala Lumpur Syariah Index (prior to 1 November 2007). FTSE Bursa Malaysia EMAS Shariah Index (1 November 2007 to 29 April 2013). FTSE Bursa Malaysia Small Cap Shariah Index (w.e.f. 30 April 2013). Underlying index data are sourced from Lipper. | BP23: 0.714 | BQ23: 2021-11-19 | BR23: 0.5401 | BS23: -24.36 | BT23: 1599
A24: PUBLIC e-ASIA EVOLVING GROWTH FUND | B24: PeAEVGF | C24: Conventional | D24: Equity | E24: Asia | F24: Capital Growth | G24: 5 | H24: Incidental | I24: 764.28 | J24: 30.11.2021 | K24: Qualified | L24: 100 | M24: 3/3 | N24: 11.61 | O24: 9.41 | P24: 2.2 | Q24: 26.36 | R24: 25.4 | S24: 0.96 | T24: 17.64 | U24: 16.9 | V24: 0.74 | AC24: =IF(OR(P24="",BL24="",BL24=0),"",P24/BL24) | AD24: =IF(OR(S24="",BL24="",BL24=0),"",S24/BL24) | AE24: =IF(OR(V24="",BL24="",BL24=0),"",V24/BL24) | AF24: =IF(OR(Y24="",BL24="",BL24=0),"",Y24/BL24) | AG24: =IF(OR(AB24="",BL24="",BL24=0),"",AB24/BL24) | AH24: 1 | AI24: 85.2 | AK24: 13.8 | AN24: 11.6 | AO24: 19.2 | AP24: 22.2 | AS24: 1.6 | AT24: 30.6 | AZ24: 13.7 | BA24: 42.8 | BB24: 1 | BC24: 23.5 | BD24: 5.2 | BK24: Samsung Electronics Company Limited | Taiwan Semiconductor Manufacturing Company Limited | SK Hynix Incorporated | Unimicron Technology Corporation | Alibaba Group Holding Limited - W | BL24: 18.5 | BM24: Very High | BN24: Equity Asia Pacific ex- Asia | BO24: ThebenchmarkforPeAEVGFisacompositeof90%customisedindexbyS&PDow JonesIndices,LLCbasedonthetop30constituentsoftheS&PBMIAsiaEx-Japan Index and 10% 3-Month Kuala Lumpur Interbank Offered Rate (KLIBOR). Underlying indexdata are sourced from S&P Dow Jones Indices, LLC and Bank Negara Malaysia and expressed in Ringgit terms. | BP24: 0.3294 | BQ24: 2026-01-28 | BR24: 0.2974 | BS24: -9.71 | BT24: 68
A25: PUBLIC ISLAMIC SUSTAINABLE GROWTH FUND | B25: PISGRTF | C25: Shariah | D25: Equity | E25: Malaysia | F25: Capital Growth | G25: 4 | H25: Incidental | I25: 122.8 | J25: 04.06.2024 | K25: Qualified | L25: 100 | M25: 2/2 | N25: 1.12 | O25: 0.9 | P25: 0.22 | Q25: 10.94 | R25: 6.81 | S25: 4.13 | AC25: =IF(OR(P25="",BL25="",BL25=0),"",P25/BL25) | AD25: =IF(OR(S25="",BL25="",BL25=0),"",S25/BL25) | AE25: =IF(OR(V25="",BL25="",BL25=0),"",V25/BL25) | AF25: =IF(OR(Y25="",BL25="",BL25=0),"",Y25/BL25) | AG25: =IF(OR(AB25="",BL25="",BL25=0),"",AB25/BL25) | AH25: 75.6 | AI25: 16.4 | AK25: 8 | AN25: 8.1 | AO25: 5.7 | AT25: 2.6 | AZ25: 20.3 | BB25: 22.6 | BC25: 24.5 | BE25: 7.2 | BF25: 9.6 | BK25: Tenaga Nasional Berhad | Sunway Berhad | Telekom Malaysia Berhad | TIME dotCom Berhad | QL Resources Berhad | BO25: Index data are sourced from Lipper. | BP25: 0.2681 | BQ25: 2026-01-27 | BR25: 0.2479 | BS25: -7.53 | BT25: 69
A26: PUBLIC ISLAMIC GLOBAL SUSTAINABLE GROWTH FUND | B26: PISGSGF | C26: Shariah | D26: Equity | E26: Global | F26: Capital Growth | G26: 5 | H26: Incidental | I26: 722.51 | J26: 20.02.2024 | K26: Qualified | L26: 100 | M26: 2/2 | N26: 0.23 | O26: -0.05 | P26: 0.28 | Q26: 16.92 | R26: 8.28 | S26: 8.64 | AC26: =IF(OR(P26="",BL26="",BL26=0),"",P26/BL26) | AD26: =IF(OR(S26="",BL26="",BL26=0),"",S26/BL26) | AE26: =IF(OR(V26="",BL26="",BL26=0),"",V26/BL26) | AF26: =IF(OR(Y26="",BL26="",BL26=0),"",Y26/BL26) | AG26: =IF(OR(AB26="",BL26="",BL26=0),"",AB26/BL26) | AH26: 3.7 | AI26: 81.2 | AK26: 15.1 | AN26: 51 | AO26: 9.5 | AP26: 8.2 | AT26: 4.5 | AV26: 6.6 | BA26: 49.8 | BB26: 5.1 | BC26: 23.4 | BD26: 5 | BE26: 1.6 | BK26: Taiwan Semiconductor Manufacturing Company Limited | Alphabet Incorporated - Class A | Apple Incorporated | Meta Platforms Incorporated | ASML Holding N.V. - NYS | BO26: The benchmark for PISGSGF is a composite of 90% S&P Global 1200 ESG Shariah Index and 10% 3-Month Islamic Interbank Money Market (IIMM) rate. UnderlyingindexdataaresourcedfromS&PDowJonesIndices,LLCandBank Negara Malaysia and expressed in Ringgit terms. | BP26: 0.3218 | BQ26: 2025-10-29 | BR26: 0.2868 | BS26: -10.88 | BT26: 159
A27: PUBLIC CHINA SELECT FUND | B27: PCSF | C27: Conventional | D27: Equity | E27: Greater China | F27: Capital Growth | G27: 5 | H27: Incidental | I27: 879.09 | J27: 05.06.2007 | K27: Qualified | L27: 80 | M27: 4/5 | N27: 2.92 | O27: 3.47 | P27: -0.55 | Q27: 28.84 | R27: 11.24 | S27: 17.6 | T27: 18.19 | U27: 10.93 | V27: 7.26 | W27: 3.99 | X27: -0.61 | Y27: 4.6 | Z27: 9.4 | AA27: 7.19 | AB27: 2.21 | AC27: =IF(OR(P27="",BL27="",BL27=0),"",P27/BL27) | AD27: =IF(OR(S27="",BL27="",BL27=0),"",S27/BL27) | AE27: =IF(OR(V27="",BL27="",BL27=0),"",V27/BL27) | AF27: =IF(OR(Y27="",BL27="",BL27=0),"",Y27/BL27) | AG27: =IF(OR(AB27="",BL27="",BL27=0),"",AB27/BL27) | AI27: 94.8 | AK27: 5.2 | AN27: 19 | AO27: 49.7 | AT27: 26.1 | AZ27: 15.5 | BA27: 40.3 | BC27: 30.6 | BD27: 8.4 | BK27: Taiwan Semiconductor Manufacturing Company Limited | Asia Vital Components Company Limited | Elite Material Company Limited | Alibaba Group Holding Limited - W | Tencent Holdings Limited | BL27: 16.4 | BM27: Very High | BN27: Equity Greater China Greater China | BP27: 0.5153 | BQ27: 2026-03-18 | BR27: 0.5025 | BS27: -2.48 | BT27: 19
A28: PB GROWTH SEQUEL FUND | B28: PBGSQF | C28: Conventional | D28: Equity | E28: Malaysia | F28: Capital Growth | G28: 4 | H28: Incidental | I28: 64.33 | J28: 15.11.2011 | K28: Qualified | L28: 80 | M28: 4/5 | N28: -0.65 | O28: 2.17 | P28: -2.82 | Q28: 13.3 | R28: 9.01 | S28: 4.29 | T28: 11.49 | U28: 5.69 | V28: 5.8 | W28: 5.16 | X28: 1.7 | Y28: 3.46 | Z28: 4.3 | AA28: 0.37 | AB28: 3.93 | AC28: =IF(OR(P28="",BL28="",BL28=0),"",P28/BL28) | AD28: =IF(OR(S28="",BL28="",BL28=0),"",S28/BL28) | AE28: =IF(OR(V28="",BL28="",BL28=0),"",V28/BL28) | AF28: =IF(OR(Y28="",BL28="",BL28=0),"",Y28/BL28) | AG28: =IF(OR(AB28="",BL28="",BL28=0),"",AB28/BL28) | AH28: 76.3 | AI28: 15.3 | AK28: 8.4 | AN28: 10.4 | AO28: 4.9 | AZ28: 28.5 | BA28: 4.9 | BB28: 24.7 | BC28: 17.7 | BE28: 8.4 | BK28: Public Bank Berhad | Sunway Berhad | Southern Cable Group Berhad | QL Resources Berhad | Malayan Cement Berhad | BL28: 8.9 | BM28: Moderate | BN28: Equity Malaysia | BO28: Index data are sourced from Lipper. | BP28: 0.3784 | BQ28: 2026-01-27 | BR28: 0.3462 | BS28: -8.51 | BT28: 69
A29: PUBLIC ITTIKAL FUND | B29: P ITTIKAL | C29: Shariah | D29: Equity | E29: Malaysia | F29: Capital Growth | G29: 4 | H29: Incidental | I29: 3917.94 | J29: 10.04.1997 | K29: Qualified | L29: 80 | M29: 4/5 | N29: -0.51 | O29: 1 | P29: -1.51 | Q29: 12.12 | R29: 7.06 | S29: 5.06 | T29: 9.97 | U29: 4.2 | V29: 5.77 | W29: 4.75 | X29: -1.2 | Y29: 5.95 | Z29: 3.48 | AA29: -0.03 | AB29: 3.51 | AC29: =IF(OR(P29="",BL29="",BL29=0),"",P29/BL29) | AD29: =IF(OR(S29="",BL29="",BL29=0),"",S29/BL29) | AE29: =IF(OR(V29="",BL29="",BL29=0),"",V29/BL29) | AF29: =IF(OR(Y29="",BL29="",BL29=0),"",Y29/BL29) | AG29: =IF(OR(AB29="",BL29="",BL29=0),"",AB29/BL29) | AH29: 75 | AI29: 20.4 | AK29: 4.6 | AN29: 12.1 | AO29: 8.3 | BA29: 12 | BB29: 13.8 | BC29: 19.1 | BE29: 21 | BF29: 9.7 | BK29: Sunway Berhad | Tenaga Nasional Berhad | IHH Healthcare Berhad | Telekom Malaysia Berhad | QL Resources Berhad | BL29: 8.5 | BM29: Moderate | BN29: Equity Malaysia Domestic | BO29: Kuala Lumpur Syariah Index (prior to 1 November 2007). FTSE Bursa Malaysia EMAS Shariah Index (w.e.f. 1 November 2007). | BP29: 1.31 | BQ29: 2000-02-24 | BR29: 0.9298 | BS29: -29.02 | BT29: 9538
A30: PUBLIC SECTOR SELECT FUND | B30: PSSF | C30: Conventional | D30: Equity | E30: Malaysia | F30: Capital Growth | G30: 4 | H30: Incidental | I30: 378.83 | J30: 13.11.2007 | K30: Qualified | L30: 80 | M30: 4/5 | N30: 1.87 | O30: 2.7 | P30: -0.83 | Q30: 13.3 | R30: 8.15 | S30: 5.15 | T30: 11.21 | U30: 6.58 | V30: 4.63 | W30: 6.17 | X30: 1.93 | Y30: 4.24 | Z30: 5.51 | AA30: 1.04 | AB30: 4.47 | AC30: =IF(OR(P30="",BL30="",BL30=0),"",P30/BL30) | AD30: =IF(OR(S30="",BL30="",BL30=0),"",S30/BL30) | AE30: =IF(OR(V30="",BL30="",BL30=0),"",V30/BL30) | AF30: =IF(OR(Y30="",BL30="",BL30=0),"",Y30/BL30) | AG30: =IF(OR(AB30="",BL30="",BL30=0),"",AB30/BL30) | AH30: 76.2 | AI30: 19.6 | AK30: 4.2 | AN30: 14.3 | AR30: 3 | AT30: 2.3 | BA30: 7 | BB30: 44.9 | BC30: 17.4 | BE30: 8.9 | BF30: 5.9 | BK30: Malayan Banking Berhad | Public Bank Berhad | Telekom Malaysia Berhad | Meta Platforms Incorporated | NVIDIA Corporation | BL30: 6.1 | BM30: Low | BN30: Equity Malaysia Domestic 25% of the fund’s NAV | BP30: 0.3973 | BQ30: 2026-02-11 | BR30: 0.3729 | BS30: -6.14 | BT30: 54
A31: PUBLIC ISLAMIC SELECT ENTERPRISES FUND | B31: PISEF | C31: Shariah | D31: Equity | E31: Malaysia | F31: Capital Growth | G31: 4 | H31: Incidental | I31: 947.53 | J31: 14.08.2008 | K31: Qualified | L31: 80 | M31: 4/5 | N31: -1.86 | O31: 1 | P31: -2.86 | Q31: 10.46 | R31: 7.06 | S31: 3.4 | T31: 8.43 | U31: 4.2 | V31: 4.23 | W31: 3.11 | X31: -1.2 | Y31: 4.31 | Z31: 2.7 | AA31: -0.03 | AB31: 2.73 | AC31: =IF(OR(P31="",BL31="",BL31=0),"",P31/BL31) | AD31: =IF(OR(S31="",BL31="",BL31=0),"",S31/BL31) | AE31: =IF(OR(V31="",BL31="",BL31=0),"",V31/BL31) | AF31: =IF(OR(Y31="",BL31="",BL31=0),"",Y31/BL31) | AG31: =IF(OR(AB31="",BL31="",BL31=0),"",AB31/BL31) | AH31: 76.5 | AI31: 17.1 | AK31: 6.4 | AN31: 11 | AR31: 2.1 | AT31: 4 | AZ31: 12.4 | BC31: 17.4 | BE31: 19 | BF31: 9.7 | BG31: 8.3 | BK31: Tenaga Nasional Berhad | Telekom Malaysia Berhad | NVIDIA Corporation | Gamuda Berhad | Malayan Cement Berhad | BL31: 8.5 | BM31: Moderate | BN31: Equity Malaysia Domestic | BP31: 0.4479 | BQ31: 2014-07-07 | BR31: 0.415 | BS31: -7.35 | BT31: 4291
A32: PB SMALLCAP GROWTH FUND | B32: PBSCGF | C32: Conventional | D32: Equity | E32: Malaysia | F32: Capital Growth | G32: 5 | H32: Incidental | I32: 128.85 | J32: 13.01.2016 | K32: Qualified | L32: 80 | M32: 4/5 | N32: -0.21 | O32: 0.01 | P32: -0.22 | Q32: 15.79 | R32: -0.45 | S32: 16.24 | T32: 4.89 | U32: 1.06 | V32: 3.83 | W32: 2.29 | X32: -0.3 | Y32: 2.59 | Z32: 4.32 | AA32: 0.81 | AB32: 3.51 | AC32: =IF(OR(P32="",BL32="",BL32=0),"",P32/BL32) | AD32: =IF(OR(S32="",BL32="",BL32=0),"",S32/BL32) | AE32: =IF(OR(V32="",BL32="",BL32=0),"",V32/BL32) | AF32: =IF(OR(Y32="",BL32="",BL32=0),"",Y32/BL32) | AG32: =IF(OR(AB32="",BL32="",BL32=0),"",AB32/BL32) | AH32: 75.7 | AI32: 16.9 | AK32: 7.4 | AN32: 11.7 | AQ32: 5.2 | AZ32: 45.9 | BB32: 7.2 | BC32: 8.1 | BE32: 22.7 | BJ32: 6.3 | BK32: Spritzer Berhad | Malaysian Pacific Industries Berhad | Hume Cement Industries Berhad | Southern Cable Group Berhad | UWC Berhad | BL32: 11.6 | BM32: High | BN32: Equity Malaysia Small & | BO32: measure of fund performance. ThebenchmarkforPBSCGFisacompositeof90%FTSEBursaMalaysiaSmall Cap Index and 10% 3-Month Kuala Lumpur Interbank Offered Rate (KLIBOR). Underlying index data are sourced from Lipper and Bank Negara Malaysia. | BP32: 0.3595 | BQ32: 2024-06-14 | BR32: 0.3058 | BS32: -14.94 | BT32: 661
A33: PUBLIC CHINA TITANS FUND | B33: PCTF | C33: Conventional | D33: Equity | E33: Greater China | F33: Capital Growth | G33: 5 | H33: Incidental | I33: 895.94 | J33: 01.04.2008 | K33: Qualified | L33: 80 | M33: 4/5 | N33: 0.31 | O33: 2.62 | P33: -2.31 | Q33: 8.7 | R33: 7.86 | S33: 0.84 | T33: 16.33 | U33: 13.6 | V33: 2.73 | W33: 2.83 | X33: 2.11 | Y33: 0.72 | Z33: 8.24 | AA33: 6.53 | AB33: 1.71 | AC33: =IF(OR(P33="",BL33="",BL33=0),"",P33/BL33) | AD33: =IF(OR(S33="",BL33="",BL33=0),"",S33/BL33) | AE33: =IF(OR(V33="",BL33="",BL33=0),"",V33/BL33) | AF33: =IF(OR(Y33="",BL33="",BL33=0),"",Y33/BL33) | AG33: =IF(OR(AB33="",BL33="",BL33=0),"",AB33/BL33) | AI33: 84.6 | AK33: 15.4 | AN33: 7.9 | AO33: 31.5 | AT33: 7 | AZ33: 7.9 | BA33: 30.3 | BB33: 20.2 | BC33: 25.1 | BE33: 1.1 | BK33: Taiwan Semiconductor Manufacturing Company Limited | Alibaba Group Holding Limited - W | China Construction Bank Corporation - H Shares | Tencent Holdings Limited | Delta Electronics Incorporated | BL33: 16 | BM33: Very High | BN33: Equity Greater China Greater China | BO33: 2020 0.50 29.5.20 1.6 The benchmark for PCTF is a composite of 40% Hang Seng China Enterprises 2021 0.75 31.5.21 2.0 Index (HSCEI), 30% Hang Seng Index (HSI) and 30% FTSE TWSE Taiwan 50 Index(priorto30April2016),30%MSCITaiwanLargeCapIndex(30April2016to 2022 0.50 31.5.22 1.7 29 April 2021), 30% S&P Taiwan LargeCap Index (w.e.f. 30 April 2021). Note: Distribution yield simply measures the level of distributions and is UnderlyingindexdataaresourcedfromLipperandS&PDowJonesIndices,LLC not a measure of fund performance. and expressed in Ringgit terms. | BP33: 0.4627 | BQ33: 2025-10-03 | BR33: 0.4085 | BS33: -11.71 | BT33: 185
A34: PUBLIC ISLAMIC GROWTH & INCOME FUND | B34: PISGIF | C34: Shariah | D34: Equity | E34: Malaysia | F34: Capital Growth + Income | G34: 4 | H34: Annual | I34: 122.12 | J34: 07.01.2014 | K34: Qualified | L34: 80 | M34: 4/5 | N34: 1.05 | O34: 1 | P34: 0.05 | Q34: 6.87 | R34: 7.06 | S34: -0.19 | T34: 6.8 | U34: 4.2 | V34: 2.6 | W34: 2.19 | X34: -1.2 | Y34: 3.39 | Z34: 2.48 | AA34: -0.03 | AB34: 2.51 | AC34: =IF(OR(P34="",BL34="",BL34=0),"",P34/BL34) | AD34: =IF(OR(S34="",BL34="",BL34=0),"",S34/BL34) | AE34: =IF(OR(V34="",BL34="",BL34=0),"",V34/BL34) | AF34: =IF(OR(Y34="",BL34="",BL34=0),"",Y34/BL34) | AG34: =IF(OR(AB34="",BL34="",BL34=0),"",AB34/BL34) | AH34: 75.7 | AI34: 20.8 | AK34: 3.5 | AN34: 9.4 | AO34: 6.4 | AR34: 5 | AZ34: 13.2 | BB34: 18.8 | BC34: 22.4 | BF34: 10.2 | BG34: 10.7 | BK34: Tenaga Nasional Berhad | Telekom Malaysia Berhad | Gamuda Berhad | IHH Healthcare Berhad | Taiwan Semiconductor Manufacturing Company Limited | BL34: 6.2 | BM34: Low | BN34: Equity Malaysia Domestic | BO34: 2022 0.20 30.12.22 0.9 | BP34: 0.2735 | BQ34: 2025-10-02 | BR34: 0.2601 | BS34: -4.9 | BT34: 186
A35: PUBLIC STRATEGIC GROWTH FUND | B35: PSTGF | C35: Conventional | D35: Equity | E35: Malaysia | F35: Capital Growth | G35: 4 | H35: Incidental | I35: 388.9 | J35: 08.12.2014 | K35: Qualified | L35: 80 | M35: 4/5 | N35: 4.68 | O35: 2.55 | P35: 2.13 | Q35: 8.79 | R35: 10.23 | S35: -1.44 | T35: 10.73 | U35: 8.2 | V35: 2.53 | W35: 4.49 | X35: 3.41 | Y35: 1.08 | Z35: 8.23 | AA35: 4.01 | AB35: 4.22 | AC35: =IF(OR(P35="",BL35="",BL35=0),"",P35/BL35) | AD35: =IF(OR(S35="",BL35="",BL35=0),"",S35/BL35) | AE35: =IF(OR(V35="",BL35="",BL35=0),"",V35/BL35) | AF35: =IF(OR(Y35="",BL35="",BL35=0),"",Y35/BL35) | AG35: =IF(OR(AB35="",BL35="",BL35=0),"",AB35/BL35) | AH35: 61.2 | AI35: 18.9 | AK35: 19.9 | AN35: 6.2 | AO35: 4.9 | AP35: 7.8 | AZ35: 19.3 | BA35: 4.9 | BB35: 34.7 | BE35: 7.2 | BF35: 6.8 | BK35: Malayan Banking Berhad | Public Bank Berhad | Tenaga Nasional Berhad | HD Hyundai Electric Company Limited | Taiwan Semiconductor Manufacturing Company Limited | BL35: 6.9 | BM35: Low | BN35: Equity Malaysia Domestic 30% of the fund’s NAV | BO35: ThebenchmarkforPSTGFisacompositeof60%FTSEBursaMalaysiaKLCI,15% DowJonesIndustrialAverage,15%customisedindexbyMSCIbasedonthetop30 constituents of MSCI AC Far-East Ex-Japan Index (prior to 30 April 2021), 15% customisedindexbyS&PDowJonesIndices,LLCbasedonthetop30constituents oftheS&PBMIAsiaEx-JapanIndex(w.e.f.30April2021)and10%3-MonthKuala Lumpur Interbank Offered Rate (KLIBOR). UnderlyingindexdataaresourcedfromLipper,S&PDowJonesIndices,LLCand Bank Negara Malaysia and expressed in Ringgit terms. | BP35: 0.4912 | BQ35: 2026-02-26 | BR35: 0.4635 | BS35: -5.64 | BT35: 39
A36: PB ISLAMIC ASIA STRATEGIC SECTOR FUND | B36: PBIASSF | C36: Conventional | D36: Equity | E36: Asia | F36: Capital Growth | G36: 5 | H36: Incidental | I36: 100.08 | J36: 06.09.2007 | K36: Qualified | L36: 80 | M36: 4/5 | N36: 21.38 | O36: 19.33 | P36: 2.05 | Q36: 44.95 | R36: 37.52 | S36: 7.43 | T36: 18.24 | U36: 16.02 | V36: 2.22 | W36: 2.63 | X36: 3.33 | Y36: -0.7 | Z36: 9.23 | AA36: 8.69 | AB36: 0.54 | AC36: =IF(OR(P36="",BL36="",BL36=0),"",P36/BL36) | AD36: =IF(OR(S36="",BL36="",BL36=0),"",S36/BL36) | AE36: =IF(OR(V36="",BL36="",BL36=0),"",V36/BL36) | AF36: =IF(OR(Y36="",BL36="",BL36=0),"",Y36/BL36) | AG36: =IF(OR(AB36="",BL36="",BL36=0),"",AB36/BL36) | AI36: 91.6 | AK36: 8.4 | AO36: 37.7 | AP36: 35.7 | AQ36: 2.8 | AT36: 15.4 | AZ36: 23.8 | BA36: 49.4 | BC36: 16.7 | BE36: 1.7 | BK36: Samsung Electronics Company Limited | Taiwan Semiconductor Manufacturing Company Limited | SK Hynix Incorporated | HD Hyundai Electric Company Limited | Alibaba Group Holding Limited - W | BL36: 19.4 | BM36: Very High | BN36: Equity Asia Pacific Asia | BO36: ThebenchmarkforPBIASSFisacompositeof90%DowJonesIslamicMarketAsia Ex-JapanIndexSM(priorto1January2009),90%S&PShariahBMIAsiaEx-Japan Index(w.e.f. 1 January 2009) and 10% 3-Month Islamic Interbank MoneyMarket (IIMM) rate. Underlying indexdata are sourced from S&P Dow Jones Indices,LLC andBank Negara Malaysia and expressed in Ringgit terms. | BP36: 0.5211 | BQ36: 2026-02-26 | BR36: 0.4814 | BS36: -7.62 | BT36: 39
A37: PUBLIC CHINA ITTIKAL FUND | B37: PCIF | C37: Shariah | D37: Equity | E37: Malaysia | F37: Capital Growth | G37: 5 | H37: Incidental | I37: 748.66 | J37: 20.11.2007 | K37: Qualified | L37: 80 | M37: 4/5 | N37: 9.35 | O37: 3.94 | P37: 5.41 | Q37: 15.83 | R37: 7.12 | S37: 8.71 | T37: 13.36 | U37: 11.48 | V37: 1.88 | W37: 0.89 | X37: 0.69 | Y37: 0.2 | Z37: 7.58 | AA37: 7.89 | AB37: -0.31 | AC37: =IF(OR(P37="",BL37="",BL37=0),"",P37/BL37) | AD37: =IF(OR(S37="",BL37="",BL37=0),"",S37/BL37) | AE37: =IF(OR(V37="",BL37="",BL37=0),"",V37/BL37) | AF37: =IF(OR(Y37="",BL37="",BL37=0),"",Y37/BL37) | AG37: =IF(OR(AB37="",BL37="",BL37=0),"",AB37/BL37) | AI37: 92.3 | AK37: 7.7 | AN37: 4 | AO37: 58.8 | AP37: 1.6 | AT37: 27.9 | AZ37: 21.7 | BA37: 35.1 | BC37: 31.3 | BD37: 2.7 | BE37: 1.5 | BK37: Taiwan Semiconductor Manufacturing Company Limited | Alibaba Group Holding Limited - W | Unimicron Technology Corporation | Delta Electronics Incorporated | Asia Vital Components Company Limited | BL37: 15.5 | BM37: Very High | BN37: Equity Greater China Greater China | BO37: ThebenchmarkforPCIFisacompositeof50%DowJonesIslamicMarketHong KongIndexSM(priorto1January2009),50%S&PShariahBMIHongKongand China'H'SharesIndex(w.e.f.1January2009),30%DowJonesIslamicMarket TaiwanIndexSM(priorto1January2009),30%S&PShariahBMITaiwanIndex (w.e.f.1January2009)and20%FTSEBursaMalaysiaEMASShariahIndex(prior to30April2011),20%FTSEBursaMalaysiaHijrahShariahIndex(w.e.f.30April 2011). UnderlyingindexdataaresourcedfromS&PDowJonesIndices,LLCandLipper and expressed in Ringgit terms. | BP37: 0.4999 | BQ37: 2021-02-17 | BR37: 0.4656 | BS37: -6.86 | BT37: 1874
A38: PUBLIC SELECT ALPHA-30 FUND | B38: PSA30F | C38: Conventional | D38: Equity | E38: Malaysia | F38: Capital Growth | G38: 4 | H38: Incidental | I38: 56.18 | J38: 07.04.2009 | K38: Qualified | L38: 80 | M38: 4/5 | N38: 1.24 | O38: 2.17 | P38: -0.93 | Q38: 10.35 | R38: 9.01 | S38: 1.34 | T38: 7.37 | U38: 5.69 | V38: 1.68 | W38: 2.01 | X38: 1.7 | Y38: 0.31 | Z38: 4.25 | AA38: 0.37 | AB38: 3.88 | AC38: =IF(OR(P38="",BL38="",BL38=0),"",P38/BL38) | AD38: =IF(OR(S38="",BL38="",BL38=0),"",S38/BL38) | AE38: =IF(OR(V38="",BL38="",BL38=0),"",V38/BL38) | AF38: =IF(OR(Y38="",BL38="",BL38=0),"",Y38/BL38) | AG38: =IF(OR(AB38="",BL38="",BL38=0),"",AB38/BL38) | AH38: 76 | AI38: 19.8 | AK38: 4.2 | AN38: 14.5 | AR38: 2.4 | AT38: 2.9 | AZ38: 15.5 | BA38: 6.8 | BB38: 34.1 | BC38: 16.9 | BF38: 10 | BK38: Malayan Banking Berhad | Tenaga Nasional Berhad | Public Bank Berhad | Meta Platforms Incorporated | NVIDIA Corporation | BL38: 8 | BM38: Moderate | BN38: Equity Malaysia Domestic 30% of the fund’s NAV | BO38: Kuala Lumpur Composite Index (prior to 6 July 2009). FTSE Bursa Malaysia KLCI (w.e.f. 6 July 2009). | BP38: 0.3857 | BQ38: 2025-10-09 | BR38: 0.3639 | BS38: -5.65 | BT38: 179
A39: PUBLIC INDEX FUND | B39: PIX | C39: Shariah | D39: Equity | E39: Malaysia | F39: Capital Growth | G39: 4 | H39: Incidental | I39: 495.38 | J39: 02.03.1992 | K39: Qualified | L39: 80 | M39: 4/5 | N39: 1.08 | O39: 2.7 | P39: -1.62 | Q39: 11.45 | R39: 8.15 | S39: 3.3 | T39: 8.19 | U39: 6.58 | V39: 1.61 | W39: 4.04 | X39: 1.93 | Y39: 2.11 | Z39: 2.86 | AA39: 1.04 | AB39: 1.82 | AC39: =IF(OR(P39="",BL39="",BL39=0),"",P39/BL39) | AD39: =IF(OR(S39="",BL39="",BL39=0),"",S39/BL39) | AE39: =IF(OR(V39="",BL39="",BL39=0),"",V39/BL39) | AF39: =IF(OR(Y39="",BL39="",BL39=0),"",Y39/BL39) | AG39: =IF(OR(AB39="",BL39="",BL39=0),"",AB39/BL39) | AH39: 96.5 | AK39: 3.5 | AZ39: 11.7 | BB39: 46.8 | BC39: 10.2 | BE39: 13.3 | BF39: 9.7 | BK39: Public Bank Berhad | LPI Capital Berhad | Tenaga Nasional Berhad | Malayan Banking Berhad | CIMB Group Holdings Berhad | BL39: 7.8 | BM39: Moderate | BN39: Equity Malaysia 100% Domestic | BO39: Kuala Lumpur Composite Index (prior to 6 July 2009). FTSE Bursa Malaysia Top 100 Index (w.e.f. 6 July 2009). Underlying index data are sourced from Lipper. | BP39: 1.101 | BQ39: 2008-01-11 | BR39: 0.7036 | BS39: -36.09 | BT39: 6660
A40: PB GLOBAL TECHNOLOGY & HEALTHCARE FUND | B40: PBGTHF | C40: Conventional | D40: Equity | E40: Global | F40: Capital Growth | G40: 5 | H40: Incidental | I40: 477.57 | J40: 09.05.2019 | K40: Qualified | L40: 75 | M40: 3/4 | N40: 1.64 | O40: -1.75 | P40: 3.39 | Q40: 17.86 | R40: 6.21 | S40: 11.65 | T40: 22.13 | U40: 14.86 | V40: 7.27 | W40: 11.37 | X40: 11.4 | Y40: -0.03 | AC40: =IF(OR(P40="",BL40="",BL40=0),"",P40/BL40) | AD40: =IF(OR(S40="",BL40="",BL40=0),"",S40/BL40) | AE40: =IF(OR(V40="",BL40="",BL40=0),"",V40/BL40) | AF40: =IF(OR(Y40="",BL40="",BL40=0),"",Y40/BL40) | AG40: =IF(OR(AB40="",BL40="",BL40=0),"",AB40/BL40) | AI40: 91.5 | AK40: 8.5 | AN40: 45.2 | AO40: 14.7 | AP40: 19.1 | AT40: 5.7 | AV40: 4.6 | AZ40: 11.3 | BA40: 49.1 | BC40: 15.7 | BD40: 2 | BJ40: 13.4 | BK40: Samsung Electronics Company Limited | SK Hynix Incorporated | Apple Incorporated | Taiwan Semiconductor Manufacturing Company Limited | HD Hyundai Electric Company Limited | BL40: 15.5 | BM40: Very High | BN40: Equity Global Global | BO40: 2022 1.25 30.06.22 3.7 ThebenchmarkforPBGTHFisacompositeof50%S&PGlobal1200Information Note: Distribution yield simply measures the level of distributions and is not a TechnologyIndex, 40% S&P Global 1200 Health Care Index and 10% 1-Month measure of fund performance. Kuala Lumpur Interbank Offered Rate (KLIBOR). Underlying index data are sourced from Lipper and Bank Negara Malaysia and expressed in Ringgit terms. | BP40: 0.625 | BQ40: 2025-11-03 | BR40: 0.5658 | BS40: -9.47 | BT40: 154
A41: PUBLIC OPTIMAL EQUITY FUND | B41: POEF | C41: Conventional | D41: Equity | E41: Malaysia | F41: Capital Growth | G41: 5 | H41: Incidental | I41: 29.8 | J41: 26.07.2016 | K41: Qualified | L41: 75 | M41: 3/4 | N41: 19.08 | O41: 6.72 | P41: 12.36 | Q41: 25.28 | R41: 18.35 | S41: 6.93 | T41: 15.27 | U41: 12.27 | V41: 3 | W41: 0.11 | X41: 2.62 | Y41: -2.51 | AC41: =IF(OR(P41="",BL41="",BL41=0),"",P41/BL41) | AD41: =IF(OR(S41="",BL41="",BL41=0),"",S41/BL41) | AE41: =IF(OR(V41="",BL41="",BL41=0),"",V41/BL41) | AF41: =IF(OR(Y41="",BL41="",BL41=0),"",Y41/BL41) | AG41: =IF(OR(AB41="",BL41="",BL41=0),"",AB41/BL41) | AI41: 90.3 | AK41: 9.7 | AN41: 2.9 | AO41: 37.4 | AP41: 30.7 | AT41: 19.3 | AZ41: 26 | BA41: 48.1 | BB41: 3.5 | BC41: 11.4 | BD41: 1.3 | BK41: Samsung Electronics Company Limited | SK Hynix Incorporated | Alibaba Group Holding Limited - W | Taiwan Semiconductor Manufacturing Company Limited | Chroma ATE Incorporated | BL41: 17.6 | BM41: Very High | BN41: Equity Asia Pacific Asia | BO41: Note: Distribution yield simply measures the level of distributions and is ThebenchmarkforPOEFisacompositeof50%customisedindexbyMSCIbased not a measure of fund performance. onthetop30constituentsofMSCIACFar-EastEx-JapanIndex(priorto30April 2021),50%customisedindexbyS&PDowJonesIndices,LLCbasedonthetop30 constituentsoftheS&PBMIAsiaEx-JapanIndex(w.e.f.30April2021),40%FTSE Bursa Malaysia KLCI and 10% 3-Month Kuala Lumpur Interbank Offered Rate (KLIBOR). UnderlyingindexdataaresourcedfromS&PDowJonesIndices,LLC,Lipperand Bank Negara Malaysia and expressed in Ringgit terms. | BP41: 0.4172 | BQ41: 2021-02-17 | BR41: 0.3275 | BS41: -21.5 | BT41: 1874
A42: PUBLIC ISLAMIC OPTIMAL EQUITY FUND | B42: PIOEF | C42: Shariah | D42: Equity | E42: Malaysia | F42: Capital Growth | G42: 5 | H42: Incidental | I42: 55.45 | J42: 26.07.2016 | K42: Qualified | L42: 75 | M42: 3/4 | N42: 19.68 | O42: 10.53 | P42: 9.15 | Q42: 25.69 | R42: 23.49 | S42: 2.2 | T42: 14.67 | U42: 11.7 | V42: 2.97 | W42: -0.6 | X42: 2.07 | Y42: -2.67 | AC42: =IF(OR(P42="",BL42="",BL42=0),"",P42/BL42) | AD42: =IF(OR(S42="",BL42="",BL42=0),"",S42/BL42) | AE42: =IF(OR(V42="",BL42="",BL42=0),"",V42/BL42) | AF42: =IF(OR(Y42="",BL42="",BL42=0),"",Y42/BL42) | AG42: =IF(OR(AB42="",BL42="",BL42=0),"",AB42/BL42) | AI42: 88 | AK42: 12 | AN42: 7.1 | AO42: 44.5 | AP42: 19.9 | AT42: 16.5 | AZ42: 25.3 | BA42: 42.9 | BC42: 8 | BD42: 11.8 | BK42: Taiwan Semiconductor Manufacturing Company Limited | Unimicron Technology Corporation | Samsung Electronics Company Limited | Alibaba Group Holding Limited - W | SK Hynix Incorporated | BL42: 16.1 | BM42: Very High | BN42: Equity Asia Pacific Asia | BP42: 0.4764 | BQ42: 2021-02-17 | BR42: 0.3823 | BS42: -19.75 | BT42: 1874
A43: PB ISLAMIC SMALLCAP FUND | B43: PBISCF | C43: Conventional | D43: Equity | E43: Malaysia | F43: Capital Growth | G43: 5 | H43: Incidental | I43: 112.66 | J43: 28.03.2017 | K43: Qualified | L43: 75 | M43: 3/4 | N43: -2.78 | O43: -1.51 | P43: -1.27 | Q43: 0.71 | R43: -0.19 | S43: 0.9 | T43: 2.77 | U43: 1.3 | V43: 1.47 | W43: 0.95 | X43: -1 | Y43: 1.95 | AC43: =IF(OR(P43="",BL43="",BL43=0),"",P43/BL43) | AD43: =IF(OR(S43="",BL43="",BL43=0),"",S43/BL43) | AE43: =IF(OR(V43="",BL43="",BL43=0),"",V43/BL43) | AF43: =IF(OR(Y43="",BL43="",BL43=0),"",Y43/BL43) | AG43: =IF(OR(AB43="",BL43="",BL43=0),"",AB43/BL43) | AH43: 18 | AI43: 75.9 | AK43: 6.1 | AN43: 4 | AO43: 5.7 | AP43: 5.4 | AQ43: 2.9 | AZ43: 54.1 | BA43: 7.5 | BB43: 6.3 | BE43: 13 | BJ43: 3.4 | BK43: Kelington Group Berhad | Spritzer Berhad | Frontken Corporation Berhad | AME Elite Consortium Berhad | Taiwan Semiconductor Manufacturing Company Limited | BL43: 11.4 | BM43: High | BN43: Equity Malaysia Small & | BO43: Index data are sourced from Lipper. | BP43: 0.4582 | BQ43: 2022-01-04 | BR43: 0.3241 | BS43: -29.27 | BT43: 1553
A44: PB ASIA-30 EQUITY FUND | B44: PBA30EF | C44: Conventional | D44: Equity | E44: Asia | F44: Capital Growth | G44: 5 | H44: Incidental | I44: 341.17 | J44: 26.07.2018 | K44: Qualified | L44: 75 | M44: 3/4 | N44: 21.3 | O44: 9.35 | P44: 11.95 | Q44: 34.66 | R44: 24.76 | S44: 9.9 | T44: 17.11 | U44: 16.43 | V44: 0.68 | W44: 0.85 | X44: 2.86 | Y44: -2.01 | AC44: =IF(OR(P44="",BL44="",BL44=0),"",P44/BL44) | AD44: =IF(OR(S44="",BL44="",BL44=0),"",S44/BL44) | AE44: =IF(OR(V44="",BL44="",BL44=0),"",V44/BL44) | AF44: =IF(OR(Y44="",BL44="",BL44=0),"",Y44/BL44) | AG44: =IF(OR(AB44="",BL44="",BL44=0),"",AB44/BL44) | AI44: 90.1 | AK44: 9.9 | AO44: 32.9 | AP44: 29.1 | AQ44: 8.1 | AT44: 20 | AZ44: 26.7 | BA44: 47.2 | BB44: 3.1 | BC44: 13.1 | BK44: SK Hynix Incorporated | Taiwan Semiconductor Manufacturing Company Limited | Samsung Electronics Company Limited | Alibaba Group Holding Limited - W | HD Hyundai Electric Company Limited | BL44: 18.6 | BM44: Very High | BN44: Equity Asia Pacific Asia | BO44: The benchmark for PBA30EF is a composite of 80% customised index byMSCI based on the top 30 constituents of MSCI AC Far-East Ex-Japan Index (prior to 30April2021),80%customisedindexbyS&PDowJonesIndices,LLCbasedon thetop30constituentsoftheS&PBMIAsiaEx-JapanIndex(w.e.f.30April2021), 10%TokyoStock Price Indexand10%3-MonthKualaLumpurInterbankOffered Rate (KLIBOR). UnderlyingindexdataaresourcedfromLipper,S&PDowJonesIndices,LLCand Bank Negara Malaysia and expressed in Ringgit terms. | BP44: 0.3996 | BQ44: 2021-02-17 | BR44: 0.3257 | BS44: -18.49 | BT44: 1874
A45: PUBLIC ISLAMIC U.S. SUSTAINABLE EQUITY FUND | B45: PIUSSEQF | C45: Shariah | D45: Equity | E45: United States | F45: Capital Growth | G45: 5 | H45: Incidental | I45: 489.16 | J45: 10.04.2019 | K45: Qualified | L45: 75 | M45: 3/4 | N45: -7.18 | O45: -3.49 | P45: -3.69 | Q45: 4.32 | R45: 1.95 | S45: 2.37 | T45: 16.83 | U45: 16.67 | V45: 0.16 | W45: 12.26 | X45: 12.21 | Y45: 0.05 | AC45: =IF(OR(P45="",BL45="",BL45=0),"",P45/BL45) | AD45: =IF(OR(S45="",BL45="",BL45=0),"",S45/BL45) | AE45: =IF(OR(V45="",BL45="",BL45=0),"",V45/BL45) | AF45: =IF(OR(Y45="",BL45="",BL45=0),"",Y45/BL45) | AG45: =IF(OR(AB45="",BL45="",BL45=0),"",AB45/BL45) | AI45: 93.1 | AK45: 6.9 | AN45: 75.4 | AQ45: 2.4 | AR45: 2 | AT45: 5.4 | AV45: 7.3 | BA45: 42.4 | BB45: 5 | BC45: 29.4 | BD45: 6.9 | BE45: 7.1 | BK45: Meta Platforms Incorporated | Microsoft Corporation | Alphabet Incorporated - Class A | Apple Incorporated | ASML Holding N.V. - NYS | BL45: 13.7 | BM45: Very High | BN45: Equity U.S. Global | BO45: The benchmark for PIUSSEQF is a composite of 90% S&P United States LargeCapShariahIndex(priorto26February2025),90%S&PGlobal1200U.S. LargeCapESGShariah8%CappedIndex(w.e.f.26February2025)and10%3- Month Islamic Interbank Money Market (IIMM) rate. UnderlyingindexdataaresourcedfromS&PDowJonesIndices,LLCandBank Negara Malaysia and expressed in Ringgit terms. | BP45: 0.684 | BQ45: 2025-10-29 | BR45: 0.582 | BS45: -14.91 | BT45: 159
A46: PUBLIC e-ISLAMIC GROWTH FUND | B46: PeIGRF | C46: Shariah | D46: Equity | E46: Malaysia | F46: Capital Growth | G46: 4 | H46: Incidental | I46: 70.95 | J46: 10.12.2021 | K46: Qualified | L46: 66.7 | M46: 2/3 | N46: -2.6 | O46: 0.96 | P46: -3.56 | Q46: 8.82 | R46: 6.76 | S46: 2.06 | T46: 6.19 | U46: 4.19 | V46: 2 | AC46: =IF(OR(P46="",BL46="",BL46=0),"",P46/BL46) | AD46: =IF(OR(S46="",BL46="",BL46=0),"",S46/BL46) | AE46: =IF(OR(V46="",BL46="",BL46=0),"",V46/BL46) | AF46: =IF(OR(Y46="",BL46="",BL46=0),"",Y46/BL46) | AG46: =IF(OR(AB46="",BL46="",BL46=0),"",AB46/BL46) | AH46: 16.8 | AI46: 75.4 | AK46: 7.8 | AN46: 13.8 | AO46: 3 | AZ46: 16 | BA46: 8.4 | BC46: 22.4 | BE46: 15.4 | BF46: 9.6 | BK46: Tenaga Nasional Berhad | Press Metal Aluminium Holdings Berhad | Telekom Malaysia Berhad | TIME dotCom Berhad | IHH Healthcare Berhad | BL46: 9.1 | BM46: Moderate | BN46: Equity Malaysia | BO46: Thebenchmark for PeIGRFis acomposite of90% FTSE Bursa MalaysiaEMAS Shariah Index and 10% 3-Month Islamic Interbank Money Market (IIMM) rate. Underlying index data are sourced from Lipper and Bank Negara Malaysia. | BP46: 0.2913 | BQ46: 2026-01-27 | BR46: 0.2743 | BS46: -5.84 | BT46: 69
A47: PUBLIC e-CARBON EFFICIENT FUND | B47: PeCEF | C47: Conventional | D47: Equity | E47: Malaysia | F47: Capital Growth | G47: 5 | H47: Incidental | I47: 390.87 | J47: 09.02.2021 | K47: Qualified | L47: 66.7 | M47: 2/3 | N47: -0.71 | O47: -0.31 | P47: -0.4 | Q47: 10.23 | R47: 8.22 | S47: 2.01 | T47: 17.01 | U47: 15.26 | V47: 1.75 | AC47: =IF(OR(P47="",BL47="",BL47=0),"",P47/BL47) | AD47: =IF(OR(S47="",BL47="",BL47=0),"",S47/BL47) | AE47: =IF(OR(V47="",BL47="",BL47=0),"",V47/BL47) | AF47: =IF(OR(Y47="",BL47="",BL47=0),"",Y47/BL47) | AG47: =IF(OR(AB47="",BL47="",BL47=0),"",AB47/BL47) | AI47: 86.8 | AK47: 13.2 | AN47: 51.6 | AO47: 9.8 | AQ47: 9 | AT47: 8.8 | AV47: 6.6 | AZ47: 5.7 | BA47: 35.2 | BB47: 5.9 | BC47: 27.2 | BD47: 12.8 | BK47: Taiwan Semiconductor Manufacturing Company Limited | Meta Platforms Incorporated | Alphabet Incorporated - Class A | Alibaba Group Holding Limited - W | Costco Wholesale Corporation | BL47: 13.8 | BM47: Very High | BN47: Equity Global Global | BO47: ThebenchmarkforPeCEFisacompositeof90%customisedindexbyS&PDow JonesIndices,LLCbasedontheconstituentswithlowercarbonfootprintoftheS&P Global1200Scored&ScreenedIndexand10%3-MonthKualaLumpurInterbank Offered Rate (KLIBOR). Underlying indexdata are sourced from S&P Dow Jones Indices, LLC and Bank Negara Malaysia and expressed in Ringgit terms. | BP47: 0.404 | BQ47: 2025-10-30 | BR47: 0.3616 | BS47: -10.5 | BT47: 158
A48: PUBLIC e-ISLAMIC ASIA THEMATIC GROWTH FUND | B48: PeIATGF | C48: Shariah | D48: Equity | E48: Asia | F48: Capital Growth | G48: 5 | H48: Incidental | I48: 484.57 | J48: 30.11.2021 | K48: Qualified | L48: 66.7 | M48: 2/3 | N48: 21.96 | O48: 21.16 | P48: 0.8 | Q48: 36.1 | R48: 41.58 | S48: -5.48 | T48: 19.72 | U48: 18.29 | V48: 1.43 | AC48: =IF(OR(P48="",BL48="",BL48=0),"",P48/BL48) | AD48: =IF(OR(S48="",BL48="",BL48=0),"",S48/BL48) | AE48: =IF(OR(V48="",BL48="",BL48=0),"",V48/BL48) | AF48: =IF(OR(Y48="",BL48="",BL48=0),"",Y48/BL48) | AG48: =IF(OR(AB48="",BL48="",BL48=0),"",AB48/BL48) | AI48: 80.3 | AK48: 19.7 | AN48: 2.7 | AO48: 38.7 | AP48: 28.7 | AT48: 10.2 | AZ48: 31.6 | BA48: 37.2 | BC48: 10.2 | BD48: 1.3 | BK48: Taiwan Semiconductor Manufacturing Company Limited | Samsung Electronics Company Limited | SK Hynix Incorporated | Alibaba Group Holding Limited - W | HD Hyundai Electric Company Limited | BL48: 17.9 | BM48: Very High | BN48: Equity Asia Pacific ex- Asia | BO48: ThebenchmarkforPeIATGFisacustomisedindexbyS&PDowJonesIndices,LLC basedonthetop100constituentsbymarketcapitalisationoftheS&PShariahBMI Asia Ex-Japan Index. Underlying index data are sourced from S&P Dow Jones Indices, LLC and expressed in Ringgit terms. | BP48: 0.3416 | BQ48: 2026-02-26 | BR48: 0.3145 | BS48: -7.93 | BT48: 39
A49: PUBLIC ASIA PACIFIC ALPHA-40 FUND | B49: PAPA40F | C49: Conventional | D49: Equity | E49: Asia Pacific | F49: Capital Growth | G49: 5 | H49: Incidental | I49: 50.57 | J49: 10.12.2021 | K49: Qualified | L49: 66.7 | M49: 2/3 | N49: 10.69 | O49: 9.35 | P49: 1.34 | Q49: 26 | R49: 24.76 | S49: 1.24 | T49: 15.62 | U49: 16.43 | V49: -0.81 | AC49: =IF(OR(P49="",BL49="",BL49=0),"",P49/BL49) | AD49: =IF(OR(S49="",BL49="",BL49=0),"",S49/BL49) | AE49: =IF(OR(V49="",BL49="",BL49=0),"",V49/BL49) | AF49: =IF(OR(Y49="",BL49="",BL49=0),"",Y49/BL49) | AG49: =IF(OR(AB49="",BL49="",BL49=0),"",AB49/BL49) | AH49: 1 | AI49: 87.4 | AK49: 11.6 | AN49: 8.9 | AO49: 15.3 | AP49: 27.3 | AQ49: 4.1 | AT49: 24.2 | AZ49: 13.4 | BA49: 38.5 | BB49: 9.2 | BC49: 20.7 | BD49: 6.6 | BK49: SK Hynix Incorporated | Taiwan Semiconductor Manufacturing Company Limited | Samsung Electronics Company Limited | Alibaba Group Holding Limited - W | Tencent Holdings Limited | BL49: 16.1 | BM49: Very High | BN49: Equity Asia Pacific Asia | BO49: ThebenchmarkforPAPA40Fisacompositeof80%customisedindexbyS&PDow JonesIndices,LLCbasedonthetop30constituentsoftheS&PBMIAsiaEx-Japan Index, 10% Tokyo Stock Price Index (TOPIX) and 10% 3-Month Kuala Lumpur Interbank Offered Rate (KLIBOR). UnderlyingindexdataaresourcedfromS&PDowJonesIndices,LLC,Lipperand Bank Negara Malaysia and expressed in Ringgit terms. | BP49: 0.347 | BQ49: 2026-02-26 | BR49: 0.3162 | BS49: -8.88 | BT49: 39
A50: PUBLIC ITTIKAL SEQUEL FUND | B50: PITSEQ | C50: Shariah | D50: Equity | E50: Malaysia | F50: Capital Growth | G50: 4 | H50: Incidental | I50: 4272.24 | J50: 11.10.2011 | K50: Qualified | L50: 60 | M50: 3/5 | N50: -1.77 | O50: 1 | P50: -2.77 | Q50: 6.82 | R50: 7.06 | S50: -0.24 | T50: 11.77 | U50: 4.2 | V50: 7.57 | W50: 5.59 | X50: -1.2 | Y50: 6.79 | Z50: 5.34 | AA50: -0.03 | AB50: 5.37 | AC50: =IF(OR(P50="",BL50="",BL50=0),"",P50/BL50) | AD50: =IF(OR(S50="",BL50="",BL50=0),"",S50/BL50) | AE50: =IF(OR(V50="",BL50="",BL50=0),"",V50/BL50) | AF50: =IF(OR(Y50="",BL50="",BL50=0),"",Y50/BL50) | AG50: =IF(OR(AB50="",BL50="",BL50=0),"",AB50/BL50) | AH50: 77 | AI50: 19.2 | AK50: 3.8 | AN50: 14.7 | AO50: 4.5 | BA50: 10.1 | BB50: 17.1 | BC50: 21 | BE50: 16.7 | BF50: 9.6 | BK50: Sunway Berhad | Tenaga Nasional Berhad | Telekom Malaysia Berhad | Gamuda Berhad | QL Resources Berhad | BL50: 6.9 | BM50: Low | BN50: Equity Malaysia Domestic | BP50: 0.4356 | BQ50: 2026-01-27 | BR50: 0.4113 | BS50: -5.58 | BT50: 69
A51: PB GROWTH FUND | B51: PBGF | C51: Conventional | D51: Equity | E51: Malaysia | F51: Capital Growth | G51: 4 | H51: Incidental | I51: 597.82 | J51: 03.10.2002 | K51: Qualified | L51: 60 | M51: 3/5 | N51: -0.91 | O51: 2.17 | P51: -3.08 | Q51: 0.84 | R51: 9.01 | S51: -8.17 | T51: 11.05 | U51: 5.69 | V51: 5.36 | W51: 2.45 | X51: 1.7 | Y51: 0.75 | Z51: 4.43 | AA51: 0.37 | AB51: 4.06 | AC51: =IF(OR(P51="",BL51="",BL51=0),"",P51/BL51) | AD51: =IF(OR(S51="",BL51="",BL51=0),"",S51/BL51) | AE51: =IF(OR(V51="",BL51="",BL51=0),"",V51/BL51) | AF51: =IF(OR(Y51="",BL51="",BL51=0),"",Y51/BL51) | AG51: =IF(OR(AB51="",BL51="",BL51=0),"",AB51/BL51) | AH51: 78.8 | AI51: 7.9 | AK51: 13.3 | AN51: 4.5 | AT51: 3.4 | BB51: 30.6 | BC51: 20.8 | BE51: 12.4 | BF51: 7.6 | BH51: 7.2 | BK51: Malayan Banking Berhad | Public Bank Berhad | Sunway Berhad | Tenaga Nasional Berhad | TIME dotCom Berhad | BL51: 9.2 | BM51: Moderate | BN51: Equity Malaysia | BP51: 1.1461 | BQ51: 2007-12-31 | BR51: 0.9162 | BS51: -20.06 | BT51: 6671
A52: PUBLIC INDUSTRY GROWTH FUND | B52: PINDGF | C52: Shariah | D52: Equity | E52: Malaysia | F52: Capital Growth | G52: 4 | H52: Incidental | I52: 239.53 | J52: 18.11.1993 | K52: Qualified | L52: 60 | M52: 3/5 | N52: -0.19 | O52: 2.17 | P52: -2.36 | Q52: 8.84 | R52: 9.01 | S52: -0.17 | T52: 9.62 | U52: 5.69 | V52: 3.93 | W52: 2.06 | X52: 1.7 | Y52: 0.36 | Z52: 4.9 | AA52: 0.37 | AB52: 4.53 | AC52: =IF(OR(P52="",BL52="",BL52=0),"",P52/BL52) | AD52: =IF(OR(S52="",BL52="",BL52=0),"",S52/BL52) | AE52: =IF(OR(V52="",BL52="",BL52=0),"",V52/BL52) | AF52: =IF(OR(Y52="",BL52="",BL52=0),"",Y52/BL52) | AG52: =IF(OR(AB52="",BL52="",BL52=0),"",AB52/BL52) | AH52: 75.7 | AI52: 12.3 | AK52: 12 | AN52: 9.8 | AR52: 2.5 | AZ52: 8.9 | BB52: 24.2 | BC52: 16 | BD52: 6.9 | BF52: 11.4 | BK52: Public Bank Berhad | Tenaga Nasional Berhad | Malayan Banking Berhad | Telekom Malaysia Berhad | TIME dotCom Berhad | BL52: 6.6 | BM52: Low | BN52: Equity Malaysia Domestic 30% of the fund’s NAV | BP52: 0.9072 | BQ52: 2007-10-31 | BR52: 0.6314 | BS52: -30.4 | BT52: 6732
A53: PUBLIC REGULARSAVINGS FUND | B53: PRSF | C53: Conventional | D53: Equity | E53: Malaysia | F53: Capital Growth + Income | G53: 4 | H53: Annual | I53: 3633.1 | J53: 25.04.1994 | K53: Qualified | L53: 60 | M53: 3/5 | N53: 1.8 | O53: 2.48 | P53: -0.68 | Q53: 7.67 | R53: 7.73 | S53: -0.06 | T53: 9.97 | U53: 6.31 | V53: 3.66 | W53: 5.21 | X53: 2.09 | Y53: 3.12 | Z53: 4.67 | AA53: 1.31 | AB53: 3.36 | AC53: =IF(OR(P53="",BL53="",BL53=0),"",P53/BL53) | AD53: =IF(OR(S53="",BL53="",BL53=0),"",S53/BL53) | AE53: =IF(OR(V53="",BL53="",BL53=0),"",V53/BL53) | AF53: =IF(OR(Y53="",BL53="",BL53=0),"",Y53/BL53) | AG53: =IF(OR(AB53="",BL53="",BL53=0),"",AB53/BL53) | AH53: 75.6 | AI53: 15.9 | AK53: 8.5 | AN53: 10.1 | AR53: 5.8 | BB53: 41.9 | BC53: 10.1 | BD53: 11.2 | BE53: 7.6 | BF53: 9.7 | BK53: Public Bank Berhad | Malayan Banking Berhad | Tenaga Nasional Berhad | CIMB Group Holdings Berhad | Gamuda Berhad | BL53: 5.7 | BM53: Low | BN53: Equity Malaysia Domestic 25% of the fund’s NAV | BO53: Kuala Lumpur Composite Index (prior to 6 July 2009). FTSE BursaMalaysiaTop100Index(6July2009to29April2015),90%FTSE BursaMalaysiaTop100Indexand10%3-MonthKualaLumpurInterbankOffered Rate (KLIBOR) (w.e.f. 30 April 2015). Underlying index data are sourced from Lipper and Bank Negara Malaysia. | BP53: 1.09 | BQ53: 2000-02-17 | BR53: 0.6374 | BS53: -41.52 | BT53: 9545
A54: PUBLIC EQUITY FUND | B54: PEF | C54: Conventional | D54: Equity | E54: Malaysia | F54: Capital Growth | G54: 4 | H54: Incidental | I54: 462.09 | J54: 15.08.2001 | K54: Qualified | L54: 60 | M54: 3/5 | N54: 0.04 | O54: 2.17 | P54: -2.13 | Q54: 7.26 | R54: 9.01 | S54: -1.75 | T54: 8.74 | U54: 5.69 | V54: 3.05 | W54: 3.07 | X54: 1.7 | Y54: 1.37 | Z54: 2.52 | AA54: 0.37 | AB54: 2.15 | AC54: =IF(OR(P54="",BL54="",BL54=0),"",P54/BL54) | AD54: =IF(OR(S54="",BL54="",BL54=0),"",S54/BL54) | AE54: =IF(OR(V54="",BL54="",BL54=0),"",V54/BL54) | AF54: =IF(OR(Y54="",BL54="",BL54=0),"",Y54/BL54) | AG54: =IF(OR(AB54="",BL54="",BL54=0),"",AB54/BL54) | AH54: 72.4 | AI54: 25.4 | AK54: 2.2 | AN54: 19.2 | AR54: 2.5 | AT54: 3.7 | BA54: 7.2 | BB54: 37.7 | BC54: 24.9 | BF54: 9.9 | BH54: 6.5 | BK54: Malayan Banking Berhad | Tenaga Nasional Berhad | Public Bank Berhad | LPI Capital Berhad | Meta Platforms Incorporated | BL54: 6.1 | BM54: Low | BN54: Equity Malaysia Domestic 30% of the fund’s NAV | BO54: Note: Distribution yield simply measures the level of distributions and is Kuala Lumpur Composite Index (prior to 6 July 2009). not a measure of fund performance. FTSE Bursa Malaysia KLCI (w.e.f. 6 July 2009). | BP54: 0.4767 | BQ54: 2007-10-31 | BR54: 0.2505 | BS54: -47.45 | BT54: 6732
A55: PB EURO PACIFIC EQUITY FUND | B55: PBEPEF | C55: Conventional | D55: Equity | E55: Malaysia | F55: Capital Growth | G55: 5 | H55: Incidental | I55: 67.87 | J55: 08.06.2007 | K55: Qualified | L55: 60 | M55: 3/5 | N55: 7.36 | O55: 8.27 | P55: -0.91 | Q55: 19.3 | R55: 20.54 | S55: -1.24 | T55: 16.17 | U55: 13.17 | V55: 3 | W55: 7.53 | X55: 6.08 | Y55: 1.45 | Z55: 8.46 | AA55: 7.75 | AB55: 0.71 | AC55: =IF(OR(P55="",BL55="",BL55=0),"",P55/BL55) | AD55: =IF(OR(S55="",BL55="",BL55=0),"",S55/BL55) | AE55: =IF(OR(V55="",BL55="",BL55=0),"",V55/BL55) | AF55: =IF(OR(Y55="",BL55="",BL55=0),"",Y55/BL55) | AG55: =IF(OR(AB55="",BL55="",BL55=0),"",AB55/BL55) | AH55: 1 | AI55: 92.2 | AK55: 6.8 | AN55: 9.2 | AO55: 17 | AP55: 24.1 | AR55: 8.7 | AT55: 18.4 | AZ55: 16.4 | BA55: 36.9 | BB55: 1.1 | BC55: 26.6 | BD55: 12.2 | BK55: Taiwan Semiconductor Manufacturing Company Limited | Samsung Electronics Company Limited | Alibaba Group Holding Limited - W | Tencent Holdings Limited | HD Hyundai Electric Company Limited | BL55: 15.1 | BM55: Very High | BN55: Equity Global Asia | BP55: 0.4336 | BQ55: 2025-10-02 | BR55: 0.3877 | BS55: -10.59 | BT55: 186
A56: PUBLIC REGULAR SAVINGS SEQUEL FUND | B56: PRSSQF | C56: Conventional | D56: Equity | E56: Malaysia | F56: Capital Growth + Income | G56: 4 | H56: Annual | I56: 43.29 | J56: 15.01.2016 | K56: Qualified | L56: 60 | M56: 3/5 | N56: -0.36 | O56: 2.48 | P56: -2.84 | Q56: 3.99 | R56: 7.73 | S56: -3.74 | T56: 8.27 | U56: 6.31 | V56: 1.96 | W56: 4.07 | X56: 2.09 | Y56: 1.98 | Z56: 3.45 | AA56: 1.31 | AB56: 2.14 | AC56: =IF(OR(P56="",BL56="",BL56=0),"",P56/BL56) | AD56: =IF(OR(S56="",BL56="",BL56=0),"",S56/BL56) | AE56: =IF(OR(V56="",BL56="",BL56=0),"",V56/BL56) | AF56: =IF(OR(Y56="",BL56="",BL56=0),"",Y56/BL56) | AG56: =IF(OR(AB56="",BL56="",BL56=0),"",AB56/BL56) | AH56: 74.5 | AI56: 16.8 | AK56: 8.7 | AN56: 12 | AR56: 4.8 | AZ56: 11.5 | BB56: 24.2 | BC56: 15.6 | BD56: 12.9 | BE56: 11.7 | BK56: Public Bank Berhad | Tenaga Nasional Berhad | Telekom Malaysia Berhad | Tesla Incorporated | Malayan Cement Berhad | BL56: 7.8 | BM56: Moderate | BN56: Equity Malaysia Domestic 25% of the fund’s NAV | BO56: 2024 0.40 29.2.24 1.5 ThebenchmarkforPRSSQFisacompositeof90%FTSEBursaMalaysiaTop100 Index and 10% 3-Month Kuala Lumpur Interbank Offered Rate (KLIBOR). 2025 0.45 28.2.25 1.6 Underlying index data are sourced from Lipper and Bank Negara Malaysia. 2026 0.46 27.2.26 1.6 Note: Distribution yield simply measures the level of distributions and is | BP56: 0.3154 | BQ56: 2024-12-17 | BR56: 0.2881 | BS56: -8.66 | BT56: 475
A57: PUBLIC OPTIMAL GROWTH FUND | B57: POGF | C57: Conventional | D57: Equity | E57: Malaysia | F57: Capital Growth + Income | G57: 4 | H57: Annual | I57: 215.06 | J57: 08.06.2010 | K57: Qualified | L57: 60 | M57: 3/5 | N57: 0.94 | O57: 2.7 | P57: -1.76 | Q57: 5.49 | R57: 8.15 | S57: -2.66 | T57: 8.42 | U57: 6.58 | V57: 1.84 | W57: 4.25 | X57: 1.93 | Y57: 2.32 | Z57: 4.13 | AA57: 1.04 | AB57: 3.09 | AC57: =IF(OR(P57="",BL57="",BL57=0),"",P57/BL57) | AD57: =IF(OR(S57="",BL57="",BL57=0),"",S57/BL57) | AE57: =IF(OR(V57="",BL57="",BL57=0),"",V57/BL57) | AF57: =IF(OR(Y57="",BL57="",BL57=0),"",Y57/BL57) | AG57: =IF(OR(AB57="",BL57="",BL57=0),"",AB57/BL57) | AH57: 77.4 | AI57: 17 | AK57: 5.6 | AN57: 6.2 | AO57: 3.2 | AS57: 5.1 | AT57: 2.5 | AZ57: 14.3 | BB57: 41.2 | BC57: 16.7 | BE57: 8.3 | BF57: 7.3 | BK57: Malayan Banking Berhad | Public Bank Berhad | Tenaga Nasional Berhad | Sunway Berhad | IGB Real Estate Investment Trust | BL57: 8.9 | BM57: Moderate | BN57: Equity Malaysia Income Domestic 25% of the fund’s NAV | BP57: 0.3813 | BQ57: 2024-07-11 | BR57: 0.343 | BS57: -10.04 | BT57: 634
A58: PUBLIC ISLAMIC DIVIDEND FUND | B58: PIDF | C58: Shariah | D58: Equity | E58: Malaysia | F58: Income | G58: 4 | H58: Semi-Annual | I58: 3347.73 | J58: 14.02.2006 | K58: Qualified | L58: 60 | M58: 3/5 | N58: -0.22 | O58: 0.96 | P58: -1.18 | Q58: 2.34 | R58: 6.76 | S58: -4.42 | T58: 5.89 | U58: 4.19 | V58: 1.7 | W58: 1.36 | X58: -0.72 | Y58: 2.08 | Z58: 3.36 | AA58: 0.35 | AB58: 3.01 | AC58: =IF(OR(P58="",BL58="",BL58=0),"",P58/BL58) | AD58: =IF(OR(S58="",BL58="",BL58=0),"",S58/BL58) | AE58: =IF(OR(V58="",BL58="",BL58=0),"",V58/BL58) | AF58: =IF(OR(Y58="",BL58="",BL58=0),"",Y58/BL58) | AG58: =IF(OR(AB58="",BL58="",BL58=0),"",AB58/BL58) | AH58: 71.2 | AI58: 23.6 | AK58: 5.2 | AN58: 9.3 | AO58: 7.9 | AR58: 4.5 | AT58: 1.9 | BA58: 9 | BB58: 11.6 | BC58: 20.9 | BE58: 18.5 | BF58: 9.7 | BK58: Tenaga Nasional Berhad | Telekom Malaysia Berhad | Taiwan Semiconductor Manufacturing Company Limited | Gamuda Berhad | IHH Healthcare Berhad | BL58: 7.5 | BM58: Low | BN58: Equity Malaysia | BP58: 0.4312 | BQ58: 2020-08-06 | BR58: 0.36 | BS58: -16.51 | BT58: 2069
A59: PUBLIC SAVINGS FUND | B59: PSF | C59: Conventional | D59: Equity | E59: Malaysia | F59: Capital Growth + Income | G59: 4 | H59: Annual | I59: 762.43 | J59: 29.03.1981 | K59: Qualified | L59: 60 | M59: 3/5 | N59: 1.36 | O59: 2.17 | P59: -0.81 | Q59: 2.16 | R59: 9.01 | S59: -6.85 | T59: 7.3 | U59: 5.69 | V59: 1.61 | W59: 2.72 | X59: 1.7 | Y59: 1.02 | Z59: 2.68 | AA59: 0.37 | AB59: 2.31 | AC59: =IF(OR(P59="",BL59="",BL59=0),"",P59/BL59) | AD59: =IF(OR(S59="",BL59="",BL59=0),"",S59/BL59) | AE59: =IF(OR(V59="",BL59="",BL59=0),"",V59/BL59) | AF59: =IF(OR(Y59="",BL59="",BL59=0),"",Y59/BL59) | AG59: =IF(OR(AB59="",BL59="",BL59=0),"",AB59/BL59) | AH59: 76.4 | AI59: 17.3 | AK59: 6.3 | AN59: 12.5 | AR59: 4.8 | BB59: 36.2 | BC59: 13.5 | BD59: 12.3 | BE59: 11.4 | BF59: 9.3 | BK59: LPI Capital Berhad | Malayan Banking Berhad | Public Bank Berhad | Tenaga Nasional Berhad | Costco Wholesale Corporation | BL59: 6.8 | BM59: Low | BN59: Equity Malaysia Domestic 30% of the fund’s NAV | BO59: Note: Distribution yield simply measures the level of distributions and is Kuala Lumpur Composite Index (prior to 6 July 2009). not a measure of fund performance. FTSE Bursa Malaysia KLCI (w.e.f. 6 July 2009). | BP59: 1.07 | BQ59: 2000-02-18 | BR59: 0.5124 | BS59: -52.11 | BT59: 9544
A60: PUBLIC CHINA ACCESS EQUITY FUND | B60: PCASEF | C60: Conventional | D60: Equity | E60: Greater China | F60: Capital Growth | G60: 5 | H60: Incidental | I60: 980.31 | J60: 18.04.2013 | K60: Qualified | L60: 60 | M60: 3/5 | N60: -7.78 | O60: -5.86 | P60: -1.92 | Q60: 10.98 | R60: 1.41 | S60: 9.57 | T60: 0.47 | U60: -0.7 | V60: 1.17 | W60: -4.98 | X60: -5 | Y60: 0.02 | Z60: 4.77 | AA60: 5.01 | AB60: -0.24 | AC60: =IF(OR(P60="",BL60="",BL60=0),"",P60/BL60) | AD60: =IF(OR(S60="",BL60="",BL60=0),"",S60/BL60) | AE60: =IF(OR(V60="",BL60="",BL60=0),"",V60/BL60) | AF60: =IF(OR(Y60="",BL60="",BL60=0),"",Y60/BL60) | AG60: =IF(OR(AB60="",BL60="",BL60=0),"",AB60/BL60) | AI60: 91.2 | AK60: 8.8 | AT60: 91.2 | BA60: 12.4 | BB60: 24.9 | BC60: 13.8 | BD60: 14.9 | BH60: 11.2 | BK60: Ping An Insurance (Group) Company of China Limited - A Shares | Contemporary Amperex Technology Company Limited - A Shares | Zhongji Innolight Company Limited - A Shares | Zijin Mining Group Company Limited - A Shares | Hygon Information Technology Company Limited - A Shares | BL60: 14.7 | BM60: Very High | BN60: Equity China Greater China | BO60: Thebenchmark forPCASEF isacompositeof90% S&P ChinaA 50Indexand 10% 3-Month Kuala Lumpur Interbank Offered Rate (KLIBOR). Underlying index data are sourced from Lipper and Bank Negara Malaysia and expressed in Ringgit terms. | BP60: 2.2029 | BQ60: 2015-06-08 | BR60: 1.1405 | BS60: -48.23 | BT60: 3955
A61: PUBLIC AGGRESSIVE GROWTH FUND | B61: PAGF | C61: Conventional | D61: Equity | E61: Malaysia | F61: Capital Growth | G61: 5 | H61: Incidental | I61: 251.31 | J61: 25.04.1994 | K61: Qualified | L61: 60 | M61: 3/5 | N61: 0.26 | O61: 2.17 | P61: -1.91 | Q61: 5.01 | R61: 9.01 | S61: -4 | T61: 6.84 | U61: 5.69 | V61: 1.15 | W61: 3.65 | X61: 1.7 | Y61: 1.95 | Z61: 4.06 | AA61: 0.37 | AB61: 3.69 | AC61: =IF(OR(P61="",BL61="",BL61=0),"",P61/BL61) | AD61: =IF(OR(S61="",BL61="",BL61=0),"",S61/BL61) | AE61: =IF(OR(V61="",BL61="",BL61=0),"",V61/BL61) | AF61: =IF(OR(Y61="",BL61="",BL61=0),"",Y61/BL61) | AG61: =IF(OR(AB61="",BL61="",BL61=0),"",AB61/BL61) | AH61: 76.4 | AI61: 19 | AK61: 4.6 | AN61: 12.9 | AR61: 2.4 | AT61: 3.7 | BA61: 6.2 | BB61: 34.5 | BC61: 20.6 | BE61: 11.8 | BF61: 8.9 | BK61: Malayan Banking Berhad | Public Bank Berhad | Tenaga Nasional Berhad | Meta Platforms Incorporated | NVIDIA Corporation | BL61: 7.5 | BM61: Low | BN61: Equity Malaysia Domestic 30% of the fund’s NAV | BO61: Kuala Lumpur Composite Index (prior to 6 July 2009). FTSE Bursa Malaysia KLCI (w.e.f. 6 July 2009). | BP61: 1.17 | BQ61: 2000-02-24 | BR61: 0.6844 | BS61: -41.5 | BT61: 9538
A62: PUBLIC ISLAMIC ALPHA-40 GROWTH FUND | B62: PIA40GF | C62: Shariah | D62: Equity | E62: Malaysia | F62: Capital Growth | G62: 4 | H62: Incidental | I62: 389.46 | J62: 16.11.2010 | K62: Qualified | L62: 60 | M62: 3/5 | N62: 0.08 | O62: 3.7 | P62: -3.62 | Q62: 7.83 | R62: 12.03 | S62: -4.2 | T62: 7.44 | U62: 6.4 | V62: 1.04 | W62: 1.32 | X62: 0.07 | Y62: 1.25 | Z62: 4.32 | AA62: 1.92 | AB62: 2.4 | AC62: =IF(OR(P62="",BL62="",BL62=0),"",P62/BL62) | AD62: =IF(OR(S62="",BL62="",BL62=0),"",S62/BL62) | AE62: =IF(OR(V62="",BL62="",BL62=0),"",V62/BL62) | AF62: =IF(OR(Y62="",BL62="",BL62=0),"",Y62/BL62) | AG62: =IF(OR(AB62="",BL62="",BL62=0),"",AB62/BL62) | AH62: 75.4 | AI62: 17.1 | AK62: 7.5 | AN62: 13.1 | AO62: 4 | AZ62: 11.7 | BB62: 11.1 | BC62: 24.3 | BE62: 21.1 | BF62: 10.3 | BK62: Tenaga Nasional Berhad | Telekom Malaysia Berhad | QL Resources Berhad | Press Metal Aluminium Holdings Berhad | Malayan Cement Berhad | BL62: 8.1 | BM62: Moderate | BN62: Equity Malaysia Domestic | BP62: 0.3848 | BQ62: 2024-07-11 | BR62: 0.3584 | BS62: -6.86 | BT62: 634
A63: PUBLIC ISLAMIC ENTERPRISES EQUITY FUND | B63: PIENTEF | C63: Shariah | D63: Equity | E63: Malaysia | F63: Capital Growth | G63: 4 | H63: Incidental | I63: 264.61 | J63: 18.03.2015 | K63: Qualified | L63: 60 | M63: 3/5 | N63: -1.1 | O63: 2.9 | P63: -4 | Q63: 6 | R63: 12.5 | S63: -6.5 | T63: 7.85 | U63: 6.88 | V63: 0.97 | W63: 2.28 | X63: 0.64 | Y63: 1.64 | Z63: 2.98 | AA63: 1.73 | AB63: 1.25 | AC63: =IF(OR(P63="",BL63="",BL63=0),"",P63/BL63) | AD63: =IF(OR(S63="",BL63="",BL63=0),"",S63/BL63) | AE63: =IF(OR(V63="",BL63="",BL63=0),"",V63/BL63) | AF63: =IF(OR(Y63="",BL63="",BL63=0),"",Y63/BL63) | AG63: =IF(OR(AB63="",BL63="",BL63=0),"",AB63/BL63) | AH63: 76.1 | AI63: 18.9 | AK63: 5 | AN63: 12.9 | AR63: 2.7 | AT63: 3.3 | BB63: 11.1 | BC63: 17.9 | BD63: 9 | BE63: 25 | BF63: 10.2 | BK63: Tenaga Nasional Berhad | QL Resources Berhad | Telekom Malaysia Berhad | IHH Healthcare Berhad | NVIDIA Corporation | BL63: 8.6 | BM63: Moderate | BN63: Equity Malaysia Domestic | BO63: ThebenchmarkforPIENTEFisacompositeof75%FTSEBursaMalaysiaHijrah ShariahIndex,15%customisedindexbyS&PDowJonesIndices,LLCbasedon top 100 constituents bymarket capitalisation of theS&P ShariahBMIAsiaEx- Japan Index and 10% 3-Month Islamic Interbank Money Market (IIMM) rate. UnderlyingindexdataaresourcedfromS&PDowJonesIndices,LLC,Lipperand Bank Negara Malaysia and expressed in Ringgit terms. | BP63: 0.3171 | BQ63: 2024-07-15 | BR63: 0.3037 | BS63: -4.23 | BT63: 630
A64: PUBLIC ISLAMIC EQUITY FUND | B64: PIEF | C64: Shariah | D64: Equity | E64: Malaysia | F64: Capital Growth | G64: 4 | H64: Incidental | I64: 1420.11 | J64: 28.05.2003 | K64: Qualified | L64: 60 | M64: 3/5 | N64: -2.23 | O64: 1 | P64: -3.23 | Q64: 2.36 | R64: 7.06 | S64: -4.7 | T64: 5.17 | U64: 4.2 | V64: 0.97 | W64: 1.14 | X64: -1.2 | Y64: 2.34 | Z64: 2.93 | AA64: -0.03 | AB64: 2.96 | AC64: =IF(OR(P64="",BL64="",BL64=0),"",P64/BL64) | AD64: =IF(OR(S64="",BL64="",BL64=0),"",S64/BL64) | AE64: =IF(OR(V64="",BL64="",BL64=0),"",V64/BL64) | AF64: =IF(OR(Y64="",BL64="",BL64=0),"",Y64/BL64) | AG64: =IF(OR(AB64="",BL64="",BL64=0),"",AB64/BL64) | AH64: 70.7 | AI64: 15.5 | AK64: 13.8 | AN64: 11 | AT64: 4.5 | AZ64: 9.4 | BC64: 25.2 | BE64: 20.8 | BF64: 10.7 | BG64: 7 | BK64: Tenaga Nasional Berhad | Telekom Malaysia Berhad | IHH Healthcare Berhad | QL Resources Berhad | Press Metal Aluminium Holdings Berhad | BL64: 7.4 | BM64: Low | BN64: Equity Malaysia Domestic | BO64: 2023 1.00 31.5.23 3.2 Kuala Lumpur Syariah Index (prior to 1 November 2007). FTSE Bursa Malaysia EMAS Shariah Index (w.e.f. 1 November 2007). Note: Distribution yield simply measures the level of distributions and is not | BP64: 0.4248 | BQ64: 2007-10-30 | BR64: 0.3533 | BS64: -16.83 | BT64: 6733
A65: PB ISLAMIC EQUITY FUND | B65: PBIEF | C65: Conventional | D65: Equity | E65: Malaysia | F65: Capital Growth | G65: 4 | H65: Incidental | I65: 210.02 | J65: 05.09.2005 | K65: Qualified | L65: 60 | M65: 3/5 | N65: 0.14 | O65: 1 | P65: -0.86 | Q65: 3.35 | R65: 7.06 | S65: -3.71 | T65: 5.14 | U65: 4.2 | V65: 0.94 | W65: 1.09 | X65: -1.2 | Y65: 2.29 | Z65: 2.61 | AA65: -0.03 | AB65: 2.64 | AC65: =IF(OR(P65="",BL65="",BL65=0),"",P65/BL65) | AD65: =IF(OR(S65="",BL65="",BL65=0),"",S65/BL65) | AE65: =IF(OR(V65="",BL65="",BL65=0),"",V65/BL65) | AF65: =IF(OR(Y65="",BL65="",BL65=0),"",Y65/BL65) | AG65: =IF(OR(AB65="",BL65="",BL65=0),"",AB65/BL65) | AH65: 13.9 | AI65: 68.7 | AK65: 17.4 | AN65: 9.1 | AT65: 4.8 | AZ65: 20.2 | BB65: 8.7 | BC65: 16 | BE65: 13.8 | BF65: 10.5 | BK65: Tenaga Nasional Berhad | Press Metal Aluminium Holdings Berhad | HEICO Corporation | TIME dotCom Berhad | Sunway Construction Group Berhad | BL65: 8.3 | BM65: Moderate | BN65: Equity Malaysia | BP65: 0.393 | BQ65: 2007-07-24 | BR65: 0.2963 | BS65: -24.61 | BT65: 6831
A66: PUBLIC GROWTH FUND | B66: PGF | C66: Conventional | D66: Equity | E66: Malaysia | F66: Capital Growth + Income | G66: 4 | H66: Incidental | I66: 786.13 | J66: 11.12.1984 | K66: Qualified | L66: 60 | M66: 3/5 | N66: -1.1 | O66: 2.17 | P66: -3.27 | Q66: 3.78 | R66: 9.01 | S66: -5.23 | T66: 6.26 | U66: 5.69 | V66: 0.57 | W66: 4.16 | X66: 1.7 | Y66: 2.46 | Z66: 3.78 | AA66: 0.37 | AB66: 3.41 | AC66: =IF(OR(P66="",BL66="",BL66=0),"",P66/BL66) | AD66: =IF(OR(S66="",BL66="",BL66=0),"",S66/BL66) | AE66: =IF(OR(V66="",BL66="",BL66=0),"",V66/BL66) | AF66: =IF(OR(Y66="",BL66="",BL66=0),"",Y66/BL66) | AG66: =IF(OR(AB66="",BL66="",BL66=0),"",AB66/BL66) | AH66: 75.2 | AI66: 22.4 | AK66: 2.4 | AN66: 14.5 | AR66: 2.6 | AT66: 5.3 | BA66: 7 | BB66: 34.7 | BC66: 23.1 | BE66: 7.6 | BF66: 11.6 | BK66: Malayan Banking Berhad | Public Bank Berhad | Tenaga Nasional Berhad | Telekom Malaysia Berhad | Meta Platforms Incorporated | BL66: 7 | BM66: Low | BN66: Equity Malaysia Domestic 30% of the fund’s NAV | BP66: 0.77 | BQ66: 2000-02-16 | BR66: 0.4792 | BS66: -37.77 | BT66: 9546
A67: PUBLIC INDONESIA SELECT FUND | B67: PINDOSF | C67: Shariah | D67: Equity | E67: Indonesia | F67: Capital Growth | G67: 5 | H67: Incidental | I67: 521.54 | J67: 01.09.2010 | K67: Qualified | L67: 60 | M67: 3/5 | N67: -4.04 | O67: -8.89 | P67: 4.85 | Q67: -5.92 | R67: 4.35 | S67: -10.27 | T67: -8.91 | U67: -8.4 | V67: -0.51 | W67: -3.39 | X67: -4.5 | Y67: 1.11 | Z67: -1.2 | AA67: -2.05 | AB67: 0.85 | AC67: =IF(OR(P67="",BL67="",BL67=0),"",P67/BL67) | AD67: =IF(OR(S67="",BL67="",BL67=0),"",S67/BL67) | AE67: =IF(OR(V67="",BL67="",BL67=0),"",V67/BL67) | AF67: =IF(OR(Y67="",BL67="",BL67=0),"",Y67/BL67) | AG67: =IF(OR(AB67="",BL67="",BL67=0),"",AB67/BL67) | AH67: 0.4 | AI67: 86.1 | AK67: 13.5 | AN67: 3.8 | AT67: 4.5 | AU67: 1.6 | AW67: 76.2 | BB67: 34.9 | BC67: 15.2 | BD67: 15.5 | BE67: 13.4 | BH67: 7 | BK67: PT Bank Mandiri (Persero) Tbk | Bank Rakyat Indonesia (Persero) Tbk | Bank Central Asia Tbk | PT Merdeka Copper Gold Tbk | Mitra Adiperkasa Tbk | BL67: 13.2 | BM67: High | BN67: Equity Indonesia ASEAN | BP67: 0.3423 | BQ67: 2013-05-31 | BR67: 0.1872 | BS67: -45.31 | BT67: 4693
A68: PUBLIC ISLAMIC OPTIMAL GROWTH FUND | B68: PIOGF | C68: Shariah | D68: Equity | E68: Malaysia | F68: Capital Growth + Income | G68: 4 | H68: Annual | I68: 121.11 | J68: 08.04.2008 | K68: Qualified | L68: 60 | M68: 3/5 | N68: 1.9 | O68: 1 | P68: 0.9 | Q68: 3.27 | R68: 7.06 | S68: -3.79 | T68: 3.4 | U68: 4.2 | V68: -0.8 | W68: 0.98 | X68: -1.2 | Y68: 2.18 | Z68: 1.39 | AA68: -0.03 | AB68: 1.42 | AC68: =IF(OR(P68="",BL68="",BL68=0),"",P68/BL68) | AD68: =IF(OR(S68="",BL68="",BL68=0),"",S68/BL68) | AE68: =IF(OR(V68="",BL68="",BL68=0),"",V68/BL68) | AF68: =IF(OR(Y68="",BL68="",BL68=0),"",Y68/BL68) | AG68: =IF(OR(AB68="",BL68="",BL68=0),"",AB68/BL68) | AH68: 75.7 | AI68: 20.8 | AK68: 3.5 | AN68: 8 | AO68: 8 | AR68: 4.8 | AZ68: 11.3 | BB68: 16.3 | BC68: 16.6 | BE68: 12.3 | BG68: 10.1 | BK68: Tenaga Nasional Berhad | Telekom Malaysia Berhad | Taiwan Semiconductor Manufacturing Company Limited | Press Metal Aluminium Holdings Berhad | IHH Healthcare Berhad | BL68: 7.5 | BM68: Low | BN68: Equity Malaysia Domestic | BP68: 0.3317 | BQ68: 2013-12-30 | BR68: 0.2592 | BS68: -21.86 | BT68: 4480
A69: PUBLIC SINGAPORE EQUITY FUND | B69: PSGEF | C69: Conventional | D69: Equity | E69: Singapore | F69: Capital Growth | G69: 5 | H69: Incidental | I69: 601.49 | J69: 07.06.2011 | K69: Qualified | L69: 60 | M69: 3/5 | N69: 2.52 | O69: 1.74 | P69: 0.78 | Q69: 12.43 | R69: 11.54 | S69: 0.89 | T69: 11.9 | U69: 13.01 | V69: -1.11 | W69: 7.67 | X69: 9.69 | Y69: -2.02 | Z69: 7.59 | AA69: 6.18 | AB69: 1.41 | AC69: =IF(OR(P69="",BL69="",BL69=0),"",P69/BL69) | AD69: =IF(OR(S69="",BL69="",BL69=0),"",S69/BL69) | AE69: =IF(OR(V69="",BL69="",BL69=0),"",V69/BL69) | AF69: =IF(OR(Y69="",BL69="",BL69=0),"",Y69/BL69) | AG69: =IF(OR(AB69="",BL69="",BL69=0),"",AB69/BL69) | AH69: 1 | AI69: 94 | AK69: 5 | AN69: 11.3 | AO69: 8.1 | AU69: 74.6 | AZ69: 22.8 | BA69: 15.3 | BB69: 35.1 | BC69: 18.4 | BD69: 3.4 | BK69: DBS Group Holdings Limited | Taiwan Semiconductor Manufacturing Company Limited | Keppel Limited | CSE Global Limited | Oversea-Chinese Banking Corporation Limited | BL69: 9.1 | BM69: Moderate | BN69: Equity Singapore ASEAN | BP69: 0.4086 | BQ69: 2025-10-08 | BR69: 0.3812 | BS69: -6.71 | BT69: 180
A70: PUBLIC ISLAMIC ASIA TACTICAL ALLOCATION FUND | B70: PIATAF | C70: Shariah | D70: Mixed Asset / Balanced | E70: Asia | F70: Capital Growth | G70: 5 | H70: Incidental | I70: 3164.64 | J70: 21.08.2007 | K70: Qualified | L70: 100 | M70: 5/5 | N70: 31.59 | O70: 14.91 | P70: 16.68 | Q70: 68.79 | R70: 29.51 | S70: 39.28 | T70: 30.11 | U70: 13.41 | V70: 16.7 | W70: 10.9 | X70: 3.57 | Y70: 7.33 | Z70: 12.94 | AA70: 7.69 | AB70: 5.25 | AC70: =IF(OR(P70="",BL70="",BL70=0),"",P70/BL70) | AD70: =IF(OR(S70="",BL70="",BL70=0),"",S70/BL70) | AE70: =IF(OR(V70="",BL70="",BL70=0),"",V70/BL70) | AF70: =IF(OR(Y70="",BL70="",BL70=0),"",Y70/BL70) | AG70: =IF(OR(AB70="",BL70="",BL70=0),"",AB70/BL70) | AI70: 97.8 | AK70: 2.2 | AO70: 54.7 | AP70: 34.9 | AQ70: 1.9 | AT70: 6.3 | AZ70: 40.4 | BA70: 49 | BC70: 8.4 | BK70: Samsung Electronics Company Limited | SK Hynix Incorporated | Taiwan Semiconductor Manufacturing Company Limited | HD Hyundai Electric Company Limited | Unimicron Technology Corporation | BL70: 21.1 | BM70: Very High | BN70: Mixed Asset MYR Asia | BO70: The benchmark for PIATAF is a composite of 70% S&P Shariah BMI Asia Ex- JapanIndexand30%3-MonthIslamicInterbankMoneyMarket(IIMM)rate(w.e.f. 12 December 2011). UnderlyingindexdataaresourcedfromS&PDowJonesIndices,LLCandBank Negara Malaysia and expressed in Ringgit terms. | BP70: 0.9506 | BQ70: 2026-02-26 | BR70: 0.884 | BS70: -7.01 | BT70: 39
A71: PUBLIC e-FLEXI ALLOCATION FUND | B71: PeFAF | C71: Conventional | D71: Mixed Asset / Balanced | E71: Malaysia | F71: Capital Growth + Income | G71: 5 | H71: Incidental | I71: 142.64 | J71: 14.07.2017 | K71: Qualified | L71: 100 | M71: 4/4 | N71: 2.21 | O71: 1.69 | P71: 0.52 | Q71: 11.31 | R71: 7.44 | S71: 3.87 | T71: 9.71 | U71: 5.14 | V71: 4.57 | W71: 4.44 | X71: 2.22 | Y71: 2.22 | AC71: =IF(OR(P71="",BL71="",BL71=0),"",P71/BL71) | AD71: =IF(OR(S71="",BL71="",BL71=0),"",S71/BL71) | AE71: =IF(OR(V71="",BL71="",BL71=0),"",V71/BL71) | AF71: =IF(OR(Y71="",BL71="",BL71=0),"",Y71/BL71) | AG71: =IF(OR(AB71="",BL71="",BL71=0),"",AB71/BL71) | AH71: 64 | AI71: 25.2 | AK71: 10.8 | AN71: 13.3 | AO71: 7.2 | AP71: 4.7 | AZ71: 24.3 | BA71: 11.9 | BB71: 18.4 | BC71: 14.7 | BF71: 10 | BK71: Malayan Banking Berhad | Tenaga Nasional Berhad | Taiwan Semiconductor Manufacturing Company Limited | Gamuda Berhad | HD Hyundai Electric Company Limited | BL71: 10.7 | BM71: High | BN71: Mixed Asset MYR Domestic 30% of the fund’s NAV | BO71: ThebenchmarkforPeFAFisacompositeof70%FTSEBursaMalaysiaKLCIand 30% 3-Month Kuala Lumpur Interbank Offered Rate (KLIBOR). Underlying index data are sourced from Lipper and Bank Negara Malaysia. | BP71: 0.453 | BQ71: 2024-07-11 | BR71: 0.4173 | BS71: -7.88 | BT71: 634
A72: PUBLIC ISLAMIC MIXED ASSET FUND | B72: PIMXAF | C72: Shariah | D72: Mixed Asset / Balanced | E72: Malaysia | F72: Capital Growth | G72: 4 | H72: Incidental | I72: 1363.56 | J72: 20.09.2005 | K72: Qualified | L72: 80 | M72: 4/5 | N72: -0.48 | O72: 0.86 | P72: -1.34 | Q72: 8.25 | R72: 6.1 | S72: 2.15 | T72: 10.62 | U72: 4.13 | V72: 6.49 | W72: 3.29 | X72: 0.2 | Y72: 3.09 | Z72: 4.08 | AA72: 1.08 | AB72: 3 | AC72: =IF(OR(P72="",BL72="",BL72=0),"",P72/BL72) | AD72: =IF(OR(S72="",BL72="",BL72=0),"",S72/BL72) | AE72: =IF(OR(V72="",BL72="",BL72=0),"",V72/BL72) | AF72: =IF(OR(Y72="",BL72="",BL72=0),"",Y72/BL72) | AG72: =IF(OR(AB72="",BL72="",BL72=0),"",AB72/BL72) | AH72: 43.3 | AI72: 21.6 | AJ72: 30.4 | AK72: 4.7 | AN72: 8.3 | AO72: 4 | AP72: 5.9 | AT72: 3.4 | AZ72: 20.4 | BC72: 14.8 | BE72: 7.8 | BF72: 9.8 | BH72: 6.3 | BK72: Tenaga Nasional Berhad | Press Metal Aluminium Holdings Berhad | HD Hyundai Electric Company Limited | Telekom Malaysia Berhad | IHH Healthcare Berhad | BL72: 7.4 | BM72: Low | BN72: Mixed Asset MYR | BO72: ThebenchmarkforPIMXAFisacompositeof70%FTSEBursaMalaysiaEMAS ShariahIndexand30%3-MonthIslamicInterbankMoneyMarket(IIMM)rate(w.e.f. 12 December 2011). Underlying index data are sourced from Lipper and Bank Negara Malaysia. | BP72: 0.3662 | BQ72: 2025-11-03 | BR72: 0.3456 | BS72: -5.63 | BT72: 154
A73: PUBLIC TACTICAL ALLOCATION FUND | B73: PTAF | C73: Conventional | D73: Mixed Asset / Balanced | E73: Malaysia | F73: Capital Growth + Income | G73: 5 | H73: Incidental | I73: 581.84 | J73: 23.01.2007 | K73: Qualified | L73: 80 | M73: 4/5 | N73: 8.49 | O73: 0.68 | P73: 7.81 | Q73: 12.84 | R73: 9.31 | S73: 3.53 | T73: 14.95 | U73: 8.87 | V73: 6.08 | W73: -1.32 | X73: 1.07 | Y73: -2.39 | Z73: 6.39 | AA73: 5.75 | AB73: 0.64 | AC73: =IF(OR(P73="",BL73="",BL73=0),"",P73/BL73) | AD73: =IF(OR(S73="",BL73="",BL73=0),"",S73/BL73) | AE73: =IF(OR(V73="",BL73="",BL73=0),"",V73/BL73) | AF73: =IF(OR(Y73="",BL73="",BL73=0),"",Y73/BL73) | AG73: =IF(OR(AB73="",BL73="",BL73=0),"",AB73/BL73) | AI73: 83.3 | AK73: 16.7 | AN73: 15.1 | AO73: 32.9 | AP73: 24.5 | AT73: 10.8 | AZ73: 21.3 | BA73: 47.2 | BC73: 12.4 | BD73: 2.4 | BK73: SK Hynix Incorporated | Taiwan Semiconductor Manufacturing Company Limited | Hon.Precision Incorporated | Samsung Electronics Company Limited | HD Hyundai Electric Company Limited | BL73: 18.5 | BM73: Very High | BN73: Mixed Asset MYR Flexible Global | BO73: The benchmark for PTAF is a composite of 70% MSCI AC Far-East Ex-Japan Index (prior to 30 April 2021), 70% S&P Pan Asia Ex-Japan, Australia, NewZealand&IndiaLargeCapIndex(30April2021to1January2024),40%S&P UnitedStatesLargeCapIndex,15%customisedindexbyS&PDowJonesIndices, LLCbasedonthetop30constituentsoftheS&PBMIAsiaEx-JapanIndex,15% TOPIX Core 30 Index (w.e.f. 2 January 2024) and 30% 3-Month Kuala Lumpur Interbank Offered Rate (KLIBOR) (w.e.f. 12 December 2011). UnderlyingindexdataaresourcedfromS&PDowJonesIndices,LLC,Lipperand Bank Negara Malaysia and expressed in Ringgit terms. | BP73: 0.5608 | BQ73: 2021-02-17 | BR73: 0.4121 | BS73: -26.52 | BT73: 1874
A74: PUBLIC FAR-EAST BALANCED FUND | B74: PFEBF | C74: Conventional | D74: Mixed Asset / Balanced | E74: Asia Pacific | F74: Capital Growth + Income | G74: 4 | H74: Incidental | I74: 220.09 | J74: 23.01.2007 | K74: Qualified | L74: 80 | M74: 4/5 | N74: 8.55 | O74: 7.23 | P74: 1.32 | Q74: 19.15 | R74: 18.41 | S74: 0.74 | T74: 11.29 | U74: 10.7 | V74: 0.59 | W74: 2.73 | X74: 2.91 | Y74: -0.18 | Z74: 6.44 | AA74: 6.22 | AB74: 0.22 | AC74: =IF(OR(P74="",BL74="",BL74=0),"",P74/BL74) | AD74: =IF(OR(S74="",BL74="",BL74=0),"",S74/BL74) | AE74: =IF(OR(V74="",BL74="",BL74=0),"",V74/BL74) | AF74: =IF(OR(Y74="",BL74="",BL74=0),"",Y74/BL74) | AG74: =IF(OR(AB74="",BL74="",BL74=0),"",AB74/BL74) | AH74: 1.1 | AI74: 55.1 | AJ74: 32.7 | AK74: 11.1 | AN74: 2.3 | AO74: 17.6 | AP74: 19.8 | AT74: 15.4 | AZ74: 11.7 | BA74: 28.7 | BB74: 1 | BC74: 13.6 | BD74: 1.2 | BK74: Taiwan Semiconductor Manufacturing Company Limited | Alibaba Group Holding Limited - W | SK Hynix Incorporated | Samsung Electronics Company Limited | HD Hyundai Electric Company Limited | BL74: 10.8 | BM74: High | BN74: Asia | BO74: The benchmark for PFEBF is a composite of 60% MSCI AC Far-East Ex-Japan Index (prior to 30 April 2021), 60% S&P Pan Asia Ex-Japan, Australia, New Zealand & India LargeCap Index(30 April 2021 to 1 January2025), 60% S&P Pan Asia Ex-Japan, Australia, New Zealand & India LargeCap 8% Capped Index (w.e.f. 2 January 2025) and 40% 3-Month Kuala Lumpur Interbank Offered Rate (KLIBOR). UnderlyingindexdataaresourcedfromS&PDowJonesIndices,LLC,Lipperand Bank Negara Malaysia and expressed in Ringgit terms. | BP74: 0.3969 | BQ74: 2021-02-17 | BR74: 0.3742 | BS74: -5.72 | BT74: 1874
A75: PUBLIC e-ISLAMIC FLEXI ALLOCATION FUND | B75: PeIFAF | C75: Shariah | D75: Mixed Asset / Balanced | E75: Malaysia | F75: Capital Growth | G75: 4 | H75: Incidental | I75: 46.57 | J75: 03.04.2018 | K75: Qualified | L75: 75 | M75: 3/4 | N75: -0.96 | O75: 0.13 | P75: -1.09 | Q75: 10.26 | R75: 6.48 | S75: 3.78 | T75: 8.65 | U75: 4.55 | V75: 4.1 | W75: 1.55 | X75: 0.72 | Y75: 0.83 | AC75: =IF(OR(P75="",BL75="",BL75=0),"",P75/BL75) | AD75: =IF(OR(S75="",BL75="",BL75=0),"",S75/BL75) | AE75: =IF(OR(V75="",BL75="",BL75=0),"",V75/BL75) | AF75: =IF(OR(Y75="",BL75="",BL75=0),"",Y75/BL75) | AG75: =IF(OR(AB75="",BL75="",BL75=0),"",AB75/BL75) | AH75: 23.7 | AI75: 70.4 | AK75: 5.9 | AN75: 16.3 | AO75: 7.4 | AZ75: 24.3 | BA75: 11.6 | BC75: 24.2 | BD75: 10.1 | BF75: 10.5 | BK75: Tenaga Nasional Berhad | Telekom Malaysia Berhad | Malayan Cement Berhad | Taiwan Semiconductor Manufacturing Company Limited | Frontken Corporation Berhad | BL75: 9.4 | BM75: Moderate | BN75: Mixed Asset MYR Domestic | BO75: The benchmark for PeIFAF is a composite of 70% FTSE Bursa Malaysia Hijrah Shariah Index and 30% 3-Month Islamic Interbank Money Market (IIMM) rate. Underlying index data are sourced from Lipper and Bank Negara Malaysia. | BP75: 0.404 | BQ75: 2025-10-29 | BR75: 0.3727 | BS75: -7.75 | BT75: 159
A76: PB BALANCED SEQUEL FUND | B76: PBBSQF | C76: Conventional | D76: Mixed Asset / Balanced | E76: Malaysia | F76: Capital Growth | G76: 3 | H76: Incidental | I76: 38.41 | J76: 10.09.2013 | K76: Qualified | L76: 60 | M76: 3/5 | N76: -0.7 | O76: 1.52 | P76: -2.22 | Q76: -1.28 | R76: 6.89 | S76: -8.17 | T76: 8.31 | U76: 4.93 | V76: 3.38 | W76: 4.06 | X76: 2.37 | Y76: 1.69 | Z76: 4.23 | AA76: 1.62 | AB76: 2.61 | AC76: =IF(OR(P76="",BL76="",BL76=0),"",P76/BL76) | AD76: =IF(OR(S76="",BL76="",BL76=0),"",S76/BL76) | AE76: =IF(OR(V76="",BL76="",BL76=0),"",V76/BL76) | AF76: =IF(OR(Y76="",BL76="",BL76=0),"",Y76/BL76) | AG76: =IF(OR(AB76="",BL76="",BL76=0),"",AB76/BL76) | AH76: 37.2 | AI76: 12.9 | AJ76: 39.9 | AK76: 10 | AN76: 2.5 | AT76: 10.4 | AZ76: 2.2 | BA76: 8 | BB76: 22.2 | BC76: 4.9 | BF76: 9.7 | BK76: Malayan Banking Berhad | Tenaga Nasional Berhad | LPI Capital Berhad | Sunway Berhad | Alibaba Group Holding Limited - W | BL76: 7.6 | BM76: Low | BN76: Mixed Asset MYR Domestic | BO76: Public Balanced Equity Index (PBEIX) is a composite of 60% the returns of the FTSE Bursa Malaysia KLCI and 40% the returns on 3-Month Kuala Lumpur Interbank Offered Rate (KLIBOR). The Index is an appropriate performance benchmark for balanced fund. Underlying index data are sourced from Lipper and Bank Negara Malaysia. | BP76: 0.3674 | BQ76: 2024-12-26 | BR76: 0.3288 | BS76: -10.51 | BT76: 466
A77: PUBLIC SELECT MIXED ASSET GROWTH FUND | B77: PSMAGF | C77: Conventional | D77: Mixed Asset / Balanced | E77: Malaysia | F77: Capital Growth + Income | G77: 4 | H77: Incidental | I77: 29.22 | J77: 16.10.2014 | K77: Qualified | L77: 60 | M77: 3/5 | N77: 0.77 | O77: 1.69 | P77: -0.92 | Q77: 6.87 | R77: 7.44 | S77: -0.57 | T77: 7.84 | U77: 5.14 | V77: 2.7 | W77: 2.62 | X77: 2.22 | Y77: 0.4 | Z77: 5.13 | AA77: 1.32 | AB77: 3.81 | AC77: =IF(OR(P77="",BL77="",BL77=0),"",P77/BL77) | AD77: =IF(OR(S77="",BL77="",BL77=0),"",S77/BL77) | AE77: =IF(OR(V77="",BL77="",BL77=0),"",V77/BL77) | AF77: =IF(OR(Y77="",BL77="",BL77=0),"",Y77/BL77) | AG77: =IF(OR(AB77="",BL77="",BL77=0),"",AB77/BL77) | AH77: 39.8 | AI77: 25.8 | AJ77: 30.7 | AK77: 3.7 | AN77: 10 | AO77: 5.9 | AP77: 6 | AT77: 3.9 | AZ77: 14.4 | BA77: 10.1 | BB77: 15.1 | BC77: 8.5 | BF77: 10.3 | BK77: Tenaga Nasional Berhad | Malayan Banking Berhad | Hanwha Aerospace Company Limited | Taiwan Semiconductor Manufacturing Company Limited | Sunway Berhad | BL77: 8.1 | BM77: Moderate | BN77: Mixed Asset MYR Domestic 30% of the fund’s NAV | BP77: 0.377 | BQ77: 2025-10-02 | BR77: 0.361 | BS77: -4.24 | BT77: 186
A78: PUBLIC GROWTH BALANCED FUND | B78: PGRBF | C78: Conventional | D78: Mixed Asset / Balanced | E78: Malaysia | F78: Capital Growth | G78: 3 | H78: Incidental | I78: 27.54 | J78: 07.10.2015 | K78: Qualified | L78: 60 | M78: 3/5 | N78: -0.52 | O78: 1.52 | P78: -2.04 | Q78: 2.15 | R78: 6.89 | S78: -4.74 | T78: 6.77 | U78: 4.93 | V78: 1.84 | W78: 3.71 | X78: 2.37 | Y78: 1.34 | Z78: 6.62 | AA78: 1.62 | AB78: 5 | AC78: =IF(OR(P78="",BL78="",BL78=0),"",P78/BL78) | AD78: =IF(OR(S78="",BL78="",BL78=0),"",S78/BL78) | AE78: =IF(OR(V78="",BL78="",BL78=0),"",V78/BL78) | AF78: =IF(OR(Y78="",BL78="",BL78=0),"",Y78/BL78) | AG78: =IF(OR(AB78="",BL78="",BL78=0),"",AB78/BL78) | AH78: 29.6 | AI78: 21.7 | AJ78: 43.7 | AK78: 5 | AN78: 13.3 | AO78: 5.8 | AT78: 2.6 | AZ78: 6.4 | BA78: 13.3 | BC78: 13.8 | BE78: 4.2 | BF78: 8 | BK78: Tenaga Nasional Berhad | Taiwan Semiconductor Manufacturing Company Limited | TIME dotCom Berhad | NVIDIA Corporation | Frontken Corporation Berhad | BL78: 6 | BM78: Low | BN78: Domestic 25% of the fund’s NAV | BO78: ThebenchmarkforPGRBFisacompositeof60%FTSEBursaMalaysiaKLCIand 40% 3-Month Kuala Lumpur Interbank Offered Rate (KLIBOR). Underlying index data are sourced from Lipper and Bank Negara Malaysia. | BP78: 0.4188 | BQ78: 2025-10-29 | BR78: 0.3966 | BS78: -5.3 | BT78: 159
A79: PUBLIC EHSAN MIXED ASSET CONSERVATIVE FUND | B79: PESMACF | C79: Shariah | D79: Mixed Asset / Balanced | E79: Malaysia | F79: Capital Growth + Income | G79: 3 | H79: Annual | I79: 860.12 | J79: 25.11.2014 | K79: Qualified | L79: 60 | M79: 3/5 | N79: 0 | O79: 0.33 | P79: -0.33 | Q79: 3.25 | R79: 5 | S79: -1.75 | T79: 5.72 | U79: 4.11 | V79: 1.61 | W79: 2.78 | X79: 1.98 | Y79: 0.8 | Z79: 5.42 | AA79: 2.13 | AB79: 3.29 | AC79: =IF(OR(P79="",BL79="",BL79=0),"",P79/BL79) | AD79: =IF(OR(S79="",BL79="",BL79=0),"",S79/BL79) | AE79: =IF(OR(V79="",BL79="",BL79=0),"",V79/BL79) | AF79: =IF(OR(Y79="",BL79="",BL79=0),"",Y79/BL79) | AG79: =IF(OR(AB79="",BL79="",BL79=0),"",AB79/BL79) | AH79: 15.2 | AI79: 15 | AJ79: 60.2 | AK79: 9.6 | AN79: 9.4 | AO79: 3.6 | AR79: 2 | AZ79: 1.6 | BA79: 5.4 | BC79: 10.4 | BD79: 3.9 | BF79: 6.4 | BK79: Tenaga Nasional Berhad | Taiwan Semiconductor Manufacturing Company Limited | Alphabet Incorporated - Class A | Meta Platforms Incorporated | Telekom Malaysia Berhad | BL79: 3.4 | BM79: Very Low | BN79: Mixed Asset MYR | BP79: 0.3493 | BQ79: 2021-02-11 | BR79: 0.3188 | BS79: -8.73 | BT79: 1880
A80: PB MIXED ASSET CONSERVATIVE FUND | B80: PBMAC | C80: Conventional | D80: Mixed Asset / Balanced | E80: Malaysia | F80: Capital Growth + Income | G80: 3 | H80: Annual | I80: 103.67 | J80: 15.01.2013 | K80: Qualified | L80: 60 | M80: 3/5 | N80: -1.32 | O80: 1.11 | P80: -2.43 | Q80: 1.82 | R80: 5.46 | S80: -3.64 | T80: 5.94 | U80: 4.38 | V80: 1.56 | W80: 2.75 | X80: 2.71 | Y80: 0.04 | Z80: 4.62 | AA80: 2.31 | AB80: 2.31 | AC80: =IF(OR(P80="",BL80="",BL80=0),"",P80/BL80) | AD80: =IF(OR(S80="",BL80="",BL80=0),"",S80/BL80) | AE80: =IF(OR(V80="",BL80="",BL80=0),"",V80/BL80) | AF80: =IF(OR(Y80="",BL80="",BL80=0),"",Y80/BL80) | AG80: =IF(OR(AB80="",BL80="",BL80=0),"",AB80/BL80) | AH80: 8.3 | AI80: 18.2 | AJ80: 60.9 | AK80: 12.6 | AN80: 11.7 | AP80: 3.7 | AT80: 2.8 | AZ80: 3.7 | BA80: 6.8 | BB80: 2.7 | BC80: 6.7 | BF80: 3.3 | BK80: Alphabet Incorporated - Class A | Advanced Micro Devices Incorporated | HD Hyundai Electric Company Limited | Tenaga Nasional Berhad | Broadcom Incorporated | BL80: 5 | BM80: Low | BN80: Mixed Asset MYR Domestic | BO80: ThebenchmarkforPBMACisacompositeof65%3-MonthKualaLumpurInterbank Offered Rate (KLIBOR) and 35% FTSE Bursa Malaysia KLCI (FBM KLCI). Underlying index data are sourced from Lipper and Bank Negara Malaysia. | BP80: 0.3071 | BQ80: 2025-11-03 | BR80: 0.276 | BS80: -10.13 | BT80: 154
A81: PUBLIC SELECT MIXED ASSET CONSERVATIVE FUND | B81: PSMACF | C81: Conventional | D81: Mixed Asset / Balanced | E81: Malaysia | F81: Capital Growth + Income | G81: 3 | H81: Annual | I81: 146.06 | J81: 16.10.2014 | K81: Qualified | L81: 60 | M81: 3/5 | N81: -1.41 | O81: 1.11 | P81: -2.52 | Q81: 3.68 | R81: 5.46 | S81: -1.78 | T81: 5.83 | U81: 4.38 | V81: 1.45 | W81: 3.54 | X81: 2.71 | Y81: 0.83 | Z81: 4.9 | AA81: 2.31 | AB81: 2.59 | AC81: =IF(OR(P81="",BL81="",BL81=0),"",P81/BL81) | AD81: =IF(OR(S81="",BL81="",BL81=0),"",S81/BL81) | AE81: =IF(OR(V81="",BL81="",BL81=0),"",V81/BL81) | AF81: =IF(OR(Y81="",BL81="",BL81=0),"",Y81/BL81) | AG81: =IF(OR(AB81="",BL81="",BL81=0),"",AB81/BL81) | AH81: 15 | AI81: 15.9 | AJ81: 60.4 | AK81: 8.7 | AN81: 9.9 | AO81: 3.9 | AT81: 2.1 | AZ81: 9.6 | BA81: 5.3 | BC81: 8.8 | BD81: 1.7 | BF81: 4.5 | BK81: Southern Cable Group Berhad | Tenaga Nasional Berhad | Alphabet Incorporated - Class A | Taiwan Semiconductor Manufacturing Company Limited | Frontken Corporation Berhad | BL81: 4.6 | BM81: Low | BN81: Mixed Asset MYR Domestic 25% of the fund’s NAV | BP81: 0.3199 | BQ81: 2025-10-03 | BR81: 0.3023 | BS81: -5.5 | BT81: 185
A82: PB BALANCED FUND | B82: PBBF | C82: Conventional | D82: Mixed Asset / Balanced | E82: Malaysia | F82: Capital Growth + Income | G82: 3 | H82: Incidental | I82: 355.79 | J82: 05.05.1998 | K82: Qualified | L82: 60 | M82: 3/5 | N82: -2.06 | O82: 1.52 | P82: -3.58 | Q82: -0.09 | R82: 6.89 | S82: -6.98 | T82: 6.38 | U82: 4.93 | V82: 1.45 | W82: 3.37 | X82: 2.37 | Y82: 1 | Z82: 3.86 | AA82: 1.62 | AB82: 2.24 | AC82: =IF(OR(P82="",BL82="",BL82=0),"",P82/BL82) | AD82: =IF(OR(S82="",BL82="",BL82=0),"",S82/BL82) | AE82: =IF(OR(V82="",BL82="",BL82=0),"",V82/BL82) | AF82: =IF(OR(Y82="",BL82="",BL82=0),"",Y82/BL82) | AG82: =IF(OR(AB82="",BL82="",BL82=0),"",AB82/BL82) | AH82: 34.9 | AI82: 14.4 | AJ82: 40.6 | AK82: 10.1 | AN82: 8.6 | AT82: 5.8 | AZ82: 6.4 | BA82: 3.8 | BB82: 9.8 | BC82: 15 | BF82: 9.5 | BK82: Tenaga Nasional Berhad | Public Bank Berhad | Alibaba Group Holding Limited - W | Frontken Corporation Berhad | QL Resources Berhad | BL82: 6.4 | BM82: Low | BN82: Mixed Asset MYR Domestic | BO82: Public Balanced Equity Index (PBEIX) is a composite of 60% the returns of the KualaLumpurCompositeIndex(priorto6July2009),60%thereturnsoftheFTSE BursaMalaysiaKLCI(w.e.f.6July2009)and40% thereturnson3-MonthKuala LumpurInterbankOfferedRate(KLIBOR).TheIndexisanappropriateperformance benchmark for balanced fund. Underlying index data are sourced from Lipper and Bank Negara Malaysia. | BP82: 1.56 | BQ82: 2000-02-18 | BR82: 0.8409 | BS82: -46.1 | BT82: 9544
A83: PB DYNAMIC ALLOCATION FUND | B83: PBDYNAF | C83: Conventional | D83: Mixed Asset / Balanced | E83: Malaysia | F83: Capital Growth + Income | G83: 5 | H83: Incidental | I83: 380.79 | J83: 19.06.2012 | K83: Qualified | L83: 60 | M83: 3/5 | N83: 3 | O83: 8.38 | P83: -5.38 | Q83: 15.39 | R83: 20.96 | S83: -5.57 | T83: 13.09 | U83: 11.82 | V83: 1.27 | W83: 3.09 | X83: 2.77 | Y83: 0.32 | Z83: 8.38 | AA83: 6.64 | AB83: 1.74 | AC83: =IF(OR(P83="",BL83="",BL83=0),"",P83/BL83) | AD83: =IF(OR(S83="",BL83="",BL83=0),"",S83/BL83) | AE83: =IF(OR(V83="",BL83="",BL83=0),"",V83/BL83) | AF83: =IF(OR(Y83="",BL83="",BL83=0),"",Y83/BL83) | AG83: =IF(OR(AB83="",BL83="",BL83=0),"",AB83/BL83) | AI83: 82 | AK83: 18 | AN83: 26.9 | AO83: 14.1 | AP83: 21.5 | AR83: 2.8 | AT83: 16.7 | AZ83: 3.4 | BA83: 49.6 | BB83: 0.8 | BC83: 25.4 | BD83: 2.8 | BK83: Samsung Electronics Company Limited | Taiwan Semiconductor Manufacturing Company Limited | SK Hynix Incorporated | Alibaba Group Holding Limited - W | Alphabet Incorporated - Class A | BL83: 15.4 | BM83: Very High | BN83: Mixed Asset MYR Global | BO83: ThebenchmarkforPBDYNAFisacompositeof70%MSCIACFar-EastEx-Japan Index(priorto30April2021),70%S&PPanAsiaEx-Japan,Australia,NewZealand &IndiaLargeCapIndex(30April2021to1January2025),70%S&PPanAsiaEx- Japan, Australia, New Zealand & India LargeCap 8% Capped Index (w.e.f. 2 January 2025) and 30% 3-Month Kuala Lumpur Interbank Offered Rate (KLIBOR). UnderlyingindexdataaresourcedfromS&PDowJonesIndices,LLC,Lipperand Bank Negara Malaysia and expressed in Ringgit terms. | BP83: 1.7432 | BQ83: 2025-10-28 | BR83: 1.5285 | BS83: -12.32 | BT83: 160
A84: PUBLIC BALANCED FUND | B84: PBF | C84: Conventional | D84: Mixed Asset / Balanced | E84: Malaysia | F84: Capital Growth + Income | G84: 3 | H84: Incidental | I84: 341.62 | J84: 07.06.1995 | K84: Qualified | L84: 60 | M84: 3/5 | N84: 1.42 | O84: 1.52 | P84: -0.1 | Q84: 5.56 | R84: 6.89 | S84: -1.33 | T84: 6.16 | U84: 4.93 | V84: 1.23 | W84: 4.03 | X84: 2.37 | Y84: 1.66 | Z84: 4.19 | AA84: 1.62 | AB84: 2.57 | AC84: =IF(OR(P84="",BL84="",BL84=0),"",P84/BL84) | AD84: =IF(OR(S84="",BL84="",BL84=0),"",S84/BL84) | AE84: =IF(OR(V84="",BL84="",BL84=0),"",V84/BL84) | AF84: =IF(OR(Y84="",BL84="",BL84=0),"",Y84/BL84) | AG84: =IF(OR(AB84="",BL84="",BL84=0),"",AB84/BL84) | AH84: 36.7 | AI84: 18.9 | AJ84: 36.4 | AK84: 8 | AN84: 3.1 | AQ84: 3.9 | AT84: 11.9 | AZ84: 6.6 | BA84: 7.7 | BB84: 21.9 | BC84: 6.3 | BF84: 9.1 | BK84: Tenaga Nasional Berhad | Malayan Banking Berhad | Alibaba Group Holding Limited - W | Semiconductor Manufacturing International Corporation | Public Bank Berhad | BL84: 7.2 | BM84: Low | BN84: Mixed Asset MYR Domestic 30% of the fund’s NAV | BO84: 2022 2.75 31.5.22 4.1 Public Balanced Equity Index (PBEIX) is a composite of 60% the returns of the Kuala Lumpur Composite Index (prior to 6July2009),60% thereturns ofFTSE 2023 1.75 31.5.23 2.6 BursaMalaysiaKLCI(w.e.f.6July2009)and40% the returns of 3-MonthKuala Note: Distribution yield simply measures the level of distributions and is LumpurInterbankOfferedRate(KLIBOR).TheIndexisanappropriateperformance not a measure of fund performance. benchmark for balanced fund. Underlying index data are sourced from Lipper and Bank Negara Malaysia. | BP84: 1.0016 | BQ84: 2007-05-22 | BR84: 0.7554 | BS84: -24.58 | BT84: 6894
A85: PUBLIC ISLAMIC ENHANCED BOND FUND | B85: PIEBF | C85: Shariah | D85: Fixed Income | E85: Malaysia | F85: Capital Growth + Income | G85: 2 | H85: Annual | I85: 500.25 | J85: 28.11.2006 | K85: Qualified | L85: 100 | M85: 5/5 | N85: 1.19 | O85: 0.32 | P85: 0.87 | Q85: 3.44 | R85: 2.59 | S85: 0.85 | T85: 6.37 | U85: 3.13 | V85: 3.24 | W85: 4.15 | X85: 2.91 | Y85: 1.24 | Z85: 4.22 | AA85: 3.06 | AB85: 1.16 | AC85: =IF(OR(P85="",BL85="",BL85=0),"",P85/BL85) | AD85: =IF(OR(S85="",BL85="",BL85=0),"",S85/BL85) | AE85: =IF(OR(V85="",BL85="",BL85=0),"",V85/BL85) | AF85: =IF(OR(Y85="",BL85="",BL85=0),"",Y85/BL85) | AG85: =IF(OR(AB85="",BL85="",BL85=0),"",AB85/BL85) | AI85: 13.5 | AJ85: 70.6 | AK85: 15.9 | BK85: Pengurusan Air SPV Berhad - 4.06% / 2039* | Government Investment Issue - 4.291% / 2043* | CIMB Islamic Bank Berhad - 4.13% / 2034* | Projek Lebuhraya Usahasama Berhad - 5.00% / 2038* | TNB Power Generation Sdn Bhd - 5.20% / 2042* | BL85: 4.6 | BM85: Low | BN85: Mixed Asset MYR | BO85: 12-Month General Investment Account (GIA) rate (prior to 1 July 2025). Public Islamic Bank 12-Month Term Deposit-i (w.e.f. 1 July 2025). | BP85: 1.2617 | BQ85: 2024-12-24 | BR85: 1.1684 | BS85: -7.39 | BT85: 468
A86: PB FIXED INCOME FUND | B86: PBFI | C86: Conventional | D86: Fixed Income | E86: Malaysia | F86: Income | G86: 2 | H86: Annual | I86: 645.61 | J86: 03.10.2002 | K86: Qualified | L86: 100 | M86: 5/5 | N86: 0.33 | O86: 0.32 | P86: 0.01 | Q86: 4.11 | R86: 2.22 | S86: 1.89 | T86: 4.63 | U86: 2.55 | V86: 2.08 | W86: 3.54 | X86: 2.38 | Y86: 1.16 | Z86: 4.19 | AA86: 2.67 | AB86: 1.52 | AC86: =IF(OR(P86="",BL86="",BL86=0),"",P86/BL86) | AD86: =IF(OR(S86="",BL86="",BL86=0),"",S86/BL86) | AE86: =IF(OR(V86="",BL86="",BL86=0),"",V86/BL86) | AF86: =IF(OR(Y86="",BL86="",BL86=0),"",Y86/BL86) | AG86: =IF(OR(AB86="",BL86="",BL86=0),"",AB86/BL86) | AJ86: 82.2 | AK86: 17.8 | BK86: Danum Capital Berhad - 3.82% / 2036* | Pengurusan Air SPV Berhad - 4.06% / 2039* | Sabah Credit Corporation - 3.78% / 2035* | Petroleum Sarawak E&P Sdn Bhd - 3.70% / 2035* | Johor Plantations Group Berhad - 4.19% / 2039* | BL86: 1.3 | BM86: Very Low | BN86: Bond MYR | BP86: 1.1445 | BQ86: 2020-06-30 | BR86: 1.0895 | BS86: -4.81 | BT86: 2106
A87: PUBLIC e-INCOME FUND | B87: PeINCF | C87: Shariah | D87: Fixed Income | E87: Malaysia | F87: Income | G87: 2 | H87: Annual | I87: 246 | J87: 01.07.2020 | K87: Qualified | L87: 100 | M87: 4/4 | N87: 0.54 | O87: 0.3 | P87: 0.24 | Q87: 3.95 | R87: 2.04 | S87: 1.91 | T87: 3.85 | U87: 2.35 | V87: 1.5 | W87: 3.09 | X87: 2.18 | Y87: 0.91 | AC87: =IF(OR(P87="",BL87="",BL87=0),"",P87/BL87) | AD87: =IF(OR(S87="",BL87="",BL87=0),"",S87/BL87) | AE87: =IF(OR(V87="",BL87="",BL87=0),"",V87/BL87) | AF87: =IF(OR(Y87="",BL87="",BL87=0),"",Y87/BL87) | AG87: =IF(OR(AB87="",BL87="",BL87=0),"",AB87/BL87) | AJ87: 36.5 | AK87: 63.5 | BK87: Bank Islam Malaysia Berhad - 3.85% / 2032** | Public Bank Berhad - 3.73% / 2032* | Sabah Credit Corporation - 3.66% / 2032** | Petroleum Sarawak E&P Sdn Bhd - 3.64% / 2032** | Pengurusan Air Selangor Sdn Bhd - 3.76% / 2035** | BL87: 0.3 | BM87: Very Low | BN87: Bond MYR | BO87: 50% Public Bank 12-Month Fixed Deposit Rate (FDR) and 50% Public Bank 1-Month FDR. | BP87: 1.0486 | BQ87: 2024-07-31 | BR87: 1.0309 | BS87: -1.69 | BT87: 614
A88: PUBLIC SELECT BOND FUND | B88: PSBF | C88: Conventional | D88: Fixed Income | E88: Malaysia | F88: Income | G88: 2 | H88: Annual | I88: 303.19 | J88: 22.11.2005 | K88: Qualified | L88: 100 | M88: 5/5 | N88: 0.53 | O88: 0.32 | P88: 0.21 | Q88: 4.23 | R88: 2.22 | S88: 2.01 | T88: 3.94 | U88: 2.55 | V88: 1.39 | W88: 2.84 | X88: 2.38 | Y88: 0.46 | Z88: 3.62 | AA88: 2.67 | AB88: 0.95 | AC88: =IF(OR(P88="",BL88="",BL88=0),"",P88/BL88) | AD88: =IF(OR(S88="",BL88="",BL88=0),"",S88/BL88) | AE88: =IF(OR(V88="",BL88="",BL88=0),"",V88/BL88) | AF88: =IF(OR(Y88="",BL88="",BL88=0),"",Y88/BL88) | AG88: =IF(OR(AB88="",BL88="",BL88=0),"",AB88/BL88) | AJ88: 85.4 | AK88: 14.6 | BK88: CIMB Islamic Bank Berhad - 4.03% / 2031* | Bank Islam Malaysia Berhad - 3.85% / 2032* | PNB Merdeka Ventures Sdn Bhd - 3.79% / 2032* | BL88: 0.9 | BM88: Very Low | BN88: Bond MYR | BP88: 1.082 | BQ88: 2007-05-23 | BR88: 1.0271 | BS88: -5.07 | BT88: 6893
A89: PUBLIC ISLAMIC SELECT BOND | B89: PISBF | C89: Shariah | D89: Fixed Income | E89: Malaysia | F89: Income | G89: 2 | H89: Annual | I89: 246.22 | J89: 10.07.2007 | K89: Qualified | L89: 100 | M89: 5/5 | N89: 0.55 | O89: 0.32 | P89: 0.23 | Q89: 4.26 | R89: 2.59 | S89: 1.67 | T89: 4.04 | U89: 3.13 | V89: 0.91 | W89: 2.96 | X89: 2.91 | Y89: 0.05 | Z89: 3.7 | AA89: 3.06 | AB89: 0.64 | AC89: =IF(OR(P89="",BL89="",BL89=0),"",P89/BL89) | AD89: =IF(OR(S89="",BL89="",BL89=0),"",S89/BL89) | AE89: =IF(OR(V89="",BL89="",BL89=0),"",V89/BL89) | AF89: =IF(OR(Y89="",BL89="",BL89=0),"",Y89/BL89) | AG89: =IF(OR(AB89="",BL89="",BL89=0),"",AB89/BL89) | AJ89: 85.6 | AK89: 14.4 | BK89: Bank Islam Malaysia Berhad - 3.85% / 2032* | OSK Rated Bond Sdn Bhd - 4.05% / 2032* | AEON Company (M) Berhad - 3.79% / 2032* | BL89: 1 | BM89: Very Low | BN89: Bond Sukuk Malaysia | BO89: 12-Month General Investment Account (GIA) rate (prior to 1 July 2025). Public Islamic Bank 12-Month Term Deposit-i (w.e.f. 1 July 2025). | BP89: 1.098 | BQ89: 2020-07-30 | BR89: 1.0482 | BS89: -4.54 | BT89: 2076
A90: PUBLIC ISLAMIC INCOME FUND | B90: PI INCOME | C90: Shariah | D90: Fixed Income | E90: Malaysia | F90: Income | G90: 2 | H90: Annual | I90: 117.16 | J90: 14.08.2008 | K90: Qualified | L90: 100 | M90: 5/5 | N90: 0.4 | O90: 0.32 | P90: 0.08 | Q90: 3.98 | R90: 2.59 | S90: 1.39 | T90: 3.98 | U90: 3.13 | V90: 0.85 | W90: 2.95 | X90: 2.91 | Y90: 0.04 | Z90: 3.47 | AA90: 3.06 | AB90: 0.41 | AC90: =IF(OR(P90="",BL90="",BL90=0),"",P90/BL90) | AD90: =IF(OR(S90="",BL90="",BL90=0),"",S90/BL90) | AE90: =IF(OR(V90="",BL90="",BL90=0),"",V90/BL90) | AF90: =IF(OR(Y90="",BL90="",BL90=0),"",Y90/BL90) | AG90: =IF(OR(AB90="",BL90="",BL90=0),"",AB90/BL90) | AJ90: 46.9 | AK90: 53.1 | BK90: Projek Lebuhraya Usahasama Berhad - 5.00% / 2038* | Pengurusan Air SPV Berhad - 4.06% / 2039* | Sabah Credit Corporation - 4.10% / 2035* | CIMB Islamic Bank Berhad - 4.07% / 2035* | Gamuda Berhad - 3.99% / 2035* | BL90: 0.8 | BM90: Very Low | BN90: Consistent | BO90: 12-Month General Investment Account (GIA) rate (prior to 1 July 2025). Public Islamic Bank 12-Month Term Deposit-i (w.e.f. 1 July 2025). | BP90: 1.1306 | BQ90: 2020-07-30 | BR90: 1.0526 | BS90: -6.9 | BT90: 2076
A91: PUBLIC e-ISLAMIC INCOME FUND | B91: PeISINCF | C91: Shariah | D91: Fixed Income | E91: Malaysia | F91: Income | G91: 2 | H91: Annual | I91: 37.96 | J91: 01.07.2020 | K91: Qualified | L91: 100 | M91: 4/4 | N91: 0.49 | O91: 0.3 | P91: 0.19 | Q91: 3.67 | R91: 2.24 | S91: 1.43 | T91: 3.48 | U91: 2.67 | V91: 0.81 | W91: 2.58 | X91: 2.46 | Y91: 0.12 | AC91: =IF(OR(P91="",BL91="",BL91=0),"",P91/BL91) | AD91: =IF(OR(S91="",BL91="",BL91=0),"",S91/BL91) | AE91: =IF(OR(V91="",BL91="",BL91=0),"",V91/BL91) | AF91: =IF(OR(Y91="",BL91="",BL91=0),"",Y91/BL91) | AG91: =IF(OR(AB91="",BL91="",BL91=0),"",AB91/BL91) | AJ91: 36.9 | AK91: 63.1 | BK91: IJM Treasury Management Sdn Bhd - 20/05/2026** | Sabah Credit Corporation - 3.66% / 2032* | Bank Islam Malaysia Berhad - 4.58% / 2029 / 2123* | Petroleum Sarawak E&P Sdn Bhd - 3.64% / 2032* | RHB Bank Berhad - 3.81% / 2032* | BL91: 0.3 | BM91: Very Low | BN91: Bond Sukuk Malaysia | BO91: 50%12-MonthGeneralInvestmentAccountRate(priorto1July2025),50%Public IslamicBank12-MonthTermDeposit-i(w.e.f.1July2025)and50%PublicIslamic Bank 1-Month Term Deposit-i. | BP91: 1.037 | BQ91: 2025-07-31 | BR91: 1.0252 | BS91: -1.14 | BT91: 249
A92: PUBLIC ENHANCED BOND FUND | B92: PEBF | C92: Conventional | D92: Fixed Income | E92: Malaysia | F92: Capital Growth + Income | G92: 2 | H92: Annual | I92: 884.86 | J92: 19.01.2005 | K92: Qualified | L92: 80 | M92: 4/5 | N92: -2.06 | O92: 0.32 | P92: -2.38 | Q92: 4.32 | R92: 2.22 | S92: 2.1 | T92: 7.38 | U92: 2.55 | V92: 4.83 | W92: 4.53 | X92: 2.38 | Y92: 2.15 | Z92: 4.66 | AA92: 2.67 | AB92: 1.99 | AC92: =IF(OR(P92="",BL92="",BL92=0),"",P92/BL92) | AD92: =IF(OR(S92="",BL92="",BL92=0),"",S92/BL92) | AE92: =IF(OR(V92="",BL92="",BL92=0),"",V92/BL92) | AF92: =IF(OR(Y92="",BL92="",BL92=0),"",Y92/BL92) | AG92: =IF(OR(AB92="",BL92="",BL92=0),"",AB92/BL92) | AH92: 2.5 | AI92: 12.6 | AJ92: 71.6 | AK92: 13.3 | BK92: Government Investment Issue - 4.291% / 2043* | Projek Lebuhraya Usahasama Berhad - 5.00% / 2038* | Danum Capital Berhad - 3.72% / 2040* | Pengurusan Air SPV Berhad - 4.06% / 2039* | PNB Merdeka Ventures Sdn Bhd - 3.79% / 2032* | BL92: 3.2 | BM92: Very Low | BN92: Mixed Asset MYR | BP92: 1.1848 | BQ92: 2025-10-06 | BR92: 1.064 | BS92: -10.2 | BT92: 182
A93: PB INFRASTRUCTURE BOND FUND | B93: PBINFBF | C93: Conventional | D93: Fixed Income | E93: Malaysia | F93: Income | G93: 2 | H93: Annual | I93: 420.97 | J93: 11.05.2010 | K93: Qualified | L93: 80 | M93: 4/5 | N93: 0.24 | O93: 0.32 | P93: -0.08 | Q93: 4.61 | R93: 2.21 | S93: 2.4 | T93: 5.44 | U93: 2.5 | V93: 2.94 | W93: 3.65 | X93: 2.35 | Y93: 1.3 | Z93: 4.28 | AA93: 2.65 | AB93: 1.63 | AC93: =IF(OR(P93="",BL93="",BL93=0),"",P93/BL93) | AD93: =IF(OR(S93="",BL93="",BL93=0),"",S93/BL93) | AE93: =IF(OR(V93="",BL93="",BL93=0),"",V93/BL93) | AF93: =IF(OR(Y93="",BL93="",BL93=0),"",Y93/BL93) | AG93: =IF(OR(AB93="",BL93="",BL93=0),"",AB93/BL93) | AJ93: 70.8 | AK93: 29.2 | BK93: Sarawak Energy Berhad - 3.88% / 2040* | Pengurusan Air Selangor Sdn Bhd - 4.26% / 2049* | YTL Power International Berhad - 4.74% / 2038* | Pengurusan Air SPV Berhad - 4.06% / 2039* | Prasarana Malaysia Berhad - 4.12% / 2046* | BL93: 1.8 | BM93: Very Low | BN93: Bond MYR | BP93: 1.1814 | BQ93: 2025-06-30 | BR93: 1.1434 | BS93: -3.22 | BT93: 280
A94: PB BOND FUND | B94: PBBOND | C94: Conventional | D94: Fixed Income | E94: Malaysia | F94: Income | G94: 2 | H94: Annual | I94: 242.68 | J94: 06.09.2011 | K94: Qualified | L94: 80 | M94: 4/5 | N94: 0.2 | O94: 0.32 | P94: -0.12 | Q94: 4.31 | R94: 2.21 | S94: 2.1 | T94: 4.93 | U94: 2.5 | V94: 2.43 | W94: 3.67 | X94: 2.35 | Y94: 1.32 | Z94: 4.19 | AA94: 2.65 | AB94: 1.54 | AC94: =IF(OR(P94="",BL94="",BL94=0),"",P94/BL94) | AD94: =IF(OR(S94="",BL94="",BL94=0),"",S94/BL94) | AE94: =IF(OR(V94="",BL94="",BL94=0),"",V94/BL94) | AF94: =IF(OR(Y94="",BL94="",BL94=0),"",Y94/BL94) | AG94: =IF(OR(AB94="",BL94="",BL94=0),"",AB94/BL94) | AJ94: 80.6 | AK94: 19.4 | BK94: Government Investment Issue - 3.775% / 2045* | Government Investment Issue - 4.291% / 2043* | IJM Treasury Management Sdn Bhd - 20/05/2026** | Projek Lebuhraya Usahasama Berhad - 5.00% / 2038* | Johor Plantations Group Berhad - 4.19% / 2039* | BL94: 1.5 | BM94: Very Low | BN94: Bond MYR | BP94: 1.1466 | BQ94: 2020-08-25 | BR94: 1.0716 | BS94: -6.54 | BT94: 2050
A95: PB AIMAN SUKUK FUND | B95: PBASF | C95: Conventional | D95: Fixed Income | E95: Malaysia | F95: Income | G95: 2 | H95: Annual | I95: 817.91 | J95: 10.09.2013 | K95: Qualified | L95: 80 | M95: 4/5 | N95: 0.23 | O95: 0.32 | P95: -0.09 | Q95: 4.79 | R95: 2.59 | S95: 2.2 | T95: 5.52 | U95: 3.13 | V95: 2.39 | W95: 4.07 | X95: 2.91 | Y95: 1.16 | Z95: 4.95 | AA95: 3.06 | AB95: 1.89 | AC95: =IF(OR(P95="",BL95="",BL95=0),"",P95/BL95) | AD95: =IF(OR(S95="",BL95="",BL95=0),"",S95/BL95) | AE95: =IF(OR(V95="",BL95="",BL95=0),"",V95/BL95) | AF95: =IF(OR(Y95="",BL95="",BL95=0),"",Y95/BL95) | AG95: =IF(OR(AB95="",BL95="",BL95=0),"",AB95/BL95) | AJ95: 80.3 | AK95: 19.7 | BK95: Government Investment Issue - 3.775% / 2045* | Sarawak Energy Berhad - 3.88% / 2040* | Pengurusan Air SPV Berhad - 4.06% / 2039* | S P Setia Berhad - 4.00% / 2036* | Government Investment Issue - 4.291% / 2043* | BL95: 1.5 | BM95: Very Low | BN95: Bond Sukuk Malaysia | BO95: 12-Month General Investment Account (GIA) rate (prior to 1 July 2025). Public Islamic Bank 12-Month Term Deposit-i (w.e.f. 1 July 2025). | BP95: 1.1679 | BQ95: 2020-08-06 | BR95: 1.1025 | BS95: -5.6 | BT95: 2069
A96: PUBLIC ENTERPRISES BOND FUND | B96: PENTBF | C96: Conventional | D96: Fixed Income | E96: Malaysia | F96: Income | G96: 2 | H96: Annual | I96: 1280.73 | J96: 20.03.2012 | K96: Qualified | L96: 80 | M96: 4/5 | N96: 0.31 | O96: 0.32 | P96: -0.01 | Q96: 4.05 | R96: 2.21 | S96: 1.84 | T96: 4.8 | U96: 2.5 | V96: 2.3 | W96: 3.52 | X96: 2.35 | Y96: 1.17 | Z96: 4.45 | AA96: 2.65 | AB96: 1.8 | AC96: =IF(OR(P96="",BL96="",BL96=0),"",P96/BL96) | AD96: =IF(OR(S96="",BL96="",BL96=0),"",S96/BL96) | AE96: =IF(OR(V96="",BL96="",BL96=0),"",V96/BL96) | AF96: =IF(OR(Y96="",BL96="",BL96=0),"",Y96/BL96) | AG96: =IF(OR(AB96="",BL96="",BL96=0),"",AB96/BL96) | AJ96: 79.9 | AK96: 20.1 | BK96: Bank Islam Malaysia Berhad - 3.85% / 2032** | Tenaga Nasional Berhad - 4.98% / 2038** | Public Bank Berhad - 3.73% / 2032* | Petroleum Sarawak E&P Sdn Bhd - 3.70% / 2035** | CIMB Islamic Bank Berhad - 4.07% / 2035** | BL96: 1.3 | BM96: Very Low | BN96: Bond MYR | BP96: 1.1489 | BQ96: 2020-08-25 | BR96: 1.0909 | BS96: -5.05 | BT96: 2050
A97: PUBLIC ISLAMIC INFRASTRUCTURE BOND FUND | B97: PIINFBF | C97: Shariah | D97: Fixed Income | E97: Malaysia | F97: Income | G97: 2 | H97: Annual | I97: 1199.86 | J97: 16.11.2010 | K97: Qualified | L97: 80 | M97: 4/5 | N97: 0.14 | O97: 0.32 | P97: -0.18 | Q97: 4.49 | R97: 2.59 | S97: 1.9 | T97: 5.37 | U97: 3.13 | V97: 2.24 | W97: 3.62 | X97: 2.91 | Y97: 0.71 | Z97: 4.16 | AA97: 3.06 | AB97: 1.1 | AC97: =IF(OR(P97="",BL97="",BL97=0),"",P97/BL97) | AD97: =IF(OR(S97="",BL97="",BL97=0),"",S97/BL97) | AE97: =IF(OR(V97="",BL97="",BL97=0),"",V97/BL97) | AF97: =IF(OR(Y97="",BL97="",BL97=0),"",Y97/BL97) | AG97: =IF(OR(AB97="",BL97="",BL97=0),"",AB97/BL97) | AJ97: 79.3 | AK97: 20.7 | BK97: TNB Power Generation Sdn Bhd - 4.84% / 2043* | Manjung Island Energy Berhad - 4.90% / 2031* | Sarawak Energy Berhad - 3.88% / 2040* | Government Investment Issue - 3.775% / 2045* | YTL Power International Berhad - 4.21% / 2037* | BL97: 1.9 | BM97: Very Low | BN97: Bond Sukuk Malaysia | BO97: 12-Month General Investment Account (GIA) rate (prior to 1 July 2025). Public Islamic Bank 12-Month Term Deposit-i (w.e.f. 1 July 2025). | BP97: 1.1604 | BQ97: 2020-08-06 | BR97: 1.1062 | BS97: -4.67 | BT97: 2069
A98: PUBLIC STRATEGIC BOND FUND | B98: PSTBF | C98: Conventional | D98: Fixed Income | E98: Malaysia | F98: Income | G98: 2 | H98: Annual | I98: 452.4 | J98: 30.12.2010 | K98: Qualified | L98: 80 | M98: 4/5 | N98: 0.31 | O98: 0.32 | P98: -0.01 | Q98: 3.93 | R98: 2.21 | S98: 1.72 | T98: 4.46 | U98: 2.5 | V98: 1.96 | W98: 3.4 | X98: 2.35 | Y98: 1.05 | Z98: 4.01 | AA98: 2.65 | AB98: 1.36 | AC98: =IF(OR(P98="",BL98="",BL98=0),"",P98/BL98) | AD98: =IF(OR(S98="",BL98="",BL98=0),"",S98/BL98) | AE98: =IF(OR(V98="",BL98="",BL98=0),"",V98/BL98) | AF98: =IF(OR(Y98="",BL98="",BL98=0),"",Y98/BL98) | AG98: =IF(OR(AB98="",BL98="",BL98=0),"",AB98/BL98) | AJ98: 80.8 | AK98: 19.2 | BK98: PNB Merdeka Ventures Sdn Bhd - 3.64% / 2030** | Danum Capital Berhad - 3.82% / 2036** | Government Investment Issue - 4.638% / 2049** | Affin Bank Berhad - 4.10% / 2029* | Saracap Ventures Sdn Bhd - 3.81% / 2035* | BL98: 1.1 | BM98: Very Low | BN98: Bond MYR | BP98: 1.1253 | BQ98: 2020-11-09 | BR98: 1.0636 | BS98: -5.48 | BT98: 1974
A99: PUBLIC SUKUK FUND | B99: PSKF | C99: Shariah | D99: Fixed Income | E99: Malaysia | F99: Income | G99: 2 | H99: Annual | I99: 668.12 | J99: 19.07.2011 | K99: Qualified | L99: 80 | M99: 4/5 | N99: 0.25 | O99: 0.32 | P99: -0.07 | Q99: 4.4 | R99: 2.59 | S99: 1.81 | T99: 5.06 | U99: 3.13 | V99: 1.93 | W99: 3.52 | X99: 2.91 | Y99: 0.61 | Z99: 4.06 | AA99: 3.06 | AB99: 1 | AC99: =IF(OR(P99="",BL99="",BL99=0),"",P99/BL99) | AD99: =IF(OR(S99="",BL99="",BL99=0),"",S99/BL99) | AE99: =IF(OR(V99="",BL99="",BL99=0),"",V99/BL99) | AF99: =IF(OR(Y99="",BL99="",BL99=0),"",Y99/BL99) | AG99: =IF(OR(AB99="",BL99="",BL99=0),"",AB99/BL99) | AJ99: 83.4 | AK99: 16.6 | BK99: Government Investment Issue - 3.775% / 2045* | Projek Lebuhraya Usahasama Berhad - 5.00% / 2038* | Government Investment Issue - 4.291% / 2043* | Johor Plantations Group Berhad - 4.19% / 2039* | IJM Treasury Management Sdn Bhd - 20/05/2026** | BL99: 1.7 | BM99: Very Low | BN99: Bond Sukuk Malaysia | BO99: 12-Month General Investment Account (GIA) rate (prior to 1 July 2025). Public Islamic Bank 12-Month Term Deposit-i (w.e.f. 1 July 2025). | BP99: 1.1584 | BQ99: 2020-08-06 | BR99: 1.0984 | BS99: -5.18 | BT99: 2069
A100: PUBLIC ISLAMIC BOND FUND | B100: PI BOND | C100: Shariah | D100: Fixed Income | E100: Malaysia | F100: Income | G100: 2 | H100: Annual | I100: 908.98 | J100: 15.08.2001 | K100: Qualified | L100: 80 | M100: 4/5 | N100: 0.29 | O100: 0.32 | P100: -0.03 | Q100: 4.29 | R100: 2.59 | S100: 1.7 | T100: 5.04 | U100: 3.13 | V100: 1.91 | W100: 3.78 | X100: 2.91 | Y100: 0.87 | Z100: 4.37 | AA100: 3.06 | AB100: 1.31 | AC100: =IF(OR(P100="",BL100="",BL100=0),"",P100/BL100) | AD100: =IF(OR(S100="",BL100="",BL100=0),"",S100/BL100) | AE100: =IF(OR(V100="",BL100="",BL100=0),"",V100/BL100) | AF100: =IF(OR(Y100="",BL100="",BL100=0),"",Y100/BL100) | AG100: =IF(OR(AB100="",BL100="",BL100=0),"",AB100/BL100) | AJ100: 80.1 | AK100: 19.9 | BK100: CIMB Islamic Bank Berhad - 4.07% / 2035* | Government Investment Issue - 3.775% / 2045* | Government Investment Issue - 4.291% / 2043* | Pengurusan Air SPV Berhad - 4.06% / 2039* | Petroleum Sarawak E&P Sdn Bhd - 3.70% / 2035* | BL100: 1.6 | BM100: Very Low | BN100: Bond Sukuk Malaysia | BO100: 12-Month General Investment Account (GIA) rate (prior to 1 July 2025). Public Islamic Bank 12-Month Term Deposit-i (w.e.f. 1 July 2025). | BP100: 1.108 | BQ100: 2010-10-26 | BR100: 0.9679 | BS100: -12.64 | BT100: 5641
...

Sheet Summary
A1: PUBLIC MUTUAL FUND SCREENER — SUMMARY | MFR February 2026
A3: SCREENING RESULTS
A4: Metric | B4: Value
A5: Total PHS files (all UT funds) | B5: 181
A6: Excluded: Class-B funds | B6: 6 | C6: (PeCDF-B, PMMF-B, PBCMF-B, PeICDF-B, PIMMF-B, PBICMF-B)
A7: Excluded: Wholesale funds | B7: 4 | C7: (PBCPF, PWSIF, PIWSIF, PeWS20F)
A8: Retail funds screened | B8: 171
A10: Funds qualified (≥60% beat rate) | B10: 111
A11: Funds disqualified | B11: 60
A12: Pass rate | B12: 64.9%
A13: Conventional funds qualified | B13: 67
A14: Shariah-compliant funds qualified | B14: 44
A16: Data source | B16: MFR February 2026
A17: Screening criteria | B17: ≥60% of YTD/1Y/3Y/5Y/10Y periods outperform benchmark
A18: Minimum data requirement | B18: ≥2 periods (YTD, 1Y, 3Y, 5Y, 10Y)
A19: Note | B19: Class-B & Wholesale funds excluded — not available to typical retail investors
A21: BREAKDOWN BY FUND TYPE
A22: Fund Type | B22: Qualified | C22: 100% Rate | D22: Shariah | E22: Conventional
A23: Equity | B23: =COUNTIFS(Master!K$4:K$174,"Qualified",Master!D$4:D$174,"Equity") | C23: =COUNTIFS(Master!K$4:K$174,"Qualified",Master!D$4:D$174,"Equity",Master!L$4:L$174,100) | D23: =COUNTIFS(Master!K$4:K$174,"Qualified",Master!D$4:D$174,"Equity",Master!C$4:C$174,"Shariah") | E23: =B23-D23
A24: Mixed Asset / Balanced | B24: =COUNTIFS(Master!K$4:K$174,"Qualified",Master!D$4:D$174,"Mixed Asset / Balanced") | C24: =COUNTIFS(Master!K$4:K$174,"Qualified",Master!D$4:D$174,"Mixed Asset / Balanced",Master!L$4:L$174,100) | D24: =COUNTIFS(Master!K$4:K$174,"Qualified",Master!D$4:D$174,"Mixed Asset / Balanced",Master!C$4:C$174,"Shariah") | E24: =B24-D24
A25: Fixed Income | B25: =COUNTIFS(Master!K$4:K$174,"Qualified",Master!D$4:D$174,"Fixed Income") | C25: =COUNTIFS(Master!K$4:K$174,"Qualified",Master!D$4:D$174,"Fixed Income",Master!L$4:L$174,100) | D25: =COUNTIFS(Master!K$4:K$174,"Qualified",Master!D$4:D$174,"Fixed Income",Master!C$4:C$174,"Shariah") | E25: =B25-D25
A26: Fund of Funds | B26: =COUNTIFS(Master!K$4:K$174,"Qualified",Master!D$4:D$174,"Fund of Funds") | C26: =COUNTIFS(Master!K$4:K$174,"Qualified",Master!D$4:D$174,"Fund of Funds",Master!L$4:L$174,100) | D26: =COUNTIFS(Master!K$4:K$174,"Qualified",Master!D$4:D$174,"Fund of Funds",Master!C$4:C$174,"Shariah") | E26: =B26-D26
A27: Money Market | B27: =COUNTIFS(Master!K$4:K$174,"Qualified",Master!D$4:D$174,"Money Market") | C27: =COUNTIFS(Master!K$4:K$174,"Qualified",Master!D$4:D$174,"Money Market",Master!L$4:L$174,100) | D27: =COUNTIFS(Master!K$4:K$174,"Qualified",Master!D$4:D$174,"Money Market",Master!C$4:C$174,"Shariah") | E27: =B27-D27
A28: TOTAL | B28: =SUM(B23:B27) | C28: =SUM(C23:C27) | D28: =SUM(D23:D27) | E28: =SUM(E23:E27)
A30: EQUITY — MEDIAN STATISTICS
A31: Metric | B31: YTD (%) | C31: 1Y (%) | D31: 3Y Ann. (%) | E31: 5Y Ann. (%) | F31: 10Y Ann. (%) | G31: 3Y Alpha (%) | H31: Beat (%)
A32: Median | B32: =IFERROR(MEDIAN(FILTER(Master!N$4:N$174,(Master!K$4:K$174="Qualified")*(Master!D$4:D$174="Equity"))),"") | C32: =IFERROR(MEDIAN(FILTER(Master!Q$4:Q$174,(Master!K$4:K$174="Qualified")*(Master!D$4:D$174="Equity"))),"") | D32: =IFERROR(MEDIAN(FILTER(Master!T$4:T$174,(Master!K$4:K$174="Qualified")*(Master!D$4:D$174="Equity"))),"") | E32: =IFERROR(MEDIAN(FILTER(Master!W$4:W$174,(Master!K$4:K$174="Qualified")*(Master!D$4:D$174="Equity"))),"") | F32: =IFERROR(MEDIAN(FILTER(Master!Z$4:Z$174,(Master!K$4:K$174="Qualified")*(Master!D$4:D$174="Equity"))),"") | G32: =IFERROR(MEDIAN(FILTER(Master!V$4:V$174,(Master!K$4:K$174="Qualified")*(Master!D$4:D$174="Equity"))),"") | H32: =IFERROR(MEDIAN(FILTER(Master!L$4:L$174,(Master!K$4:K$174="Qualified")*(Master!D$4:D$174="Equity"))),"")
A34: EQUITY — TOP 5 BY 3Y ANN. FUND RETURN
A35: Fund Name | B35: Abbr | C35: 3Y Fund (%) | D35: 3Y Alpha (%) | E35: Beat (%) | F35: AUM (RM M) | G35: VC
A36: =IFERROR(INDEX(SORT(FILTER({Master!A$4:A$174,Master!B$4:B$174,Master!T$4:T$174,Master!V$4:V$174,Master!L$4:L$174,Master!I$4:I$174,Master!BM$4:BM$174},Master!K$4:K$174="Qualified",Master!D$4:D$174="Equity",Master!T$4:T$174<>""),3,FALSE),1,1),"") | B36: =IFERROR(INDEX(SORT(FILTER({Master!A$4:A$174,Master!B$4:B$174,Master!T$4:T$174,Master!V$4:V$174,Master!L$4:L$174,Master!I$4:I$174,Master!BM$4:BM$174},Master!K$4:K$174="Qualified",Master!D$4:D$174="Equity",Master!T$4:T$174<>""),3,FALSE),1,2),"") | C36: =IFERROR(INDEX(SORT(FILTER({Master!A$4:A$174,Master!B$4:B$174,Master!T$4:T$174,Master!V$4:V$174,Master!L$4:L$174,Master!I$4:I$174,Master!BM$4:BM$174},Master!K$4:K$174="Qualified",Master!D$4:D$174="Equity",Master!T$4:T$174<>""),3,FALSE),1,3),"") | D36: =IFERROR(INDEX(SORT(FILTER({Master!A$4:A$174,Master!B$4:B$174,Master!T$4:T$174,Master!V$4:V$174,Master!L$4:L$174,Master!I$4:I$174,Master!BM$4:BM$174},Master!K$4:K$174="Qualified",Master!D$4:D$174="Equity",Master!T$4:T$174<>""),3,FALSE),1,4),"") | E36: =IFERROR(INDEX(SORT(FILTER({Master!A$4:A$174,Master!B$4:B$174,Master!T$4:T$174,Master!V$4:V$174,Master!L$4:L$174,Master!I$4:I$174,Master!BM$4:BM$174},Master!K$4:K$174="Qualified",Master!D$4:D$174="Equity",Master!T$4:T$174<>""),3,FALSE),1,5),"") | F36: =IFERROR(INDEX(SORT(FILTER({Master!A$4:A$174,Master!B$4:B$174,Master!T$4:T$174,Master!V$4:V$174,Master!L$4:L$174,Master!I$4:I$174,Master!BM$4:BM$174},Master!K$4:K$174="Qualified",Master!D$4:D$174="Equity",Master!T$4:T$174<>""),3,FALSE),1,6),"") | G36: =IFERROR(INDEX(SORT(FILTER({Master!A$4:A$174,Master!B$4:B$174,Master!T$4:T$174,Master!V$4:V$174,Master!L$4:L$174,Master!I$4:I$174,Master!BM$4:BM$174},Master!K$4:K$174="Qualified",Master!D$4:D$174="Equity",Master!T$4:T$174<>""),3,FALSE),1,7),"")
A37: =IFERROR(INDEX(SORT(FILTER({Master!A$4:A$174,Master!B$4:B$174,Master!T$4:T$174,Master!V$4:V$174,Master!L$4:L$174,Master!I$4:I$174,Master!BM$4:BM$174},Master!K$4:K$174="Qualified",Master!D$4:D$174="Equity",Master!T$4:T$174<>""),3,FALSE),2,1),"") | B37: =IFERROR(INDEX(SORT(FILTER({Master!A$4:A$174,Master!B$4:B$174,Master!T$4:T$174,Master!V$4:V$174,Master!L$4:L$174,Master!I$4:I$174,Master!BM$4:BM$174},Master!K$4:K$174="Qualified",Master!D$4:D$174="Equity",Master!T$4:T$174<>""),3,FALSE),2,2),"") | C37: =IFERROR(INDEX(SORT(FILTER({Master!A$4:A$174,Master!B$4:B$174,Master!T$4:T$174,Master!V$4:V$174,Master!L$4:L$174,Master!I$4:I$174,Master!BM$4:BM$174},Master!K$4:K$174="Qualified",Master!D$4:D$174="Equity",Master!T$4:T$174<>""),3,FALSE),2,3),"") | D37: =IFERROR(INDEX(SORT(FILTER({Master!A$4:A$174,Master!B$4:B$174,Master!T$4:T$174,Master!V$4:V$174,Master!L$4:L$174,Master!I$4:I$174,Master!BM$4:BM$174},Master!K$4:K$174="Qualified",Master!D$4:D$174="Equity",Master!T$4:T$174<>""),3,FALSE),2,4),"") | E37: =IFERROR(INDEX(SORT(FILTER({Master!A$4:A$174,Master!B$4:B$174,Master!T$4:T$174,Master!V$4:V$174,Master!L$4:L$174,Master!I$4:I$174,Master!BM$4:BM$174},Master!K$4:K$174="Qualified",Master!D$4:D$174="Equity",Master!T$4:T$174<>""),3,FALSE),2,5),"") | F37: =IFERROR(INDEX(SORT(FILTER({Master!A$4:A$174,Master!B$4:B$174,Master!T$4:T$174,Master!V$4:V$174,Master!L$4:L$174,Master!I$4:I$174,Master!BM$4:BM$174},Master!K$4:K$174="Qualified",Master!D$4:D$174="Equity",Master!T$4:T$174<>""),3,FALSE),2,6),"") | G37: =IFERROR(INDEX(SORT(FILTER({Master!A$4:A$174,Master!B$4:B$174,Master!T$4:T$174,Master!V$4:V$174,Master!L$4:L$174,Master!I$4:I$174,Master!BM$4:BM$174},Master!K$4:K$174="Qualified",Master!D$4:D$174="Equity",Master!T$4:T$174<>""),3,FALSE),2,7),"")
A38: =IFERROR(INDEX(SORT(FILTER({Master!A$4:A$174,Master!B$4:B$174,Master!T$4:T$174,Master!V$4:V$174,Master!L$4:L$174,Master!I$4:I$174,Master!BM$4:BM$174},Master!K$4:K$174="Qualified",Master!D$4:D$174="Equity",Master!T$4:T$174<>""),3,FALSE),3,1),"") | B38: =IFERROR(INDEX(SORT(FILTER({Master!A$4:A$174,Master!B$4:B$174,Master!T$4:T$174,Master!V$4:V$174,Master!L$4:L$174,Master!I$4:I$174,Master!BM$4:BM$174},Master!K$4:K$174="Qualified",Master!D$4:D$174="Equity",Master!T$4:T$174<>""),3,FALSE),3,2),"") | C38: =IFERROR(INDEX(SORT(FILTER({Master!A$4:A$174,Master!B$4:B$174,Master!T$4:T$174,Master!V$4:V$174,Master!L$4:L$174,Master!I$4:I$174,Master!BM$4:BM$174},Master!K$4:K$174="Qualified",Master!D$4:D$174="Equity",Master!T$4:T$174<>""),3,FALSE),3,3),"") | D38: =IFERROR(INDEX(SORT(FILTER({Master!A$4:A$174,Master!B$4:B$174,Master!T$4:T$174,Master!V$4:V$174,Master!L$4:L$174,Master!I$4:I$174,Master!BM$4:BM$174},Master!K$4:K$174="Qualified",Master!D$4:D$174="Equity",Master!T$4:T$174<>""),3,FALSE),3,4),"") | E38: =IFERROR(INDEX(SORT(FILTER({Master!A$4:A$174,Master!B$4:B$174,Master!T$4:T$174,Master!V$4:V$174,Master!L$4:L$174,Master!I$4:I$174,Master!BM$4:BM$174},Master!K$4:K$174="Qualified",Master!D$4:D$174="Equity",Master!T$4:T$174<>""),3,FALSE),3,5),"") | F38: =IFERROR(INDEX(SORT(FILTER({Master!A$4:A$174,Master!B$4:B$174,Master!T$4:T$174,Master!V$4:V$174,Master!L$4:L$174,Master!I$4:I$174,Master!BM$4:BM$174},Master!K$4:K$174="Qualified",Master!D$4:D$174="Equity",Master!T$4:T$174<>""),3,FALSE),3,6),"") | G38: =IFERROR(INDEX(SORT(FILTER({Master!A$4:A$174,Master!B$4:B$174,Master!T$4:T$174,Master!V$4:V$174,Master!L$4:L$174,Master!I$4:I$174,Master!BM$4:BM$174},Master!K$4:K$174="Qualified",Master!D$4:D$174="Equity",Master!T$4:T$174<>""),3,FALSE),3,7),"")
A39: =IFERROR(INDEX(SORT(FILTER({Master!A$4:A$174,Master!B$4:B$174,Master!T$4:T$174,Master!V$4:V$174,Master!L$4:L$174,Master!I$4:I$174,Master!BM$4:BM$174},Master!K$4:K$174="Qualified",Master!D$4:D$174="Equity",Master!T$4:T$174<>""),3,FALSE),4,1),"") | B39: =IFERROR(INDEX(SORT(FILTER({Master!A$4:A$174,Master!B$4:B$174,Master!T$4:T$174,Master!V$4:V$174,Master!L$4:L$174,Master!I$4:I$174,Master!BM$4:BM$174},Master!K$4:K$174="Qualified",Master!D$4:D$174="Equity",Master!T$4:T$174<>""),3,FALSE),4,2),"") | C39: =IFERROR(INDEX(SORT(FILTER({Master!A$4:A$174,Master!B$4:B$174,Master!T$4:T$174,Master!V$4:V$174,Master!L$4:L$174,Master!I$4:I$174,Master!BM$4:BM$174},Master!K$4:K$174="Qualified",Master!D$4:D$174="Equity",Master!T$4:T$174<>""),3,FALSE),4,3),"") | D39: =IFERROR(INDEX(SORT(FILTER({Master!A$4:A$174,Master!B$4:B$174,Master!T$4:T$174,Master!V$4:V$174,Master!L$4:L$174,Master!I$4:I$174,Master!BM$4:BM$174},Master!K$4:K$174="Qualified",Master!D$4:D$174="Equity",Master!T$4:T$174<>""),3,FALSE),4,4),"") | E39: =IFERROR(INDEX(SORT(FILTER({Master!A$4:A$174,Master!B$4:B$174,Master!T$4:T$174,Master!V$4:V$174,Master!L$4:L$174,Master!I$4:I$174,Master!BM$4:BM$174},Master!K$4:K$174="Qualified",Master!D$4:D$174="Equity",Master!T$4:T$174<>""),3,FALSE),4,5),"") | F39: =IFERROR(INDEX(SORT(FILTER({Master!A$4:A$174,Master!B$4:B$174,Master!T$4:T$174,Master!V$4:V$174,Master!L$4:L$174,Master!I$4:I$174,Master!BM$4:BM$174},Master!K$4:K$174="Qualified",Master!D$4:D$174="Equity",Master!T$4:T$174<>""),3,FALSE),4,6),"") | G39: =IFERROR(INDEX(SORT(FILTER({Master!A$4:A$174,Master!B$4:B$174,Master!T$4:T$174,Master!V$4:V$174,Master!L$4:L$174,Master!I$4:I$174,Master!BM$4:BM$174},Master!K$4:K$174="Qualified",Master!D$4:D$174="Equity",Master!T$4:T$174<>""),3,FALSE),4,7),"")
A40: =IFERROR(INDEX(SORT(FILTER({Master!A$4:A$174,Master!B$4:B$174,Master!T$4:T$174,Master!V$4:V$174,Master!L$4:L$174,Master!I$4:I$174,Master!BM$4:BM$174},Master!K$4:K$174="Qualified",Master!D$4:D$174="Equity",Master!T$4:T$174<>""),3,FALSE),5,1),"") | B40: =IFERROR(INDEX(SORT(FILTER({Master!A$4:A$174,Master!B$4:B$174,Master!T$4:T$174,Master!V$4:V$174,Master!L$4:L$174,Master!I$4:I$174,Master!BM$4:BM$174},Master!K$4:K$174="Qualified",Master!D$4:D$174="Equity",Master!T$4:T$174<>""),3,FALSE),5,2),"") | C40: =IFERROR(INDEX(SORT(FILTER({Master!A$4:A$174,Master!B$4:B$174,Master!T$4:T$174,Master!V$4:V$174,Master!L$4:L$174,Master!I$4:I$174,Master!BM$4:BM$174},Master!K$4:K$174="Qualified",Master!D$4:D$174="Equity",Master!T$4:T$174<>""),3,FALSE),5,3),"") | D40: =IFERROR(INDEX(SORT(FILTER({Master!A$4:A$174,Master!B$4:B$174,Master!T$4:T$174,Master!V$4:V$174,Master!L$4:L$174,Master!I$4:I$174,Master!BM$4:BM$174},Master!K$4:K$174="Qualified",Master!D$4:D$174="Equity",Master!T$4:T$174<>""),3,FALSE),5,4),"") | E40: =IFERROR(INDEX(SORT(FILTER({Master!A$4:A$174,Master!B$4:B$174,Master!T$4:T$174,Master!V$4:V$174,Master!L$4:L$174,Master!I$4:I$174,Master!BM$4:BM$174},Master!K$4:K$174="Qualified",Master!D$4:D$174="Equity",Master!T$4:T$174<>""),3,FALSE),5,5),"") | F40: =IFERROR(INDEX(SORT(FILTER({Master!A$4:A$174,Master!B$4:B$174,Master!T$4:T$174,Master!V$4:V$174,Master!L$4:L$174,Master!I$4:I$174,Master!BM$4:BM$174},Master!K$4:K$174="Qualified",Master!D$4:D$174="Equity",Master!T$4:T$174<>""),3,FALSE),5,6),"") | G40: =IFERROR(INDEX(SORT(FILTER({Master!A$4:A$174,Master!B$4:B$174,Master!T$4:T$174,Master!V$4:V$174,Master!L$4:L$174,Master!I$4:I$174,Master!BM$4:BM$174},Master!K$4:K$174="Qualified",Master!D$4:D$174="Equity",Master!T$4:T$174<>""),3,FALSE),5,7),"")
A42: EQUITY — TOP 5 BY 3Y ANN. ALPHA
A43: Fund Name | B43: Abbr | C43: 3Y Fund (%) | D43: 3Y Alpha (%) | E43: Beat (%) | F43: AUM (RM M) | G43: VC
A44: =IFERROR(INDEX(SORT(FILTER({Master!A$4:A$174,Master!B$4:B$174,Master!T$4:T$174,Master!V$4:V$174,Master!L$4:L$174,Master!I$4:I$174,Master!BM$4:BM$174},Master!K$4:K$174="Qualified",Master!D$4:D$174="Equity",Master!V$4:V$174<>""),4,FALSE),1,1),"") | B44: =IFERROR(INDEX(SORT(FILTER({Master!A$4:A$174,Master!B$4:B$174,Master!T$4:T$174,Master!V$4:V$174,Master!L$4:L$174,Master!I$4:I$174,Master!BM$4:BM$174},Master!K$4:K$174="Qualified",Master!D$4:D$174="Equity",Master!V$4:V$174<>""),4,FALSE),1,2),"") | C44: =IFERROR(INDEX(SORT(FILTER({Master!A$4:A$174,Master!B$4:B$174,Master!T$4:T$174,Master!V$4:V$174,Master!L$4:L$174,Master!I$4:I$174,Master!BM$4:BM$174},Master!K$4:K$174="Qualified",Master!D$4:D$174="Equity",Master!V$4:V$174<>""),4,FALSE),1,3),"") | D44: =IFERROR(INDEX(SORT(FILTER({Master!A$4:A$174,Master!B$4:B$174,Master!T$4:T$174,Master!V$4:V$174,Master!L$4:L$174,Master!I$4:I$174,Master!BM$4:BM$174},Master!K$4:K$174="Qualified",Master!D$4:D$174="Equity",Master!V$4:V$174<>""),4,FALSE),1,4),"") | E44: =IFERROR(INDEX(SORT(FILTER({Master!A$4:A$174,Master!B$4:B$174,Master!T$4:T$174,Master!V$4:V$174,Master!L$4:L$174,Master!I$4:I$174,Master!BM$4:BM$174},Master!K$4:K$174="Qualified",Master!D$4:D$174="Equity",Master!V$4:V$174<>""),4,FALSE),1,5),"") | F44: =IFERROR(INDEX(SORT(FILTER({Master!A$4:A$174,Master!B$4:B$174,Master!T$4:T$174,Master!V$4:V$174,Master!L$4:L$174,Master!I$4:I$174,Master!BM$4:BM$174},Master!K$4:K$174="Qualified",Master!D$4:D$174="Equity",Master!V$4:V$174<>""),4,FALSE),1,6),"") | G44: =IFERROR(INDEX(SORT(FILTER({Master!A$4:A$174,Master!B$4:B$174,Master!T$4:T$174,Master!V$4:V$174,Master!L$4:L$174,Master!I$4:I$174,Master!BM$4:BM$174},Master!K$4:K$174="Qualified",Master!D$4:D$174="Equity",Master!V$4:V$174<>""),4,FALSE),1,7),"")
A45: =IFERROR(INDEX(SORT(FILTER({Master!A$4:A$174,Master!B$4:B$174,Master!T$4:T$174,Master!V$4:V$174,Master!L$4:L$174,Master!I$4:I$174,Master!BM$4:BM$174},Master!K$4:K$174="Qualified",Master!D$4:D$174="Equity",Master!V$4:V$174<>""),4,FALSE),2,1),"") | B45: =IFERROR(INDEX(SORT(FILTER({Master!A$4:A$174,Master!B$4:B$174,Master!T$4:T$174,Master!V$4:V$174,Master!L$4:L$174,Master!I$4:I$174,Master!BM$4:BM$174},Master!K$4:K$174="Qualified",Master!D$4:D$174="Equity",Master!V$4:V$174<>""),4,FALSE),2,2),"") | C45: =IFERROR(INDEX(SORT(FILTER({Master!A$4:A$174,Master!B$4:B$174,Master!T$4:T$174,Master!V$4:V$174,Master!L$4:L$174,Master!I$4:I$174,Master!BM$4:BM$174},Master!K$4:K$174="Qualified",Master!D$4:D$174="Equity",Master!V$4:V$174<>""),4,FALSE),2,3),"") | D45: =IFERROR(INDEX(SORT(FILTER({Master!A$4:A$174,Master!B$4:B$174,Master!T$4:T$174,Master!V$4:V$174,Master!L$4:L$174,Master!I$4:I$174,Master!BM$4:BM$174},Master!K$4:K$174="Qualified",Master!D$4:D$174="Equity",Master!V$4:V$174<>""),4,FALSE),2,4),"") | E45: =IFERROR(INDEX(SORT(FILTER({Master!A$4:A$174,Master!B$4:B$174,Master!T$4:T$174,Master!V$4:V$174,Master!L$4:L$174,Master!I$4:I$174,Master!BM$4:BM$174},Master!K$4:K$174="Qualified",Master!D$4:D$174="Equity",Master!V$4:V$174<>""),4,FALSE),2,5),"") | F45: =IFERROR(INDEX(SORT(FILTER({Master!A$4:A$174,Master!B$4:B$174,Master!T$4:T$174,Master!V$4:V$174,Master!L$4:L$174,Master!I$4:I$174,Master!BM$4:BM$174},Master!K$4:K$174="Qualified",Master!D$4:D$174="Equity",Master!V$4:V$174<>""),4,FALSE),2,6),"") | G45: =IFERROR(INDEX(SORT(FILTER({Master!A$4:A$174,Master!B$4:B$174,Master!T$4:T$174,Master!V$4:V$174,Master!L$4:L$174,Master!I$4:I$174,Master!BM$4:BM$174},Master!K$4:K$174="Qualified",Master!D$4:D$174="Equity",Master!V$4:V$174<>""),4,FALSE),2,7),"")
A46: =IFERROR(INDEX(SORT(FILTER({Master!A$4:A$174,Master!B$4:B$174,Master!T$4:T$174,Master!V$4:V$174,Master!L$4:L$174,Master!I$4:I$174,Master!BM$4:BM$174},Master!K$4:K$174="Qualified",Master!D$4:D$174="Equity",Master!V$4:V$174<>""),4,FALSE),3,1),"") | B46: =IFERROR(INDEX(SORT(FILTER({Master!A$4:A$174,Master!B$4:B$174,Master!T$4:T$174,Master!V$4:V$174,Master!L$4:L$174,Master!I$4:I$174,Master!BM$4:BM$174},Master!K$4:K$174="Qualified",Master!D$4:D$174="Equity",Master!V$4:V$174<>""),4,FALSE),3,2),"") | C46: =IFERROR(INDEX(SORT(FILTER({Master!A$4:A$174,Master!B$4:B$174,Master!T$4:T$174,Master!V$4:V$174,Master!L$4:L$174,Master!I$4:I$174,Master!BM$4:BM$174},Master!K$4:K$174="Qualified",Master!D$4:D$174="Equity",Master!V$4:V$174<>""),4,FALSE),3,3),"") | D46: =IFERROR(INDEX(SORT(FILTER({Master!A$4:A$174,Master!B$4:B$174,Master!T$4:T$174,Master!V$4:V$174,Master!L$4:L$174,Master!I$4:I$174,Master!BM$4:BM$174},Master!K$4:K$174="Qualified",Master!D$4:D$174="Equity",Master!V$4:V$174<>""),4,FALSE),3,4),"") | E46: =IFERROR(INDEX(SORT(FILTER({Master!A$4:A$174,Master!B$4:B$174,Master!T$4:T$174,Master!V$4:V$174,Master!L$4:L$174,Master!I$4:I$174,Master!BM$4:BM$174},Master!K$4:K$174="Qualified",Master!D$4:D$174="Equity",Master!V$4:V$174<>""),4,FALSE),3,5),"") | F46: =IFERROR(INDEX(SORT(FILTER({Master!A$4:A$174,Master!B$4:B$174,Master!T$4:T$174,Master!V$4:V$174,Master!L$4:L$174,Master!I$4:I$174,Master!BM$4:BM$174},Master!K$4:K$174="Qualified",Master!D$4:D$174="Equity",Master!V$4:V$174<>""),4,FALSE),3,6),"") | G46: =IFERROR(INDEX(SORT(FILTER({Master!A$4:A$174,Master!B$4:B$174,Master!T$4:T$174,Master!V$4:V$174,Master!L$4:L$174,Master!I$4:I$174,Master!BM$4:BM$174},Master!K$4:K$174="Qualified",Master!D$4:D$174="Equity",Master!V$4:V$174<>""),4,FALSE),3,7),"")
A47: =IFERROR(INDEX(SORT(FILTER({Master!A$4:A$174,Master!B$4:B$174,Master!T$4:T$174,Master!V$4:V$174,Master!L$4:L$174,Master!I$4:I$174,Master!BM$4:BM$174},Master!K$4:K$174="Qualified",Master!D$4:D$174="Equity",Master!V$4:V$174<>""),4,FALSE),4,1),"") | B47: =IFERROR(INDEX(SORT(FILTER({Master!A$4:A$174,Master!B$4:B$174,Master!T$4:T$174,Master!V$4:V$174,Master!L$4:L$174,Master!I$4:I$174,Master!BM$4:BM$174},Master!K$4:K$174="Qualified",Master!D$4:D$174="Equity",Master!V$4:V$174<>""),4,FALSE),4,2),"") | C47: =IFERROR(INDEX(SORT(FILTER({Master!A$4:A$174,Master!B$4:B$174,Master!T$4:T$174,Master!V$4:V$174,Master!L$4:L$174,Master!I$4:I$174,Master!BM$4:BM$174},Master!K$4:K$174="Qualified",Master!D$4:D$174="Equity",Master!V$4:V$174<>""),4,FALSE),4,3),"") | D47: =IFERROR(INDEX(SORT(FILTER({Master!A$4:A$174,Master!B$4:B$174,Master!T$4:T$174,Master!V$4:V$174,Master!L$4:L$174,Master!I$4:I$174,Master!BM$4:BM$174},Master!K$4:K$174="Qualified",Master!D$4:D$174="Equity",Master!V$4:V$174<>""),4,FALSE),4,4),"") | E47: =IFERROR(INDEX(SORT(FILTER({Master!A$4:A$174,Master!B$4:B$174,Master!T$4:T$174,Master!V$4:V$174,Master!L$4:L$174,Master!I$4:I$174,Master!BM$4:BM$174},Master!K$4:K$174="Qualified",Master!D$4:D$174="Equity",Master!V$4:V$174<>""),4,FALSE),4,5),"") | F47: =IFERROR(INDEX(SORT(FILTER({Master!A$4:A$174,Master!B$4:B$174,Master!T$4:T$174,Master!V$4:V$174,Master!L$4:L$174,Master!I$4:I$174,Master!BM$4:BM$174},Master!K$4:K$174="Qualified",Master!D$4:D$174="Equity",Master!V$4:V$174<>""),4,FALSE),4,6),"") | G47: =IFERROR(INDEX(SORT(FILTER({Master!A$4:A$174,Master!B$4:B$174,Master!T$4:T$174,Master!V$4:V$174,Master!L$4:L$174,Master!I$4:I$174,Master!BM$4:BM$174},Master!K$4:K$174="Qualified",Master!D$4:D$174="Equity",Master!V$4:V$174<>""),4,FALSE),4,7),"")
A48: =IFERROR(INDEX(SORT(FILTER({Master!A$4:A$174,Master!B$4:B$174,Master!T$4:T$174,Master!V$4:V$174,Master!L$4:L$174,Master!I$4:I$174,Master!BM$4:BM$174},Master!K$4:K$174="Qualified",Master!D$4:D$174="Equity",Master!V$4:V$174<>""),4,FALSE),5,1),"") | B48: =IFERROR(INDEX(SORT(FILTER({Master!A$4:A$174,Master!B$4:B$174,Master!T$4:T$174,Master!V$4:V$174,Master!L$4:L$174,Master!I$4:I$174,Master!BM$4:BM$174},Master!K$4:K$174="Qualified",Master!D$4:D$174="Equity",Master!V$4:V$174<>""),4,FALSE),5,2),"") | C48: =IFERROR(INDEX(SORT(FILTER({Master!A$4:A$174,Master!B$4:B$174,Master!T$4:T$174,Master!V$4:V$174,Master!L$4:L$174,Master!I$4:I$174,Master!BM$4:BM$174},Master!K$4:K$174="Qualified",Master!D$4:D$174="Equity",Master!V$4:V$174<>""),4,FALSE),5,3),"") | D48: =IFERROR(INDEX(SORT(FILTER({Master!A$4:A$174,Master!B$4:B$174,Master!T$4:T$174,Master!V$4:V$174,Master!L$4:L$174,Master!I$4:I$174,Master!BM$4:BM$174},Master!K$4:K$174="Qualified",Master!D$4:D$174="Equity",Master!V$4:V$174<>""),4,FALSE),5,4),"") | E48: =IFERROR(INDEX(SORT(FILTER({Master!A$4:A$174,Master!B$4:B$174,Master!T$4:T$174,Master!V$4:V$174,Master!L$4:L$174,Master!I$4:I$174,Master!BM$4:BM$174},Master!K$4:K$174="Qualified",Master!D$4:D$174="Equity",Master!V$4:V$174<>""),4,FALSE),5,5),"") | F48: =IFERROR(INDEX(SORT(FILTER({Master!A$4:A$174,Master!B$4:B$174,Master!T$4:T$174,Master!V$4:V$174,Master!L$4:L$174,Master!I$4:I$174,Master!BM$4:BM$174},Master!K$4:K$174="Qualified",Master!D$4:D$174="Equity",Master!V$4:V$174<>""),4,FALSE),5,6),"") | G48: =IFERROR(INDEX(SORT(FILTER({Master!A$4:A$174,Master!B$4:B$174,Master!T$4:T$174,Master!V$4:V$174,Master!L$4:L$174,Master!I$4:I$174,Master!BM$4:BM$174},Master!K$4:K$174="Qualified",Master!D$4:D$174="Equity",Master!V$4:V$174<>""),4,FALSE),5,7),"")
A50: EQUITY — TOP 5 BY ALPHA EFFICIENCY
A51: Fund Name | B51: Abbr | C51: Alpha Eff | D51: 3Y Alpha (%) | E51: Beat (%) | F51: AUM (RM M) | G51: VC
A52: =IFERROR(INDEX(SORT(FILTER({Master!A$4:A$174,Master!B$4:B$174,Master!AE$4:AE$174,Master!V$4:V$174,Master!L$4:L$174,Master!I$4:I$174,Master!BM$4:BM$174},Master!K$4:K$174="Qualified",Master!D$4:D$174="Equity",Master!AE$4:AE$174<>""),3,FALSE),1,1),"") | B52: =IFERROR(INDEX(SORT(FILTER({Master!A$4:A$174,Master!B$4:B$174,Master!AE$4:AE$174,Master!V$4:V$174,Master!L$4:L$174,Master!I$4:I$174,Master!BM$4:BM$174},Master!K$4:K$174="Qualified",Master!D$4:D$174="Equity",Master!AE$4:AE$174<>""),3,FALSE),1,2),"") | C52: =IFERROR(INDEX(SORT(FILTER({Master!A$4:A$174,Master!B$4:B$174,Master!AE$4:AE$174,Master!V$4:V$174,Master!L$4:L$174,Master!I$4:I$174,Master!BM$4:BM$174},Master!K$4:K$174="Qualified",Master!D$4:D$174="Equity",Master!AE$4:AE$174<>""),3,FALSE),1,3),"") | D52: =IFERROR(INDEX(SORT(FILTER({Master!A$4:A$174,Master!B$4:B$174,Master!AE$4:AE$174,Master!V$4:V$174,Master!L$4:L$174,Master!I$4:I$174,Master!BM$4:BM$174},Master!K$4:K$174="Qualified",Master!D$4:D$174="Equity",Master!AE$4:AE$174<>""),3,FALSE),1,4),"") | E52: =IFERROR(INDEX(SORT(FILTER({Master!A$4:A$174,Master!B$4:B$174,Master!AE$4:AE$174,Master!V$4:V$174,Master!L$4:L$174,Master!I$4:I$174,Master!BM$4:BM$174},Master!K$4:K$174="Qualified",Master!D$4:D$174="Equity",Master!AE$4:AE$174<>""),3,FALSE),1,5),"") | F52: =IFERROR(INDEX(SORT(FILTER({Master!A$4:A$174,Master!B$4:B$174,Master!AE$4:AE$174,Master!V$4:V$174,Master!L$4:L$174,Master!I$4:I$174,Master!BM$4:BM$174},Master!K$4:K$174="Qualified",Master!D$4:D$174="Equity",Master!AE$4:AE$174<>""),3,FALSE),1,6),"") | G52: =IFERROR(INDEX(SORT(FILTER({Master!A$4:A$174,Master!B$4:B$174,Master!AE$4:AE$174,Master!V$4:V$174,Master!L$4:L$174,Master!I$4:I$174,Master!BM$4:BM$174},Master!K$4:K$174="Qualified",Master!D$4:D$174="Equity",Master!AE$4:AE$174<>""),3,FALSE),1,7),"")
A53: =IFERROR(INDEX(SORT(FILTER({Master!A$4:A$174,Master!B$4:B$174,Master!AE$4:AE$174,Master!V$4:V$174,Master!L$4:L$174,Master!I$4:I$174,Master!BM$4:BM$174},Master!K$4:K$174="Qualified",Master!D$4:D$174="Equity",Master!AE$4:AE$174<>""),3,FALSE),2,1),"") | B53: =IFERROR(INDEX(SORT(FILTER({Master!A$4:A$174,Master!B$4:B$174,Master!AE$4:AE$174,Master!V$4:V$174,Master!L$4:L$174,Master!I$4:I$174,Master!BM$4:BM$174},Master!K$4:K$174="Qualified",Master!D$4:D$174="Equity",Master!AE$4:AE$174<>""),3,FALSE),2,2),"") | C53: =IFERROR(INDEX(SORT(FILTER({Master!A$4:A$174,Master!B$4:B$174,Master!AE$4:AE$174,Master!V$4:V$174,Master!L$4:L$174,Master!I$4:I$174,Master!BM$4:BM$174},Master!K$4:K$174="Qualified",Master!D$4:D$174="Equity",Master!AE$4:AE$174<>""),3,FALSE),2,3),"") | D53: =IFERROR(INDEX(SORT(FILTER({Master!A$4:A$174,Master!B$4:B$174,Master!AE$4:AE$174,Master!V$4:V$174,Master!L$4:L$174,Master!I$4:I$174,Master!BM$4:BM$174},Master!K$4:K$174="Qualified",Master!D$4:D$174="Equity",Master!AE$4:AE$174<>""),3,FALSE),2,4),"") | E53: =IFERROR(INDEX(SORT(FILTER({Master!A$4:A$174,Master!B$4:B$174,Master!AE$4:AE$174,Master!V$4:V$174,Master!L$4:L$174,Master!I$4:I$174,Master!BM$4:BM$174},Master!K$4:K$174="Qualified",Master!D$4:D$174="Equity",Master!AE$4:AE$174<>""),3,FALSE),2,5),"") | F53: =IFERROR(INDEX(SORT(FILTER({Master!A$4:A$174,Master!B$4:B$174,Master!AE$4:AE$174,Master!V$4:V$174,Master!L$4:L$174,Master!I$4:I$174,Master!BM$4:BM$174},Master!K$4:K$174="Qualified",Master!D$4:D$174="Equity",Master!AE$4:AE$174<>""),3,FALSE),2,6),"") | G53: =IFERROR(INDEX(SORT(FILTER({Master!A$4:A$174,Master!B$4:B$174,Master!AE$4:AE$174,Master!V$4:V$174,Master!L$4:L$174,Master!I$4:I$174,Master!BM$4:BM$174},Master!K$4:K$174="Qualified",Master!D$4:D$174="Equity",Master!AE$4:AE$174<>""),3,FALSE),2,7),"")
A54: =IFERROR(INDEX(SORT(FILTER({Master!A$4:A$174,Master!B$4:B$174,Master!AE$4:AE$174,Master!V$4:V$174,Master!L$4:L$174,Master!I$4:I$174,Master!BM$4:BM$174},Master!K$4:K$174="Qualified",Master!D$4:D$174="Equity",Master!AE$4:AE$174<>""),3,FALSE),3,1),"") | B54: =IFERROR(INDEX(SORT(FILTER({Master!A$4:A$174,Master!B$4:B$174,Master!AE$4:AE$174,Master!V$4:V$174,Master!L$4:L$174,Master!I$4:I$174,Master!BM$4:BM$174},Master!K$4:K$174="Qualified",Master!D$4:D$174="Equity",Master!AE$4:AE$174<>""),3,FALSE),3,2),"") | C54: =IFERROR(INDEX(SORT(FILTER({Master!A$4:A$174,Master!B$4:B$174,Master!AE$4:AE$174,Master!V$4:V$174,Master!L$4:L$174,Master!I$4:I$174,Master!BM$4:BM$174},Master!K$4:K$174="Qualified",Master!D$4:D$174="Equity",Master!AE$4:AE$174<>""),3,FALSE),3,3),"") | D54: =IFERROR(INDEX(SORT(FILTER({Master!A$4:A$174,Master!B$4:B$174,Master!AE$4:AE$174,Master!V$4:V$174,Master!L$4:L$174,Master!I$4:I$174,Master!BM$4:BM$174},Master!K$4:K$174="Qualified",Master!D$4:D$174="Equity",Master!AE$4:AE$174<>""),3,FALSE),3,4),"") | E54: =IFERROR(INDEX(SORT(FILTER({Master!A$4:A$174,Master!B$4:B$174,Master!AE$4:AE$174,Master!V$4:V$174,Master!L$4:L$174,Master!I$4:I$174,Master!BM$4:BM$174},Master!K$4:K$174="Qualified",Master!D$4:D$174="Equity",Master!AE$4:AE$174<>""),3,FALSE),3,5),"") | F54: =IFERROR(INDEX(SORT(FILTER({Master!A$4:A$174,Master!B$4:B$174,Master!AE$4:AE$174,Master!V$4:V$174,Master!L$4:L$174,Master!I$4:I$174,Master!BM$4:BM$174},Master!K$4:K$174="Qualified",Master!D$4:D$174="Equity",Master!AE$4:AE$174<>""),3,FALSE),3,6),"") | G54: =IFERROR(INDEX(SORT(FILTER({Master!A$4:A$174,Master!B$4:B$174,Master!AE$4:AE$174,Master!V$4:V$174,Master!L$4:L$174,Master!I$4:I$174,Master!BM$4:BM$174},Master!K$4:K$174="Qualified",Master!D$4:D$174="Equity",Master!AE$4:AE$174<>""),3,FALSE),3,7),"")
A55: =IFERROR(INDEX(SORT(FILTER({Master!A$4:A$174,Master!B$4:B$174,Master!AE$4:AE$174,Master!V$4:V$174,Master!L$4:L$174,Master!I$4:I$174,Master!BM$4:BM$174},Master!K$4:K$174="Qualified",Master!D$4:D$174="Equity",Master!AE$4:AE$174<>""),3,FALSE),4,1),"") | B55: =IFERROR(INDEX(SORT(FILTER({Master!A$4:A$174,Master!B$4:B$174,Master!AE$4:AE$174,Master!V$4:V$174,Master!L$4:L$174,Master!I$4:I$174,Master!BM$4:BM$174},Master!K$4:K$174="Qualified",Master!D$4:D$174="Equity",Master!AE$4:AE$174<>""),3,FALSE),4,2),"") | C55: =IFERROR(INDEX(SORT(FILTER({Master!A$4:A$174,Master!B$4:B$174,Master!AE$4:AE$174,Master!V$4:V$174,Master!L$4:L$174,Master!I$4:I$174,Master!BM$4:BM$174},Master!K$4:K$174="Qualified",Master!D$4:D$174="Equity",Master!AE$4:AE$174<>""),3,FALSE),4,3),"") | D55: =IFERROR(INDEX(SORT(FILTER({Master!A$4:A$174,Master!B$4:B$174,Master!AE$4:AE$174,Master!V$4:V$174,Master!L$4:L$174,Master!I$4:I$174,Master!BM$4:BM$174},Master!K$4:K$174="Qualified",Master!D$4:D$174="Equity",Master!AE$4:AE$174<>""),3,FALSE),4,4),"") | E55: =IFERROR(INDEX(SORT(FILTER({Master!A$4:A$174,Master!B$4:B$174,Master!AE$4:AE$174,Master!V$4:V$174,Master!L$4:L$174,Master!I$4:I$174,Master!BM$4:BM$174},Master!K$4:K$174="Qualified",Master!D$4:D$174="Equity",Master!AE$4:AE$174<>""),3,FALSE),4,5),"") | F55: =IFERROR(INDEX(SORT(FILTER({Master!A$4:A$174,Master!B$4:B$174,Master!AE$4:AE$174,Master!V$4:V$174,Master!L$4:L$174,Master!I$4:I$174,Master!BM$4:BM$174},Master!K$4:K$174="Qualified",Master!D$4:D$174="Equity",Master!AE$4:AE$174<>""),3,FALSE),4,6),"") | G55: =IFERROR(INDEX(SORT(FILTER({Master!A$4:A$174,Master!B$4:B$174,Master!AE$4:AE$174,Master!V$4:V$174,Master!L$4:L$174,Master!I$4:I$174,Master!BM$4:BM$174},Master!K$4:K$174="Qualified",Master!D$4:D$174="Equity",Master!AE$4:AE$174<>""),3,FALSE),4,7),"")
A56: =IFERROR(INDEX(SORT(FILTER({Master!A$4:A$174,Master!B$4:B$174,Master!AE$4:AE$174,Master!V$4:V$174,Master!L$4:L$174,Master!I$4:I$174,Master!BM$4:BM$174},Master!K$4:K$174="Qualified",Master!D$4:D$174="Equity",Master!AE$4:AE$174<>""),3,FALSE),5,1),"") | B56: =IFERROR(INDEX(SORT(FILTER({Master!A$4:A$174,Master!B$4:B$174,Master!AE$4:AE$174,Master!V$4:V$174,Master!L$4:L$174,Master!I$4:I$174,Master!BM$4:BM$174},Master!K$4:K$174="Qualified",Master!D$4:D$174="Equity",Master!AE$4:AE$174<>""),3,FALSE),5,2),"") | C56: =IFERROR(INDEX(SORT(FILTER({Master!A$4:A$174,Master!B$4:B$174,Master!AE$4:AE$174,Master!V$4:V$174,Master!L$4:L$174,Master!I$4:I$174,Master!BM$4:BM$174},Master!K$4:K$174="Qualified",Master!D$4:D$174="Equity",Master!AE$4:AE$174<>""),3,FALSE),5,3),"") | D56: =IFERROR(INDEX(SORT(FILTER({Master!A$4:A$174,Master!B$4:B$174,Master!AE$4:AE$174,Master!V$4:V$174,Master!L$4:L$174,Master!I$4:I$174,Master!BM$4:BM$174},Master!K$4:K$174="Qualified",Master!D$4:D$174="Equity",Master!AE$4:AE$174<>""),3,FALSE),5,4),"") | E56: =IFERROR(INDEX(SORT(FILTER({Master!A$4:A$174,Master!B$4:B$174,Master!AE$4:AE$174,Master!V$4:V$174,Master!L$4:L$174,Master!I$4:I$174,Master!BM$4:BM$174},Master!K$4:K$174="Qualified",Master!D$4:D$174="Equity",Master!AE$4:AE$174<>""),3,FALSE),5,5),"") | F56: =IFERROR(INDEX(SORT(FILTER({Master!A$4:A$174,Master!B$4:B$174,Master!AE$4:AE$174,Master!V$4:V$174,Master!L$4:L$174,Master!I$4:I$174,Master!BM$4:BM$174},Master!K$4:K$174="Qualified",Master!D$4:D$174="Equity",Master!AE$4:AE$174<>""),3,FALSE),5,6),"") | G56: =IFERROR(INDEX(SORT(FILTER({Master!A$4:A$174,Master!B$4:B$174,Master!AE$4:AE$174,Master!V$4:V$174,Master!L$4:L$174,Master!I$4:I$174,Master!BM$4:BM$174},Master!K$4:K$174="Qualified",Master!D$4:D$174="Equity",Master!AE$4:AE$174<>""),3,FALSE),5,7),"")
A58: EQUITY — TOP 5 BY AUM
A59: Fund Name | B59: Abbr | C59: AUM (RM M) | D59: 3Y Fund (%) | E59: 3Y Alpha (%) | F59: Beat (%) | G59: VC
A60: =IFERROR(INDEX(SORT(FILTER({Master!A$4:A$174,Master!B$4:B$174,Master!I$4:I$174,Master!T$4:T$174,Master!V$4:V$174,Master!L$4:L$174,Master!BM$4:BM$174},Master!K$4:K$174="Qualified",Master!D$4:D$174="Equity",Master!I$4:I$174<>""),3,FALSE),1,1),"") | B60: =IFERROR(INDEX(SORT(FILTER({Master!A$4:A$174,Master!B$4:B$174,Master!I$4:I$174,Master!T$4:T$174,Master!V$4:V$174,Master!L$4:L$174,Master!BM$4:BM$174},Master!K$4:K$174="Qualified",Master!D$4:D$174="Equity",Master!I$4:I$174<>""),3,FALSE),1,2),"") | C60: =IFERROR(INDEX(SORT(FILTER({Master!A$4:A$174,Master!B$4:B$174,Master!I$4:I$174,Master!T$4:T$174,Master!V$4:V$174,Master!L$4:L$174,Master!BM$4:BM$174},Master!K$4:K$174="Qualified",Master!D$4:D$174="Equity",Master!I$4:I$174<>""),3,FALSE),1,3),"") | D60: =IFERROR(INDEX(SORT(FILTER({Master!A$4:A$174,Master!B$4:B$174,Master!I$4:I$174,Master!T$4:T$174,Master!V$4:V$174,Master!L$4:L$174,Master!BM$4:BM$174},Master!K$4:K$174="Qualified",Master!D$4:D$174="Equity",Master!I$4:I$174<>""),3,FALSE),1,4),"") | E60: =IFERROR(INDEX(SORT(FILTER({Master!A$4:A$174,Master!B$4:B$174,Master!I$4:I$174,Master!T$4:T$174,Master!V$4:V$174,Master!L$4:L$174,Master!BM$4:BM$174},Master!K$4:K$174="Qualified",Master!D$4:D$174="Equity",Master!I$4:I$174<>""),3,FALSE),1,5),"") | F60: =IFERROR(INDEX(SORT(FILTER({Master!A$4:A$174,Master!B$4:B$174,Master!I$4:I$174,Master!T$4:T$174,Master!V$4:V$174,Master!L$4:L$174,Master!BM$4:BM$174},Master!K$4:K$174="Qualified",Master!D$4:D$174="Equity",Master!I$4:I$174<>""),3,FALSE),1,6),"") | G60: =IFERROR(INDEX(SORT(FILTER({Master!A$4:A$174,Master!B$4:B$174,Master!I$4:I$174,Master!T$4:T$174,Master!V$4:V$174,Master!L$4:L$174,Master!BM$4:BM$174},Master!K$4:K$174="Qualified",Master!D$4:D$174="Equity",Master!I$4:I$174<>""),3,FALSE),1,7),"")
A61: =IFERROR(INDEX(SORT(FILTER({Master!A$4:A$174,Master!B$4:B$174,Master!I$4:I$174,Master!T$4:T$174,Master!V$4:V$174,Master!L$4:L$174,Master!BM$4:BM$174},Master!K$4:K$174="Qualified",Master!D$4:D$174="Equity",Master!I$4:I$174<>""),3,FALSE),2,1),"") | B61: =IFERROR(INDEX(SORT(FILTER({Master!A$4:A$174,Master!B$4:B$174,Master!I$4:I$174,Master!T$4:T$174,Master!V$4:V$174,Master!L$4:L$174,Master!BM$4:BM$174},Master!K$4:K$174="Qualified",Master!D$4:D$174="Equity",Master!I$4:I$174<>""),3,FALSE),2,2),"") | C61: =IFERROR(INDEX(SORT(FILTER({Master!A$4:A$174,Master!B$4:B$174,Master!I$4:I$174,Master!T$4:T$174,Master!V$4:V$174,Master!L$4:L$174,Master!BM$4:BM$174},Master!K$4:K$174="Qualified",Master!D$4:D$174="Equity",Master!I$4:I$174<>""),3,FALSE),2,3),"") | D61: =IFERROR(INDEX(SORT(FILTER({Master!A$4:A$174,Master!B$4:B$174,Master!I$4:I$174,Master!T$4:T$174,Master!V$4:V$174,Master!L$4:L$174,Master!BM$4:BM$174},Master!K$4:K$174="Qualified",Master!D$4:D$174="Equity",Master!I$4:I$174<>""),3,FALSE),2,4),"") | E61: =IFERROR(INDEX(SORT(FILTER({Master!A$4:A$174,Master!B$4:B$174,Master!I$4:I$174,Master!T$4:T$174,Master!V$4:V$174,Master!L$4:L$174,Master!BM$4:BM$174},Master!K$4:K$174="Qualified",Master!D$4:D$174="Equity",Master!I$4:I$174<>""),3,FALSE),2,5),"") | F61: =IFERROR(INDEX(SORT(FILTER({Master!A$4:A$174,Master!B$4:B$174,Master!I$4:I$174,Master!T$4:T$174,Master!V$4:V$174,Master!L$4:L$174,Master!BM$4:BM$174},Master!K$4:K$174="Qualified",Master!D$4:D$174="Equity",Master!I$4:I$174<>""),3,FALSE),2,6),"") | G61: =IFERROR(INDEX(SORT(FILTER({Master!A$4:A$174,Master!B$4:B$174,Master!I$4:I$174,Master!T$4:T$174,Master!V$4:V$174,Master!L$4:L$174,Master!BM$4:BM$174},Master!K$4:K$174="Qualified",Master!D$4:D$174="Equity",Master!I$4:I$174<>""),3,FALSE),2,7),"")
A62: =IFERROR(INDEX(SORT(FILTER({Master!A$4:A$174,Master!B$4:B$174,Master!I$4:I$174,Master!T$4:T$174,Master!V$4:V$174,Master!L$4:L$174,Master!BM$4:BM$174},Master!K$4:K$174="Qualified",Master!D$4:D$174="Equity",Master!I$4:I$174<>""),3,FALSE),3,1),"") | B62: =IFERROR(INDEX(SORT(FILTER({Master!A$4:A$174,Master!B$4:B$174,Master!I$4:I$174,Master!T$4:T$174,Master!V$4:V$174,Master!L$4:L$174,Master!BM$4:BM$174},Master!K$4:K$174="Qualified",Master!D$4:D$174="Equity",Master!I$4:I$174<>""),3,FALSE),3,2),"") | C62: =IFERROR(INDEX(SORT(FILTER({Master!A$4:A$174,Master!B$4:B$174,Master!I$4:I$174,Master!T$4:T$174,Master!V$4:V$174,Master!L$4:L$174,Master!BM$4:BM$174},Master!K$4:K$174="Qualified",Master!D$4:D$174="Equity",Master!I$4:I$174<>""),3,FALSE),3,3),"") | D62: =IFERROR(INDEX(SORT(FILTER({Master!A$4:A$174,Master!B$4:B$174,Master!I$4:I$174,Master!T$4:T$174,Master!V$4:V$174,Master!L$4:L$174,Master!BM$4:BM$174},Master!K$4:K$174="Qualified",Master!D$4:D$174="Equity",Master!I$4:I$174<>""),3,FALSE),3,4),"") | E62: =IFERROR(INDEX(SORT(FILTER({Master!A$4:A$174,Master!B$4:B$174,Master!I$4:I$174,Master!T$4:T$174,Master!V$4:V$174,Master!L$4:L$174,Master!BM$4:BM$174},Master!K$4:K$174="Qualified",Master!D$4:D$174="Equity",Master!I$4:I$174<>""),3,FALSE),3,5),"") | F62: =IFERROR(INDEX(SORT(FILTER({Master!A$4:A$174,Master!B$4:B$174,Master!I$4:I$174,Master!T$4:T$174,Master!V$4:V$174,Master!L$4:L$174,Master!BM$4:BM$174},Master!K$4:K$174="Qualified",Master!D$4:D$174="Equity",Master!I$4:I$174<>""),3,FALSE),3,6),"") | G62: =IFERROR(INDEX(SORT(FILTER({Master!A$4:A$174,Master!B$4:B$174,Master!I$4:I$174,Master!T$4:T$174,Master!V$4:V$174,Master!L$4:L$174,Master!BM$4:BM$174},Master!K$4:K$174="Qualified",Master!D$4:D$174="Equity",Master!I$4:I$174<>""),3,FALSE),3,7),"")
A63: =IFERROR(INDEX(SORT(FILTER({Master!A$4:A$174,Master!B$4:B$174,Master!I$4:I$174,Master!T$4:T$174,Master!V$4:V$174,Master!L$4:L$174,Master!BM$4:BM$174},Master!K$4:K$174="Qualified",Master!D$4:D$174="Equity",Master!I$4:I$174<>""),3,FALSE),4,1),"") | B63: =IFERROR(INDEX(SORT(FILTER({Master!A$4:A$174,Master!B$4:B$174,Master!I$4:I$174,Master!T$4:T$174,Master!V$4:V$174,Master!L$4:L$174,Master!BM$4:BM$174},Master!K$4:K$174="Qualified",Master!D$4:D$174="Equity",Master!I$4:I$174<>""),3,FALSE),4,2),"") | C63: =IFERROR(INDEX(SORT(FILTER({Master!A$4:A$174,Master!B$4:B$174,Master!I$4:I$174,Master!T$4:T$174,Master!V$4:V$174,Master!L$4:L$174,Master!BM$4:BM$174},Master!K$4:K$174="Qualified",Master!D$4:D$174="Equity",Master!I$4:I$174<>""),3,FALSE),4,3),"") | D63: =IFERROR(INDEX(SORT(FILTER({Master!A$4:A$174,Master!B$4:B$174,Master!I$4:I$174,Master!T$4:T$174,Master!V$4:V$174,Master!L$4:L$174,Master!BM$4:BM$174},Master!K$4:K$174="Qualified",Master!D$4:D$174="Equity",Master!I$4:I$174<>""),3,FALSE),4,4),"") | E63: =IFERROR(INDEX(SORT(FILTER({Master!A$4:A$174,Master!B$4:B$174,Master!I$4:I$174,Master!T$4:T$174,Master!V$4:V$174,Master!L$4:L$174,Master!BM$4:BM$174},Master!K$4:K$174="Qualified",Master!D$4:D$174="Equity",Master!I$4:I$174<>""),3,FALSE),4,5),"") | F63: =IFERROR(INDEX(SORT(FILTER({Master!A$4:A$174,Master!B$4:B$174,Master!I$4:I$174,Master!T$4:T$174,Master!V$4:V$174,Master!L$4:L$174,Master!BM$4:BM$174},Master!K$4:K$174="Qualified",Master!D$4:D$174="Equity",Master!I$4:I$174<>""),3,FALSE),4,6),"") | G63: =IFERROR(INDEX(SORT(FILTER({Master!A$4:A$174,Master!B$4:B$174,Master!I$4:I$174,Master!T$4:T$174,Master!V$4:V$174,Master!L$4:L$174,Master!BM$4:BM$174},Master!K$4:K$174="Qualified",Master!D$4:D$174="Equity",Master!I$4:I$174<>""),3,FALSE),4,7),"")
A64: =IFERROR(INDEX(SORT(FILTER({Master!A$4:A$174,Master!B$4:B$174,Master!I$4:I$174,Master!T$4:T$174,Master!V$4:V$174,Master!L$4:L$174,Master!BM$4:BM$174},Master!K$4:K$174="Qualified",Master!D$4:D$174="Equity",Master!I$4:I$174<>""),3,FALSE),5,1),"") | B64: =IFERROR(INDEX(SORT(FILTER({Master!A$4:A$174,Master!B$4:B$174,Master!I$4:I$174,Master!T$4:T$174,Master!V$4:V$174,Master!L$4:L$174,Master!BM$4:BM$174},Master!K$4:K$174="Qualified",Master!D$4:D$174="Equity",Master!I$4:I$174<>""),3,FALSE),5,2),"") | C64: =IFERROR(INDEX(SORT(FILTER({Master!A$4:A$174,Master!B$4:B$174,Master!I$4:I$174,Master!T$4:T$174,Master!V$4:V$174,Master!L$4:L$174,Master!BM$4:BM$174},Master!K$4:K$174="Qualified",Master!D$4:D$174="Equity",Master!I$4:I$174<>""),3,FALSE),5,3),"") | D64: =IFERROR(INDEX(SORT(FILTER({Master!A$4:A$174,Master!B$4:B$174,Master!I$4:I$174,Master!T$4:T$174,Master!V$4:V$174,Master!L$4:L$174,Master!BM$4:BM$174},Master!K$4:K$174="Qualified",Master!D$4:D$174="Equity",Master!I$4:I$174<>""),3,FALSE),5,4),"") | E64: =IFERROR(INDEX(SORT(FILTER({Master!A$4:A$174,Master!B$4:B$174,Master!I$4:I$174,Master!T$4:T$174,Master!V$4:V$174,Master!L$4:L$174,Master!BM$4:BM$174},Master!K$4:K$174="Qualified",Master!D$4:D$174="Equity",Master!I$4:I$174<>""),3,FALSE),5,5),"") | F64: =IFERROR(INDEX(SORT(FILTER({Master!A$4:A$174,Master!B$4:B$174,Master!I$4:I$174,Master!T$4:T$174,Master!V$4:V$174,Master!L$4:L$174,Master!BM$4:BM$174},Master!K$4:K$174="Qualified",Master!D$4:D$174="Equity",Master!I$4:I$174<>""),3,FALSE),5,6),"") | G64: =IFERROR(INDEX(SORT(FILTER({Master!A$4:A$174,Master!B$4:B$174,Master!I$4:I$174,Master!T$4:T$174,Master!V$4:V$174,Master!L$4:L$174,Master!BM$4:BM$174},Master!K$4:K$174="Qualified",Master!D$4:D$174="Equity",Master!I$4:I$174<>""),3,FALSE),5,7),"")
A66: BALANCED / MIXED ASSET — MEDIAN STATISTICS
A67: Metric | B67: YTD (%) | C67: 1Y (%) | D67: 3Y Ann. (%) | E67: 5Y Ann. (%) | F67: 10Y Ann. (%) | G67: 3Y Alpha (%) | H67: Beat (%)
A68: Median | B68: =IFERROR(MEDIAN(FILTER(Master!N$4:N$174,(Master!K$4:K$174="Qualified")*(Master!D$4:D$174="Mixed Asset / Balanced"))),"") | C68: =IFERROR(MEDIAN(FILTER(Master!Q$4:Q$174,(Master!K$4:K$174="Qualified")*(Master!D$4:D$174="Mixed Asset / Balanced"))),"") | D68: =IFERROR(MEDIAN(FILTER(Master!T$4:T$174,(Master!K$4:K$174="Qualified")*(Master!D$4:D$174="Mixed Asset / Balanced"))),"") | E68: =IFERROR(MEDIAN(FILTER(Master!W$4:W$174,(Master!K$4:K$174="Qualified")*(Master!D$4:D$174="Mixed Asset / Balanced"))),"") | F68: =IFERROR(MEDIAN(FILTER(Master!Z$4:Z$174,(Master!K$4:K$174="Qualified")*(Master!D$4:D$174="Mixed Asset / Balanced"))),"") | G68: =IFERROR(MEDIAN(FILTER(Master!V$4:V$174,(Master!K$4:K$174="Qualified")*(Master!D$4:D$174="Mixed Asset / Balanced"))),"") | H68: =IFERROR(MEDIAN(FILTER(Master!L$4:L$174,(Master!K$4:K$174="Qualified")*(Master!D$4:D$174="Mixed Asset / Balanced"))),"")
A70: BALANCED / MIXED ASSET — TOP 5 BY 3Y ANN. FUND RETURN
A71: Fund Name | B71: Abbr | C71: 3Y Fund (%) | D71: 3Y Alpha (%) | E71: Beat (%) | F71: AUM (RM M) | G71: VC
A72: =IFERROR(INDEX(SORT(FILTER({Master!A$4:A$174,Master!B$4:B$174,Master!T$4:T$174,Master!V$4:V$174,Master!L$4:L$174,Master!I$4:I$174,Master!BM$4:BM$174},Master!K$4:K$174="Qualified",Master!D$4:D$174="Mixed Asset / Balanced",Master!T$4:T$174<>""),3,FALSE),1,1),"") | B72: =IFERROR(INDEX(SORT(FILTER({Master!A$4:A$174,Master!B$4:B$174,Master!T$4:T$174,Master!V$4:V$174,Master!L$4:L$174,Master!I$4:I$174,Master!BM$4:BM$174},Master!K$4:K$174="Qualified",Master!D$4:D$174="Mixed Asset / Balanced",Master!T$4:T$174<>""),3,FALSE),1,2),"") | C72: =IFERROR(INDEX(SORT(FILTER({Master!A$4:A$174,Master!B$4:B$174,Master!T$4:T$174,Master!V$4:V$174,Master!L$4:L$174,Master!I$4:I$174,Master!BM$4:BM$174},Master!K$4:K$174="Qualified",Master!D$4:D$174="Mixed Asset / Balanced",Master!T$4:T$174<>""),3,FALSE),1,3),"") | D72: =IFERROR(INDEX(SORT(FILTER({Master!A$4:A$174,Master!B$4:B$174,Master!T$4:T$174,Master!V$4:V$174,Master!L$4:L$174,Master!I$4:I$174,Master!BM$4:BM$174},Master!K$4:K$174="Qualified",Master!D$4:D$174="Mixed Asset / Balanced",Master!T$4:T$174<>""),3,FALSE),1,4),"") | E72: =IFERROR(INDEX(SORT(FILTER({Master!A$4:A$174,Master!B$4:B$174,Master!T$4:T$174,Master!V$4:V$174,Master!L$4:L$174,Master!I$4:I$174,Master!BM$4:BM$174},Master!K$4:K$174="Qualified",Master!D$4:D$174="Mixed Asset / Balanced",Master!T$4:T$174<>""),3,FALSE),1,5),"") | F72: =IFERROR(INDEX(SORT(FILTER({Master!A$4:A$174,Master!B$4:B$174,Master!T$4:T$174,Master!V$4:V$174,Master!L$4:L$174,Master!I$4:I$174,Master!BM$4:BM$174},Master!K$4:K$174="Qualified",Master!D$4:D$174="Mixed Asset / Balanced",Master!T$4:T$174<>""),3,FALSE),1,6),"") | G72: =IFERROR(INDEX(SORT(FILTER({Master!A$4:A$174,Master!B$4:B$174,Master!T$4:T$174,Master!V$4:V$174,Master!L$4:L$174,Master!I$4:I$174,Master!BM$4:BM$174},Master!K$4:K$174="Qualified",Master!D$4:D$174="Mixed Asset / Balanced",Master!T$4:T$174<>""),3,FALSE),1,7),"")
A73: =IFERROR(INDEX(SORT(FILTER({Master!A$4:A$174,Master!B$4:B$174,Master!T$4:T$174,Master!V$4:V$174,Master!L$4:L$174,Master!I$4:I$174,Master!BM$4:BM$174},Master!K$4:K$174="Qualified",Master!D$4:D$174="Mixed Asset / Balanced",Master!T$4:T$174<>""),3,FALSE),2,1),"") | B73: =IFERROR(INDEX(SORT(FILTER({Master!A$4:A$174,Master!B$4:B$174,Master!T$4:T$174,Master!V$4:V$174,Master!L$4:L$174,Master!I$4:I$174,Master!BM$4:BM$174},Master!K$4:K$174="Qualified",Master!D$4:D$174="Mixed Asset / Balanced",Master!T$4:T$174<>""),3,FALSE),2,2),"") | C73: =IFERROR(INDEX(SORT(FILTER({Master!A$4:A$174,Master!B$4:B$174,Master!T$4:T$174,Master!V$4:V$174,Master!L$4:L$174,Master!I$4:I$174,Master!BM$4:BM$174},Master!K$4:K$174="Qualified",Master!D$4:D$174="Mixed Asset / Balanced",Master!T$4:T$174<>""),3,FALSE),2,3),"") | D73: =IFERROR(INDEX(SORT(FILTER({Master!A$4:A$174,Master!B$4:B$174,Master!T$4:T$174,Master!V$4:V$174,Master!L$4:L$174,Master!I$4:I$174,Master!BM$4:BM$174},Master!K$4:K$174="Qualified",Master!D$4:D$174="Mixed Asset / Balanced",Master!T$4:T$174<>""),3,FALSE),2,4),"") | E73: =IFERROR(INDEX(SORT(FILTER({Master!A$4:A$174,Master!B$4:B$174,Master!T$4:T$174,Master!V$4:V$174,Master!L$4:L$174,Master!I$4:I$174,Master!BM$4:BM$174},Master!K$4:K$174="Qualified",Master!D$4:D$174="Mixed Asset / Balanced",Master!T$4:T$174<>""),3,FALSE),2,5),"") | F73: =IFERROR(INDEX(SORT(FILTER({Master!A$4:A$174,Master!B$4:B$174,Master!T$4:T$174,Master!V$4:V$174,Master!L$4:L$174,Master!I$4:I$174,Master!BM$4:BM$174},Master!K$4:K$174="Qualified",Master!D$4:D$174="Mixed Asset / Balanced",Master!T$4:T$174<>""),3,FALSE),2,6),"") | G73: =IFERROR(INDEX(SORT(FILTER({Master!A$4:A$174,Master!B$4:B$174,Master!T$4:T$174,Master!V$4:V$174,Master!L$4:L$174,Master!I$4:I$174,Master!BM$4:BM$174},Master!K$4:K$174="Qualified",Master!D$4:D$174="Mixed Asset / Balanced",Master!T$4:T$174<>""),3,FALSE),2,7),"")
A74: =IFERROR(INDEX(SORT(FILTER({Master!A$4:A$174,Master!B$4:B$174,Master!T$4:T$174,Master!V$4:V$174,Master!L$4:L$174,Master!I$4:I$174,Master!BM$4:BM$174},Master!K$4:K$174="Qualified",Master!D$4:D$174="Mixed Asset / Balanced",Master!T$4:T$174<>""),3,FALSE),3,1),"") | B74: =IFERROR(INDEX(SORT(FILTER({Master!A$4:A$174,Master!B$4:B$174,Master!T$4:T$174,Master!V$4:V$174,Master!L$4:L$174,Master!I$4:I$174,Master!BM$4:BM$174},Master!K$4:K$174="Qualified",Master!D$4:D$174="Mixed Asset / Balanced",Master!T$4:T$174<>""),3,FALSE),3,2),"") | C74: =IFERROR(INDEX(SORT(FILTER({Master!A$4:A$174,Master!B$4:B$174,Master!T$4:T$174,Master!V$4:V$174,Master!L$4:L$174,Master!I$4:I$174,Master!BM$4:BM$174},Master!K$4:K$174="Qualified",Master!D$4:D$174="Mixed Asset / Balanced",Master!T$4:T$174<>""),3,FALSE),3,3),"") | D74: =IFERROR(INDEX(SORT(FILTER({Master!A$4:A$174,Master!B$4:B$174,Master!T$4:T$174,Master!V$4:V$174,Master!L$4:L$174,Master!I$4:I$174,Master!BM$4:BM$174},Master!K$4:K$174="Qualified",Master!D$4:D$174="Mixed Asset / Balanced",Master!T$4:T$174<>""),3,FALSE),3,4),"") | E74: =IFERROR(INDEX(SORT(FILTER({Master!A$4:A$174,Master!B$4:B$174,Master!T$4:T$174,Master!V$4:V$174,Master!L$4:L$174,Master!I$4:I$174,Master!BM$4:BM$174},Master!K$4:K$174="Qualified",Master!D$4:D$174="Mixed Asset / Balanced",Master!T$4:T$174<>""),3,FALSE),3,5),"") | F74: =IFERROR(INDEX(SORT(FILTER({Master!A$4:A$174,Master!B$4:B$174,Master!T$4:T$174,Master!V$4:V$174,Master!L$4:L$174,Master!I$4:I$174,Master!BM$4:BM$174},Master!K$4:K$174="Qualified",Master!D$4:D$174="Mixed Asset / Balanced",Master!T$4:T$174<>""),3,FALSE),3,6),"") | G74: =IFERROR(INDEX(SORT(FILTER({Master!A$4:A$174,Master!B$4:B$174,Master!T$4:T$174,Master!V$4:V$174,Master!L$4:L$174,Master!I$4:I$174,Master!BM$4:BM$174},Master!K$4:K$174="Qualified",Master!D$4:D$174="Mixed Asset / Balanced",Master!T$4:T$174<>""),3,FALSE),3,7),"")
A75: =IFERROR(INDEX(SORT(FILTER({Master!A$4:A$174,Master!B$4:B$174,Master!T$4:T$174,Master!V$4:V$174,Master!L$4:L$174,Master!I$4:I$174,Master!BM$4:BM$174},Master!K$4:K$174="Qualified",Master!D$4:D$174="Mixed Asset / Balanced",Master!T$4:T$174<>""),3,FALSE),4,1),"") | B75: =IFERROR(INDEX(SORT(FILTER({Master!A$4:A$174,Master!B$4:B$174,Master!T$4:T$174,Master!V$4:V$174,Master!L$4:L$174,Master!I$4:I$174,Master!BM$4:BM$174},Master!K$4:K$174="Qualified",Master!D$4:D$174="Mixed Asset / Balanced",Master!T$4:T$174<>""),3,FALSE),4,2),"") | C75: =IFERROR(INDEX(SORT(FILTER({Master!A$4:A$174,Master!B$4:B$174,Master!T$4:T$174,Master!V$4:V$174,Master!L$4:L$174,Master!I$4:I$174,Master!BM$4:BM$174},Master!K$4:K$174="Qualified",Master!D$4:D$174="Mixed Asset / Balanced",Master!T$4:T$174<>""),3,FALSE),4,3),"") | D75: =IFERROR(INDEX(SORT(FILTER({Master!A$4:A$174,Master!B$4:B$174,Master!T$4:T$174,Master!V$4:V$174,Master!L$4:L$174,Master!I$4:I$174,Master!BM$4:BM$174},Master!K$4:K$174="Qualified",Master!D$4:D$174="Mixed Asset / Balanced",Master!T$4:T$174<>""),3,FALSE),4,4),"") | E75: =IFERROR(INDEX(SORT(FILTER({Master!A$4:A$174,Master!B$4:B$174,Master!T$4:T$174,Master!V$4:V$174,Master!L$4:L$174,Master!I$4:I$174,Master!BM$4:BM$174},Master!K$4:K$174="Qualified",Master!D$4:D$174="Mixed Asset / Balanced",Master!T$4:T$174<>""),3,FALSE),4,5),"") | F75: =IFERROR(INDEX(SORT(FILTER({Master!A$4:A$174,Master!B$4:B$174,Master!T$4:T$174,Master!V$4:V$174,Master!L$4:L$174,Master!I$4:I$174,Master!BM$4:BM$174},Master!K$4:K$174="Qualified",Master!D$4:D$174="Mixed Asset / Balanced",Master!T$4:T$174<>""),3,FALSE),4,6),"") | G75: =IFERROR(INDEX(SORT(FILTER({Master!A$4:A$174,Master!B$4:B$174,Master!T$4:T$174,Master!V$4:V$174,Master!L$4:L$174,Master!I$4:I$174,Master!BM$4:BM$174},Master!K$4:K$174="Qualified",Master!D$4:D$174="Mixed Asset / Balanced",Master!T$4:T$174<>""),3,FALSE),4,7),"")
A76: =IFERROR(INDEX(SORT(FILTER({Master!A$4:A$174,Master!B$4:B$174,Master!T$4:T$174,Master!V$4:V$174,Master!L$4:L$174,Master!I$4:I$174,Master!BM$4:BM$174},Master!K$4:K$174="Qualified",Master!D$4:D$174="Mixed Asset / Balanced",Master!T$4:T$174<>""),3,FALSE),5,1),"") | B76: =IFERROR(INDEX(SORT(FILTER({Master!A$4:A$174,Master!B$4:B$174,Master!T$4:T$174,Master!V$4:V$174,Master!L$4:L$174,Master!I$4:I$174,Master!BM$4:BM$174},Master!K$4:K$174="Qualified",Master!D$4:D$174="Mixed Asset / Balanced",Master!T$4:T$174<>""),3,FALSE),5,2),"") | C76: =IFERROR(INDEX(SORT(FILTER({Master!A$4:A$174,Master!B$4:B$174,Master!T$4:T$174,Master!V$4:V$174,Master!L$4:L$174,Master!I$4:I$174,Master!BM$4:BM$174},Master!K$4:K$174="Qualified",Master!D$4:D$174="Mixed Asset / Balanced",Master!T$4:T$174<>""),3,FALSE),5,3),"") | D76: =IFERROR(INDEX(SORT(FILTER({Master!A$4:A$174,Master!B$4:B$174,Master!T$4:T$174,Master!V$4:V$174,Master!L$4:L$174,Master!I$4:I$174,Master!BM$4:BM$174},Master!K$4:K$174="Qualified",Master!D$4:D$174="Mixed Asset / Balanced",Master!T$4:T$174<>""),3,FALSE),5,4),"") | E76: =IFERROR(INDEX(SORT(FILTER({Master!A$4:A$174,Master!B$4:B$174,Master!T$4:T$174,Master!V$4:V$174,Master!L$4:L$174,Master!I$4:I$174,Master!BM$4:BM$174},Master!K$4:K$174="Qualified",Master!D$4:D$174="Mixed Asset / Balanced",Master!T$4:T$174<>""),3,FALSE),5,5),"") | F76: =IFERROR(INDEX(SORT(FILTER({Master!A$4:A$174,Master!B$4:B$174,Master!T$4:T$174,Master!V$4:V$174,Master!L$4:L$174,Master!I$4:I$174,Master!BM$4:BM$174},Master!K$4:K$174="Qualified",Master!D$4:D$174="Mixed Asset / Balanced",Master!T$4:T$174<>""),3,FALSE),5,6),"") | G76: =IFERROR(INDEX(SORT(FILTER({Master!A$4:A$174,Master!B$4:B$174,Master!T$4:T$174,Master!V$4:V$174,Master!L$4:L$174,Master!I$4:I$174,Master!BM$4:BM$174},Master!K$4:K$174="Qualified",Master!D$4:D$174="Mixed Asset / Balanced",Master!T$4:T$174<>""),3,FALSE),5,7),"")
A78: BALANCED / MIXED ASSET — TOP 5 BY 3Y ANN. ALPHA
A79: Fund Name | B79: Abbr | C79: 3Y Fund (%) | D79: 3Y Alpha (%) | E79: Beat (%) | F79: AUM (RM M) | G79: VC
A80: =IFERROR(INDEX(SORT(FILTER({Master!A$4:A$174,Master!B$4:B$174,Master!T$4:T$174,Master!V$4:V$174,Master!L$4:L$174,Master!I$4:I$174,Master!BM$4:BM$174},Master!K$4:K$174="Qualified",Master!D$4:D$174="Mixed Asset / Balanced",Master!V$4:V$174<>""),4,FALSE),1,1),"") | B80: =IFERROR(INDEX(SORT(FILTER({Master!A$4:A$174,Master!B$4:B$174,Master!T$4:T$174,Master!V$4:V$174,Master!L$4:L$174,Master!I$4:I$174,Master!BM$4:BM$174},Master!K$4:K$174="Qualified",Master!D$4:D$174="Mixed Asset / Balanced",Master!V$4:V$174<>""),4,FALSE),1,2),"") | C80: =IFERROR(INDEX(SORT(FILTER({Master!A$4:A$174,Master!B$4:B$174,Master!T$4:T$174,Master!V$4:V$174,Master!L$4:L$174,Master!I$4:I$174,Master!BM$4:BM$174},Master!K$4:K$174="Qualified",Master!D$4:D$174="Mixed Asset / Balanced",Master!V$4:V$174<>""),4,FALSE),1,3),"") | D80: =IFERROR(INDEX(SORT(FILTER({Master!A$4:A$174,Master!B$4:B$174,Master!T$4:T$174,Master!V$4:V$174,Master!L$4:L$174,Master!I$4:I$174,Master!BM$4:BM$174},Master!K$4:K$174="Qualified",Master!D$4:D$174="Mixed Asset / Balanced",Master!V$4:V$174<>""),4,FALSE),1,4),"") | E80: =IFERROR(INDEX(SORT(FILTER({Master!A$4:A$174,Master!B$4:B$174,Master!T$4:T$174,Master!V$4:V$174,Master!L$4:L$174,Master!I$4:I$174,Master!BM$4:BM$174},Master!K$4:K$174="Qualified",Master!D$4:D$174="Mixed Asset / Balanced",Master!V$4:V$174<>""),4,FALSE),1,5),"") | F80: =IFERROR(INDEX(SORT(FILTER({Master!A$4:A$174,Master!B$4:B$174,Master!T$4:T$174,Master!V$4:V$174,Master!L$4:L$174,Master!I$4:I$174,Master!BM$4:BM$174},Master!K$4:K$174="Qualified",Master!D$4:D$174="Mixed Asset / Balanced",Master!V$4:V$174<>""),4,FALSE),1,6),"") | G80: =IFERROR(INDEX(SORT(FILTER({Master!A$4:A$174,Master!B$4:B$174,Master!T$4:T$174,Master!V$4:V$174,Master!L$4:L$174,Master!I$4:I$174,Master!BM$4:BM$174},Master!K$4:K$174="Qualified",Master!D$4:D$174="Mixed Asset / Balanced",Master!V$4:V$174<>""),4,FALSE),1,7),"")
A81: =IFERROR(INDEX(SORT(FILTER({Master!A$4:A$174,Master!B$4:B$174,Master!T$4:T$174,Master!V$4:V$174,Master!L$4:L$174,Master!I$4:I$174,Master!BM$4:BM$174},Master!K$4:K$174="Qualified",Master!D$4:D$174="Mixed Asset / Balanced",Master!V$4:V$174<>""),4,FALSE),2,1),"") | B81: =IFERROR(INDEX(SORT(FILTER({Master!A$4:A$174,Master!B$4:B$174,Master!T$4:T$174,Master!V$4:V$174,Master!L$4:L$174,Master!I$4:I$174,Master!BM$4:BM$174},Master!K$4:K$174="Qualified",Master!D$4:D$174="Mixed Asset / Balanced",Master!V$4:V$174<>""),4,FALSE),2,2),"") | C81: =IFERROR(INDEX(SORT(FILTER({Master!A$4:A$174,Master!B$4:B$174,Master!T$4:T$174,Master!V$4:V$174,Master!L$4:L$174,Master!I$4:I$174,Master!BM$4:BM$174},Master!K$4:K$174="Qualified",Master!D$4:D$174="Mixed Asset / Balanced",Master!V$4:V$174<>""),4,FALSE),2,3),"") | D81: =IFERROR(INDEX(SORT(FILTER({Master!A$4:A$174,Master!B$4:B$174,Master!T$4:T$174,Master!V$4:V$174,Master!L$4:L$174,Master!I$4:I$174,Master!BM$4:BM$174},Master!K$4:K$174="Qualified",Master!D$4:D$174="Mixed Asset / Balanced",Master!V$4:V$174<>""),4,FALSE),2,4),"") | E81: =IFERROR(INDEX(SORT(FILTER({Master!A$4:A$174,Master!B$4:B$174,Master!T$4:T$174,Master!V$4:V$174,Master!L$4:L$174,Master!I$4:I$174,Master!BM$4:BM$174},Master!K$4:K$174="Qualified",Master!D$4:D$174="Mixed Asset / Balanced",Master!V$4:V$174<>""),4,FALSE),2,5),"") | F81: =IFERROR(INDEX(SORT(FILTER({Master!A$4:A$174,Master!B$4:B$174,Master!T$4:T$174,Master!V$4:V$174,Master!L$4:L$174,Master!I$4:I$174,Master!BM$4:BM$174},Master!K$4:K$174="Qualified",Master!D$4:D$174="Mixed Asset / Balanced",Master!V$4:V$174<>""),4,FALSE),2,6),"") | G81: =IFERROR(INDEX(SORT(FILTER({Master!A$4:A$174,Master!B$4:B$174,Master!T$4:T$174,Master!V$4:V$174,Master!L$4:L$174,Master!I$4:I$174,Master!BM$4:BM$174},Master!K$4:K$174="Qualified",Master!D$4:D$174="Mixed Asset / Balanced",Master!V$4:V$174<>""),4,FALSE),2,7),"")
A82: =IFERROR(INDEX(SORT(FILTER({Master!A$4:A$174,Master!B$4:B$174,Master!T$4:T$174,Master!V$4:V$174,Master!L$4:L$174,Master!I$4:I$174,Master!BM$4:BM$174},Master!K$4:K$174="Qualified",Master!D$4:D$174="Mixed Asset / Balanced",Master!V$4:V$174<>""),4,FALSE),3,1),"") | B82: =IFERROR(INDEX(SORT(FILTER({Master!A$4:A$174,Master!B$4:B$174,Master!T$4:T$174,Master!V$4:V$174,Master!L$4:L$174,Master!I$4:I$174,Master!BM$4:BM$174},Master!K$4:K$174="Qualified",Master!D$4:D$174="Mixed Asset / Balanced",Master!V$4:V$174<>""),4,FALSE),3,2),"") | C82: =IFERROR(INDEX(SORT(FILTER({Master!A$4:A$174,Master!B$4:B$174,Master!T$4:T$174,Master!V$4:V$174,Master!L$4:L$174,Master!I$4:I$174,Master!BM$4:BM$174},Master!K$4:K$174="Qualified",Master!D$4:D$174="Mixed Asset / Balanced",Master!V$4:V$174<>""),4,FALSE),3,3),"") | D82: =IFERROR(INDEX(SORT(FILTER({Master!A$4:A$174,Master!B$4:B$174,Master!T$4:T$174,Master!V$4:V$174,Master!L$4:L$174,Master!I$4:I$174,Master!BM$4:BM$174},Master!K$4:K$174="Qualified",Master!D$4:D$174="Mixed Asset / Balanced",Master!V$4:V$174<>""),4,FALSE),3,4),"") | E82: =IFERROR(INDEX(SORT(FILTER({Master!A$4:A$174,Master!B$4:B$174,Master!T$4:T$174,Master!V$4:V$174,Master!L$4:L$174,Master!I$4:I$174,Master!BM$4:BM$174},Master!K$4:K$174="Qualified",Master!D$4:D$174="Mixed Asset / Balanced",Master!V$4:V$174<>""),4,FALSE),3,5),"") | F82: =IFERROR(INDEX(SORT(FILTER({Master!A$4:A$174,Master!B$4:B$174,Master!T$4:T$174,Master!V$4:V$174,Master!L$4:L$174,Master!I$4:I$174,Master!BM$4:BM$174},Master!K$4:K$174="Qualified",Master!D$4:D$174="Mixed Asset / Balanced",Master!V$4:V$174<>""),4,FALSE),3,6),"") | G82: =IFERROR(INDEX(SORT(FILTER({Master!A$4:A$174,Master!B$4:B$174,Master!T$4:T$174,Master!V$4:V$174,Master!L$4:L$174,Master!I$4:I$174,Master!BM$4:BM$174},Master!K$4:K$174="Qualified",Master!D$4:D$174="Mixed Asset / Balanced",Master!V$4:V$174<>""),4,FALSE),3,7),"")
A83: =IFERROR(INDEX(SORT(FILTER({Master!A$4:A$174,Master!B$4:B$174,Master!T$4:T$174,Master!V$4:V$174,Master!L$4:L$174,Master!I$4:I$174,Master!BM$4:BM$174},Master!K$4:K$174="Qualified",Master!D$4:D$174="Mixed Asset / Balanced",Master!V$4:V$174<>""),4,FALSE),4,1),"") | B83: =IFERROR(INDEX(SORT(FILTER({Master!A$4:A$174,Master!B$4:B$174,Master!T$4:T$174,Master!V$4:V$174,Master!L$4:L$174,Master!I$4:I$174,Master!BM$4:BM$174},Master!K$4:K$174="Qualified",Master!D$4:D$174="Mixed Asset / Balanced",Master!V$4:V$174<>""),4,FALSE),4,2),"") | C83: =IFERROR(INDEX(SORT(FILTER({Master!A$4:A$174,Master!B$4:B$174,Master!T$4:T$174,Master!V$4:V$174,Master!L$4:L$174,Master!I$4:I$174,Master!BM$4:BM$174},Master!K$4:K$174="Qualified",Master!D$4:D$174="Mixed Asset / Balanced",Master!V$4:V$174<>""),4,FALSE),4,3),"") | D83: =IFERROR(INDEX(SORT(FILTER({Master!A$4:A$174,Master!B$4:B$174,Master!T$4:T$174,Master!V$4:V$174,Master!L$4:L$174,Master!I$4:I$174,Master!BM$4:BM$174},Master!K$4:K$174="Qualified",Master!D$4:D$174="Mixed Asset / Balanced",Master!V$4:V$174<>""),4,FALSE),4,4),"") | E83: =IFERROR(INDEX(SORT(FILTER({Master!A$4:A$174,Master!B$4:B$174,Master!T$4:T$174,Master!V$4:V$174,Master!L$4:L$174,Master!I$4:I$174,Master!BM$4:BM$174},Master!K$4:K$174="Qualified",Master!D$4:D$174="Mixed Asset / Balanced",Master!V$4:V$174<>""),4,FALSE),4,5),"") | F83: =IFERROR(INDEX(SORT(FILTER({Master!A$4:A$174,Master!B$4:B$174,Master!T$4:T$174,Master!V$4:V$174,Master!L$4:L$174,Master!I$4:I$174,Master!BM$4:BM$174},Master!K$4:K$174="Qualified",Master!D$4:D$174="Mixed Asset / Balanced",Master!V$4:V$174<>""),4,FALSE),4,6),"") | G83: =IFERROR(INDEX(SORT(FILTER({Master!A$4:A$174,Master!B$4:B$174,Master!T$4:T$174,Master!V$4:V$174,Master!L$4:L$174,Master!I$4:I$174,Master!BM$4:BM$174},Master!K$4:K$174="Qualified",Master!D$4:D$174="Mixed Asset / Balanced",Master!V$4:V$174<>""),4,FALSE),4,7),"")
A84: =IFERROR(INDEX(SORT(FILTER({Master!A$4:A$174,Master!B$4:B$174,Master!T$4:T$174,Master!V$4:V$174,Master!L$4:L$174,Master!I$4:I$174,Master!BM$4:BM$174},Master!K$4:K$174="Qualified",Master!D$4:D$174="Mixed Asset / Balanced",Master!V$4:V$174<>""),4,FALSE),5,1),"") | B84: =IFERROR(INDEX(SORT(FILTER({Master!A$4:A$174,Master!B$4:B$174,Master!T$4:T$174,Master!V$4:V$174,Master!L$4:L$174,Master!I$4:I$174,Master!BM$4:BM$174},Master!K$4:K$174="Qualified",Master!D$4:D$174="Mixed Asset / Balanced",Master!V$4:V$174<>""),4,FALSE),5,2),"") | C84: =IFERROR(INDEX(SORT(FILTER({Master!A$4:A$174,Master!B$4:B$174,Master!T$4:T$174,Master!V$4:V$174,Master!L$4:L$174,Master!I$4:I$174,Master!BM$4:BM$174},Master!K$4:K$174="Qualified",Master!D$4:D$174="Mixed Asset / Balanced",Master!V$4:V$174<>""),4,FALSE),5,3),"") | D84: =IFERROR(INDEX(SORT(FILTER({Master!A$4:A$174,Master!B$4:B$174,Master!T$4:T$174,Master!V$4:V$174,Master!L$4:L$174,Master!I$4:I$174,Master!BM$4:BM$174},Master!K$4:K$174="Qualified",Master!D$4:D$174="Mixed Asset / Balanced",Master!V$4:V$174<>""),4,FALSE),5,4),"") | E84: =IFERROR(INDEX(SORT(FILTER({Master!A$4:A$174,Master!B$4:B$174,Master!T$4:T$174,Master!V$4:V$174,Master!L$4:L$174,Master!I$4:I$174,Master!BM$4:BM$174},Master!K$4:K$174="Qualified",Master!D$4:D$174="Mixed Asset / Balanced",Master!V$4:V$174<>""),4,FALSE),5,5),"") | F84: =IFERROR(INDEX(SORT(FILTER({Master!A$4:A$174,Master!B$4:B$174,Master!T$4:T$174,Master!V$4:V$174,Master!L$4:L$174,Master!I$4:I$174,Master!BM$4:BM$174},Master!K$4:K$174="Qualified",Master!D$4:D$174="Mixed Asset / Balanced",Master!V$4:V$174<>""),4,FALSE),5,6),"") | G84: =IFERROR(INDEX(SORT(FILTER({Master!A$4:A$174,Master!B$4:B$174,Master!T$4:T$174,Master!V$4:V$174,Master!L$4:L$174,Master!I$4:I$174,Master!BM$4:BM$174},Master!K$4:K$174="Qualified",Master!D$4:D$174="Mixed Asset / Balanced",Master!V$4:V$174<>""),4,FALSE),5,7),"")
A86: BALANCED / MIXED ASSET — TOP 5 BY ALPHA EFFICIENCY
A87: Fund Name | B87: Abbr | C87: Alpha Eff | D87: 3Y Alpha (%) | E87: Beat (%) | F87: AUM (RM M) | G87: VC
A88: =IFERROR(INDEX(SORT(FILTER({Master!A$4:A$174,Master!B$4:B$174,Master!AE$4:AE$174,Master!V$4:V$174,Master!L$4:L$174,Master!I$4:I$174,Master!BM$4:BM$174},Master!K$4:K$174="Qualified",Master!D$4:D$174="Mixed Asset / Balanced",Master!AE$4:AE$174<>""),3,FALSE),1,1),"") | B88: =IFERROR(INDEX(SORT(FILTER({Master!A$4:A$174,Master!B$4:B$174,Master!AE$4:AE$174,Master!V$4:V$174,Master!L$4:L$174,Master!I$4:I$174,Master!BM$4:BM$174},Master!K$4:K$174="Qualified",Master!D$4:D$174="Mixed Asset / Balanced",Master!AE$4:AE$174<>""),3,FALSE),1,2),"") | C88: =IFERROR(INDEX(SORT(FILTER({Master!A$4:A$174,Master!B$4:B$174,Master!AE$4:AE$174,Master!V$4:V$174,Master!L$4:L$174,Master!I$4:I$174,Master!BM$4:BM$174},Master!K$4:K$174="Qualified",Master!D$4:D$174="Mixed Asset / Balanced",Master!AE$4:AE$174<>""),3,FALSE),1,3),"") | D88: =IFERROR(INDEX(SORT(FILTER({Master!A$4:A$174,Master!B$4:B$174,Master!AE$4:AE$174,Master!V$4:V$174,Master!L$4:L$174,Master!I$4:I$174,Master!BM$4:BM$174},Master!K$4:K$174="Qualified",Master!D$4:D$174="Mixed Asset / Balanced",Master!AE$4:AE$174<>""),3,FALSE),1,4),"") | E88: =IFERROR(INDEX(SORT(FILTER({Master!A$4:A$174,Master!B$4:B$174,Master!AE$4:AE$174,Master!V$4:V$174,Master!L$4:L$174,Master!I$4:I$174,Master!BM$4:BM$174},Master!K$4:K$174="Qualified",Master!D$4:D$174="Mixed Asset / Balanced",Master!AE$4:AE$174<>""),3,FALSE),1,5),"") | F88: =IFERROR(INDEX(SORT(FILTER({Master!A$4:A$174,Master!B$4:B$174,Master!AE$4:AE$174,Master!V$4:V$174,Master!L$4:L$174,Master!I$4:I$174,Master!BM$4:BM$174},Master!K$4:K$174="Qualified",Master!D$4:D$174="Mixed Asset / Balanced",Master!AE$4:AE$174<>""),3,FALSE),1,6),"") | G88: =IFERROR(INDEX(SORT(FILTER({Master!A$4:A$174,Master!B$4:B$174,Master!AE$4:AE$174,Master!V$4:V$174,Master!L$4:L$174,Master!I$4:I$174,Master!BM$4:BM$174},Master!K$4:K$174="Qualified",Master!D$4:D$174="Mixed Asset / Balanced",Master!AE$4:AE$174<>""),3,FALSE),1,7),"")
A89: =IFERROR(INDEX(SORT(FILTER({Master!A$4:A$174,Master!B$4:B$174,Master!AE$4:AE$174,Master!V$4:V$174,Master!L$4:L$174,Master!I$4:I$174,Master!BM$4:BM$174},Master!K$4:K$174="Qualified",Master!D$4:D$174="Mixed Asset / Balanced",Master!AE$4:AE$174<>""),3,FALSE),2,1),"") | B89: =IFERROR(INDEX(SORT(FILTER({Master!A$4:A$174,Master!B$4:B$174,Master!AE$4:AE$174,Master!V$4:V$174,Master!L$4:L$174,Master!I$4:I$174,Master!BM$4:BM$174},Master!K$4:K$174="Qualified",Master!D$4:D$174="Mixed Asset / Balanced",Master!AE$4:AE$174<>""),3,FALSE),2,2),"") | C89: =IFERROR(INDEX(SORT(FILTER({Master!A$4:A$174,Master!B$4:B$174,Master!AE$4:AE$174,Master!V$4:V$174,Master!L$4:L$174,Master!I$4:I$174,Master!BM$4:BM$174},Master!K$4:K$174="Qualified",Master!D$4:D$174="Mixed Asset / Balanced",Master!AE$4:AE$174<>""),3,FALSE),2,3),"") | D89: =IFERROR(INDEX(SORT(FILTER({Master!A$4:A$174,Master!B$4:B$174,Master!AE$4:AE$174,Master!V$4:V$174,Master!L$4:L$174,Master!I$4:I$174,Master!BM$4:BM$174},Master!K$4:K$174="Qualified",Master!D$4:D$174="Mixed Asset / Balanced",Master!AE$4:AE$174<>""),3,FALSE),2,4),"") | E89: =IFERROR(INDEX(SORT(FILTER({Master!A$4:A$174,Master!B$4:B$174,Master!AE$4:AE$174,Master!V$4:V$174,Master!L$4:L$174,Master!I$4:I$174,Master!BM$4:BM$174},Master!K$4:K$174="Qualified",Master!D$4:D$174="Mixed Asset / Balanced",Master!AE$4:AE$174<>""),3,FALSE),2,5),"") | F89: =IFERROR(INDEX(SORT(FILTER({Master!A$4:A$174,Master!B$4:B$174,Master!AE$4:AE$174,Master!V$4:V$174,Master!L$4:L$174,Master!I$4:I$174,Master!BM$4:BM$174},Master!K$4:K$174="Qualified",Master!D$4:D$174="Mixed Asset / Balanced",Master!AE$4:AE$174<>""),3,FALSE),2,6),"") | G89: =IFERROR(INDEX(SORT(FILTER({Master!A$4:A$174,Master!B$4:B$174,Master!AE$4:AE$174,Master!V$4:V$174,Master!L$4:L$174,Master!I$4:I$174,Master!BM$4:BM$174},Master!K$4:K$174="Qualified",Master!D$4:D$174="Mixed Asset / Balanced",Master!AE$4:AE$174<>""),3,FALSE),2,7),"")
A90: =IFERROR(INDEX(SORT(FILTER({Master!A$4:A$174,Master!B$4:B$174,Master!AE$4:AE$174,Master!V$4:V$174,Master!L$4:L$174,Master!I$4:I$174,Master!BM$4:BM$174},Master!K$4:K$174="Qualified",Master!D$4:D$174="Mixed Asset / Balanced",Master!AE$4:AE$174<>""),3,FALSE),3,1),"") | B90: =IFERROR(INDEX(SORT(FILTER({Master!A$4:A$174,Master!B$4:B$174,Master!AE$4:AE$174,Master!V$4:V$174,Master!L$4:L$174,Master!I$4:I$174,Master!BM$4:BM$174},Master!K$4:K$174="Qualified",Master!D$4:D$174="Mixed Asset / Balanced",Master!AE$4:AE$174<>""),3,FALSE),3,2),"") | C90: =IFERROR(INDEX(SORT(FILTER({Master!A$4:A$174,Master!B$4:B$174,Master!AE$4:AE$174,Master!V$4:V$174,Master!L$4:L$174,Master!I$4:I$174,Master!BM$4:BM$174},Master!K$4:K$174="Qualified",Master!D$4:D$174="Mixed Asset / Balanced",Master!AE$4:AE$174<>""),3,FALSE),3,3),"") | D90: =IFERROR(INDEX(SORT(FILTER({Master!A$4:A$174,Master!B$4:B$174,Master!AE$4:AE$174,Master!V$4:V$174,Master!L$4:L$174,Master!I$4:I$174,Master!BM$4:BM$174},Master!K$4:K$174="Qualified",Master!D$4:D$174="Mixed Asset / Balanced",Master!AE$4:AE$174<>""),3,FALSE),3,4),"") | E90: =IFERROR(INDEX(SORT(FILTER({Master!A$4:A$174,Master!B$4:B$174,Master!AE$4:AE$174,Master!V$4:V$174,Master!L$4:L$174,Master!I$4:I$174,Master!BM$4:BM$174},Master!K$4:K$174="Qualified",Master!D$4:D$174="Mixed Asset / Balanced",Master!AE$4:AE$174<>""),3,FALSE),3,5),"") | F90: =IFERROR(INDEX(SORT(FILTER({Master!A$4:A$174,Master!B$4:B$174,Master!AE$4:AE$174,Master!V$4:V$174,Master!L$4:L$174,Master!I$4:I$174,Master!BM$4:BM$174},Master!K$4:K$174="Qualified",Master!D$4:D$174="Mixed Asset / Balanced",Master!AE$4:AE$174<>""),3,FALSE),3,6),"") | G90: =IFERROR(INDEX(SORT(FILTER({Master!A$4:A$174,Master!B$4:B$174,Master!AE$4:AE$174,Master!V$4:V$174,Master!L$4:L$174,Master!I$4:I$174,Master!BM$4:BM$174},Master!K$4:K$174="Qualified",Master!D$4:D$174="Mixed Asset / Balanced",Master!AE$4:AE$174<>""),3,FALSE),3,7),"")
A91: =IFERROR(INDEX(SORT(FILTER({Master!A$4:A$174,Master!B$4:B$174,Master!AE$4:AE$174,Master!V$4:V$174,Master!L$4:L$174,Master!I$4:I$174,Master!BM$4:BM$174},Master!K$4:K$174="Qualified",Master!D$4:D$174="Mixed Asset / Balanced",Master!AE$4:AE$174<>""),3,FALSE),4,1),"") | B91: =IFERROR(INDEX(SORT(FILTER({Master!A$4:A$174,Master!B$4:B$174,Master!AE$4:AE$174,Master!V$4:V$174,Master!L$4:L$174,Master!I$4:I$174,Master!BM$4:BM$174},Master!K$4:K$174="Qualified",Master!D$4:D$174="Mixed Asset / Balanced",Master!AE$4:AE$174<>""),3,FALSE),4,2),"") | C91: =IFERROR(INDEX(SORT(FILTER({Master!A$4:A$174,Master!B$4:B$174,Master!AE$4:AE$174,Master!V$4:V$174,Master!L$4:L$174,Master!I$4:I$174,Master!BM$4:BM$174},Master!K$4:K$174="Qualified",Master!D$4:D$174="Mixed Asset / Balanced",Master!AE$4:AE$174<>""),3,FALSE),4,3),"") | D91: =IFERROR(INDEX(SORT(FILTER({Master!A$4:A$174,Master!B$4:B$174,Master!AE$4:AE$174,Master!V$4:V$174,Master!L$4:L$174,Master!I$4:I$174,Master!BM$4:BM$174},Master!K$4:K$174="Qualified",Master!D$4:D$174="Mixed Asset / Balanced",Master!AE$4:AE$174<>""),3,FALSE),4,4),"") | E91: =IFERROR(INDEX(SORT(FILTER({Master!A$4:A$174,Master!B$4:B$174,Master!AE$4:AE$174,Master!V$4:V$174,Master!L$4:L$174,Master!I$4:I$174,Master!BM$4:BM$174},Master!K$4:K$174="Qualified",Master!D$4:D$174="Mixed Asset / Balanced",Master!AE$4:AE$174<>""),3,FALSE),4,5),"") | F91: =IFERROR(INDEX(SORT(FILTER({Master!A$4:A$174,Master!B$4:B$174,Master!AE$4:AE$174,Master!V$4:V$174,Master!L$4:L$174,Master!I$4:I$174,Master!BM$4:BM$174},Master!K$4:K$174="Qualified",Master!D$4:D$174="Mixed Asset / Balanced",Master!AE$4:AE$174<>""),3,FALSE),4,6),"") | G91: =IFERROR(INDEX(SORT(FILTER({Master!A$4:A$174,Master!B$4:B$174,Master!AE$4:AE$174,Master!V$4:V$174,Master!L$4:L$174,Master!I$4:I$174,Master!BM$4:BM$174},Master!K$4:K$174="Qualified",Master!D$4:D$174="Mixed Asset / Balanced",Master!AE$4:AE$174<>""),3,FALSE),4,7),"")
A92: =IFERROR(INDEX(SORT(FILTER({Master!A$4:A$174,Master!B$4:B$174,Master!AE$4:AE$174,Master!V$4:V$174,Master!L$4:L$174,Master!I$4:I$174,Master!BM$4:BM$174},Master!K$4:K$174="Qualified",Master!D$4:D$174="Mixed Asset / Balanced",Master!AE$4:AE$174<>""),3,FALSE),5,1),"") | B92: =IFERROR(INDEX(SORT(FILTER({Master!A$4:A$174,Master!B$4:B$174,Master!AE$4:AE$174,Master!V$4:V$174,Master!L$4:L$174,Master!I$4:I$174,Master!BM$4:BM$174},Master!K$4:K$174="Qualified",Master!D$4:D$174="Mixed Asset / Balanced",Master!AE$4:AE$174<>""),3,FALSE),5,2),"") | C92: =IFERROR(INDEX(SORT(FILTER({Master!A$4:A$174,Master!B$4:B$174,Master!AE$4:AE$174,Master!V$4:V$174,Master!L$4:L$174,Master!I$4:I$174,Master!BM$4:BM$174},Master!K$4:K$174="Qualified",Master!D$4:D$174="Mixed Asset / Balanced",Master!AE$4:AE$174<>""),3,FALSE),5,3),"") | D92: =IFERROR(INDEX(SORT(FILTER({Master!A$4:A$174,Master!B$4:B$174,Master!AE$4:AE$174,Master!V$4:V$174,Master!L$4:L$174,Master!I$4:I$174,Master!BM$4:BM$174},Master!K$4:K$174="Qualified",Master!D$4:D$174="Mixed Asset / Balanced",Master!AE$4:AE$174<>""),3,FALSE),5,4),"") | E92: =IFERROR(INDEX(SORT(FILTER({Master!A$4:A$174,Master!B$4:B$174,Master!AE$4:AE$174,Master!V$4:V$174,Master!L$4:L$174,Master!I$4:I$174,Master!BM$4:BM$174},Master!K$4:K$174="Qualified",Master!D$4:D$174="Mixed Asset / Balanced",Master!AE$4:AE$174<>""),3,FALSE),5,5),"") | F92: =IFERROR(INDEX(SORT(FILTER({Master!A$4:A$174,Master!B$4:B$174,Master!AE$4:AE$174,Master!V$4:V$174,Master!L$4:L$174,Master!I$4:I$174,Master!BM$4:BM$174},Master!K$4:K$174="Qualified",Master!D$4:D$174="Mixed Asset / Balanced",Master!AE$4:AE$174<>""),3,FALSE),5,6),"") | G92: =IFERROR(INDEX(SORT(FILTER({Master!A$4:A$174,Master!B$4:B$174,Master!AE$4:AE$174,Master!V$4:V$174,Master!L$4:L$174,Master!I$4:I$174,Master!BM$4:BM$174},Master!K$4:K$174="Qualified",Master!D$4:D$174="Mixed Asset / Balanced",Master!AE$4:AE$174<>""),3,FALSE),5,7),"")
A94: BALANCED / MIXED ASSET — TOP 5 BY AUM
A95: Fund Name | B95: Abbr | C95: AUM (RM M) | D95: 3Y Fund (%) | E95: 3Y Alpha (%) | F95: Beat (%) | G95: VC
A96: =IFERROR(INDEX(SORT(FILTER({Master!A$4:A$174,Master!B$4:B$174,Master!I$4:I$174,Master!T$4:T$174,Master!V$4:V$174,Master!L$4:L$174,Master!BM$4:BM$174},Master!K$4:K$174="Qualified",Master!D$4:D$174="Mixed Asset / Balanced",Master!I$4:I$174<>""),3,FALSE),1,1),"") | B96: =IFERROR(INDEX(SORT(FILTER({Master!A$4:A$174,Master!B$4:B$174,Master!I$4:I$174,Master!T$4:T$174,Master!V$4:V$174,Master!L$4:L$174,Master!BM$4:BM$174},Master!K$4:K$174="Qualified",Master!D$4:D$174="Mixed Asset / Balanced",Master!I$4:I$174<>""),3,FALSE),1,2),"") | C96: =IFERROR(INDEX(SORT(FILTER({Master!A$4:A$174,Master!B$4:B$174,Master!I$4:I$174,Master!T$4:T$174,Master!V$4:V$174,Master!L$4:L$174,Master!BM$4:BM$174},Master!K$4:K$174="Qualified",Master!D$4:D$174="Mixed Asset / Balanced",Master!I$4:I$174<>""),3,FALSE),1,3),"") | D96: =IFERROR(INDEX(SORT(FILTER({Master!A$4:A$174,Master!B$4:B$174,Master!I$4:I$174,Master!T$4:T$174,Master!V$4:V$174,Master!L$4:L$174,Master!BM$4:BM$174},Master!K$4:K$174="Qualified",Master!D$4:D$174="Mixed Asset / Balanced",Master!I$4:I$174<>""),3,FALSE),1,4),"") | E96: =IFERROR(INDEX(SORT(FILTER({Master!A$4:A$174,Master!B$4:B$174,Master!I$4:I$174,Master!T$4:T$174,Master!V$4:V$174,Master!L$4:L$174,Master!BM$4:BM$174},Master!K$4:K$174="Qualified",Master!D$4:D$174="Mixed Asset / Balanced",Master!I$4:I$174<>""),3,FALSE),1,5),"") | F96: =IFERROR(INDEX(SORT(FILTER({Master!A$4:A$174,Master!B$4:B$174,Master!I$4:I$174,Master!T$4:T$174,Master!V$4:V$174,Master!L$4:L$174,Master!BM$4:BM$174},Master!K$4:K$174="Qualified",Master!D$4:D$174="Mixed Asset / Balanced",Master!I$4:I$174<>""),3,FALSE),1,6),"") | G96: =IFERROR(INDEX(SORT(FILTER({Master!A$4:A$174,Master!B$4:B$174,Master!I$4:I$174,Master!T$4:T$174,Master!V$4:V$174,Master!L$4:L$174,Master!BM$4:BM$174},Master!K$4:K$174="Qualified",Master!D$4:D$174="Mixed Asset / Balanced",Master!I$4:I$174<>""),3,FALSE),1,7),"")
A97: =IFERROR(INDEX(SORT(FILTER({Master!A$4:A$174,Master!B$4:B$174,Master!I$4:I$174,Master!T$4:T$174,Master!V$4:V$174,Master!L$4:L$174,Master!BM$4:BM$174},Master!K$4:K$174="Qualified",Master!D$4:D$174="Mixed Asset / Balanced",Master!I$4:I$174<>""),3,FALSE),2,1),"") | B97: =IFERROR(INDEX(SORT(FILTER({Master!A$4:A$174,Master!B$4:B$174,Master!I$4:I$174,Master!T$4:T$174,Master!V$4:V$174,Master!L$4:L$174,Master!BM$4:BM$174},Master!K$4:K$174="Qualified",Master!D$4:D$174="Mixed Asset / Balanced",Master!I$4:I$174<>""),3,FALSE),2,2),"") | C97: =IFERROR(INDEX(SORT(FILTER({Master!A$4:A$174,Master!B$4:B$174,Master!I$4:I$174,Master!T$4:T$174,Master!V$4:V$174,Master!L$4:L$174,Master!BM$4:BM$174},Master!K$4:K$174="Qualified",Master!D$4:D$174="Mixed Asset / Balanced",Master!I$4:I$174<>""),3,FALSE),2,3),"") | D97: =IFERROR(INDEX(SORT(FILTER({Master!A$4:A$174,Master!B$4:B$174,Master!I$4:I$174,Master!T$4:T$174,Master!V$4:V$174,Master!L$4:L$174,Master!BM$4:BM$174},Master!K$4:K$174="Qualified",Master!D$4:D$174="Mixed Asset / Balanced",Master!I$4:I$174<>""),3,FALSE),2,4),"") | E97: =IFERROR(INDEX(SORT(FILTER({Master!A$4:A$174,Master!B$4:B$174,Master!I$4:I$174,Master!T$4:T$174,Master!V$4:V$174,Master!L$4:L$174,Master!BM$4:BM$174},Master!K$4:K$174="Qualified",Master!D$4:D$174="Mixed Asset / Balanced",Master!I$4:I$174<>""),3,FALSE),2,5),"") | F97: =IFERROR(INDEX(SORT(FILTER({Master!A$4:A$174,Master!B$4:B$174,Master!I$4:I$174,Master!T$4:T$174,Master!V$4:V$174,Master!L$4:L$174,Master!BM$4:BM$174},Master!K$4:K$174="Qualified",Master!D$4:D$174="Mixed Asset / Balanced",Master!I$4:I$174<>""),3,FALSE),2,6),"") | G97: =IFERROR(INDEX(SORT(FILTER({Master!A$4:A$174,Master!B$4:B$174,Master!I$4:I$174,Master!T$4:T$174,Master!V$4:V$174,Master!L$4:L$174,Master!BM$4:BM$174},Master!K$4:K$174="Qualified",Master!D$4:D$174="Mixed Asset / Balanced",Master!I$4:I$174<>""),3,FALSE),2,7),"")
A98: =IFERROR(INDEX(SORT(FILTER({Master!A$4:A$174,Master!B$4:B$174,Master!I$4:I$174,Master!T$4:T$174,Master!V$4:V$174,Master!L$4:L$174,Master!BM$4:BM$174},Master!K$4:K$174="Qualified",Master!D$4:D$174="Mixed Asset / Balanced",Master!I$4:I$174<>""),3,FALSE),3,1),"") | B98: =IFERROR(INDEX(SORT(FILTER({Master!A$4:A$174,Master!B$4:B$174,Master!I$4:I$174,Master!T$4:T$174,Master!V$4:V$174,Master!L$4:L$174,Master!BM$4:BM$174},Master!K$4:K$174="Qualified",Master!D$4:D$174="Mixed Asset / Balanced",Master!I$4:I$174<>""),3,FALSE),3,2),"") | C98: =IFERROR(INDEX(SORT(FILTER({Master!A$4:A$174,Master!B$4:B$174,Master!I$4:I$174,Master!T$4:T$174,Master!V$4:V$174,Master!L$4:L$174,Master!BM$4:BM$174},Master!K$4:K$174="Qualified",Master!D$4:D$174="Mixed Asset / Balanced",Master!I$4:I$174<>""),3,FALSE),3,3),"") | D98: =IFERROR(INDEX(SORT(FILTER({Master!A$4:A$174,Master!B$4:B$174,Master!I$4:I$174,Master!T$4:T$174,Master!V$4:V$174,Master!L$4:L$174,Master!BM$4:BM$174},Master!K$4:K$174="Qualified",Master!D$4:D$174="Mixed Asset / Balanced",Master!I$4:I$174<>""),3,FALSE),3,4),"") | E98: =IFERROR(INDEX(SORT(FILTER({Master!A$4:A$174,Master!B$4:B$174,Master!I$4:I$174,Master!T$4:T$174,Master!V$4:V$174,Master!L$4:L$174,Master!BM$4:BM$174},Master!K$4:K$174="Qualified",Master!D$4:D$174="Mixed Asset / Balanced",Master!I$4:I$174<>""),3,FALSE),3,5),"") | F98: =IFERROR(INDEX(SORT(FILTER({Master!A$4:A$174,Master!B$4:B$174,Master!I$4:I$174,Master!T$4:T$174,Master!V$4:V$174,Master!L$4:L$174,Master!BM$4:BM$174},Master!K$4:K$174="Qualified",Master!D$4:D$174="Mixed Asset / Balanced",Master!I$4:I$174<>""),3,FALSE),3,6),"") | G98: =IFERROR(INDEX(SORT(FILTER({Master!A$4:A$174,Master!B$4:B$174,Master!I$4:I$174,Master!T$4:T$174,Master!V$4:V$174,Master!L$4:L$174,Master!BM$4:BM$174},Master!K$4:K$174="Qualified",Master!D$4:D$174="Mixed Asset / Balanced",Master!I$4:I$174<>""),3,FALSE),3,7),"")
A99: =IFERROR(INDEX(SORT(FILTER({Master!A$4:A$174,Master!B$4:B$174,Master!I$4:I$174,Master!T$4:T$174,Master!V$4:V$174,Master!L$4:L$174,Master!BM$4:BM$174},Master!K$4:K$174="Qualified",Master!D$4:D$174="Mixed Asset / Balanced",Master!I$4:I$174<>""),3,FALSE),4,1),"") | B99: =IFERROR(INDEX(SORT(FILTER({Master!A$4:A$174,Master!B$4:B$174,Master!I$4:I$174,Master!T$4:T$174,Master!V$4:V$174,Master!L$4:L$174,Master!BM$4:BM$174},Master!K$4:K$174="Qualified",Master!D$4:D$174="Mixed Asset / Balanced",Master!I$4:I$174<>""),3,FALSE),4,2),"") | C99: =IFERROR(INDEX(SORT(FILTER({Master!A$4:A$174,Master!B$4:B$174,Master!I$4:I$174,Master!T$4:T$174,Master!V$4:V$174,Master!L$4:L$174,Master!BM$4:BM$174},Master!K$4:K$174="Qualified",Master!D$4:D$174="Mixed Asset / Balanced",Master!I$4:I$174<>""),3,FALSE),4,3),"") | D99: =IFERROR(INDEX(SORT(FILTER({Master!A$4:A$174,Master!B$4:B$174,Master!I$4:I$174,Master!T$4:T$174,Master!V$4:V$174,Master!L$4:L$174,Master!BM$4:BM$174},Master!K$4:K$174="Qualified",Master!D$4:D$174="Mixed Asset / Balanced",Master!I$4:I$174<>""),3,FALSE),4,4),"") | E99: =IFERROR(INDEX(SORT(FILTER({Master!A$4:A$174,Master!B$4:B$174,Master!I$4:I$174,Master!T$4:T$174,Master!V$4:V$174,Master!L$4:L$174,Master!BM$4:BM$174},Master!K$4:K$174="Qualified",Master!D$4:D$174="Mixed Asset / Balanced",Master!I$4:I$174<>""),3,FALSE),4,5),"") | F99: =IFERROR(INDEX(SORT(FILTER({Master!A$4:A$174,Master!B$4:B$174,Master!I$4:I$174,Master!T$4:T$174,Master!V$4:V$174,Master!L$4:L$174,Master!BM$4:BM$174},Master!K$4:K$174="Qualified",Master!D$4:D$174="Mixed Asset / Balanced",Master!I$4:I$174<>""),3,FALSE),4,6),"") | G99: =IFERROR(INDEX(SORT(FILTER({Master!A$4:A$174,Master!B$4:B$174,Master!I$4:I$174,Master!T$4:T$174,Master!V$4:V$174,Master!L$4:L$174,Master!BM$4:BM$174},Master!K$4:K$174="Qualified",Master!D$4:D$174="Mixed Asset / Balanced",Master!I$4:I$174<>""),3,FALSE),4,7),"")
