Workbook

Sheet Master
A1: PUBLIC MUTUAL — FUND MASTER | Data: MFR April 2026 | 134 Qualified / 171 Total Funds
A2: FUND DETAILS | J2: SCREENING | O2: ANNUALISED RETURNS vs BENCHMARK (MFR FEB 2026) | AD2: ALPHA EFFICIENCY (Alpha / VF) | AI2: ASSET ALLOCATION (%) | AO2: GEOGRAPHICAL BREAKDOWN (%) | BA2: SECTOR BREAKDOWN (%) | BL2: TOP 5 | BM2: META | BQ2: ATH MOMENTUM
A3: Fund Name | B3: Abbr | C3: Shariah-compliant | D3: Fund Type | E3: Objective | F3: Risk Level | G3: Distribution | H3: Size (RM M) | I3: Launch | J3: Status | K3: Beat (%) | L3: Periods | M3: Rationale | N3: Wtd Alpha (%) | O3: YTD Fund (%) | P3: YTD Bench (%) | Q3: YTD Alpha (%) | R3: 1Y Fund (%) | S3: 1Y Bench (%) | T3: 1Y Alpha (%) | U3: 3Y Fund (%) | V3: 3Y Bench (%) | W3: 3Y Alpha (%) | X3: 5Y Fund (%) | Y3: 5Y Bench (%) | Z3: 5Y Alpha (%) | AA3: 10Y Fund (%) | AB3: 10Y Bench (%) | AC3: 10Y Alpha (%) | AD3: AE YTD | AE3: AE 1Y | AF3: AE 3Y | AG3: AE 5Y | AH3: AE 10Y | AI3: Dom. Equity (%) | AJ3: For. Equity (%) | AK3: FI / Sukuk (%) | AL3: Money Mkt (%) | AM3: Deposits (%) | AN3: Alloc Other (%) | AO3: USA (%) | AP3: Taiwan (%) | AQ3: Korea (%) | AR3: Japan (%) | AS3: France (%) | AT3: Germany (%) | AU3: China (%) | AV3: Singapore (%) | AW3: Netherlands (%) | AX3: Indonesia (%) | AY3: Australia (%) | AZ3: Geo Other (%) | BA3: Industrial (%) | BB3: Technology (%) | BC3: Financial (%) | BD3: Comms (%) | BE3: Cons. Disc. (%) | BF3: Cons. Staples (%) | BG3: Utilities (%) | BH3: Energy (%) | BI3: Materials (%) | BJ3: Real Estate (%) | BK3: Sector Other (%) | BL3: Top 5 Holdings | BM3: VF | BN3: VC | BO3: Lipper Class | BP3: Benchmark | BQ3: ATH NAV | BR3: ATH Date | BS3: Cur NAV | BT3: Drawdown (%) | BU3: Days from ATH
A4: PUBLIC ASIA PACIFIC FOCUS FUND | B4: PAPFF | C4: Conventional | D4: Equity | E4: Capital Growth | F4: 5 | G4: Incidental | H4: 132.41 | I4: 30.11.2021 | J4: Qualified | K4: 100 | L4: 3/3 | M4: Qualified (WA: +19.55%) — YTD✔ 1Y✔ 3Y✔ | N4: 19.55 | O4: 33.32 | P4: 12.92 | Q4: 20.4 | R4: 84.84 | S4: 39.58 | T4: 45.26 | U4: 27.63 | V4: 17.82 | W4: 9.81 | AD4: =IF(OR(Q4="",BM4="",BM4=0),"",Q4/BM4) | AE4: =IF(OR(T4="",BM4="",BM4=0),"",T4/BM4) | AF4: =IF(OR(W4="",BM4="",BM4=0),"",W4/BM4) | AG4: =IF(OR(Z4="",BM4="",BM4=0),"",Z4/BM4) | AH4: =IF(OR(AC4="",BM4="",BM4=0),"",AC4/BM4) | AI4: 0.8 | AJ4: 92.3 | AL4: 6.9 | AO4: 10.2 | AP4: 32.6 | AQ4: 34.6 | AR4: 7.7 | AU4: 7.2 | BA4: 24.4 | BB4: 52 | BC4: 2 | BD4: 14.7 | BL4: SK Hynix Incorporated | Taiwan Semiconductor Manufacturing Company Limited | Samsung Electronics Company Limited | HD Hyundai Electric Company Limited | Hanwha Aerospace Company Limited | BM4: 20.2 | BN4: Very High | BO4: Equity Asia Pacific Asia | BP4: ThebenchmarkforPAPFFisacompositeof80%customisedindexbyS&PDow JonesIndices,LLCbasedonthetop30constituentsoftheS&PBMIAsiaEx-Japan Index, 10% Tokyo Stock Price Index (TOPIX) and 10% 3-Month Kuala Lumpur Interbank Offered Rate (KLIBOR). UnderlyingindexdataaresourcedfromS&PDowJonesIndices,LLC,Lipperand Bank Negara Malaysia and expressed in Ringgit terms. | BQ4: 0.475 | BR4: 2026-06-04 | BS4: 0.46 | BT4: -3.16 | BU4: 11
A5: PUBLIC CHINA SELECT FUND | B5: PCSF | C5: Conventional | D5: Equity | E5: Capital Growth | F5: 5 | G5: Incidental | H5: 1054.97 | I5: 05.06.2007 | J5: Qualified | K5: 100 | L5: 5/5 | M5: Qualified (WA: +18.36%) — YTD✔ 1Y✔ 3Y✔ 5Y✔ 10Y✔ | N5: 18.36 | O5: 28.22 | P5: 7.04 | Q5: 21.18 | R5: 83.16 | S5: 26.81 | T5: 56.35 | U5: 27.21 | V5: 12.44 | W5: 14.77 | X5: 8.99 | Y5: -0.18 | Z5: 9.17 | AA5: 11.89 | AB5: 7.55 | AC5: 4.34 | AD5: =IF(OR(Q5="",BM5="",BM5=0),"",Q5/BM5) | AE5: =IF(OR(T5="",BM5="",BM5=0),"",T5/BM5) | AF5: =IF(OR(W5="",BM5="",BM5=0),"",W5/BM5) | AG5: =IF(OR(Z5="",BM5="",BM5=0),"",Z5/BM5) | AH5: =IF(OR(AC5="",BM5="",BM5=0),"",AC5/BM5) | AJ5: 97.2 | AL5: 2.8 | AO5: 18.8 | AP5: 58.3 | AU5: 20.1 | BA5: 25.9 | BB5: 34.8 | BD5: 28.8 | BE5: 7.7 | BL5: Elite Material Company Limited | Asia Vital Components Company Limited | Jentech Precision Industrial Company Limited | Taiwan Semiconductor Manufacturing Company Limited | Alphabet Incorporated - Class A | BM5: 16.2 | BN5: Very High | BO5: Equity Greater China Greater China | BQ5: 0.6555 | BR5: 2026-06-03 | BS5: 0.6216 | BT5: -5.17 | BU5: 12
A6: PUBLIC CHINA ITTIKAL FUND | B6: PCIF | C6: Shariah | D6: Equity | E6: Capital Growth | F6: 5 | G6: Incidental | H6: 923.46 | I6: 20.11.2007 | J6: Qualified | K6: 100 | L6: 5/5 | M6: Qualified (WA: +14.74%) — YTD✔ 1Y✔ 3Y✔ 5Y✔ 10Y✔ | N6: 14.74 | O6: 40.62 | P6: 7.79 | Q6: 32.83 | R6: 72.7 | S6: 23.44 | T6: 49.26 | U6: 24.34 | V6: 13.8 | W6: 10.54 | X6: 5.56 | Y6: 0.86 | Z6: 4.7 | AA6: 10.52 | AB6: 8.37 | AC6: 2.15 | AD6: =IF(OR(Q6="",BM6="",BM6=0),"",Q6/BM6) | AE6: =IF(OR(T6="",BM6="",BM6=0),"",T6/BM6) | AF6: =IF(OR(W6="",BM6="",BM6=0),"",W6/BM6) | AG6: =IF(OR(Z6="",BM6="",BM6=0),"",Z6/BM6) | AH6: =IF(OR(AC6="",BM6="",BM6=0),"",AC6/BM6) | AJ6: 96 | AL6: 4 | AO6: 3.9 | AP6: 70 | AQ6: 3 | AU6: 19.1 | BA6: 28.6 | BB6: 38.7 | BD6: 24.9 | BE6: 2.6 | BF6: 1.2 | BL6: Unimicron Technology Corporation | Taiwan Semiconductor Manufacturing Company Limited | Asia Vital Components Company Limited | Delta Electronics Incorporated | Accton Technology Corporation | BM6: 15.5 | BN6: Very High | BO6: Equity Greater China Greater China | BQ6: 0.6841 | BR6: 2026-06-03 | BS6: 0.643 | BT6: -6.01 | BU6: 12
A7: PUBLIC ISLAMIC REGIONAL ESG FUND | B7: PIRESGF | C7: Shariah | D7: Equity | E7: Capital Growth | F7: 5 | G7: Incidental | H7: 223.79 | I7: 07.11.2023 | J7: Qualified | K7: 100 | L7: 2/2 | M7: Qualified (WA: +14.22%) — YTD✔ 1Y✔ | N7: 14.22 | O7: 30.44 | P7: 23.61 | Q7: 6.83 | R7: 76.57 | S7: 59.89 | T7: 16.68 | AD7: =IF(OR(Q7="",BM7="",BM7=0),"",Q7/BM7) | AE7: =IF(OR(T7="",BM7="",BM7=0),"",T7/BM7) | AF7: =IF(OR(W7="",BM7="",BM7=0),"",W7/BM7) | AG7: =IF(OR(Z7="",BM7="",BM7=0),"",Z7/BM7) | AH7: =IF(OR(AC7="",BM7="",BM7=0),"",AC7/BM7) | AJ7: 87.3 | AL7: 12.7 | AO7: 7.8 | AP7: 28.3 | AQ7: 30.7 | AR7: 14.3 | AU7: 6.2 | BA7: 25.6 | BB7: 39.7 | BD7: 18.3 | BE7: 3.7 | BL7: SK Hynix Incorporated | HD Hyundai Electric Company Limited | Delta Electronics Incorporated | Taiwan Semiconductor Manufacturing Company Limited | Samsung Electronics Company Limited | BP7: ThebenchmarkforPIRESGFisacustomisedindexbyS&PDowJonesIndices, LLCbasedonconstituentsoftheS&PGlobalLargeMidCapESGShariahIndex comprisingJapan,China‘H’Shares,HongKong,Taiwan,SouthKorea,Malaysia, Singapore, Thailand, Indonesia & Philippines. Underlying index data are sourced from S&P Dow Jones Indices, LLC and expressed in Ringgit terms. | BQ7: 0.5179 | BR7: 2026-06-04 | BS7: 0.5049 | BT7: -2.51 | BU7: 11
A8: PUBLIC REGIONAL SECTOR FUND | B8: PRSEC | C8: Conventional | D8: Equity | E8: Capital Growth | F8: 5 | G8: Incidental | H8: 653.11 | I8: 21.03.2006 | J8: Qualified | K8: 100 | L8: 5/5 | M8: Qualified (WA: +13.81%) — YTD✔ 1Y✔ 3Y✔ 5Y✔ 10Y✔ | N8: 13.81 | O8: 35.22 | P8: 12.52 | Q8: 22.7 | R8: 80.56 | S8: 37.33 | T8: 43.23 | U8: 26.15 | V8: 14.67 | W8: 11.48 | X8: 7.27 | Y8: 2.35 | Z8: 4.92 | AA8: 9.86 | AB8: 7.38 | AC8: 2.48 | AD8: =IF(OR(Q8="",BM8="",BM8=0),"",Q8/BM8) | AE8: =IF(OR(T8="",BM8="",BM8=0),"",T8/BM8) | AF8: =IF(OR(W8="",BM8="",BM8=0),"",W8/BM8) | AG8: =IF(OR(Z8="",BM8="",BM8=0),"",Z8/BM8) | AH8: =IF(OR(AC8="",BM8="",BM8=0),"",AC8/BM8) | AI8: 0.8 | AJ8: 92.4 | AL8: 6.8 | AP8: 36.1 | AQ8: 32.8 | AR8: 8.5 | AU8: 8.6 | AV8: 3 | BA8: 20.9 | BB8: 51.1 | BC8: 7.7 | BD8: 13.5 | BL8: Samsung Electronics Company Limited | Taiwan Semiconductor Manufacturing Company Limited | SK Hynix Incorporated | WinWay Technology Company Limited | HD Hyundai Electric Company Limited | BM8: 18.6 | BN8: Very High | BO8: Equity Asia Pacific Asia | BQ8: 0.4827 | BR8: 2026-06-04 | BS8: 0.4734 | BT8: -1.93 | BU8: 11
A9: PUBLIC ASIA ITTIKAL FUND | B9: PAIF | C9: Shariah | D9: Equity | E9: Capital Growth | F9: 5 | G9: Incidental | H9: 5815.79 | I9: 22.08.2006 | J9: Qualified | K9: 100 | L9: 5/5 | M9: Qualified (WA: +13.70%) — YTD✔ 1Y✔ 3Y✔ 5Y✔ 10Y✔ | N9: 13.7 | O9: 42.6 | P9: 23.97 | Q9: 18.63 | R9: 101.66 | S9: 53.9 | T9: 47.76 | U9: 27.66 | V9: 17.23 | W9: 10.43 | X9: 7.64 | Y9: 3.7 | Z9: 3.94 | AA9: 11.37 | AB9: 8.42 | AC9: 2.95 | AD9: =IF(OR(Q9="",BM9="",BM9=0),"",Q9/BM9) | AE9: =IF(OR(T9="",BM9="",BM9=0),"",T9/BM9) | AF9: =IF(OR(W9="",BM9="",BM9=0),"",W9/BM9) | AG9: =IF(OR(Z9="",BM9="",BM9=0),"",Z9/BM9) | AH9: =IF(OR(AC9="",BM9="",BM9=0),"",AC9/BM9) | AJ9: 94.5 | AL9: 5.5 | AO9: 3.7 | AP9: 36.5 | AQ9: 37.6 | AR9: 10.7 | AU9: 6 | BA9: 30.6 | BB9: 50.9 | BD9: 13 | BL9: SK Hynix Incorporated | Samsung Electronics Company Limited | Taiwan Semiconductor Manufacturing Company Limited | Delta Electronics Incorporated | HD Hyundai Electric Company Limited | BM9: 21.6 | BN9: Very High | BO9: Equity Asia Pacific Asia | BP9: ThebenchmarkforPAIFisacompositeof30%KualaLumpurSyariahIndex(prior to 1 November 2007), 30% FTSE Bursa Malaysia EMAS Shariah Index (1 November 2007 to 29 April 2011), 30% FTSE Bursa Malaysia Hijrah Shariah Index (30April2011to29April2013),15%FTSEBursaMalaysiaHijrahShariahIndex (w.e.f. 30 April 2013), 15% customised indexbyS&P Dow Jones Indices, LLC based on top 20 constituents bymarket capitalisation of the S&P BMIShariah JapanIndex(w.e.f.30April2013)and70%DowJonesIslamicMarketAsiaEx- JapanIndexSM(priorto1January2009),70%S&PShariahBMIAsiaEx-Japan Index (w.e.f. 1 January 2009). UnderlyingindexdataaresourcedfromS&PDowJonesIndices,LLCandLipper and expressed in Ringgit terms. | BQ9: 0.865 | BR9: 2026-06-04 | BS9: 0.8362 | BT9: -3.33 | BU9: 11
A10: PUBLIC ISLAMIC GLOBAL SUSTAINABLE GROWTH FUND | B10: PISGSGF | C10: Shariah | D10: Equity | E10: Capital Growth | F10: 5 | G10: Incidental | H10: 761.58 | I10: 20.02.2024 | J10: Qualified | K10: 100 | L10: 2/2 | M10: Qualified (WA: +12.62%) — YTD✔ 1Y✔ | N10: 12.62 | O10: 7.02 | P10: 3.84 | Q10: 3.18 | R10: 38.2 | S10: 22.43 | T10: 15.77 | AD10: =IF(OR(Q10="",BM10="",BM10=0),"",Q10/BM10) | AE10: =IF(OR(T10="",BM10="",BM10=0),"",T10/BM10) | AF10: =IF(OR(W10="",BM10="",BM10=0),"",W10/BM10) | AG10: =IF(OR(Z10="",BM10="",BM10=0),"",Z10/BM10) | AH10: =IF(OR(AC10="",BM10="",BM10=0),"",AC10/BM10) | AI10: 3.3 | AJ10: 87.4 | AL10: 9.3 | AO10: 63.5 | AP10: 10.1 | AQ10: 2.6 | AU10: 3.9 | AW10: 6.4 | BB10: 53.4 | BC10: 4.6 | BD10: 25.8 | BE10: 5.4 | BF10: 1.5 | BL10: Alphabet Incorporated - Class A | Taiwan Semiconductor Manufacturing Company Limited | Apple Incorporated | Broadcom Incorporated | Microsoft Corporation | BP10: The benchmark for PISGSGF is a composite of 90% S&P Global 1200 ESG Shariah Index and 10% 3-Month Islamic Interbank Money Market (IIMM) rate. UnderlyingindexdataaresourcedfromS&PDowJonesIndices,LLCandBank Negara Malaysia and expressed in Ringgit terms. | BQ10: 0.3597 | BR10: 2026-06-03 | BS10: 0.346 | BT10: -3.81 | BU10: 12
A11: PB GREATER CHINA A-SHARES FUND | B11: PBGCASF | C11: Conventional | D11: Equity | E11: Capital Growth | F11: 5 | G11: Incidental | H11: 520.93 | I11: 10.03.2020 | J11: Qualified | K11: 100 | L11: 4/4 | M11: Qualified (WA: +11.01%) — YTD✔ 1Y✔ 3Y✔ 5Y✔ | N11: 11.01 | O11: 7.6 | P11: 4.56 | Q11: 3.04 | R11: 59.99 | S11: 19.36 | T11: 40.63 | U11: 15.56 | V11: 8.83 | W11: 6.73 | X11: 2.16 | Y11: 0.49 | Z11: 1.67 | AD11: =IF(OR(Q11="",BM11="",BM11=0),"",Q11/BM11) | AE11: =IF(OR(T11="",BM11="",BM11=0),"",T11/BM11) | AF11: =IF(OR(W11="",BM11="",BM11=0),"",W11/BM11) | AG11: =IF(OR(Z11="",BM11="",BM11=0),"",Z11/BM11) | AH11: =IF(OR(AC11="",BM11="",BM11=0),"",AC11/BM11) | AJ11: 92.6 | AL11: 7.4 | AO11: 2.6 | AP11: 26.2 | AU11: 63.8 | BA11: 8.2 | BB11: 45.6 | BD11: 17.9 | BE11: 8.8 | BI11: 4.5 | BL11: Taiwan Semiconductor Manufacturing Company Limited | Zhongji Innolight Company Limited - A Shares (HKS) | Hygon Information Technology Company Limited - A Shares (HKS) | Cambricon Technologies Corporation Limited - A Shares (HKS) | Alchip Technologies Limited | BM11: 20 | BN11: Very High | BO11: Equity Greater China Greater China | BP11: ThebenchmarkforPBGCASFisacompositeof50%S&PChinaA50Index,25% Hang Seng China Enterprises Index(HSCEI), 15% S&P Taiwan LargeCap Index and 10% 3-Month Kuala Lumpur Interbank Offered Rate (KLIBOR). UnderlyingindexdataaresourcedfromLipper,S&PDowJonesIndices,LLCand Bank Negara Malaysia and expressed in Ringgit terms. | BQ11: 0.4192 | BR11: 2026-06-03 | BS11: 0.4015 | BT11: -4.22 | BU11: 12
A12: PUBLIC ISLAMIC SELECT TREASURES FUND | B12: PISTF | C12: Shariah | D12: Equity | E12: Capital Growth | F12: 5 | G12: Incidental | H12: 1363.56 | I12: 26.02.2008 | J12: Qualified | K12: 100 | L12: 5/5 | M12: Qualified (WA: +10.99%) — YTD✔ 1Y✔ 3Y✔ 5Y✔ 10Y✔ | N12: 10.99 | O12: 14.88 | P12: 3.4 | Q12: 11.48 | R12: 32.33 | S12: 7.08 | T12: 25.25 | U12: 12.9 | V12: 2.71 | W12: 10.19 | X12: 4.49 | Y12: -2.5 | Z12: 6.99 | AA12: 6.45 | AB12: 1.07 | AC12: 5.38 | AD12: =IF(OR(Q12="",BM12="",BM12=0),"",Q12/BM12) | AE12: =IF(OR(T12="",BM12="",BM12=0),"",T12/BM12) | AF12: =IF(OR(W12="",BM12="",BM12=0),"",W12/BM12) | AG12: =IF(OR(Z12="",BM12="",BM12=0),"",Z12/BM12) | AH12: =IF(OR(AC12="",BM12="",BM12=0),"",AC12/BM12) | AI12: 75.2 | AJ12: 20.4 | AL12: 4.4 | AO12: 5.4 | AP12: 9.2 | AQ12: 2.6 | AR12: 3.2 | BA12: 40 | BB12: 6.7 | BC12: 15.6 | BD12: 7.8 | BF12: 20.7 | BL12: KPJ Healthcare Berhad | TIME dotCom Berhad | Frontken Corporation Berhad | Vitrox Corporation Berhad | Kelington Group Berhad | BM12: 9.2 | BN12: Moderate | BO12: Equity Malaysia Domestic | BQ12: 0.5474 | BR12: 2026-05-29 | BS12: 0.5439 | BT12: -0.64 | BU12: 17
A13: PB GLOBAL TECHNOLOGY & HEALTHCARE FUND | B13: PBGTHF | C13: Conventional | D13: Equity | E13: Capital Growth | F13: 5 | G13: Incidental | H13: 482.66 | I13: 09.05.2019 | J13: Qualified | K13: 100 | L13: 4/4 | M13: Qualified (WA: +9.74%) — YTD✔ 1Y✔ 3Y✔ 5Y✔ | N13: 9.74 | O13: 11.48 | P13: 1.58 | Q13: 9.9 | R13: 40.43 | S13: 19.19 | T13: 21.24 | U13: 24.21 | V13: 13.49 | W13: 10.72 | X13: 11.93 | Y13: 10.68 | Z13: 1.25 | AD13: =IF(OR(Q13="",BM13="",BM13=0),"",Q13/BM13) | AE13: =IF(OR(T13="",BM13="",BM13=0),"",T13/BM13) | AF13: =IF(OR(W13="",BM13="",BM13=0),"",W13/BM13) | AG13: =IF(OR(Z13="",BM13="",BM13=0),"",Z13/BM13) | AH13: =IF(OR(AC13="",BM13="",BM13=0),"",AC13/BM13) | AJ13: 93.4 | AL13: 6.6 | AO13: 49.4 | AP13: 17.2 | AQ13: 15.8 | AU13: 4.6 | AW13: 4.6 | BA13: 12.4 | BB13: 54.7 | BD13: 15.5 | BE13: 1.9 | BK13: 8.9 | BL13: Advanced Micro Devices Incorporated | Apple Incorporated | Taiwan Semiconductor Manufacturing Company Limited | HD Hyundai Electric Company Limited | Microsoft Corporation | BM13: 16.1 | BN13: Very High | BO13: Equity Global Global | BP13: ThebenchmarkforPBGTHFisacompositeof50%S&PGlobal1200Information Technology Index, 40% S&P Global 1200 Health Care Index and 10% 1-Month Kuala Lumpur Interbank Offered Rate (KLIBOR). Underlying index data are sourced from Lipper and Bank Negara Malaysia and expressed in Ringgit terms. | BQ13: 0.7637 | BR13: 2026-06-04 | BS13: 0.7398 | BT13: -3.13 | BU13: 11
A14: PUBLIC ISLAMIC OPTIMAL EQUITY FUND | B14: PIOEF | C14: Shariah | D14: Equity | E14: Capital Growth | F14: 5 | G14: Incidental | H14: 57.96 | I14: 26.07.2016 | J14: Qualified | K14: 75 | L14: 3/4 | M14: Qualified (WA: +9.36%) — YTD✔ 1Y✔ 3Y✔ 5Y✘ | N14: 9.36 | O14: 37.02 | P14: 17.86 | Q14: 19.16 | R14: 68.53 | S14: 39.51 | T14: 29.02 | U14: 21.55 | V14: 14.42 | W14: 7.13 | X14: 2.12 | Y14: 2.95 | Z14: -0.83 | AD14: =IF(OR(Q14="",BM14="",BM14=0),"",Q14/BM14) | AE14: =IF(OR(T14="",BM14="",BM14=0),"",T14/BM14) | AF14: =IF(OR(W14="",BM14="",BM14=0),"",W14/BM14) | AG14: =IF(OR(Z14="",BM14="",BM14=0),"",Z14/BM14) | AH14: =IF(OR(AC14="",BM14="",BM14=0),"",AC14/BM14) | AJ14: 85.9 | AL14: 14.1 | AO14: 7.9 | AP14: 49.4 | AQ14: 17 | AU14: 11.6 | BA14: 27.8 | BB14: 43.6 | BD14: 6.8 | BE14: 7.7 | BL14: Unimicron Technology Corporation | Taiwan Semiconductor Manufacturing Company Limited | Alibaba Group Holding Limited - W | Alchip Technologies Limited | HD Hyundai Electric Company Limited | BM14: 18 | BN14: Very High | BO14: Equity Asia Pacific Asia | BQ14: 0.5798 | BR14: 2026-06-04 | BS14: 0.5596 | BT14: -3.48 | BU14: 11
A15: PB ISLAMIC ASIA STRATEGIC SECTOR FUND | B15: PBIASSF | C15: Conventional | D15: Equity | E15: Capital Growth | F15: 5 | G15: Incidental | H15: 135.58 | I15: 06.09.2007 | J15: Qualified | K15: 100 | L15: 5/5 | M15: Qualified (WA: +9.28%) — YTD✔ 1Y✔ 3Y✔ 5Y✔ 10Y✔ | N15: 9.28 | O15: 43.35 | P15: 27.13 | Q15: 16.22 | R15: 96.3 | S15: 61.51 | T15: 34.79 | U15: 25.05 | V15: 18.79 | W15: 6.26 | X15: 5.87 | Y15: 4.1 | Z15: 1.77 | AA15: 11.36 | AB15: 9.33 | AC15: 2.03 | AD15: =IF(OR(Q15="",BM15="",BM15=0),"",Q15/BM15) | AE15: =IF(OR(T15="",BM15="",BM15=0),"",T15/BM15) | AF15: =IF(OR(W15="",BM15="",BM15=0),"",W15/BM15) | AG15: =IF(OR(Z15="",BM15="",BM15=0),"",Z15/BM15) | AH15: =IF(OR(AC15="",BM15="",BM15=0),"",AC15/BM15) | AJ15: 84.8 | AL15: 15.2 | AP15: 46.8 | AQ15: 26.7 | AR15: 2 | AU15: 9.3 | BA15: 29.6 | BB15: 42.3 | BD15: 12.9 | BL15: Delta Electronics Incorporated | SK Hynix Incorporated | Samsung Electronics Company Limited | Taiwan Semiconductor Manufacturing Company Limited | HD Hyundai Electric Company Limited | BM15: 20.8 | BN15: Very High | BO15: Equity Asia Pacific Asia | BP15: ThebenchmarkforPBIASSFisacompositeof90%DowJonesIslamicMarketAsia Ex-JapanIndexSM(priorto1January2009),90%S&PShariahBMIAsiaEx-Japan Index (w.e.f. 1 January 2009) and 10% 3-Month Islamic Interbank MoneyMarket (IIMM) rate. Underlying indexdata are sourced from S&P Dow Jones Indices, LLC and Bank Negara Malaysia and expressed in Ringgit terms. | BQ15: 0.7042 | BR15: 2026-06-04 | BS15: 0.6803 | BT15: -3.39 | BU15: 11
A16: PUBLIC e-ASIA EVOLVING GROWTH FUND | B16: PeAEVGF | C16: Conventional | D16: Equity | E16: Capital Growth | F16: 5 | G16: Incidental | H16: 782.73 | I16: 30.11.2021 | J16: Qualified | K16: 100 | L16: 3/3 | M16: Qualified (WA: +7.87%) — YTD✔ 1Y✔ 3Y✔ | N16: 7.87 | O16: 24.13 | P16: 13.7 | Q16: 10.43 | R16: 60.52 | S16: 42.63 | T16: 17.89 | U16: 22.21 | V16: 18.42 | W16: 3.79 | AD16: =IF(OR(Q16="",BM16="",BM16=0),"",Q16/BM16) | AE16: =IF(OR(T16="",BM16="",BM16=0),"",T16/BM16) | AF16: =IF(OR(W16="",BM16="",BM16=0),"",W16/BM16) | AG16: =IF(OR(Z16="",BM16="",BM16=0),"",Z16/BM16) | AH16: =IF(OR(AC16="",BM16="",BM16=0),"",AC16/BM16) | AI16: 1 | AJ16: 95.6 | AL16: 3.4 | AO16: 16.5 | AP16: 24.9 | AQ16: 23.5 | AT16: 1.3 | AU16: 29.4 | BA16: 18 | BB16: 43.2 | BC16: 1 | BD16: 31.7 | BE16: 2.7 | BL16: Taiwan Semiconductor Manufacturing Company Limited | SK Hynix Incorporated | Unimicron Technology Corporation | Tencent Holdings Limited | Alibaba Group Holding Limited - W | BM16: 19.7 | BN16: Very High | BO16: Equity Asia Pacific ex- Asia | BP16: ThebenchmarkforPeAEVGFisacompositeof90%customisedindexbyS&PDow JonesIndices,LLCbasedonthetop30constituentsoftheS&PBMIAsiaEx-Japan Index and 10% 3-Month Kuala Lumpur Interbank Offered Rate (KLIBOR). Underlying indexdata are sourced from S&P Dow Jones Indices, LLC and Bank Negara Malaysia and expressed in Ringgit terms. | BQ16: 0.4341 | BR16: 2026-06-04 | BS16: 0.422 | BT16: -2.79 | BU16: 11
A17: PUBLIC SMALLCAP FUND | B17: P SmallCap | C17: Conventional | D17: Equity | E17: Capital Growth | F17: 5 | G17: Incidental | H17: 1424.31 | I17: 13.06.2000 | J17: Qualified | K17: 100 | L17: 5/5 | M17: Qualified (WA: +7.86%) — YTD✔ 1Y✔ 3Y✔ 5Y✔ 10Y✔ | N17: 7.86 | O17: 3.42 | P17: -1.01 | Q17: 4.43 | R17: 18.7 | S17: 1.82 | T17: 16.88 | U17: 7.48 | V17: 0.25 | W17: 7.23 | X17: 3.79 | Y17: -1.91 | Z17: 5.7 | AA17: 5.41 | AB17: 0.12 | AC17: 5.29 | AD17: =IF(OR(Q17="",BM17="",BM17=0),"",Q17/BM17) | AE17: =IF(OR(T17="",BM17="",BM17=0),"",T17/BM17) | AF17: =IF(OR(W17="",BM17="",BM17=0),"",W17/BM17) | AG17: =IF(OR(Z17="",BM17="",BM17=0),"",Z17/BM17) | AH17: =IF(OR(AC17="",BM17="",BM17=0),"",AC17/BM17) | AI17: 76 | AJ17: 17.6 | AL17: 6.4 | AO17: 14.1 | AR17: 3.5 | BA17: 23 | BC17: 33.7 | BD17: 20.9 | BF17: 7.2 | BK17: 6.6 | BL17: TIME dotCom Berhad | IGB Real Estate Investment Trust | Malaysian Pacific Industries Berhad | Alphabet Incorporated - Class A | Hong Leong Industries Berhad | BM17: 8.9 | BN17: Moderate | BO17: Equity Malaysia Domestic 30% of the fund’s NAV | BQ17: 1.1808 | BR17: 2026-05-14 | BS17: 1.1432 | BT17: -3.18 | BU17: 32
A18: PUBLIC STRATEGIC SMALLCAP FUND | B18: PSSCF | C18: Conventional | D18: Equity | E18: Capital Growth | F18: 5 | G18: Incidental | H18: 448.96 | I18: 20.03.2012 | J18: Qualified | K18: 100 | L18: 5/5 | M18: Qualified (WA: +7.54%) — YTD✔ 1Y✔ 3Y✔ 5Y✔ 10Y✔ | N18: 7.54 | O18: 1.35 | P18: -1.01 | Q18: 2.36 | R18: 19.52 | S18: 1.82 | T18: 17.7 | U18: 7.99 | V18: 0.25 | W18: 7.74 | X18: 2.44 | Y18: -1.91 | Z18: 4.35 | AA18: 4.04 | AB18: 0.12 | AC18: 3.92 | AD18: =IF(OR(Q18="",BM18="",BM18=0),"",Q18/BM18) | AE18: =IF(OR(T18="",BM18="",BM18=0),"",T18/BM18) | AF18: =IF(OR(W18="",BM18="",BM18=0),"",W18/BM18) | AG18: =IF(OR(Z18="",BM18="",BM18=0),"",Z18/BM18) | AH18: =IF(OR(AC18="",BM18="",BM18=0),"",AC18/BM18) | AI18: 77.1 | AJ18: 18.9 | AL18: 4 | AO18: 15.3 | AR18: 3.6 | BA18: 40.3 | BC18: 14.2 | BD18: 15.9 | BF18: 13.7 | BK18: 6.3 | BL18: Kelington Group Berhad | Spritzer Berhad | Alphabet Incorporated - Class A | Malaysian Pacific Industries Berhad | SAM Engineering & Equipment (M) Berhad | BM18: 12.8 | BN18: High | BO18: Equity Malaysia Domestic 30% of the fund’s NAV | BP18: Index data are sourced from Lipper. | BQ18: 0.4893 | BR18: 2024-05-23 | BS18: 0.4739 | BT18: -3.15 | BU18: 753
A19: PUBLIC OPTIMAL EQUITY FUND | B19: POEF | C19: Conventional | D19: Equity | E19: Capital Growth | F19: 5 | G19: Incidental | H19: 29.69 | I19: 26.07.2016 | J19: Qualified | K19: 75 | L19: 3/4 | M19: Qualified (WA: +7.35%) — YTD✔ 1Y✔ 3Y✔ 5Y✘ | N19: 7.35 | O19: 26.63 | P19: 8.72 | Q19: 17.91 | R19: 51.86 | S19: 28.07 | T19: 23.79 | U19: 18.48 | V19: 13.36 | W19: 5.12 | X19: 1.78 | Y19: 2.84 | Z19: -1.06 | AD19: =IF(OR(Q19="",BM19="",BM19=0),"",Q19/BM19) | AE19: =IF(OR(T19="",BM19="",BM19=0),"",T19/BM19) | AF19: =IF(OR(W19="",BM19="",BM19=0),"",W19/BM19) | AG19: =IF(OR(Z19="",BM19="",BM19=0),"",Z19/BM19) | AH19: =IF(OR(AC19="",BM19="",BM19=0),"",AC19/BM19) | AJ19: 94.7 | AL19: 5.3 | AO19: 8.3 | AP19: 44.8 | AQ19: 26.7 | AU19: 14.9 | BA19: 23 | BB19: 50.5 | BD19: 19.1 | BE19: 2.1 | BL19: SK Hynix Incorporated | Samsung Electronics Company Limited | Taiwan Semiconductor Manufacturing Company Limited | Tencent Holdings Limited | Advanced Micro Devices Incorporated | BM19: 19.3 | BN19: Very High | BO19: Equity Asia Pacific Asia | BQ19: 0.4587 | BR19: 2026-06-04 | BS19: 0.4367 | BT19: -4.8 | BU19: 11
A20: PUBLIC ISLAMIC EMERGING OPPORTUNITIES FUND | B20: PIEMOF | C20: Shariah | D20: Equity | E20: Capital Growth | F20: 5 | G20: Incidental | H20: 101.17 | I20: 30.03.2016 | J20: Qualified | K20: 100 | L20: 5/5 | M20: Qualified (WA: +6.62%) — YTD✔ 1Y✔ 3Y✔ 5Y✔ 10Y✔ | N20: 6.62 | O20: 8.67 | P20: 3.19 | Q20: 5.48 | R20: 20.26 | S20: 6.76 | T20: 13.5 | U20: 9.37 | V20: 2.88 | W20: 6.49 | X20: 2.56 | Y20: -1.86 | Z20: 4.42 | AA20: 5.54 | AB20: 1.39 | AC20: 4.15 | AD20: =IF(OR(Q20="",BM20="",BM20=0),"",Q20/BM20) | AE20: =IF(OR(T20="",BM20="",BM20=0),"",T20/BM20) | AF20: =IF(OR(W20="",BM20="",BM20=0),"",W20/BM20) | AG20: =IF(OR(Z20="",BM20="",BM20=0),"",Z20/BM20) | AH20: =IF(OR(AC20="",BM20="",BM20=0),"",AC20/BM20) | AI20: 74.2 | AJ20: 21.6 | AL20: 4.2 | AO20: 7.9 | AP20: 6.1 | AQ20: 3.1 | AR20: 4.5 | BA20: 34.6 | BC20: 13.9 | BF20: 21.5 | BH20: 8.7 | BK20: 5.1 | BL20: Gas Malaysia Berhad | Spritzer Berhad | Vitrox Corporation Berhad | Kinik Company | KPJ Healthcare Berhad | BM20: 10 | BN20: Moderate | BO20: Equity Malaysia Domestic | BQ20: 0.4221 | BR20: 2026-05-29 | BS20: 0.4192 | BT20: -0.69 | BU20: 17
A21: PUBLIC ITTIKAL SEQUEL FUND | B21: PITSEQ | C21: Shariah | D21: Equity | E21: Capital Growth | F21: 4 | G21: Incidental | H21: 4541.6 | I21: 11.10.2011 | J21: Qualified | K21: 80 | L21: 4/5 | M21: Qualified (WA: +6.16%) — YTD✘ 1Y✔ 3Y✔ 5Y✔ 10Y✔ | N21: 6.16 | O21: 4.24 | P21: 5.14 | Q21: -0.9 | R21: 15.15 | S21: 12.81 | T21: 2.34 | U21: 13.88 | V21: 5.79 | W21: 8.09 | X21: 6.25 | Y21: -0.85 | Z21: 7.1 | AA21: 6.01 | AB21: 0.41 | AC21: 5.6 | AD21: =IF(OR(Q21="",BM21="",BM21=0),"",Q21/BM21) | AE21: =IF(OR(T21="",BM21="",BM21=0),"",T21/BM21) | AF21: =IF(OR(W21="",BM21="",BM21=0),"",W21/BM21) | AG21: =IF(OR(Z21="",BM21="",BM21=0),"",Z21/BM21) | AH21: =IF(OR(AC21="",BM21="",BM21=0),"",AC21/BM21) | AI21: 73.4 | AJ21: 22.7 | AL21: 3.9 | AO21: 18.2 | AP21: 4.5 | BB21: 13.7 | BC21: 15.4 | BD21: 19.7 | BF21: 16.6 | BG21: 9.1 | BL21: Tenaga Nasional Berhad | Telekom Malaysia Berhad | Sunway Berhad | Gamuda Berhad | Press Metal Aluminium Holdings Berhad | BM21: 7.5 | BN21: Low | BO21: Equity Malaysia Domestic | BP21: Index data are sourced from Lipper. 2022 1.00 30.11.22 3.4 Note: Distribution yield simply measures the level of distributions and is not a measure of fund performance. | BQ21: 0.4597 | BR21: 2026-05-12 | BS21: 0.4541 | BT21: -1.22 | BU21: 34
A22: PUBLIC ISLAMIC ASIA DIVIDEND FUND | B22: PIADF | C22: Shariah | D22: Equity | E22: Income | F22: 5 | G22: Annual | H22: 1765.59 | I22: 03.04.2007 | J22: Qualified | K22: 100 | L22: 5/5 | M22: Qualified (WA: +5.90%) — YTD✔ 1Y✔ 3Y✔ 5Y✔ 10Y✔ | N22: 5.9 | O22: 31.7 | P22: 22.05 | Q22: 9.65 | R22: 62.66 | S22: 49.56 | T22: 13.1 | U22: 22.95 | V22: 16.19 | W22: 6.76 | X22: 5.19 | Y22: 3.53 | Z22: 1.66 | AA22: 9.75 | AB22: 7.54 | AC22: 2.21 | AD22: =IF(OR(Q22="",BM22="",BM22=0),"",Q22/BM22) | AE22: =IF(OR(T22="",BM22="",BM22=0),"",T22/BM22) | AF22: =IF(OR(W22="",BM22="",BM22=0),"",W22/BM22) | AG22: =IF(OR(Z22="",BM22="",BM22=0),"",Z22/BM22) | AH22: =IF(OR(AC22="",BM22="",BM22=0),"",AC22/BM22) | AI22: 1.7 | AJ22: 90.9 | AL22: 7.4 | AO22: 5.6 | AP22: 31.1 | AQ22: 34 | AU22: 13 | AY22: 3.5 | BA22: 29.7 | BB22: 30.1 | BD22: 25.9 | BE22: 3.3 | BI22: 2.2 | BL22: Samsung Electronics Company Limited | SK Hynix Incorporated | Taiwan Semiconductor Manufacturing Company Limited | Hanwha Aerospace Company Limited | Elite Material Company Limited | BM22: 16.1 | BN22: Very High | BO22: Equity Asia Pacific Asia | BQ22: 0.6678 | BR22: 2026-06-04 | BS22: 0.6493 | BT22: -2.77 | BU22: 11
A23: PUBLIC GREATER CHINA FUND | B23: PGCF | C23: Conventional | D23: Equity | E23: Capital Growth | F23: 5 | G23: Incidental | H23: 384.55 | I23: 26.10.2017 | J23: Qualified | K23: 100 | L23: 4/4 | M23: Qualified (WA: +5.90%) — YTD✔ 1Y✔ 3Y✔ 5Y✔ | N23: 5.9 | O23: 14.71 | P23: 7.04 | Q23: 7.67 | R23: 37.36 | S23: 26.81 | T23: 10.55 | U23: 18.18 | V23: 12.44 | W23: 5.74 | X23: 2.84 | Y23: -0.18 | Z23: 3.02 | AD23: =IF(OR(Q23="",BM23="",BM23=0),"",Q23/BM23) | AE23: =IF(OR(T23="",BM23="",BM23=0),"",T23/BM23) | AF23: =IF(OR(W23="",BM23="",BM23=0),"",W23/BM23) | AG23: =IF(OR(Z23="",BM23="",BM23=0),"",Z23/BM23) | AH23: =IF(OR(AC23="",BM23="",BM23=0),"",AC23/BM23) | AJ23: 93.5 | AL23: 6.5 | AO23: 13.7 | AP23: 45.7 | AT23: 1.4 | AU23: 1.3 | BA23: 19.7 | BB23: 32.1 | BC23: 3.4 | BD23: 30.2 | BE23: 8.1 | BL23: Taiwan Semiconductor Manufacturing Company Limited | Alibaba Group Holding Limited - W | Delta Electronics Incorporated | Tencent Holdings Limited | ASPEED Technology Incorporated | BM23: 15.6 | BN23: Very High | BO23: Greater China | BP23: MSCI Golden Dragon Index (prior to 30 April 2021), S&P Greater China LargeMidCap Index (30 April 2021 to 1 January 2025), S&P Greater China LargeMidCap 8% Capped Index (w.e.f. 2 January 2025). UnderlyingIndexdataaresourcedfromS&PDowJonesIndices,LLCandLipper and expressed in Ringgit terms. | BQ23: 0.4085 | BR23: 2026-06-03 | BS23: 0.3901 | BT23: -4.5 | BU23: 12
A24: PUBLIC ISLAMIC SAVINGS FUND | B24: PISVF | C24: Shariah | D24: Equity | E24: Income | F24: 4 | G24: Semi-Annual | H24: 510.62 | I24: 15.12.2011 | J24: Qualified | K24: 100 | L24: 5/5 | M24: Qualified (WA: +5.89%) — YTD✔ 1Y✔ 3Y✔ 5Y✔ 10Y✔ | N24: 5.89 | O24: 7.69 | P24: 4.74 | Q24: 2.95 | R24: 25.36 | S24: 11.86 | T24: 13.5 | U24: 10.99 | V24: 5.62 | W24: 5.37 | X24: 3.14 | Y24: -0.4 | Z24: 3.54 | AA24: 5.3 | AB24: 0.75 | AC24: 4.55 | AD24: =IF(OR(Q24="",BM24="",BM24=0),"",Q24/BM24) | AE24: =IF(OR(T24="",BM24="",BM24=0),"",T24/BM24) | AF24: =IF(OR(W24="",BM24="",BM24=0),"",W24/BM24) | AG24: =IF(OR(Z24="",BM24="",BM24=0),"",Z24/BM24) | AH24: =IF(OR(AC24="",BM24="",BM24=0),"",AC24/BM24) | AI24: 75.7 | AJ24: 21.6 | AL24: 2.7 | AO24: 10.6 | AP24: 3.8 | AQ24: 7.2 | BA24: 26.1 | BB24: 12.1 | BC24: 12.1 | BD24: 13.1 | BF24: 10.1 | BL24: Press Metal Aluminium Holdings Berhad | Tenaga Nasional Berhad | HD Hyundai Electric Company Limited | Telekom Malaysia Berhad | IHH Healthcare Berhad | BM24: 9.5 | BN24: Moderate | BO24: Equity Malaysia Domestic | BQ24: 0.4381 | BR24: 2026-05-14 | BS24: 0.4286 | BT24: -2.17 | BU24: 32
A25: PB CHINA PACIFIC EQUITY FUND | B25: PBCPEF | C25: Conventional | D25: Equity | E25: Capital Growth | F25: 5 | G25: Incidental | H25: 229.83 | I25: 23.10.2007 | J25: Qualified | K25: 100 | L25: 5/5 | M25: Qualified (WA: +5.76%) — YTD✔ 1Y✔ 3Y✔ 5Y✔ 10Y✔ | N25: 5.76 | O25: 23.14 | P25: 9.66 | Q25: 13.48 | R25: 44.67 | S25: 32.09 | T25: 12.58 | U25: 17.11 | V25: 11.4 | W25: 5.71 | X25: 1.25 | Y25: -1.3 | Z25: 2.55 | AA25: 8.66 | AB25: 6.82 | AC25: 1.84 | AD25: =IF(OR(Q25="",BM25="",BM25=0),"",Q25/BM25) | AE25: =IF(OR(T25="",BM25="",BM25=0),"",T25/BM25) | AF25: =IF(OR(W25="",BM25="",BM25=0),"",W25/BM25) | AG25: =IF(OR(Z25="",BM25="",BM25=0),"",Z25/BM25) | AH25: =IF(OR(AC25="",BM25="",BM25=0),"",AC25/BM25) | AJ25: 95 | AL25: 5 | AO25: 4.8 | AP25: 47.3 | AQ25: 28.4 | AR25: 0.4 | AU25: 14.1 | BA25: 26.5 | BB25: 50 | BD25: 18 | BE25: 0.5 | BL25: SK Hynix Incorporated | Taiwan Semiconductor Manufacturing Company Limited | Samsung Electronics Company Limited | Tencent Holdings Limited | Delta Electronics Incorporated | BM25: 19.3 | BN25: Very High | BO25: Equity Asia Pacific Greater China | BP25: ThebenchmarkforPBCPEFisacompositeof70%HangSengChinaEnterprises Index (HSCEI) and 30% Hang Seng Index (HSI) (prior to 1 January 2009). MSCI Zhong Hua Index (1 January 2009 to 29 April 2015). 80%MSCIZhongHuaIndex(30April2015to29April2021),80%S&PChina& HongKongLargeMidCapIndex(30April 2021to28December2025),60%S&P China&HongKongLargeMidCapIndex(w.e.f.29December2025),10%KOSPI50 Index (30 April 2015 to 29 April 2016), 10% MSCI Korea Large Cap Index (30April2016to29April2021),10%S&PKoreaLargeCapIndex(30April2021to 28December2025),15%S&PKoreaLargeCapIndex(w.e.f.29December2025), 10% FTSE TWSE Taiwan50 Index(30 April 2015 to29 April 2016), 10% MSCI Taiwan Large Cap Index (30 April 2016 to 29 April 2021), 10% S&P Taiwan LargeCapIndex(30April2021to28December2025),15%S&PTaiwanLargeCap Index(w.e.f.29December2025)and10%3-MonthKualaLumpurInterbankOffered Rate (KLIBOR) (w.e.f. 29 December 2025). UnderlyingindexdataaresourcedfromS&PDowJonesIndices,LLC,Lipperand Bank Negara Malaysia and expressed in Ringgit terms. | BQ25: 0.5509 | BR25: 2026-06-04 | BS25: 0.5278 | BT25: -4.19 | BU25: 11
A26: PB SMALLCAP GROWTH FUND | B26: PBSCGF | C26: Conventional | D26: Equity | E26: Capital Growth | F26: 5 | G26: Incidental | H26: 123.09 | I26: 13.01.2016 | J26: Qualified | K26: 80 | L26: 4/5 | M26: Qualified (WA: +5.70%) — YTD✘ 1Y✔ 3Y✔ 5Y✔ 10Y✔ | N26: 5.7 | O26: -1.39 | P26: -0.78 | Q26: -0.61 | R26: 19.08 | S26: 2.02 | T26: 17.06 | U26: 5.06 | V26: 0.65 | W26: 4.41 | X26: 2.09 | Y26: -1.34 | Z26: 3.43 | AA26: 4.2 | AB26: 0.54 | AC26: 3.66 | AD26: =IF(OR(Q26="",BM26="",BM26=0),"",Q26/BM26) | AE26: =IF(OR(T26="",BM26="",BM26=0),"",T26/BM26) | AF26: =IF(OR(W26="",BM26="",BM26=0),"",W26/BM26) | AG26: =IF(OR(Z26="",BM26="",BM26=0),"",Z26/BM26) | AH26: =IF(OR(AC26="",BM26="",BM26=0),"",AC26/BM26) | AI26: 77.2 | AJ26: 17.2 | AL26: 5.6 | AO26: 12.6 | AR26: 4.6 | BA26: 44 | BC26: 7.4 | BD26: 9.2 | BF26: 23.5 | BK26: 7.6 | BL26: Spritzer Berhad | Malaysian Pacific Industries Berhad | UWC Berhad | MN Holdings Berhad | Southern Cable Group Berhad | BM26: 12.9 | BN26: High | BO26: Equity Malaysia Small & | BQ26: 0.3595 | BR26: 2024-06-14 | BS26: 0.3516 | BT26: -2.2 | BU26: 731
A27: PB ISLAMIC ASIA EQUITY FUND | B27: PBIAEF | C27: Conventional | D27: Equity | E27: Capital Growth | F27: 5 | G27: Incidental | H27: 139.65 | I27: 08.01.2007 | J27: Qualified | K27: 100 | L27: 5/5 | M27: Qualified (WA: +5.49%) — YTD✔ 1Y✔ 3Y✔ 5Y✔ 10Y✔ | N27: 5.49 | O27: 29.83 | P27: 25.06 | Q27: 4.77 | R27: 79.45 | S27: 56.89 | T27: 22.56 | U27: 22.33 | V27: 17.8 | W27: 4.53 | X27: 3.7 | Y27: 3.47 | Z27: 0.23 | AA27: 8.1 | AB27: 8.09 | AC27: 0.01 | AD27: =IF(OR(Q27="",BM27="",BM27=0),"",Q27/BM27) | AE27: =IF(OR(T27="",BM27="",BM27=0),"",T27/BM27) | AF27: =IF(OR(W27="",BM27="",BM27=0),"",W27/BM27) | AG27: =IF(OR(Z27="",BM27="",BM27=0),"",Z27/BM27) | AH27: =IF(OR(AC27="",BM27="",BM27=0),"",AC27/BM27) | AJ27: 83.4 | AL27: 16.6 | AP27: 33.2 | AQ27: 29.8 | AR27: 0.9 | AU27: 17.3 | AZ27: 2.2 | BA27: 15.8 | BB27: 43 | BD27: 24.6 | BL27: SK Hynix Incorporated | Taiwan Semiconductor Manufacturing Company Limited | Alibaba Group Holding Limited - W | Samsung Electronics Company Limited | Tencent Holdings Limited | BM27: 16.3 | BN27: Very High | BO27: Equity Asia Pacific Asia | BP27: The benchmark for PBIAEF is a composite of 20% Kuala Lumpur Syariah Index (prior to 1 November 2007), 20% FTSE Bursa Malaysia EMAS Shariah Index (1 November 2007 to 29 April 2011), 20% FTSE Bursa Malaysia Hijrah Shariah Index (w.e.f. 30 April 2011) and 80% Dow Jones Islamic Market Asia Ex-Japan IndexSM (prior to 1 January 2009), 80% S&P Shariah BMI Asia Ex-Japan Index (w.e.f. 1 January 2009). UnderlyingindexdataaresourcedfromS&PDowJonesIndices,LLCandLipper and expressed in Ringgit terms. | BQ27: 0.4907 | BR27: 2026-06-04 | BS27: 0.4773 | BT27: -2.73 | BU27: 11
A28: PUBLIC ISLAMIC OPPORTUNITIES FUND | B28: PIOF | C28: Shariah | D28: Equity | E28: Capital Growth | F28: 5 | G28: Incidental | H28: 1137.4 | I28: 28.06.2005 | J28: Qualified | K28: 100 | L28: 5/5 | M28: Qualified (WA: +5.43%) — YTD✔ 1Y✔ 3Y✔ 5Y✔ 10Y✔ | N28: 5.43 | O28: 8.56 | P28: -2.13 | Q28: 10.69 | R28: 13.5 | S28: 3 | T28: 10.5 | U28: 5.51 | V28: 0.98 | W28: 4.53 | X28: 0.43 | Y28: -1.87 | Z28: 2.3 | AA28: 6.28 | AB28: 0.04 | AC28: 6.24 | AD28: =IF(OR(Q28="",BM28="",BM28=0),"",Q28/BM28) | AE28: =IF(OR(T28="",BM28="",BM28=0),"",T28/BM28) | AF28: =IF(OR(W28="",BM28="",BM28=0),"",W28/BM28) | AG28: =IF(OR(Z28="",BM28="",BM28=0),"",Z28/BM28) | AH28: =IF(OR(AC28="",BM28="",BM28=0),"",AC28/BM28) | AI28: 76.3 | AJ28: 19.4 | AL28: 4.3 | AO28: 5.7 | AP28: 5.7 | AQ28: 8 | BA28: 42.9 | BB28: 16.1 | BC28: 11 | BE28: 6.7 | BF28: 11.2 | BL28: Kelington Group Berhad | Frontken Corporation Berhad | Taiwan Semiconductor Manufacturing Company Limited | UWC Berhad | HD Hyundai Electric Company Limited | BM28: 11.5 | BN28: High | BO28: Equity Malaysia Domestic | BP28: 2023 1.00 31.7.23 1.9 Kuala Lumpur Syariah Index (prior to 1 November 2007). Note: Distribution yield simply measures the level of distributions and is not FTSE Bursa Malaysia EMAS Shariah Index (1 November 2007 to 29 April 2013). a measure of fund performance. FTSE Bursa Malaysia Small Cap Shariah Index (w.e.f. 30 April 2013). Underlying index data are sourced from Lipper. | BQ28: 0.714 | BR28: 2021-11-19 | BS28: 0.6276 | BT28: -12.1 | BU28: 1669
A29: PUBLIC ITTIKAL FUND | B29: P ITTIKAL | C29: Shariah | D29: Equity | E29: Capital Growth | F29: 4 | G29: Incidental | H29: 3992.97 | I29: 10.04.1997 | J29: Qualified | K29: 80 | L29: 4/5 | M29: Qualified (WA: +5.40%) — YTD✘ 1Y✔ 3Y✔ 5Y✔ 10Y✔ | N29: 5.4 | O29: 4.47 | P29: 5.14 | Q29: -0.67 | R29: 21.24 | S29: 12.81 | T29: 8.43 | U29: 11.24 | V29: 5.79 | W29: 5.45 | X29: 4.98 | Y29: -0.85 | Z29: 5.83 | AA29: 3.98 | AB29: 0.41 | AC29: 3.57 | AD29: =IF(OR(Q29="",BM29="",BM29=0),"",Q29/BM29) | AE29: =IF(OR(T29="",BM29="",BM29=0),"",T29/BM29) | AF29: =IF(OR(W29="",BM29="",BM29=0),"",W29/BM29) | AG29: =IF(OR(Z29="",BM29="",BM29=0),"",Z29/BM29) | AH29: =IF(OR(AC29="",BM29="",BM29=0),"",AC29/BM29) | AI29: 74.7 | AJ29: 23.3 | AL29: 2 | AO29: 14.5 | AP29: 8.8 | BB29: 15.3 | BC29: 13.2 | BD29: 19.1 | BF29: 20.5 | BG29: 9.6 | BL29: Tenaga Nasional Berhad | IHH Healthcare Berhad | Telekom Malaysia Berhad | Sunway Berhad | Taiwan Semiconductor Manufacturing Company Limited | BM29: 8.6 | BN29: Moderate | BO29: Equity Malaysia Domestic | BP29: Kuala Lumpur Syariah Index (prior to 1 November 2007). FTSE Bursa Malaysia EMAS Shariah Index (w.e.f. 1 November 2007). | BQ29: 1.31 | BR29: 2000-02-24 | BS29: 1.0312 | BT29: -21.28 | BU29: 9608
A30: PUBLIC EMERGING OPPORTUNITIES FUND | B30: PEMOF | C30: Conventional | D30: Equity | E30: Capital Growth | F30: 5 | G30: Incidental | H30: 148.42 | I30: 30.03.2016 | J30: Qualified | K30: 100 | L30: 5/5 | M30: Qualified (WA: +5.40%) — YTD✔ 1Y✔ 3Y✔ 5Y✔ 10Y✔ | N30: 5.4 | O30: 9 | P30: 4.34 | Q30: 4.66 | R30: 23.41 | S30: 8.88 | T30: 14.53 | U30: 11.14 | V30: 6.55 | W30: 4.59 | X30: 2.76 | Y30: 1.66 | Z30: 1.1 | AA30: 8.36 | AB30: 2.54 | AC30: 5.82 | AD30: =IF(OR(Q30="",BM30="",BM30=0),"",Q30/BM30) | AE30: =IF(OR(T30="",BM30="",BM30=0),"",T30/BM30) | AF30: =IF(OR(W30="",BM30="",BM30=0),"",W30/BM30) | AG30: =IF(OR(Z30="",BM30="",BM30=0),"",Z30/BM30) | AH30: =IF(OR(AC30="",BM30="",BM30=0),"",AC30/BM30) | AI30: 76.1 | AJ30: 21.9 | AL30: 2 | AO30: 4.6 | AP30: 15 | AT30: 2.3 | BA30: 46.2 | BB30: 8 | BC30: 25.5 | BD30: 4.3 | BF30: 8.2 | BL30: Kelington Group Berhad | Hon.Precision Incorporated | Kinik Company | Sunway Real Estate Investment Trust | IGB Real Estate Investment Trust | BM30: 11.6 | BN30: High | BO30: Equity Malaysia Domestic 25% of the fund’s NAV | BP30: ThebenchmarkforPEMOFisacompositeof60%FTSEBursaMalaysiaMid70 Index, 30% FTSE Bursa Malaysia Small Cap Index and 10% 3-Month Kuala Lumpur Interbank Offered Rate (KLIBOR). Underlying index data are sourced from Lipper and Bank Negara Malaysia. | BQ30: 0.609 | BR30: 2026-05-29 | BS30: 0.5943 | BT30: -2.41 | BU30: 17
A31: PUBLIC e-ISLAMIC ASIA THEMATIC GROWTH FUND | B31: PeIATGF | C31: Shariah | D31: Equity | E31: Capital Growth | F31: 5 | G31: Incidental | H31: 538.28 | I31: 30.11.2021 | J31: Qualified | K31: 100 | L31: 3/3 | M31: Qualified (WA: +5.37%) — YTD✔ 1Y✔ 3Y✔ | N31: 5.37 | O31: 42.09 | P31: 32.08 | Q31: 10.01 | R31: 78.32 | S31: 72.28 | T31: 6.04 | U31: 26.7 | V31: 22.16 | W31: 4.54 | AD31: =IF(OR(Q31="",BM31="",BM31=0),"",Q31/BM31) | AE31: =IF(OR(T31="",BM31="",BM31=0),"",T31/BM31) | AF31: =IF(OR(W31="",BM31="",BM31=0),"",W31/BM31) | AG31: =IF(OR(Z31="",BM31="",BM31=0),"",Z31/BM31) | AH31: =IF(OR(AC31="",BM31="",BM31=0),"",AC31/BM31) | AJ31: 92.3 | AL31: 7.7 | AO31: 5.2 | AP31: 50 | AQ31: 27.9 | AU31: 9.2 | BA31: 33.3 | BB31: 45.9 | BD31: 13.1 | BL31: SK Hynix Incorporated | Samsung Electronics Company Limited | Delta Electronics Incorporated | Taiwan Semiconductor Manufacturing Company Limited | Alibaba Group Holding Limited - W | BM31: 19.7 | BN31: Very High | BO31: Equity Asia Pacific ex- Asia | BP31: ThebenchmarkforPeIATGFisacustomisedindexbyS&PDowJonesIndices,LLC basedonthetop100constituentsbymarketcapitalisationoftheS&PShariahBMI Asia Ex-Japan Index. Underlying index data are sourced from S&P Dow Jones Indices, LLC and expressed in Ringgit terms. | BQ31: 0.4862 | BR31: 2026-06-04 | BS31: 0.4636 | BT31: -4.65 | BU31: 11
A32: PB ISLAMIC SMALLCAP FUND | B32: PBISCF | C32: Conventional | D32: Equity | E32: Capital Growth | F32: 5 | G32: Incidental | H32: 114.01 | I32: 28.03.2017 | J32: Qualified | K32: 100 | L32: 4/4 | M32: Qualified (WA: +4.83%) — YTD✔ 1Y✔ 3Y✔ 5Y✔ | N32: 4.83 | O32: 0.8 | P32: -2.13 | Q32: 2.93 | R32: 13.89 | S32: 3 | T32: 10.89 | U32: 4.59 | V32: 0.98 | W32: 3.61 | X32: 1.67 | Y32: -1.87 | Z32: 3.54 | AD32: =IF(OR(Q32="",BM32="",BM32=0),"",Q32/BM32) | AE32: =IF(OR(T32="",BM32="",BM32=0),"",T32/BM32) | AF32: =IF(OR(W32="",BM32="",BM32=0),"",W32/BM32) | AG32: =IF(OR(Z32="",BM32="",BM32=0),"",Z32/BM32) | AH32: =IF(OR(AC32="",BM32="",BM32=0),"",AC32/BM32) | AI32: 75.5 | AJ32: 19.6 | AL32: 4.9 | AO32: 4.8 | AP32: 6.1 | AQ32: 6.3 | AR32: 2.4 | BA32: 54 | BB32: 8.1 | BC32: 6.2 | BF32: 17.3 | BK32: 3.8 | BL32: Kelington Group Berhad | Frontken Corporation Berhad | Spritzer Berhad | HD Hyundai Electric Company Limited | Taiwan Semiconductor Manufacturing Company Limited | BM32: 12.6 | BN32: High | BO32: Equity Malaysia Small & | BP32: Index data are sourced from Lipper. | BQ32: 0.4582 | BR32: 2022-01-04 | BS32: 0.3887 | BT32: -15.17 | BU32: 1623
A33: PUBLIC ISLAMIC TREASURES GROWTH FUND | B33: PITGF | C33: Shariah | D33: Equity | E33: Capital Growth | F33: 5 | G33: Incidental | H33: 278.85 | I33: 19.07.2011 | J33: Qualified | K33: 100 | L33: 5/5 | M33: Qualified (WA: +4.81%) — YTD✔ 1Y✔ 3Y✔ 5Y✔ 10Y✔ | N33: 4.81 | O33: 10.86 | P33: 3.19 | Q33: 7.67 | R33: 18.02 | S33: 6.76 | T33: 11.26 | U33: 7.3 | V33: 2.88 | W33: 4.42 | X33: 0.33 | Y33: -1.86 | Z33: 2.19 | AA33: 4.19 | AB33: 1.39 | AC33: 2.8 | AD33: =IF(OR(Q33="",BM33="",BM33=0),"",Q33/BM33) | AE33: =IF(OR(T33="",BM33="",BM33=0),"",T33/BM33) | AF33: =IF(OR(W33="",BM33="",BM33=0),"",W33/BM33) | AG33: =IF(OR(Z33="",BM33="",BM33=0),"",Z33/BM33) | AH33: =IF(OR(AC33="",BM33="",BM33=0),"",AC33/BM33) | AI33: 76 | AJ33: 18.5 | AL33: 5.5 | AO33: 7.8 | AP33: 6.1 | AR33: 4.6 | BA33: 35.1 | BC33: 11.9 | BD33: 8.3 | BF33: 18.1 | BK33: 7.7 | BL33: Vitrox Corporation Berhad | TIME dotCom Berhad | Malaysian Pacific Industries Berhad | QL Resources Berhad | Bursa Malaysia Berhad | BM33: 10.3 | BN33: High | BO33: Equity Malaysia Domestic | BP33: The benchmark for PITGF is a composite of 90% FTSE Bursa Malaysia EMAS Shariah Index (prior to 30 April 2013), 90% FTSE Bursa Malaysia Small Cap ShariahIndex(FBMSSC)(30April2013to29April2015),90%customisedindex byFTSEbasedontheconstituentswithmarketcapitalisationbelowRM6.0billion withintheFTSE BursaMalaysiaEMAS ShariahIndex(w.e.f. 30April 2015)and 10% 3-Month Islamic Interbank Money Market (IIMM) rate. Underlying index data are sourced from FTSE International Limited, Lipper and Bank Negara Malaysia. | BQ33: 0.437 | BR33: 2026-05-29 | BS33: 0.436 | BT33: -0.23 | BU33: 17
A34: PUBLIC e-ISLAMIC GROWTH FUND | B34: PeIGRF | C34: Shariah | D34: Equity | E34: Capital Growth | F34: 4 | G34: Incidental | H34: 65.65 | I34: 10.12.2021 | J34: Qualified | K34: 66.7 | L34: 2/3 | M34: Qualified (WA: +4.71%) — YTD✘ 1Y✔ 3Y✔ | N34: 4.71 | O34: 3.96 | P34: 4.74 | Q34: -0.78 | R34: 21.83 | S34: 11.86 | T34: 9.97 | U34: 9.04 | V34: 5.62 | W34: 3.42 | AD34: =IF(OR(Q34="",BM34="",BM34=0),"",Q34/BM34) | AE34: =IF(OR(T34="",BM34="",BM34=0),"",T34/BM34) | AF34: =IF(OR(W34="",BM34="",BM34=0),"",W34/BM34) | AG34: =IF(OR(Z34="",BM34="",BM34=0),"",Z34/BM34) | AH34: =IF(OR(AC34="",BM34="",BM34=0),"",AC34/BM34) | AI34: 77.8 | AJ34: 17.3 | AL34: 4.9 | AO34: 13.8 | AP34: 3.5 | BA34: 12.7 | BD34: 25.3 | BF34: 17 | BG34: 10.7 | BI34: 9.2 | BL34: Tenaga Nasional Berhad | Press Metal Aluminium Holdings Berhad | Telekom Malaysia Berhad | TIME dotCom Berhad | IHH Healthcare Berhad | BM34: 9.3 | BN34: Moderate | BO34: Equity Malaysia | BP34: Thebenchmark for PeIGRFis acomposite of90% FTSE Bursa MalaysiaEMAS Shariah Index and 10% 3-Month Islamic Interbank Money Market (IIMM) rate. Underlying index data are sourced from Lipper and Bank Negara Malaysia. | BQ34: 0.3082 | BR34: 2026-05-22 | BS34: 0.3029 | BT34: -1.72 | BU34: 24
A35: PB GROWTH SEQUEL FUND | B35: PBGSQF | C35: Conventional | D35: Equity | E35: Capital Growth | F35: 4 | G35: Incidental | H35: 63.12 | I35: 15.11.2011 | J35: Qualified | K35: 80 | L35: 4/5 | M35: Qualified (WA: +4.63%) — YTD✘ 1Y✔ 3Y✔ 5Y✔ 10Y✔ | N35: 4.63 | O35: 0.73 | P35: 2.49 | Q35: -1.76 | R35: 17.11 | S35: 11.8 | T35: 5.31 | U35: 12.53 | V35: 6.72 | W35: 5.81 | X35: 5.38 | Y35: 1.46 | Z35: 3.92 | AA35: 4.39 | AB35: 0.29 | AC35: 4.1 | AD35: =IF(OR(Q35="",BM35="",BM35=0),"",Q35/BM35) | AE35: =IF(OR(T35="",BM35="",BM35=0),"",T35/BM35) | AF35: =IF(OR(W35="",BM35="",BM35=0),"",W35/BM35) | AG35: =IF(OR(Z35="",BM35="",BM35=0),"",Z35/BM35) | AH35: =IF(OR(AC35="",BM35="",BM35=0),"",AC35/BM35) | AI35: 74.4 | AJ35: 22.8 | AL35: 2.8 | AO35: 15.9 | AP35: 6.4 | BA35: 27.7 | BB35: 10.3 | BC35: 23.8 | BD35: 19.2 | BF35: 8 | BL35: Public Bank Berhad | Sunway Berhad | QL Resources Berhad | Southern Cable Group Berhad | Alphabet Incorporated - Class A | BM35: 10.1 | BN35: Moderate | BO35: Equity Malaysia | BP35: Index data are sourced from Lipper. | BQ35: 0.3945 | BR35: 2026-06-03 | BS35: 0.3913 | BT35: -0.81 | BU35: 12
A36: PUBLIC INDUSTRY GROWTH FUND | B36: PINDGF | C36: Shariah | D36: Equity | E36: Capital Growth | F36: 4 | G36: Incidental | H36: 248.52 | I36: 18.11.1993 | J36: Qualified | K36: 100 | L36: 5/5 | M36: Qualified (WA: +4.44%) — YTD✔ 1Y✔ 3Y✔ 5Y✔ 10Y✔ | N36: 4.44 | O36: 5.94 | P36: 2.49 | Q36: 3.45 | R36: 18.27 | S36: 11.8 | T36: 6.47 | U36: 11.75 | V36: 6.72 | W36: 5.03 | X36: 3.55 | Y36: 1.46 | Z36: 2.09 | AA36: 5.35 | AB36: 0.29 | AC36: 5.06 | AD36: =IF(OR(Q36="",BM36="",BM36=0),"",Q36/BM36) | AE36: =IF(OR(T36="",BM36="",BM36=0),"",T36/BM36) | AF36: =IF(OR(W36="",BM36="",BM36=0),"",W36/BM36) | AG36: =IF(OR(Z36="",BM36="",BM36=0),"",Z36/BM36) | AH36: =IF(OR(AC36="",BM36="",BM36=0),"",AC36/BM36) | AI36: 75.5 | AJ36: 17.2 | AL36: 7.3 | AO36: 15.3 | AS36: 1.9 | BA36: 9.2 | BB36: 12.2 | BC36: 23.7 | BD36: 15.4 | BG36: 12 | BL36: Malayan Banking Berhad | Tenaga Nasional Berhad | Public Bank Berhad | Telekom Malaysia Berhad | Press Metal Aluminium Holdings Berhad | BM36: 6.9 | BN36: Low | BO36: Equity Malaysia Domestic 30% of the fund’s NAV | BQ36: 0.9072 | BR36: 2007-10-31 | BS36: 0.7059 | BT36: -22.19 | BU36: 6802
A37: PUBLIC SELECT TREASURES EQUITY FUND | B37: PSTEF | C37: Conventional | D37: Equity | E37: Capital Growth | F37: 5 | G37: Incidental | H37: 402.54 | I37: 22.07.2015 | J37: Qualified | K37: 80 | L37: 4/5 | M37: Qualified (WA: +4.24%) — YTD✘ 1Y✔ 3Y✔ 5Y✔ 10Y✔ | N37: 4.24 | O37: 5.15 | P37: 5.21 | Q37: -0.06 | R37: 23.87 | S37: 10.05 | T37: 13.82 | U37: 10.48 | V37: 7.54 | W37: 2.94 | X37: 3.45 | Y37: 2.15 | Z37: 1.3 | AA37: 7.29 | AB37: 2.85 | AC37: 4.44 | AD37: =IF(OR(Q37="",BM37="",BM37=0),"",Q37/BM37) | AE37: =IF(OR(T37="",BM37="",BM37=0),"",T37/BM37) | AF37: =IF(OR(W37="",BM37="",BM37=0),"",W37/BM37) | AG37: =IF(OR(Z37="",BM37="",BM37=0),"",Z37/BM37) | AH37: =IF(OR(AC37="",BM37="",BM37=0),"",AC37/BM37) | AI37: 74.8 | AJ37: 22.3 | AL37: 2.9 | AO37: 4.4 | AP37: 15 | AT37: 2.9 | BA37: 35.9 | BB37: 7.7 | BC37: 31.4 | BD37: 5.7 | BF37: 11.8 | BL37: Hon.Precision Incorporated | Kinik Company | TIME dotCom Berhad | IGB Real Estate Investment Trust | Frontken Corporation Berhad | BM37: 10.4 | BN37: High | BO37: Equity Malaysia Domestic 25% of the fund’s NAV | BQ37: 0.4931 | BR37: 2026-05-29 | BS37: 0.4776 | BT37: -3.14 | BU37: 17
A38: PUBLIC FAR-EAST SELECT FUND | B38: PFES | C38: Conventional | D38: Equity | E38: Capital Growth | F38: 5 | G38: Incidental | H38: 864.41 | I38: 22.11.2005 | J38: Qualified | K38: 80 | L38: 4/5 | M38: Qualified (WA: +4.19%) — YTD✔ 1Y✔ 3Y✔ 5Y✔ 10Y✘ | N38: 4.19 | O38: 22.42 | P38: 13.74 | Q38: 8.68 | R38: 55.4 | S38: 41.49 | T38: 13.91 | U38: 19.07 | V38: 15.79 | W38: 3.28 | X38: 3.56 | Y38: 2.09 | Z38: 1.47 | AA38: 7.62 | AB38: 7.7 | AC38: -0.08 | AD38: =IF(OR(Q38="",BM38="",BM38=0),"",Q38/BM38) | AE38: =IF(OR(T38="",BM38="",BM38=0),"",T38/BM38) | AF38: =IF(OR(W38="",BM38="",BM38=0),"",W38/BM38) | AG38: =IF(OR(Z38="",BM38="",BM38=0),"",Z38/BM38) | AH38: =IF(OR(AC38="",BM38="",BM38=0),"",AC38/BM38) | AI38: 0.9 | AJ38: 93.2 | AL38: 5.9 | AP38: 35.2 | AQ38: 26.8 | AU38: 30.5 | AZ38: 0.7 | BA38: 15.2 | BB38: 47.7 | BC38: 2.2 | BD38: 21.4 | BE38: 7.3 | BL38: Samsung Electronics Company Limited | Taiwan Semiconductor Manufacturing Company Limited | SK Hynix Incorporated | Alibaba Group Holding Limited - W | Tencent Holdings Limited | BM38: 17.7 | BN38: Very High | BO38: Equity Asia Pacific Asia | BP38: 2021 0.80 31.5.21 2.1 ThebenchmarkforPFESisacompositeof70%MSCIACFar-EastEx-JapanIndex 2022 0.80 31.5.22 2.7 and30%KualaLumpurCompositeIndex(priorto6July2009),30%FTSEBursa Malaysia KLCI (6 July 2009 to 29 April 2010). Note: Distribution yield simply measures the level of distributions and is MSCIACFar-EastEx-JapanIndex(30April2010to29April2021),S&PPanAsia not a measure of fund performance. Ex-Japan, Australia, New Zealand & India LargeCap Index (30 April 2021 to 1 January 2025), S&P Pan Asia Ex-Japan, Australia, New Zealand & India LargeCap 8% Capped Index (w.e.f. 2 January 2025). UnderlyingindexdataaresourcedfromS&PDowJonesIndices,LLCandLipper and expressed in Ringgit terms. | BQ38: 0.5227 | BR38: 2026-06-04 | BS38: 0.5015 | BT38: -4.06 | BU38: 11
A39: PB ASIA EQUITY FUND | B39: PBAEF | C39: Conventional | D39: Equity | E39: Capital Growth | F39: 5 | G39: Incidental | H39: 197.56 | I39: 27.06.2006 | J39: Qualified | K39: 100 | L39: 5/5 | M39: Qualified (WA: +4.01%) — YTD✔ 1Y✔ 3Y✔ 5Y✔ 10Y✔ | N39: 4.01 | O39: 26.67 | P39: 15.29 | Q39: 11.38 | R39: 56.42 | S39: 43.26 | T39: 13.16 | U39: 20 | V39: 16.79 | W39: 3.21 | X39: 5.47 | Y39: 5.06 | Z39: 0.41 | AA39: 8.73 | AB39: 8.2 | AC39: 0.53 | AD39: =IF(OR(Q39="",BM39="",BM39=0),"",Q39/BM39) | AE39: =IF(OR(T39="",BM39="",BM39=0),"",T39/BM39) | AF39: =IF(OR(W39="",BM39="",BM39=0),"",W39/BM39) | AG39: =IF(OR(Z39="",BM39="",BM39=0),"",Z39/BM39) | AH39: =IF(OR(AC39="",BM39="",BM39=0),"",AC39/BM39) | AI39: 0.8 | AJ39: 86.6 | AL39: 12.6 | AO39: 7.6 | AP39: 31.2 | AQ39: 28.1 | AR39: 5.4 | AU39: 14.3 | BA39: 28.8 | BB39: 36.2 | BC39: 3 | BD39: 14.5 | BE39: 4.9 | BL39: Taiwan Semiconductor Manufacturing Company Limited | Samsung Electronics Company Limited | HD Hyundai Electric Company Limited | Elite Material Company Limited | SK Hynix Incorporated | BM39: 16.5 | BN39: Very High | BO39: Equity Asia Pacific Asia | BP39: 2016 1.50 30.06.16 6.0 ThebenchmarkforPBAEFisacompositeof20%KualaLumpurCompositeIndex (priorto6July2009), 20%FTSE BursaMalaysiaKLCI(w.e.f.6July2009),20% 2017 1.50 30.06.17 4.9 TokyoStockPriceIndex(priorto30April2013),20%TOPIXCore30Index(w.e.f. 2018 1.50 29.06.18 5.3 30April 2013),20% KoreaCompositeStock PriceIndex(priorto30 April 2013), 20%KOSPI50Index(30April2013to29April2017),20%MSCIKoreaLargeCap 2019 1.00 28.06.19 3.7 Index (30 April 2017 to 29 April 2021), 20% S&P Korea LargeCap Index (w.e.f. 2020 1.75 30.06.20 6.0 30April2021)and40%MSCIGoldenDragonIndex(priorto30April2021),40% 2021 1.75 30.06.21 5.1 S&P Greater China LargeMidCap Index (30 April 2021 to 1 January2025), 40% S&P Greater China LargeMidCap 8% Capped Index (w.e.f. 2 January 2025). Note: Distribution yield simply measures the level of distributions and is not a measure of fund performance. UnderlyingindexdataaresourcedfromS&PDowJonesIndices,LLCandLipper and expressed in Ringgit terms. | BQ39: 0.5019 | BR39: 2026-06-04 | BS39: 0.4929 | BT39: -1.79 | BU39: 11
A40: PB ASIA-30 EQUITY FUND | B40: PBA30EF | C40: Conventional | D40: Equity | E40: Capital Growth | F40: 5 | G40: Incidental | H40: 337.92 | I40: 26.07.2018 | J40: Qualified | K40: 75 | L40: 3/4 | M40: Qualified (WA: +3.95%) — YTD✔ 1Y✔ 3Y✔ 5Y✘ | N40: 3.95 | O40: 26.03 | P40: 12.92 | Q40: 13.11 | R40: 55.74 | S40: 39.58 | T40: 16.16 | U40: 19.43 | V40: 17.82 | W40: 1.61 | X40: 2.06 | Y40: 3.52 | Z40: -1.46 | AD40: =IF(OR(Q40="",BM40="",BM40=0),"",Q40/BM40) | AE40: =IF(OR(T40="",BM40="",BM40=0),"",T40/BM40) | AF40: =IF(OR(W40="",BM40="",BM40=0),"",W40/BM40) | AG40: =IF(OR(Z40="",BM40="",BM40=0),"",Z40/BM40) | AH40: =IF(OR(AC40="",BM40="",BM40=0),"",AC40/BM40) | AJ40: 95.4 | AL40: 4.6 | AO40: 2.4 | AP40: 48 | AQ40: 30.2 | AR40: 0.7 | AU40: 14.1 | BA40: 24.1 | BB40: 50.4 | BD40: 18.5 | BE40: 2.4 | BL40: SK Hynix Incorporated | Taiwan Semiconductor Manufacturing Company Limited | Samsung Electronics Company Limited | Alibaba Group Holding Limited - W | Delta Electronics Incorporated | BM40: 20.3 | BN40: Very High | BO40: Equity Asia Pacific Asia | BQ40: 0.4564 | BR40: 2026-06-04 | BS40: 0.4345 | BT40: -4.8 | BU40: 11
A41: PUBLIC ADVANTAGE GROWTH EQUITY FUND | B41: PAVGEF | C41: Conventional | D41: Equity | E41: Capital Growth | F41: 5 | G41: Incidental | H41: 19.06 | I41: 08.09.2015 | J41: Qualified | K41: 100 | L41: 5/5 | M41: Qualified (WA: +3.60%) — YTD✔ 1Y✔ 3Y✔ 5Y✔ 10Y✔ | N41: 3.6 | O41: 5.13 | P41: 2.49 | Q41: 2.64 | R41: 22.34 | S41: 11.8 | T41: 10.54 | U41: 9.09 | V41: 6.72 | W41: 2.37 | X41: 2.6 | Y41: 1.46 | Z41: 1.14 | AA41: 4.66 | AB41: 0.29 | AC41: 4.37 | AD41: =IF(OR(Q41="",BM41="",BM41=0),"",Q41/BM41) | AE41: =IF(OR(T41="",BM41="",BM41=0),"",T41/BM41) | AF41: =IF(OR(W41="",BM41="",BM41=0),"",W41/BM41) | AG41: =IF(OR(Z41="",BM41="",BM41=0),"",Z41/BM41) | AH41: =IF(OR(AC41="",BM41="",BM41=0),"",AC41/BM41) | AI41: 75 | AJ41: 22.5 | AL41: 2.5 | AO41: 9.9 | AP41: 3.9 | AU41: 6.4 | BA41: 15.9 | BB41: 10.2 | BC41: 26.9 | BD41: 20.2 | BG41: 9.3 | BL41: Tenaga Nasional Berhad | Malayan Banking Berhad | Telekom Malaysia Berhad | Hong Leong Industries Berhad | Alphabet Incorporated - Class A | BM41: 11.1 | BN41: High | BO41: Equity Malaysia Domestic 25% of the fund’s NAV | BP41: Index data are sourced from Lipper. | BQ41: 0.364 | BR41: 2026-06-03 | BS41: 0.3563 | BT41: -2.12 | BU41: 12
A42: PUBLIC ASIA PACIFIC ALPHA-40 FUND | B42: PAPA40F | C42: Conventional | D42: Equity | E42: Capital Growth | F42: 5 | G42: Incidental | H42: 53.33 | I42: 10.12.2021 | J42: Qualified | K42: 100 | L42: 3/3 | M42: Qualified (WA: +3.47%) — YTD✔ 1Y✔ 3Y✔ | N42: 3.47 | O42: 16.97 | P42: 12.92 | Q42: 4.05 | R42: 49.67 | S42: 39.58 | T42: 10.09 | U42: 18.73 | V42: 17.82 | W42: 0.91 | AD42: =IF(OR(Q42="",BM42="",BM42=0),"",Q42/BM42) | AE42: =IF(OR(T42="",BM42="",BM42=0),"",T42/BM42) | AF42: =IF(OR(W42="",BM42="",BM42=0),"",W42/BM42) | AG42: =IF(OR(Z42="",BM42="",BM42=0),"",Z42/BM42) | AH42: =IF(OR(AC42="",BM42="",BM42=0),"",AC42/BM42) | AI42: 0.8 | AJ42: 89.3 | AL42: 9.9 | AO42: 8.6 | AP42: 21.6 | AQ42: 26.5 | AR42: 3.9 | AU42: 23.4 | BA42: 16.8 | BB42: 42.5 | BC42: 8.5 | BD42: 17 | BE42: 5.3 | BL42: SK Hynix Incorporated | Samsung Electronics Company Limited | Taiwan Semiconductor Manufacturing Company Limited | Alibaba Group Holding Limited - W | Tencent Holdings Limited | BM42: 17.2 | BN42: Very High | BO42: Equity Asia Pacific Asia | BP42: ThebenchmarkforPAPA40Fisacompositeof80%customisedindexbyS&PDow JonesIndices,LLCbasedonthetop30constituentsoftheS&PBMIAsiaEx-Japan Index, 10% Tokyo Stock Price Index (TOPIX) and 10% 3-Month Kuala Lumpur Interbank Offered Rate (KLIBOR). UnderlyingindexdataaresourcedfromS&PDowJonesIndices,LLC,Lipperand Bank Negara Malaysia and expressed in Ringgit terms. | BQ42: 0.4402 | BR42: 2026-06-04 | BS42: 0.4263 | BT42: -3.16 | BU42: 11
A43: PUBLIC ISLAMIC U.S. SUSTAINABLE EQUITY FUND | B43: PIUSSEQF | C43: Shariah | D43: Equity | E43: Capital Growth | F43: 5 | G43: Incidental | H43: 517.48 | I43: 10.04.2019 | J43: Qualified | K43: 100 | L43: 4/4 | M43: Qualified (WA: +3.45%) — YTD✔ 1Y✔ 3Y✔ 5Y✔ | N43: 3.45 | O43: 2.01 | P43: 0.33 | Q43: 1.68 | R43: 26.09 | S43: 16.81 | T43: 9.28 | U43: 17.83 | V43: 15.21 | W43: 2.62 | X43: 12.62 | Y43: 11 | Z43: 1.62 | AD43: =IF(OR(Q43="",BM43="",BM43=0),"",Q43/BM43) | AE43: =IF(OR(T43="",BM43="",BM43=0),"",T43/BM43) | AF43: =IF(OR(W43="",BM43="",BM43=0),"",W43/BM43) | AG43: =IF(OR(Z43="",BM43="",BM43=0),"",Z43/BM43) | AH43: =IF(OR(AC43="",BM43="",BM43=0),"",AC43/BM43) | AJ43: 97.3 | AL43: 2.7 | AO43: 81.3 | AR43: 2.2 | AS43: 1.5 | AU43: 4.7 | AW43: 7 | BB43: 47.4 | BC43: 4.7 | BD43: 30.6 | BE43: 6 | BF43: 6.5 | BL43: Alphabet Incorporated - Class A | Microsoft Corporation | Meta Platforms Incorporated | Apple Incorporated | Advanced Micro Devices Incorporated | BM43: 14.7 | BN43: Very High | BO43: Equity U.S. Global | BP43: The benchmark for PIUSSEQF is a composite of 90% S&P United States LargeCapShariahIndex(priorto26February2025),90%S&PGlobal1200U.S. LargeCapESGShariah8%CappedIndex(w.e.f.26February2025)and10%3- Month Islamic Interbank Money Market (IIMM) rate. UnderlyingindexdataaresourcedfromS&PDowJonesIndices,LLCandBank Negara Malaysia and expressed in Ringgit terms. | BQ43: 0.7124 | BR43: 2026-06-04 | BS43: 0.6908 | BT43: -3.03 | BU43: 11
A44: PB GROWTH FUND | B44: PBGF | C44: Conventional | D44: Equity | E44: Capital Growth | F44: 4 | G44: Incidental | H44: 599.45 | I44: 03.10.2002 | J44: Qualified | K44: 80 | L44: 4/5 | M44: Qualified (WA: +3.35%) — YTD✔ 1Y✘ 3Y✔ 5Y✔ 10Y✔ | N44: 3.35 | O44: 2.74 | P44: 2.49 | Q44: 0.25 | R44: 10.64 | S44: 11.8 | T44: -1.16 | U44: 12.7 | V44: 6.72 | W44: 5.98 | X44: 3.35 | Y44: 1.46 | Z44: 1.89 | AA44: 4.63 | AB44: 0.29 | AC44: 4.34 | AD44: =IF(OR(Q44="",BM44="",BM44=0),"",Q44/BM44) | AE44: =IF(OR(T44="",BM44="",BM44=0),"",T44/BM44) | AF44: =IF(OR(W44="",BM44="",BM44=0),"",W44/BM44) | AG44: =IF(OR(Z44="",BM44="",BM44=0),"",Z44/BM44) | AH44: =IF(OR(AC44="",BM44="",BM44=0),"",AC44/BM44) | AI44: 75.6 | AJ44: 20.7 | AL44: 3.7 | AO44: 8.6 | AP44: 5.8 | AQ44: 4.8 | AU44: 1.5 | BB44: 15.3 | BC44: 27 | BD44: 19.9 | BF44: 12.3 | BI44: 8.7 | BL44: Public Bank Berhad | Malayan Banking Berhad | Press Metal Aluminium Holdings Berhad | Tenaga Nasional Berhad | TIME dotCom Berhad | BM44: 9.5 | BN44: Moderate | BO44: Equity Malaysia | BQ44: 1.1461 | BR44: 2007-12-31 | BS44: 1.0041 | BT44: -12.39 | BU44: 6741
A45: PUBLIC WORLDWIDE EQUITY FUND | B45: PWEF | C45: Conventional | D45: Equity | E45: Capital Growth | F45: 5 | G45: Incidental | H45: 134.46 | I45: 30.06.2009 | J45: Qualified | K45: 60 | L45: 3/5 | M45: Qualified (WA: +3.30%) — YTD✔ 1Y✔ 3Y✔ 5Y✘ 10Y✘ | N45: 3.3 | O45: 3.56 | P45: 1.72 | Q45: 1.84 | R45: 25.27 | S45: 11.24 | T45: 14.03 | U45: 14.31 | V45: 8.56 | W45: 5.75 | X45: 3.96 | Y45: 7.51 | Z45: -3.55 | AA45: 7.01 | AB45: 9.08 | AC45: -2.07 | AD45: =IF(OR(Q45="",BM45="",BM45=0),"",Q45/BM45) | AE45: =IF(OR(T45="",BM45="",BM45=0),"",T45/BM45) | AF45: =IF(OR(W45="",BM45="",BM45=0),"",W45/BM45) | AG45: =IF(OR(Z45="",BM45="",BM45=0),"",Z45/BM45) | AH45: =IF(OR(AC45="",BM45="",BM45=0),"",AC45/BM45) | AI45: 0.7 | AJ45: 93.4 | AL45: 5.9 | AO45: 48.1 | AP45: 16.4 | AQ45: 4.8 | AU45: 6.5 | BB45: 48.3 | BC45: 5.5 | BD45: 25.3 | BE45: 10.3 | BF45: 2.9 | BL45: Taiwan Semiconductor Manufacturing Company Limited | Tesla Incorporated | Advanced Micro Devices Incorporated | Alibaba Group Holding Limited - W | Alphabet Incorporated - Class A | BM45: 16.7 | BN45: Very High | BO45: Equity Global Global | BQ45: 0.4418 | BR45: 2026-06-03 | BS45: 0.4249 | BT45: -3.83 | BU45: 12
A46: PUBLIC HEALTHCARE-GLOBAL EQUITY FUND | B46: PHGEF | C46: Conventional | D46: Equity | E46: Capital Growth | F46: 5 | G46: Incidental | H46: 417.19 | I46: 20.10.2020 | J46: Qualified | K46: 50 | L46: 2/4 | M46: Qualified (WA: +3.21%) — YTD✘ 1Y✔ 3Y✔ 5Y✘ | N46: 3.21 | O46: -3.9 | P46: 1.25 | Q46: -5.15 | R46: 15.05 | S46: 12.8 | T46: 2.25 | U46: 14.29 | V46: 7.34 | W46: 6.95 | X46: 4.05 | Y46: 4.57 | Z46: -0.52 | AD46: =IF(OR(Q46="",BM46="",BM46=0),"",Q46/BM46) | AE46: =IF(OR(T46="",BM46="",BM46=0),"",T46/BM46) | AF46: =IF(OR(W46="",BM46="",BM46=0),"",W46/BM46) | AG46: =IF(OR(Z46="",BM46="",BM46=0),"",Z46/BM46) | AH46: =IF(OR(AC46="",BM46="",BM46=0),"",AC46/BM46) | AJ46: 96.7 | AL46: 3.3 | AO46: 70.8 | AP46: 13 | AQ46: 5.2 | AU46: 5.4 | AW46: 1.2 | BB46: 20.9 | BD46: 26.7 | BE46: 9.3 | BF46: 4 | BK46: 32.8 | BL46: Taiwan Semiconductor Manufacturing Company Limited | Tesla Incorporated | Alphabet Incorporated - Class A | iShares Global Healthcare ETF | iShares U.S. Medical Devices ETF | BM46: 11.8 | BN46: High | BO46: Equity Global Global | BQ46: 0.3575 | BR46: 2025-10-27 | BS46: 0.3425 | BT46: -4.2 | BU46: 231
A47: PUBLIC CHINA ACCESS EQUITY FUND | B47: PCASEF | C47: Conventional | D47: Equity | E47: Capital Growth | F47: 5 | G47: Incidental | H47: 1036.27 | I47: 18.04.2013 | J47: Qualified | K47: 80 | L47: 4/5 | M47: Qualified (WA: +3.12%) — YTD✘ 1Y✔ 3Y✔ 5Y✔ 10Y✔ | N47: 3.12 | O47: 1.56 | P47: 2.39 | Q47: -0.83 | R47: 29.3 | S47: 14.62 | T47: 14.68 | U47: 4.9 | V47: 2.67 | W47: 2.23 | X47: -2.41 | Y47: -2.65 | Z47: 0.24 | AA47: 5.71 | AB47: 5.63 | AC47: 0.08 | AD47: =IF(OR(Q47="",BM47="",BM47=0),"",Q47/BM47) | AE47: =IF(OR(T47="",BM47="",BM47=0),"",T47/BM47) | AF47: =IF(OR(W47="",BM47="",BM47=0),"",W47/BM47) | AG47: =IF(OR(Z47="",BM47="",BM47=0),"",Z47/BM47) | AH47: =IF(OR(AC47="",BM47="",BM47=0),"",AC47/BM47) | AJ47: 91.3 | AL47: 8.7 | AU47: 91.3 | BA47: 10.9 | BB47: 15.1 | BC47: 17.7 | BD47: 15.3 | BE47: 18.7 | BL47: Zhongji Innolight Company Limited - A Shares | Contemporary Amperex Technology Company Limited - A Shares | NAURA Technology Group Company Limited - A Shares | Ping An Insurance (Group) Company of China Limited - A Shares | Hygon Information Technology Company Limited - A Shares | BM47: 14.8 | BN47: Very High | BO47: Equity China Greater China | BP47: Thebenchmark forPCASEF isacompositeof90% S&P ChinaA 50Indexand 10% 3-Month Kuala Lumpur Interbank Offered Rate (KLIBOR). Underlying index data are sourced from Lipper and Bank Negara Malaysia and expressed in Ringgit terms. | BQ47: 2.2029 | BR47: 2015-06-08 | BS47: 1.3214 | BT47: -40.02 | BU47: 4025
A48: PUBLIC ISLAMIC SELECT ENTERPRISES FUND | B48: PISEF | C48: Shariah | D48: Equity | E48: Capital Growth | F48: 4 | G48: Incidental | H48: 936.11 | I48: 14.08.2008 | J48: Qualified | K48: 80 | L48: 4/5 | M48: Qualified (WA: +3.11%) — YTD✘ 1Y✔ 3Y✔ 5Y✔ 10Y✔ | N48: 3.11 | O48: 0.44 | P48: 5.14 | Q48: -4.7 | R48: 17.37 | S48: 12.81 | T48: 4.56 | U48: 9.12 | V48: 5.79 | W48: 3.33 | X48: 2.92 | Y48: -0.85 | Z48: 3.77 | AA48: 2.98 | AB48: 0.41 | AC48: 2.57 | AD48: =IF(OR(Q48="",BM48="",BM48=0),"",Q48/BM48) | AE48: =IF(OR(T48="",BM48="",BM48=0),"",T48/BM48) | AF48: =IF(OR(W48="",BM48="",BM48=0),"",W48/BM48) | AG48: =IF(OR(Z48="",BM48="",BM48=0),"",Z48/BM48) | AH48: =IF(OR(AC48="",BM48="",BM48=0),"",AC48/BM48) | AI48: 78.2 | AJ48: 18.6 | AL48: 3.2 | AO48: 13.3 | AS48: 1.7 | AU48: 3.6 | BA48: 11.8 | BC48: 9.5 | BD48: 17.5 | BF48: 18.9 | BG48: 10 | BL48: Telekom Malaysia Berhad | Tenaga Nasional Berhad | NVIDIA Corporation | Gamuda Berhad | Press Metal Aluminium Holdings Berhad | BM48: 8.7 | BN48: Moderate | BO48: Equity Malaysia Domestic | BQ48: 0.4479 | BR48: 2014-07-07 | BS48: 0.4274 | BT48: -4.58 | BU48: 4361
A49: PUBLIC SECTOR SELECT FUND | B49: PSSF | C49: Conventional | D49: Equity | E49: Capital Growth | F49: 4 | G49: Incidental | H49: 371.6 | I49: 13.11.2007 | J49: Qualified | K49: 80 | L49: 4/5 | M49: Qualified (WA: +3.08%) — YTD✘ 1Y✔ 3Y✔ 5Y✔ 10Y✔ | N49: 3.08 | O49: 1.76 | P49: 3.75 | Q49: -1.99 | R49: 13.59 | S49: 12.31 | T49: 1.28 | U49: 11 | V49: 7.59 | W49: 3.41 | X49: 5.85 | Y49: 1.87 | Z49: 3.98 | AA49: 5.22 | AB49: 1.03 | AC49: 4.19 | AD49: =IF(OR(Q49="",BM49="",BM49=0),"",Q49/BM49) | AE49: =IF(OR(T49="",BM49="",BM49=0),"",T49/BM49) | AF49: =IF(OR(W49="",BM49="",BM49=0),"",W49/BM49) | AG49: =IF(OR(Z49="",BM49="",BM49=0),"",Z49/BM49) | AH49: =IF(OR(AC49="",BM49="",BM49=0),"",AC49/BM49) | AI49: 76.7 | AJ49: 20.1 | AL49: 3.2 | AO49: 15.4 | AS49: 2.6 | AU49: 2.1 | BA49: 7.2 | BB49: 8.2 | BC49: 40 | BD49: 17.3 | BF49: 8.9 | BL49: Public Bank Berhad | Malayan Banking Berhad | NVIDIA Corporation | Telekom Malaysia Berhad | Meta Platforms Incorporated | BM49: 6.8 | BN49: Low | BO49: Equity Malaysia Domestic 25% of the fund’s NAV | BQ49: 0.3973 | BR49: 2026-02-11 | BS49: 0.3839 | BT49: -3.37 | BU49: 124
A50: PUBLIC CHINA TITANS FUND | B50: PCTF | C50: Conventional | D50: Equity | E50: Capital Growth | F50: 5 | G50: Incidental | H50: 947.69 | I50: 01.04.2008 | J50: Qualified | K50: 100 | L50: 5/5 | M50: Qualified (WA: +3.07%) — YTD✔ 1Y✔ 3Y✔ 5Y✔ 10Y✔ | N50: 3.07 | O50: 6.35 | P50: 6.09 | Q50: 0.26 | R50: 28.71 | S50: 23.92 | T50: 4.79 | U50: 19.07 | V50: 14.84 | W50: 4.23 | X50: 3.62 | Y50: 2.37 | Z50: 1.25 | AA50: 9.07 | AB50: 6.83 | AC50: 2.24 | AD50: =IF(OR(Q50="",BM50="",BM50=0),"",Q50/BM50) | AE50: =IF(OR(T50="",BM50="",BM50=0),"",T50/BM50) | AF50: =IF(OR(W50="",BM50="",BM50=0),"",W50/BM50) | AG50: =IF(OR(Z50="",BM50="",BM50=0),"",Z50/BM50) | AH50: =IF(OR(AC50="",BM50="",BM50=0),"",AC50/BM50) | AJ50: 88.2 | AL50: 11.8 | AO50: 12.3 | AP50: 35.1 | AU50: 6 | BA50: 10 | BB50: 31.7 | BC50: 16.7 | BD50: 23.7 | BE50: 4.7 | BL50: Taiwan Semiconductor Manufacturing Company Limited | Delta Electronics Incorporated | China Construction Bank Corporation - H Shares | Alibaba Group Holding Limited - W | Tencent Holdings Limited | BM50: 16.2 | BN50: Very High | BO50: Equity Greater China Greater China | BP50: 2020 0.50 29.5.20 1.6 The benchmark for PCTF is a composite of 40% Hang Seng China Enterprises 2021 0.75 31.5.21 2.0 Index (HSCEI), 30% Hang Seng Index (HSI) and 30% FTSE TWSE Taiwan 50 Index(priorto30April2016),30%MSCITaiwanLargeCapIndex(30April2016to 2022 0.50 31.5.22 1.7 29 April 2021), 30% S&P Taiwan LargeCap Index (w.e.f. 30 April 2021). Note: Distribution yield simply measures the level of distributions and is UnderlyingindexdataaresourcedfromLipperandS&PDowJonesIndices,LLC not a measure of fund performance. and expressed in Ringgit terms. | BQ50: 0.4952 | BR50: 2026-06-03 | BS50: 0.4745 | BT50: -4.18 | BU50: 12
A51: PUBLIC ISLAMIC SUSTAINABLE GROWTH FUND | B51: PISGRTF | C51: Shariah | D51: Equity | E51: Capital Growth | F51: 4 | G51: Incidental | H51: 118.8 | I51: 04.06.2024 | J51: Qualified | K51: 50 | L51: 1/2 | M51: Qualified (WA: +3.04%) — YTD✘ 1Y✔ | N51: 3.04 | O51: 3.13 | P51: 5.79 | Q51: -2.66 | R51: 18.05 | S51: 13.11 | T51: 4.94 | AD51: =IF(OR(Q51="",BM51="",BM51=0),"",Q51/BM51) | AE51: =IF(OR(T51="",BM51="",BM51=0),"",T51/BM51) | AF51: =IF(OR(W51="",BM51="",BM51=0),"",W51/BM51) | AG51: =IF(OR(Z51="",BM51="",BM51=0),"",Z51/BM51) | AH51: =IF(OR(AC51="",BM51="",BM51=0),"",AC51/BM51) | AI51: 76.7 | AJ51: 21.4 | AL51: 1.9 | AO51: 12.1 | AP51: 6.3 | AU51: 3 | BA51: 21.3 | BC51: 22 | BD51: 29.4 | BF51: 6.9 | BG51: 10 | BL51: Tenaga Nasional Berhad | Telekom Malaysia Berhad | TIME dotCom Berhad | Sunway Berhad | QL Resources Berhad | BP51: Index data are sourced from Lipper. | BQ51: 0.2809 | BR51: 2026-05-14 | BS51: 0.2749 | BT51: -2.14 | BU51: 32
A52: PUBLIC e-ISLAMIC SUSTAINABLE MILLENNIAL FUND | B52: PeISMF | C52: Shariah | D52: Equity | E52: Capital Growth | F52: 5 | G52: Incidental | H52: 468.08 | I52: 05.11.2019 | J52: Qualified | K52: 75 | L52: 3/4 | M52: Qualified (WA: +3.03%) — YTD✘ 1Y✔ 3Y✔ 5Y✔ | N52: 3.03 | O52: 2.74 | P52: 3.84 | Q52: -1.1 | R52: 29.45 | S52: 22.43 | T52: 7.02 | U52: 17.15 | V52: 13.76 | W52: 3.39 | X52: 10.85 | Y52: 9.96 | Z52: 0.89 | AD52: =IF(OR(Q52="",BM52="",BM52=0),"",Q52/BM52) | AE52: =IF(OR(T52="",BM52="",BM52=0),"",T52/BM52) | AF52: =IF(OR(W52="",BM52="",BM52=0),"",W52/BM52) | AG52: =IF(OR(Z52="",BM52="",BM52=0),"",Z52/BM52) | AH52: =IF(OR(AC52="",BM52="",BM52=0),"",AC52/BM52) | AJ52: 97.3 | AL52: 2.7 | AO52: 67.4 | AP52: 10.1 | AR52: 3.8 | AU52: 8.9 | AW52: 3 | BA52: 2.6 | BB52: 45.8 | BD52: 32.9 | BE52: 12.1 | BF52: 2.8 | BL52: Advanced Micro Devices Incorporated | Alphabet Incorporated - Class A | Taiwan Semiconductor Manufacturing Company Limited | Alibaba Group Holding Limited - W | Meta Platforms Incorporated | BM52: 15.2 | BN52: Very High | BO52: Equity Global | BP52: ThebenchmarkforPeISMFisacompositeof90%S&PGlobal1200ESGShariah Index and 10% 3-Month Islamic Interbank Money Market (IIMM) rate. Underlying indexdata are sourced from S&P Dow Jones Indices, LLC and Bank Negara Malaysia and expressed in Ringgit terms. | BQ52: 0.5869 | BR52: 2026-06-03 | BS52: 0.5633 | BT52: -4.02 | BU52: 12
A53: PUBLIC INDONESIA SELECT FUND | B53: PINDOSF | C53: Shariah | D53: Equity | E53: Capital Growth | F53: 5 | G53: Incidental | H53: 487.36 | I53: 01.09.2010 | J53: Qualified | K53: 100 | L53: 5/5 | M53: Qualified (WA: +2.98%) — YTD✔ 1Y✔ 3Y✔ 5Y✔ 10Y✔ | N53: 2.98 | O53: -14.54 | P53: -28.04 | Q53: 13.5 | R53: -19.54 | S53: -21.17 | T53: 1.63 | U53: -14.13 | V53: -16.75 | W53: 2.62 | X53: -4.81 | Y53: -7.84 | Z53: 3.03 | AA53: -2.01 | AB53: -3.74 | AC53: 1.73 | AD53: =IF(OR(Q53="",BM53="",BM53=0),"",Q53/BM53) | AE53: =IF(OR(T53="",BM53="",BM53=0),"",T53/BM53) | AF53: =IF(OR(W53="",BM53="",BM53=0),"",W53/BM53) | AG53: =IF(OR(Z53="",BM53="",BM53=0),"",Z53/BM53) | AH53: =IF(OR(AC53="",BM53="",BM53=0),"",AC53/BM53) | AJ53: 93.1 | AL53: 6.9 | AO53: 12.9 | AU53: 3.4 | AV53: 3.9 | AX53: 72.9 | BB53: 6.8 | BC53: 32.4 | BD53: 18.5 | BE53: 17 | BF53: 11.7 | BL53: PT Bank Mandiri (Persero) Tbk | Bank Central Asia Tbk | Bank Rakyat Indonesia (Persero) Tbk | NVIDIA Corporation | AKR Corporindo Tbk | BM53: 13.4 | BN53: High | BO53: Equity Indonesia ASEAN | BQ53: 0.3423 | BR53: 2013-05-31 | BS53: 0.1723 | BT53: -49.66 | BU53: 4763
A54: PUBLIC FOCUS SELECT FUND | B54: PFSF | C54: Conventional | D54: Equity | E54: Capital Growth | F54: 5 | G54: Incidental | H54: 477.84 | I54: 25.11.2004 | J54: Qualified | K54: 80 | L54: 4/5 | M54: Qualified (WA: +2.73%) — YTD✘ 1Y✔ 3Y✔ 5Y✔ 10Y✔ | N54: 2.73 | O54: 4.1 | P54: 7.63 | Q54: -3.53 | R54: 19.84 | S54: 13.42 | T54: 6.42 | U54: 13.04 | V54: 10.15 | W54: 2.89 | X54: 5.05 | Y54: 3.03 | Z54: 2.02 | AA54: 5.26 | AB54: 3.38 | AC54: 1.88 | AD54: =IF(OR(Q54="",BM54="",BM54=0),"",Q54/BM54) | AE54: =IF(OR(T54="",BM54="",BM54=0),"",T54/BM54) | AF54: =IF(OR(W54="",BM54="",BM54=0),"",W54/BM54) | AG54: =IF(OR(Z54="",BM54="",BM54=0),"",Z54/BM54) | AH54: =IF(OR(AC54="",BM54="",BM54=0),"",AC54/BM54) | AI54: 75.6 | AJ54: 22.4 | AL54: 2 | AO54: 4.8 | AP54: 16.1 | AT54: 1.5 | BA54: 31.7 | BB54: 8.5 | BC54: 32.2 | BD54: 5.9 | BF54: 14.4 | BL54: Hon.Precision Incorporated | Kinik Company | QL Resources Berhad | TIME dotCom Berhad | LPI Capital Berhad | BM54: 9.2 | BN54: Moderate | BO54: Equity Malaysia Domestic 30% of the fund’s NAV | BP54: Kuala Lumpur Composite Index (prior to 30 April 2008). FTSE Bursa Malaysia Mid 70 Index (w.e.f. 30 April 2008). Underlying index data are sourced from Lipper. | BQ54: 0.4477 | BR54: 2026-05-29 | BS54: 0.4381 | BT54: -2.14 | BU54: 17
A55: PB VIETNAM GLOBAL 40 FUND | B55: PBVG40F | C55: Conventional | D55: Equity | E55: Capital Growth | F55: 5 | G55: Incidental | H55: 68.15 | I55: 18.09.2020 | J55: Qualified | K55: 50 | L55: 2/4 | M55: Qualified (WA: +2.53%) — YTD✘ 1Y✔ 3Y✔ 5Y✘ | N55: 2.53 | O55: 4.43 | P55: 4.83 | Q55: -0.4 | R55: 33.38 | S55: 28.9 | T55: 4.48 | U55: 18.2 | V55: 14.2 | W55: 4 | X55: 5.56 | Y55: 5.96 | Z55: -0.4 | AD55: =IF(OR(Q55="",BM55="",BM55=0),"",Q55/BM55) | AE55: =IF(OR(T55="",BM55="",BM55=0),"",T55/BM55) | AF55: =IF(OR(W55="",BM55="",BM55=0),"",W55/BM55) | AG55: =IF(OR(Z55="",BM55="",BM55=0),"",Z55/BM55) | AH55: =IF(OR(AC55="",BM55="",BM55=0),"",AC55/BM55) | AJ55: 95.3 | AL55: 4.7 | AO55: 31.2 | AP55: 10.4 | AQ55: 15.7 | AU55: 11.1 | AZ55: 22 | BA55: 8.2 | BB55: 34 | BD55: 27.8 | BE55: 5.5 | BK55: 14.3 | BL55: Taiwan Semiconductor Manufacturing Company Limited | Alphabet Incorporated - Class A | NVIDIA Corporation | Alibaba Group Holding Limited - W | Meta Platforms Incorporated | BM55: 15.3 | BN55: Very High | BO55: Equity Global Global | BP55: ThebenchmarkforPBVG40Fisacompositeof35%DowJonesIndustrialAverage, 35% customised index by S&P Dow Jones Indices, LLC based on the top 30 constituents of the S&P BMI Asia Ex-Japan Index, 20% VN30 Index and 10% 3-Month Kuala Lumpur Interbank Offered Rate (KLIBOR). UnderlyingindexdataaresourcedfromLipper,S&PDowJonesIndices,LLCand Bank Negara Malaysia and expressed in Ringgit terms. | BQ55: 0.3715 | BR55: 2026-06-04 | BS55: 0.3605 | BT55: -2.96 | BU55: 11
A56: PUBLIC FAR-EAST PROPERTY & RESORTS FUND | B56: PFEPRF | C56: Conventional | D56: Equity | E56: Capital Growth | F56: 5 | G56: Annual | H56: 188.44 | I56: 10.07.2007 | J56: Qualified | K56: 100 | L56: 5/5 | M56: Qualified (WA: +2.50%) — YTD✔ 1Y✔ 3Y✔ 5Y✔ 10Y✔ | N56: 2.5 | O56: 4.29 | P56: 4.05 | Q56: 0.24 | R56: 11.8 | S56: 10.19 | T56: 1.61 | U56: 7.32 | V56: 4.62 | W56: 2.7 | X56: 2.59 | Y56: -0.72 | Z56: 3.31 | AA56: 2.82 | AB56: 0.54 | AC56: 2.28 | AD56: =IF(OR(Q56="",BM56="",BM56=0),"",Q56/BM56) | AE56: =IF(OR(T56="",BM56="",BM56=0),"",T56/BM56) | AF56: =IF(OR(W56="",BM56="",BM56=0),"",W56/BM56) | AG56: =IF(OR(Z56="",BM56="",BM56=0),"",Z56/BM56) | AH56: =IF(OR(AC56="",BM56="",BM56=0),"",AC56/BM56) | AI56: 24.2 | AJ56: 59.6 | AL56: 16.2 | AR56: 21.7 | AU56: 7.7 | AV56: 3.3 | AY56: 16.4 | BJ56: 83.8 | BL56: Goodman Group | China Resources Land Limited | IGB Real Estate Investment Trust | Mitsui Fudosan Company Limited | Sun Hung Kai Properties Limited | BM56: 10.8 | BN56: High | BO56: Equity Sector Real Asia | BQ56: 0.3479 | BR56: 2013-05-20 | BS56: 0.2728 | BT56: -21.59 | BU56: 4774
A57: PUBLIC DIVIDEND SELECT FUND | B57: PDSF | C57: Conventional | D57: Equity | E57: Income | F57: 4 | G57: Semi-Annual | H57: 854.71 | I57: 03.05.2005 | J57: Qualified | K57: 80 | L57: 4/5 | M57: Qualified (WA: +2.40%) — YTD✘ 1Y✔ 3Y✔ 5Y✔ 10Y✔ | N57: 2.4 | O57: 3.3 | P57: 3.49 | Q57: -0.19 | R57: 13.28 | S57: 11.41 | T57: 1.87 | U57: 10.25 | V57: 7.22 | W57: 3.03 | X57: 4.4 | Y57: 2.04 | Z57: 2.36 | AA57: 3.51 | AB57: 1.3 | AC57: 2.21 | AD57: =IF(OR(Q57="",BM57="",BM57=0),"",Q57/BM57) | AE57: =IF(OR(T57="",BM57="",BM57=0),"",T57/BM57) | AF57: =IF(OR(W57="",BM57="",BM57=0),"",W57/BM57) | AG57: =IF(OR(Z57="",BM57="",BM57=0),"",Z57/BM57) | AH57: =IF(OR(AC57="",BM57="",BM57=0),"",AC57/BM57) | AI57: 76.6 | AJ57: 20.8 | AL57: 2.6 | AO57: 16.4 | AS57: 4.4 | BA57: 7.6 | BC57: 46.2 | BD57: 10.7 | BE57: 14.9 | BG57: 9.2 | BL57: Public Bank Berhad | Malayan Banking Berhad | IGB Real Estate Investment Trust | CIMB Group Holdings Berhad | Tenaga Nasional Berhad | BM57: 6.9 | BN57: Low | BO57: Equity Malaysia Income Domestic 30% of the fund’s NAV | BQ57: 0.3542 | BR57: 2007-10-31 | BS57: 0.2945 | BT57: -16.85 | BU57: 6802
A58: PUBLIC SINGAPORE EQUITY FUND | B58: PSGEF | C58: Conventional | D58: Equity | E58: Capital Growth | F58: 5 | G58: Incidental | H58: 608.44 | I58: 07.06.2011 | J58: Qualified | K58: 80 | L58: 4/5 | M58: Qualified (WA: +2.26%) — YTD✔ 1Y✔ 3Y✔ 5Y✘ 10Y✔ | N58: 2.26 | O58: 4.11 | P58: -0.76 | Q58: 4.87 | R58: 18.77 | S58: 8.17 | T58: 10.6 | U58: 11.64 | V58: 10.82 | W58: 0.82 | X58: 6.6 | Y58: 7.37 | Z58: -0.77 | AA58: 7.47 | AB58: 5.55 | AC58: 1.92 | AD58: =IF(OR(Q58="",BM58="",BM58=0),"",Q58/BM58) | AE58: =IF(OR(T58="",BM58="",BM58=0),"",T58/BM58) | AF58: =IF(OR(W58="",BM58="",BM58=0),"",W58/BM58) | AG58: =IF(OR(Z58="",BM58="",BM58=0),"",Z58/BM58) | AH58: =IF(OR(AC58="",BM58="",BM58=0),"",AC58/BM58) | AI58: 0.9 | AJ58: 95 | AL58: 4.1 | AO58: 10.8 | AP58: 8.6 | AV58: 75.6 | BA58: 23.1 | BB58: 16.1 | BC58: 36.8 | BD58: 16.7 | BE58: 3.2 | BL58: DBS Group Holdings Limited | Oversea-Chinese Banking Corporation Limited | Taiwan Semiconductor Manufacturing Company Limited | CSE Global Limited | Singapore Technologies Engineering Limited | BM58: 9.4 | BN58: Moderate | BO58: Equity Singapore ASEAN | BQ58: 0.4408 | BR58: 2026-06-03 | BS58: 0.4229 | BT58: -4.06 | BU58: 12
A59: PB EURO PACIFIC EQUITY FUND | B59: PBEPEF | C59: Conventional | D59: Equity | E59: Capital Growth | F59: 5 | G59: Incidental | H59: 64.44 | I59: 08.06.2007 | J59: Qualified | K59: 80 | L59: 4/5 | M59: Qualified (WA: +2.20%) — YTD✔ 1Y✘ 3Y✔ 5Y✔ 10Y✔ | N59: 2.2 | O59: 8.54 | P59: 8.08 | Q59: 0.46 | R59: 25.81 | S59: 26 | T59: -0.19 | U59: 15.72 | V59: 11.88 | W59: 3.84 | X59: 7.36 | Y59: 5.25 | Z59: 2.11 | AA59: 8.58 | AB59: 7.62 | AC59: 0.96 | AD59: =IF(OR(Q59="",BM59="",BM59=0),"",Q59/BM59) | AE59: =IF(OR(T59="",BM59="",BM59=0),"",T59/BM59) | AF59: =IF(OR(W59="",BM59="",BM59=0),"",W59/BM59) | AG59: =IF(OR(Z59="",BM59="",BM59=0),"",Z59/BM59) | AH59: =IF(OR(AC59="",BM59="",BM59=0),"",AC59/BM59) | AI59: 1.1 | AJ59: 97.1 | AL59: 1.8 | AO59: 11.9 | AP59: 13.6 | AQ59: 28.5 | AS59: 7.5 | AU59: 19.8 | BA59: 18.5 | BB59: 41.1 | BC59: 1.1 | BD59: 24.6 | BE59: 12.9 | BL59: Taiwan Semiconductor Manufacturing Company Limited | Samsung Electronics Company Limited | Alibaba Group Holding Limited - W | Tencent Holdings Limited | HD Hyundai Electric Company Limited | BM59: 16.6 | BN59: Very High | BO59: Equity Global Asia | BP59: ThebenchmarkforPBEPEFisacompositeof50%MSCIACFar-EastEx-Japan Index(priorto30April2021),50%S&PPanAsiaEx-Japan,Australia,NewZealand &IndiaLargeCapIndex(30April2021to1January2025),50%S&PPanAsiaEx- Japan, Australia, New Zealand & India LargeCap 8% Capped Index (w.e.f. 2 January 2025), 40% STOXX Europe 50 Index and 10% Tokyo Stock Price Index. UnderlyingindexdataaresourcedfromS&PDowJonesIndices,LLCandLipper and expressed in Ringgit terms. | BQ59: 0.4973 | BR59: 2026-06-04 | BS59: 0.4921 | BT59: -1.05 | BU59: 11
A60: PUBLIC EQUITY FUND | B60: PEF | C60: Conventional | D60: Equity | E60: Capital Growth | F60: 4 | G60: Incidental | H60: 458.18 | I60: 15.08.2001 | J60: Qualified | K60: 80 | L60: 4/5 | M60: Qualified (WA: +1.87%) — YTD✘ 1Y✔ 3Y✔ 5Y✔ 10Y✔ | N60: 1.87 | O60: 1.7 | P60: 2.49 | Q60: -0.79 | R60: 12.54 | S60: 11.8 | T60: 0.74 | U60: 9.44 | V60: 6.72 | W60: 2.72 | X60: 3 | Y60: 1.46 | Z60: 1.54 | AA60: 2.48 | AB60: 0.29 | AC60: 2.19 | AD60: =IF(OR(Q60="",BM60="",BM60=0),"",Q60/BM60) | AE60: =IF(OR(T60="",BM60="",BM60=0),"",T60/BM60) | AF60: =IF(OR(W60="",BM60="",BM60=0),"",W60/BM60) | AG60: =IF(OR(Z60="",BM60="",BM60=0),"",Z60/BM60) | AH60: =IF(OR(AC60="",BM60="",BM60=0),"",AC60/BM60) | AI60: 68.3 | AJ60: 26.8 | AL60: 4.9 | AO60: 21 | AS60: 2.1 | AU60: 3.7 | BB60: 8.4 | BC60: 35.9 | BD60: 25.7 | BG60: 10.1 | BI60: 5.1 | BL60: Tenaga Nasional Berhad | Public Bank Berhad | Malayan Banking Berhad | LPI Capital Berhad | NVIDIA Corporation | BM60: 6.7 | BN60: Low | BO60: Equity Malaysia Domestic 30% of the fund’s NAV | BP60: Note: Distribution yield simply measures the level of distributions and is Kuala Lumpur Composite Index (prior to 6 July 2009). not a measure of fund performance. FTSE Bursa Malaysia KLCI (w.e.f. 6 July 2009). | BQ60: 0.4767 | BR60: 2007-10-31 | BS60: 0.2639 | BT60: -44.64 | BU60: 6802
A61: PB ISLAMIC EQUITY FUND | B61: PBIEF | C61: Conventional | D61: Equity | E61: Capital Growth | F61: 4 | G61: Incidental | H61: 214.41 | I61: 05.09.2005 | J61: Qualified | K61: 100 | L61: 5/5 | M61: Qualified (WA: +1.74%) — YTD✔ 1Y✔ 3Y✔ 5Y✔ 10Y✔ | N61: 1.74 | O61: 5.41 | P61: 5.14 | Q61: 0.27 | R61: 14.25 | S61: 12.81 | T61: 1.44 | U61: 6.91 | V61: 5.79 | W61: 1.12 | X61: 1.8 | Y61: -0.85 | Z61: 2.65 | AA61: 3.07 | AB61: 0.41 | AC61: 2.66 | AD61: =IF(OR(Q61="",BM61="",BM61=0),"",Q61/BM61) | AE61: =IF(OR(T61="",BM61="",BM61=0),"",T61/BM61) | AF61: =IF(OR(W61="",BM61="",BM61=0),"",W61/BM61) | AG61: =IF(OR(Z61="",BM61="",BM61=0),"",Z61/BM61) | AH61: =IF(OR(AC61="",BM61="",BM61=0),"",AC61/BM61) | AI61: 70 | AJ61: 23.3 | AL61: 6.7 | AO61: 11.4 | AP61: 7.7 | AU61: 4.2 | BA61: 19.8 | BB61: 13.4 | BD61: 15.2 | BF61: 13.8 | BG61: 9.5 | BL61: Tenaga Nasional Berhad | Press Metal Aluminium Holdings Berhad | Taiwan Semiconductor Manufacturing Company Limited | HEICO Corporation | Broadcom Incorporated | BM61: 8.2 | BN61: Moderate | BO61: Equity Malaysia | BQ61: 0.393 | BR61: 2007-07-24 | BS61: 0.316 | BT61: -19.59 | BU61: 6901
A62: PUBLIC REGULARSAVINGS FUND | B62: PRSF | C62: Conventional | D62: Equity | E62: Capital Growth + Income | F62: 4 | G62: Annual | H62: 3570.49 | I62: 25.04.1994 | J62: Qualified | K62: 60 | L62: 3/5 | M62: Qualified (WA: +1.73%) — YTD✘ 1Y✘ 3Y✔ 5Y✔ 10Y✔ | N62: 1.73 | O62: 1.89 | P62: 3.49 | Q62: -1.6 | R62: 8.48 | S62: 11.41 | T62: -2.93 | U62: 10.01 | V62: 7.22 | W62: 2.79 | X62: 4.66 | Y62: 2.04 | Z62: 2.62 | AA62: 4.51 | AB62: 1.3 | AC62: 3.21 | AD62: =IF(OR(Q62="",BM62="",BM62=0),"",Q62/BM62) | AE62: =IF(OR(T62="",BM62="",BM62=0),"",T62/BM62) | AF62: =IF(OR(W62="",BM62="",BM62=0),"",W62/BM62) | AG62: =IF(OR(Z62="",BM62="",BM62=0),"",Z62/BM62) | AH62: =IF(OR(AC62="",BM62="",BM62=0),"",AC62/BM62) | AI62: 75.8 | AJ62: 21.2 | AL62: 3 | AO62: 16.4 | AS62: 4.8 | BC62: 41 | BD62: 11.5 | BE62: 15.3 | BF62: 7.1 | BG62: 10.1 | BL62: Public Bank Berhad | Malayan Banking Berhad | Tenaga Nasional Berhad | CIMB Group Holdings Berhad | Gamuda Berhad | BM62: 6.1 | BN62: Low | BO62: Equity Malaysia Domestic 25% of the fund’s NAV | BP62: 2026 1.82 31.3.26 2.8 Kuala Lumpur Composite Index (prior to 6 July 2009). Note: Distribution yield simply measures the level of distributions and is FTSE BursaMalaysiaTop100Index(6July2009to29April2015),90%FTSE not a measure of fund performance. BursaMalaysiaTop100Indexand10%3-MonthKualaLumpurInterbankOffered Rate (KLIBOR) (w.e.f. 30 April 2015). Underlying index data are sourced from Lipper and Bank Negara Malaysia. | BQ62: 1.09 | BR62: 2000-02-17 | BS62: 0.65 | BT62: -40.37 | BU62: 9615
A63: PB SUSTAINABLE GROWTH FUND | B63: PBSTGRF | C63: Conventional | D63: Equity | E63: Capital Growth | F63: 4 | G63: Incidental | H63: 278.08 | I63: 05.09.2023 | J63: Qualified | K63: 100 | L63: 2/2 | M63: Qualified (WA: +1.72%) — YTD✔ 1Y✔ | N63: 1.72 | O63: 4.02 | P63: 3.73 | Q63: 0.29 | R63: 13.81 | S63: 11.62 | T63: 2.19 | AD63: =IF(OR(Q63="",BM63="",BM63=0),"",Q63/BM63) | AE63: =IF(OR(T63="",BM63="",BM63=0),"",T63/BM63) | AF63: =IF(OR(W63="",BM63="",BM63=0),"",W63/BM63) | AG63: =IF(OR(Z63="",BM63="",BM63=0),"",Z63/BM63) | AH63: =IF(OR(AC63="",BM63="",BM63=0),"",AC63/BM63) | AI63: 67.4 | AJ63: 29.8 | AL63: 2.8 | AO63: 15.7 | AP63: 11.2 | AU63: 2.9 | BB63: 15 | BC63: 30.7 | BD63: 20 | BF63: 8.7 | BG63: 10.1 | BL63: Taiwan Semiconductor Manufacturing Company Limited | Malayan Banking Berhad | Tenaga Nasional Berhad | Public Bank Berhad | Sunway Berhad | BO63: Equity Malaysia | BP63: Index data are sourced from Lipper. | BQ63: 0.3135 | BR63: 2026-05-14 | BS63: 0.3056 | BT63: -2.52 | BU63: 32
A64: PB SINGAPORE ADVANTAGE-30 EQUITY FUND | B64: PBSGA30EF | C64: Conventional | D64: Equity | E64: Capital Growth | F64: 5 | G64: Incidental | H64: 132.69 | I64: 11.05.2010 | J64: Qualified | K64: 60 | L64: 3/5 | M64: Qualified (WA: +1.69%) — YTD✔ 1Y✔ 3Y✘ 5Y✘ 10Y✔ | N64: 1.69 | O64: 5.71 | P64: -0.76 | Q64: 6.47 | R64: 21.1 | S64: 8.17 | T64: 12.93 | U64: 9.32 | V64: 10.82 | W64: -1.5 | X64: 7.1 | Y64: 7.37 | Z64: -0.27 | AA64: 6.2 | AB64: 5.55 | AC64: 0.65 | AD64: =IF(OR(Q64="",BM64="",BM64=0),"",Q64/BM64) | AE64: =IF(OR(T64="",BM64="",BM64=0),"",T64/BM64) | AF64: =IF(OR(W64="",BM64="",BM64=0),"",W64/BM64) | AG64: =IF(OR(Z64="",BM64="",BM64=0),"",Z64/BM64) | AH64: =IF(OR(AC64="",BM64="",BM64=0),"",AC64/BM64) | AJ64: 94.6 | AL64: 5.4 | AO64: 12.7 | AP64: 4.4 | AU64: 2.9 | AV64: 74.6 | BA64: 22.5 | BB64: 17.2 | BC64: 36.1 | BD64: 17 | BE64: 1.8 | BL64: DBS Group Holdings Limited | Oversea-Chinese Banking Corporation Limited | United Overseas Bank Limited | Broadcom Incorporated | Flex Limited | BM64: 9.3 | BN64: Moderate | BO64: Equity Singapore ASEAN | BP64: 2020 1.25 30.06.20 5.4 ThebenchmarkforPBSGA30EFistheStraitsTimesIndex(priorto30April2016), MSCI Singapore Index (30 April 2016 to 29 April 2021), S&P Singapore 2021 1.50 30.06.21 6.0 LargeMidCap 10% Capped Index (w.e.f. 30 April 2021). 2022 0.80 30.06.22 3.4 UnderlyingindexdataaresourcedfromS&PDowJonesIndices,LLCandLipper 2023 1.00 30.06.23 4.0 and expressed in Ringgit terms. Note: Distribution yield simply measures the level of distributions and is not a | BQ64: 0.3721 | BR64: 2026-06-03 | BS64: 0.3542 | BT64: -4.81 | BU64: 12
A65: PUBLIC OPTIMAL GROWTH FUND | B65: POGF | C65: Conventional | D65: Equity | E65: Capital Growth + Income | F65: 4 | G65: Annual | H65: 211.85 | I65: 08.06.2010 | J65: Qualified | K65: 60 | L65: 3/5 | M65: Qualified (WA: +1.55%) — YTD✘ 1Y✘ 3Y✔ 5Y✔ 10Y✔ | N65: 1.55 | O65: 2.1 | P65: 3.75 | Q65: -1.65 | R65: 12.23 | S65: 12.31 | T65: -0.08 | U65: 9.38 | V65: 7.59 | W65: 1.79 | X65: 3.85 | Y65: 1.87 | Z65: 1.98 | AA65: 3.89 | AB65: 1.03 | AC65: 2.86 | AD65: =IF(OR(Q65="",BM65="",BM65=0),"",Q65/BM65) | AE65: =IF(OR(T65="",BM65="",BM65=0),"",T65/BM65) | AF65: =IF(OR(W65="",BM65="",BM65=0),"",W65/BM65) | AG65: =IF(OR(Z65="",BM65="",BM65=0),"",Z65/BM65) | AH65: =IF(OR(AC65="",BM65="",BM65=0),"",AC65/BM65) | AI65: 76.1 | AJ65: 21.3 | AL65: 2.6 | AO65: 11.1 | AP65: 3.4 | AT65: 4.3 | AU65: 2.5 | BA65: 14.6 | BB65: 8.1 | BC65: 37.8 | BD65: 18.9 | BF65: 8.1 | BL65: Public Bank Berhad | Malayan Banking Berhad | Tenaga Nasional Berhad | IGB Real Estate Investment Trust | Sunway Berhad | BM65: 9.6 | BN65: Moderate | BO65: Equity Malaysia Income Domestic 25% of the fund’s NAV | BQ65: 0.3813 | BR65: 2024-07-11 | BS65: 0.3646 | BT65: -4.38 | BU65: 704
A66: PUBLIC INDEX FUND | B66: PIX | C66: Shariah | D66: Equity | E66: Capital Growth | F66: 4 | G66: Incidental | H66: 488.48 | I66: 02.03.1992 | J66: Qualified | K66: 80 | L66: 4/5 | M66: Qualified (WA: +1.55%) — YTD✘ 1Y✔ 3Y✔ 5Y✔ 10Y✔ | N66: 1.55 | O66: 1.92 | P66: 3.75 | Q66: -1.83 | R66: 14.48 | S66: 12.31 | T66: 2.17 | U66: 8.97 | V66: 7.59 | W66: 1.38 | X66: 3.85 | Y66: 1.87 | Z66: 1.98 | AA66: 2.8 | AB66: 1.03 | AC66: 1.77 | AD66: =IF(OR(Q66="",BM66="",BM66=0),"",Q66/BM66) | AE66: =IF(OR(T66="",BM66="",BM66=0),"",T66/BM66) | AF66: =IF(OR(W66="",BM66="",BM66=0),"",W66/BM66) | AG66: =IF(OR(Z66="",BM66="",BM66=0),"",Z66/BM66) | AH66: =IF(OR(AC66="",BM66="",BM66=0),"",AC66/BM66) | AI66: 96.5 | AL66: 3.5 | BA66: 11.9 | BC66: 45.2 | BD66: 10.4 | BF66: 14.3 | BG66: 9.9 | BL66: Tenaga Nasional Berhad | LPI Capital Berhad | Public Bank Berhad | Malayan Banking Berhad | CIMB Group Holdings Berhad | BM66: 7.9 | BN66: Moderate | BO66: Equity Malaysia 100% Domestic | BP66: Kuala Lumpur Composite Index (prior to 6 July 2009). FTSE Bursa Malaysia Top 100 Index (w.e.f. 6 July 2009). Underlying index data are sourced from Lipper. | BQ66: 1.101 | BR66: 2008-01-11 | BS66: 0.7419 | BT66: -32.62 | BU66: 6730
A67: PUBLIC SELECT ALPHA-30 FUND | B67: PSA30F | C67: Conventional | D67: Equity | E67: Capital Growth | F67: 4 | G67: Incidental | H67: 57.08 | I67: 07.04.2009 | J67: Qualified | K67: 80 | L67: 4/5 | M67: Qualified (WA: +1.49%) — YTD✘ 1Y✔ 3Y✔ 5Y✔ 10Y✔ | N67: 1.49 | O67: 2.41 | P67: 2.49 | Q67: -0.08 | R67: 13.52 | S67: 11.8 | T67: 1.72 | U67: 7.89 | V67: 6.72 | W67: 1.17 | X67: 2.03 | Y67: 1.46 | Z67: 0.57 | AA67: 4.44 | AB67: 0.29 | AC67: 4.15 | AD67: =IF(OR(Q67="",BM67="",BM67=0),"",Q67/BM67) | AE67: =IF(OR(T67="",BM67="",BM67=0),"",T67/BM67) | AF67: =IF(OR(W67="",BM67="",BM67=0),"",W67/BM67) | AG67: =IF(OR(Z67="",BM67="",BM67=0),"",Z67/BM67) | AH67: =IF(OR(AC67="",BM67="",BM67=0),"",AC67/BM67) | AI67: 76.5 | AJ67: 20.5 | AL67: 3 | AO67: 15 | AS67: 2 | AU67: 3.5 | BA67: 15.5 | BB67: 7.7 | BC67: 30 | BD67: 19.5 | BG67: 9.6 | BL67: Tenaga Nasional Berhad | Malayan Banking Berhad | Public Bank Berhad | NVIDIA Corporation | Meta Platforms Incorporated | BM67: 8.2 | BN67: Moderate | BO67: Equity Malaysia Domestic 30% of the fund’s NAV | BP67: Kuala Lumpur Composite Index (prior to 6 July 2009). FTSE Bursa Malaysia KLCI (w.e.f. 6 July 2009). | BQ67: 0.3961 | BR67: 2026-05-14 | BS67: 0.3842 | BT67: -3 | BU67: 32
A68: PUBLIC ISLAMIC GROWTH & INCOME FUND | B68: PISGIF | C68: Shariah | D68: Equity | E68: Capital Growth + Income | F68: 4 | G68: Annual | H68: 121.91 | I68: 07.01.2014 | J68: Qualified | K68: 60 | L68: 3/5 | M68: Qualified (WA: +1.37%) — YTD✘ 1Y✘ 3Y✔ 5Y✔ 10Y✔ | N68: 1.37 | O68: 2.6 | P68: 5.14 | Q68: -2.54 | R68: 11.5 | S68: 12.81 | T68: -1.31 | U68: 7.41 | V68: 5.79 | W68: 1.62 | X68: 1.96 | Y68: -0.85 | Z68: 2.81 | AA68: 2.67 | AB68: 0.41 | AC68: 2.26 | AD68: =IF(OR(Q68="",BM68="",BM68=0),"",Q68/BM68) | AE68: =IF(OR(T68="",BM68="",BM68=0),"",T68/BM68) | AF68: =IF(OR(W68="",BM68="",BM68=0),"",W68/BM68) | AG68: =IF(OR(Z68="",BM68="",BM68=0),"",Z68/BM68) | AH68: =IF(OR(AC68="",BM68="",BM68=0),"",AC68/BM68) | AI68: 75.7 | AJ68: 21.5 | AL68: 2.8 | AO68: 10.6 | AP68: 6.9 | AS68: 4 | BA68: 11.1 | BC68: 17 | BD68: 24.4 | BF68: 11.8 | BH68: 12.5 | BL68: Telekom Malaysia Berhad | Tenaga Nasional Berhad | IHH Healthcare Berhad | Gamuda Berhad | Taiwan Semiconductor Manufacturing Company Limited | BM68: 6.6 | BN68: Low | BO68: Equity Malaysia Domestic | BP68: 2022 0.20 30.12.22 0.9 | BQ68: 0.2778 | BR68: 2026-05-06 | BS68: 0.2706 | BT68: -2.59 | BU68: 40
A69: PUBLIC e-CARBON EFFICIENT FUND | B69: PeCEF | C69: Conventional | D69: Equity | E69: Capital Growth | F69: 5 | G69: Incidental | H69: 401.64 | I69: 09.02.2021 | J69: Qualified | K69: 50 | L69: 2/4 | M69: Qualified (WA: +1.19%) — YTD✘ 1Y✔ 3Y✔ 5Y✘ | N69: 1.19 | O69: 2.61 | P69: 2.96 | Q69: -0.35 | R69: 27.18 | S69: 20.35 | T69: 6.83 | U69: 15.46 | V69: 14.77 | W69: 0.69 | X69: 8.47 | Y69: 9.55 | Z69: -1.08 | AD69: =IF(OR(Q69="",BM69="",BM69=0),"",Q69/BM69) | AE69: =IF(OR(T69="",BM69="",BM69=0),"",T69/BM69) | AF69: =IF(OR(W69="",BM69="",BM69=0),"",W69/BM69) | AG69: =IF(OR(Z69="",BM69="",BM69=0),"",Z69/BM69) | AH69: =IF(OR(AC69="",BM69="",BM69=0),"",AC69/BM69) | AJ69: 88.8 | AL69: 11.2 | AO69: 49.2 | AP69: 12.4 | AR69: 8 | AU69: 9.3 | AW69: 6.9 | BA69: 7.4 | BB69: 32.2 | BC69: 7.1 | BD69: 29.1 | BE69: 13 | BL69: Alphabet Incorporated - Class A | Taiwan Semiconductor Manufacturing Company Limited | NVIDIA Corporation | Alibaba Group Holding Limited - W | Meta Platforms Incorporated | BM69: 14.2 | BN69: Very High | BO69: Equity Global Global | BP69: ThebenchmarkforPeCEFisacompositeof90%customisedindexbyS&PDow JonesIndices,LLCbasedontheconstituentswithlowercarbonfootprintoftheS&P Global1200Scored&ScreenedIndexand10%3-MonthKualaLumpurInterbank Offered Rate (KLIBOR). Underlying indexdata are sourced from S&P Dow Jones Indices, LLC and Bank Negara Malaysia and expressed in Ringgit terms. | BQ69: 0.4136 | BR69: 2026-06-04 | BS69: 0.4032 | BT69: -2.51 | BU69: 11
A70: PUBLIC ISLAMIC DIVIDEND FUND | B70: PIDF | C70: Shariah | D70: Equity | E70: Income | F70: 4 | G70: Semi-Annual | H70: 3422.73 | I70: 14.02.2006 | J70: Qualified | K70: 60 | L70: 3/5 | M70: Qualified (WA: +1.16%) — YTD✘ 1Y✘ 3Y✔ 5Y✔ 10Y✔ | N70: 1.16 | O70: 3.52 | P70: 4.74 | Q70: -1.22 | R70: 10.95 | S70: 11.86 | T70: -0.91 | U70: 6.72 | V70: 5.62 | W70: 1.1 | X70: 1.46 | Y70: -0.4 | Z70: 1.86 | AA70: 3.75 | AB70: 0.75 | AC70: 3 | AD70: =IF(OR(Q70="",BM70="",BM70=0),"",Q70/BM70) | AE70: =IF(OR(T70="",BM70="",BM70=0),"",T70/BM70) | AF70: =IF(OR(W70="",BM70="",BM70=0),"",W70/BM70) | AG70: =IF(OR(Z70="",BM70="",BM70=0),"",Z70/BM70) | AH70: =IF(OR(AC70="",BM70="",BM70=0),"",AC70/BM70) | AI70: 72 | AJ70: 22.7 | AL70: 5.3 | AO70: 10.1 | AP70: 8.3 | AS70: 3.5 | AU70: 0.8 | BA70: 10.5 | BC70: 10.5 | BD70: 22.3 | BF70: 18 | BG70: 9.6 | BL70: Tenaga Nasional Berhad | Taiwan Semiconductor Manufacturing Company Limited | Telekom Malaysia Berhad | Gamuda Berhad | Amazon.com Incorporated | BM70: 7.6 | BN70: Low | BO70: Equity Malaysia | BQ70: 0.4312 | BR70: 2020-08-06 | BS70: 0.3713 | BT70: -13.89 | BU70: 2139
A71: PUBLIC ISLAMIC ALPHA-40 GROWTH FUND | B71: PIA40GF | C71: Shariah | D71: Equity | E71: Capital Growth | F71: 4 | G71: Incidental | H71: 414.07 | I71: 16.11.2010 | J71: Qualified | K71: 60 | L71: 3/5 | M71: Qualified (WA: +1.11%) — YTD✘ 1Y✘ 3Y✔ 5Y✔ 10Y✔ | N71: 1.11 | O71: 6.06 | P71: 8.56 | Q71: -2.5 | R71: 18.86 | S71: 19.55 | T71: -0.69 | U71: 9.53 | V71: 8.18 | W71: 1.35 | X71: 2.21 | Y71: 0.61 | Z71: 1.6 | AA71: 5.02 | AB71: 2.39 | AC71: 2.63 | AD71: =IF(OR(Q71="",BM71="",BM71=0),"",Q71/BM71) | AE71: =IF(OR(T71="",BM71="",BM71=0),"",T71/BM71) | AF71: =IF(OR(W71="",BM71="",BM71=0),"",W71/BM71) | AG71: =IF(OR(Z71="",BM71="",BM71=0),"",Z71/BM71) | AH71: =IF(OR(AC71="",BM71="",BM71=0),"",AC71/BM71) | AI71: 74.4 | AJ71: 22.6 | AL71: 3 | AO71: 18.5 | AP71: 4.1 | BA71: 11.3 | BB71: 9.4 | BC71: 10.6 | BD71: 27.7 | BF71: 21.4 | BL71: Telekom Malaysia Berhad | Tenaga Nasional Berhad | QL Resources Berhad | IHH Healthcare Berhad | Press Metal Aluminium Holdings Berhad | BM71: 8.4 | BN71: Moderate | BO71: Equity Malaysia Domestic | BQ71: 0.3981 | BR71: 2026-05-12 | BS71: 0.3942 | BT71: -0.98 | BU71: 34
A72: PUBLIC STRATEGIC GROWTH FUND | B72: PSTGF | C72: Conventional | D72: Equity | E72: Capital Growth | F72: 4 | G72: Incidental | H72: 383.53 | I72: 08.12.2014 | J72: Qualified | K72: 80 | L72: 4/5 | M72: Qualified (WA: +1.09%) — YTD✔ 1Y✘ 3Y✔ 5Y✔ 10Y✔ | N72: 1.09 | O72: 4.57 | P72: 4.16 | Q72: 0.41 | R72: 12.53 | S72: 16.23 | T72: -3.7 | U72: 10.86 | V72: 9.12 | W72: 1.74 | X72: 4.28 | Y72: 3.26 | Z72: 1.02 | AA72: 8.57 | AB72: 4.06 | AC72: 4.51 | AD72: =IF(OR(Q72="",BM72="",BM72=0),"",Q72/BM72) | AE72: =IF(OR(T72="",BM72="",BM72=0),"",T72/BM72) | AF72: =IF(OR(W72="",BM72="",BM72=0),"",W72/BM72) | AG72: =IF(OR(Z72="",BM72="",BM72=0),"",Z72/BM72) | AH72: =IF(OR(AC72="",BM72="",BM72=0),"",AC72/BM72) | AI72: 58.5 | AJ72: 22.1 | AL72: 19.4 | AO72: 6.5 | AP72: 5.3 | AQ72: 10.3 | BA72: 20.1 | BB72: 6.4 | BC72: 32.4 | BF72: 7.1 | BG72: 7 | BL72: Public Bank Berhad | Malayan Banking Berhad | HD Hyundai Electric Company Limited | Tenaga Nasional Berhad | Taiwan Semiconductor Manufacturing Company Limited | BM72: 8 | BN72: Moderate | BO72: Equity Malaysia Domestic 30% of the fund’s NAV | BP72: ThebenchmarkforPSTGFisacompositeof60%FTSEBursaMalaysiaKLCI,15% DowJonesIndustrialAverage,15%customisedindexbyMSCIbasedonthetop30 constituents of MSCI AC Far-East Ex-Japan Index (prior to 30 April 2021), 15% customisedindexbyS&PDowJonesIndices,LLCbasedonthetop30constituents oftheS&PBMIAsiaEx-JapanIndex(w.e.f.30April2021)and10%3-MonthKuala Lumpur Interbank Offered Rate (KLIBOR). UnderlyingindexdataaresourcedfromLipper,S&PDowJonesIndices,LLCand Bank Negara Malaysia and expressed in Ringgit terms. | BQ72: 0.5058 | BR72: 2026-05-07 | BS72: 0.4931 | BT72: -2.51 | BU72: 39
A73: PB U.S. EAGLE FUND | B73: PBUSEF | C73: Conventional | D73: Equity | E73: Capital Growth | F73: 5 | G73: Incidental | H73: 187.93 | I73: 05.01.2021 | J73: Qualified | K73: 25 | L73: 1/4 | M73: Qualified (WA: +1.01%) — YTD✘ 1Y✘ 3Y✔ 5Y✘ | N73: 1.01 | O73: -3.65 | P73: 1.13 | Q73: -4.78 | R73: 10.27 | S73: 11.51 | T73: -1.24 | U73: 12.36 | V73: 8.56 | W73: 3.8 | X73: 6.02 | Y73: 6.97 | Z73: -0.95 | AD73: =IF(OR(Q73="",BM73="",BM73=0),"",Q73/BM73) | AE73: =IF(OR(T73="",BM73="",BM73=0),"",T73/BM73) | AF73: =IF(OR(W73="",BM73="",BM73=0),"",W73/BM73) | AG73: =IF(OR(Z73="",BM73="",BM73=0),"",Z73/BM73) | AH73: =IF(OR(AC73="",BM73="",BM73=0),"",AC73/BM73) | AJ73: 95.6 | AL73: 4.4 | AO73: 75.5 | AP73: 10.2 | AQ73: 7.1 | AU73: 2.8 | BA73: 9.8 | BB73: 37.4 | BC73: 9.2 | BD73: 22.5 | BE73: 15 | BL73: Alphabet Incorporated - Class A | Goldman Sachs Group Incorporated | Costco Wholesale Corporation | NVIDIA Corporation | Tesla Incorporated | BM73: 16.4 | BN73: Very High | BO73: Equity U.S. Global | BP73: ThebenchmarkforPBUSEFisacompositeof90%DowJonesIndustrialAverage and 10% 3-Month Kuala Lumpur Interbank Offered Rate (KLIBOR). Underlying index data are sourced from Lipper and Bank Negara Malaysia and expressed in Ringgit terms. | BQ73: 0.3898 | BR73: 2025-11-03 | BS73: 0.3694 | BT73: -5.23 | BU73: 224
A74: PUBLIC AGGRESSIVE GROWTH FUND | B74: PAGF | C74: Conventional | D74: Equity | E74: Capital Growth | F74: 5 | G74: Incidental | H74: 249.53 | I74: 25.04.1994 | J74: Qualified | K74: 60 | L74: 3/5 | M74: Qualified (WA: +0.89%) — YTD✘ 1Y✘ 3Y✔ 5Y✔ 10Y✔ | N74: 0.89 | O74: 1.55 | P74: 2.49 | Q74: -0.94 | R74: 8.53 | S74: 11.8 | T74: -3.27 | U74: 7.48 | V74: 6.72 | W74: 0.76 | X74: 3.77 | Y74: 1.46 | Z74: 2.31 | AA74: 3.95 | AB74: 0.29 | AC74: 3.66 | AD74: =IF(OR(Q74="",BM74="",BM74=0),"",Q74/BM74) | AE74: =IF(OR(T74="",BM74="",BM74=0),"",T74/BM74) | AF74: =IF(OR(W74="",BM74="",BM74=0),"",W74/BM74) | AG74: =IF(OR(Z74="",BM74="",BM74=0),"",Z74/BM74) | AH74: =IF(OR(AC74="",BM74="",BM74=0),"",AC74/BM74) | AI74: 76.4 | AJ74: 19.1 | AL74: 4.5 | AO74: 13.7 | AS74: 2 | AU74: 3.4 | BB74: 7.2 | BC74: 32.9 | BD74: 20.1 | BF74: 11.4 | BG74: 9.1 | BL74: Public Bank Berhad | Tenaga Nasional Berhad | Malayan Banking Berhad | NVIDIA Corporation | Meta Platforms Incorporated | BM74: 7.8 | BN74: Moderate | BO74: Equity Malaysia Domestic 30% of the fund’s NAV | BP74: not a measure of fund performance. Kuala Lumpur Composite Index (prior to 6 July 2009). FTSE Bursa Malaysia KLCI (w.e.f. 6 July 2009). | BQ74: 1.17 | BR74: 2000-02-24 | BS74: 0.7072 | BT74: -39.56 | BU74: 9608
A75: PUBLIC e-ISLAMIC INNOVATIVE TECHNOLOGY FUND | B75: PeISITF | C75: Shariah | D75: Equity | E75: Capital Growth | F75: 5 | G75: Incidental | H75: 580.44 | I75: 25.05.2021 | J75: Qualified | K75: 66.7 | L75: 2/3 | M75: Qualified (WA: +0.81%) — YTD✔ 1Y✔ 3Y✘ | N75: 0.81 | O75: 16.54 | P75: 14.32 | Q75: 2.22 | R75: 60.36 | S75: 49.19 | T75: 11.17 | U75: 25.86 | V75: 29.11 | W75: -3.25 | AD75: =IF(OR(Q75="",BM75="",BM75=0),"",Q75/BM75) | AE75: =IF(OR(T75="",BM75="",BM75=0),"",T75/BM75) | AF75: =IF(OR(W75="",BM75="",BM75=0),"",W75/BM75) | AG75: =IF(OR(Z75="",BM75="",BM75=0),"",Z75/BM75) | AH75: =IF(OR(AC75="",BM75="",BM75=0),"",AC75/BM75) | AJ75: 95.1 | AL75: 4.9 | AO75: 61.3 | AP75: 12.9 | AQ75: 8.7 | AU75: 4.4 | AW75: 5.6 | BB75: 69.8 | BD75: 22.5 | BE75: 2.8 | BL75: Alphabet Incorporated - Class A | Taiwan Semiconductor Manufacturing Company Limited | Broadcom Incorporated | Microsoft Corporation | Advanced Micro Devices Incorporated | BM75: 17.6 | BN75: Very High | BO75: Equity Sector Global | BP75: The benchmark for PeISITF is a composite of 90% S&P Global 1200 Shariah Information Technology (Sector) 10% Capped Index and 10% 1-Month Islamic Interbank Money Market (IIMM) rate. Underlying indexdata are sourced from S&P Dow Jones Indices, LLC and Bank Negara Malaysia and expressed in Ringgit terms. | BQ75: 0.5439 | BR75: 2026-06-04 | BS75: 0.5246 | BT75: -3.55 | BU75: 11
A76: PUBLIC GROWTH FUND | B76: PGF | C76: Conventional | D76: Equity | E76: Capital Growth + Income | F76: 4 | G76: Incidental | H76: 774.8 | I76: 11.12.1984 | J76: Qualified | K76: 60 | L76: 3/5 | M76: Qualified (WA: +0.77%) — YTD✘ 1Y✘ 3Y✔ 5Y✔ 10Y✔ | N76: 0.77 | O76: -0.48 | P76: 2.49 | Q76: -2.97 | R76: 9.43 | S76: 11.8 | T76: -2.37 | U76: 7.1 | V76: 6.72 | W76: 0.38 | X76: 3.92 | Y76: 1.46 | Z76: 2.46 | AA76: 3.69 | AB76: 0.29 | AC76: 3.4 | AD76: =IF(OR(Q76="",BM76="",BM76=0),"",Q76/BM76) | AE76: =IF(OR(T76="",BM76="",BM76=0),"",T76/BM76) | AF76: =IF(OR(W76="",BM76="",BM76=0),"",W76/BM76) | AG76: =IF(OR(Z76="",BM76="",BM76=0),"",Z76/BM76) | AH76: =IF(OR(AC76="",BM76="",BM76=0),"",AC76/BM76) | AI76: 72.1 | AJ76: 22.6 | AL76: 5.3 | AO76: 15.6 | AS76: 2.2 | AU76: 4.8 | BB76: 8.2 | BC76: 30.8 | BD76: 22.6 | BF76: 8.3 | BG76: 9.9 | BL76: Tenaga Nasional Berhad | Public Bank Berhad | Telekom Malaysia Berhad | Malayan Banking Berhad | NVIDIA Corporation | BM76: 7.6 | BN76: Low | BO76: Equity Malaysia Domestic 30% of the fund’s NAV | BQ76: 0.77 | BR76: 2000-02-16 | BS76: 0.4944 | BT76: -35.79 | BU76: 9616
A77: PUBLIC ISLAMIC EQUITY FUND | B77: PIEF | C77: Shariah | D77: Equity | E77: Capital Growth | F77: 4 | G77: Incidental | H77: 1424.47 | I77: 28.05.2003 | J77: Qualified | K77: 60 | L77: 3/5 | M77: Qualified (WA: +0.73%) — YTD✘ 1Y✘ 3Y✔ 5Y✔ 10Y✔ | N77: 0.73 | O77: 1.62 | P77: 5.14 | Q77: -3.52 | R77: 11 | S77: 12.81 | T77: -1.81 | U77: 6.27 | V77: 5.79 | W77: 0.48 | X77: 1.33 | Y77: -0.85 | Z77: 2.18 | AA77: 3.37 | AB77: 0.41 | AC77: 2.96 | AD77: =IF(OR(Q77="",BM77="",BM77=0),"",Q77/BM77) | AE77: =IF(OR(T77="",BM77="",BM77=0),"",T77/BM77) | AF77: =IF(OR(W77="",BM77="",BM77=0),"",W77/BM77) | AG77: =IF(OR(Z77="",BM77="",BM77=0),"",Z77/BM77) | AH77: =IF(OR(AC77="",BM77="",BM77=0),"",AC77/BM77) | AI77: 68.4 | AJ77: 27.4 | AL77: 4.2 | AO77: 15.7 | AP77: 7.7 | AU77: 4 | BA77: 9.2 | BB77: 15.3 | BD77: 24.5 | BF77: 19.3 | BG77: 9.6 | BL77: Tenaga Nasional Berhad | Telekom Malaysia Berhad | IHH Healthcare Berhad | Taiwan Semiconductor Manufacturing Company Limited | Broadcom Incorporated | BM77: 7.5 | BN77: Low | BO77: Equity Malaysia Domestic | BP77: 2022 1.00 31.5.22 3.0 Kuala Lumpur Syariah Index (prior to 1 November 2007). FTSE Bursa Malaysia EMAS Shariah Index (w.e.f. 1 November 2007). 2023 1.00 31.5.23 3.2 | BQ77: 0.4248 | BR77: 2007-10-30 | BS77: 0.367 | BT77: -13.61 | BU77: 6803
A78: PUBLIC REGULAR SAVINGS SEQUEL FUND | B78: PRSSQF | C78: Conventional | D78: Equity | E78: Capital Growth + Income | F78: 4 | G78: Annual | H78: 42.98 | I78: 15.01.2016 | J78: Qualified | K78: 60 | L78: 3/5 | M78: Qualified (WA: +0.68%) — YTD✘ 1Y✘ 3Y✔ 5Y✔ 10Y✔ | N78: 0.68 | O78: -0.01 | P78: 3.49 | Q78: -3.5 | R78: 7.99 | S78: 11.41 | T78: -3.42 | U78: 8.8 | V78: 7.22 | W78: 1.58 | X78: 3.71 | Y78: 2.04 | Z78: 1.67 | AA78: 3.42 | AB78: 1.3 | AC78: 2.12 | AD78: =IF(OR(Q78="",BM78="",BM78=0),"",Q78/BM78) | AE78: =IF(OR(T78="",BM78="",BM78=0),"",T78/BM78) | AF78: =IF(OR(W78="",BM78="",BM78=0),"",W78/BM78) | AG78: =IF(OR(Z78="",BM78="",BM78=0),"",Z78/BM78) | AH78: =IF(OR(AC78="",BM78="",BM78=0),"",AC78/BM78) | AI78: 75.6 | AJ78: 19.4 | AL78: 5 | AO78: 15.5 | AS78: 3.9 | BA78: 11.3 | BC78: 24.5 | BD78: 17.2 | BE78: 14.1 | BF78: 12.3 | BL78: Tenaga Nasional Berhad | Public Bank Berhad | Telekom Malaysia Berhad | Press Metal Aluminium Holdings Berhad | IHH Healthcare Berhad | BM78: 8.2 | BN78: Moderate | BO78: Equity Malaysia Domestic 25% of the fund’s NAV | BP78: 2024 0.40 29.2.24 1.5 ThebenchmarkforPRSSQFisacompositeof90%FTSEBursaMalaysiaTop100 Index and 10% 3-Month Kuala Lumpur Interbank Offered Rate (KLIBOR). 2025 0.45 28.2.25 1.6 Underlying index data are sourced from Lipper and Bank Negara Malaysia. 2026 0.46 27.2.26 1.6 Note: Distribution yield simply measures the level of distributions and is | BQ78: 0.3154 | BR78: 2024-12-17 | BS78: 0.3009 | BT78: -4.6 | BU78: 545
A79: PUBLIC ISLAMIC ASIA LEADERS EQUITY FUND | B79: PIALEF | C79: Shariah | D79: Equity | E79: Capital Growth | F79: 5 | G79: Incidental | H79: 1773.91 | I79: 19.01.2010 | J79: Qualified | K79: 40 | L79: 2/5 | M79: Qualified (WA: +0.54%) — YTD✔ 1Y✔ 3Y✘ 5Y✘ 10Y✘ | N79: 0.54 | O79: 32.17 | P79: 28.78 | Q79: 3.39 | R79: 73.16 | S79: 64.12 | T79: 9.04 | U79: 18.8 | V79: 20.43 | W79: -1.63 | X79: 3.01 | Y79: 4.23 | Z79: -1.22 | AA79: 9.74 | AB79: 9.91 | AC79: -0.17 | AD79: =IF(OR(Q79="",BM79="",BM79=0),"",Q79/BM79) | AE79: =IF(OR(T79="",BM79="",BM79=0),"",T79/BM79) | AF79: =IF(OR(W79="",BM79="",BM79=0),"",W79/BM79) | AG79: =IF(OR(Z79="",BM79="",BM79=0),"",Z79/BM79) | AH79: =IF(OR(AC79="",BM79="",BM79=0),"",AC79/BM79) | AJ79: 95.8 | AL79: 4.2 | AO79: 13.9 | AP79: 35.8 | AQ79: 34.6 | AU79: 11.5 | BA79: 27.6 | BB79: 44 | BD79: 20.9 | BE79: 3.3 | BL79: SK Hynix Incorporated | Taiwan Semiconductor Manufacturing Company Limited | Samsung Electronics Company Limited | HD Hyundai Electric Company Limited | Delta Electronics Incorporated | BM79: 20.4 | BN79: Very High | BO79: Equity Asia Pacific Asia | BP79: ThebenchmarkforPIALEFisacompositeof90%customisedindexbyS&PDow JonesIndices,LLCbasedontop100constituentsbymarketcapitalisationofthe S&PShariahBMIAsiaEx-JapanIndexand10%3-MonthIslamicInterbankMoney Market (IIMM) rate. UnderlyingindexdataaresourcedfromS&PDowJonesIndices,LLCandBank Negara Malaysia and expressed in Ringgit terms. | BQ79: 0.7974 | BR79: 2026-06-04 | BS79: 0.7714 | BT79: -3.26 | BU79: 11
A80: PUBLIC SAVINGS FUND | B80: PSF | C80: Conventional | D80: Equity | E80: Capital Growth + Income | F80: 4 | G80: Annual | H80: 758.39 | I80: 29.03.1981 | J80: Qualified | K80: 80 | L80: 4/5 | M80: Qualified (WA: +0.50%) — YTD✔ 1Y✘ 3Y✔ 5Y✔ 10Y✔ | N80: 0.5 | O80: 2.93 | P80: 2.49 | Q80: 0.44 | R80: 6.96 | S80: 11.8 | T80: -4.84 | U80: 8.09 | V80: 6.72 | W80: 1.37 | X80: 2.68 | Y80: 1.46 | Z80: 1.22 | AA80: 2.65 | AB80: 0.29 | AC80: 2.36 | AD80: =IF(OR(Q80="",BM80="",BM80=0),"",Q80/BM80) | AE80: =IF(OR(T80="",BM80="",BM80=0),"",T80/BM80) | AF80: =IF(OR(W80="",BM80="",BM80=0),"",W80/BM80) | AG80: =IF(OR(Z80="",BM80="",BM80=0),"",Z80/BM80) | AH80: =IF(OR(AC80="",BM80="",BM80=0),"",AC80/BM80) | AI80: 76.2 | AJ80: 20.3 | AL80: 3.5 | AO80: 16.4 | AS80: 3.9 | BC80: 34.8 | BD80: 14.9 | BE80: 14 | BF80: 10.8 | BG80: 9.5 | BL80: LPI Capital Berhad | Tenaga Nasional Berhad | Public Bank Berhad | Malayan Banking Berhad | Alphabet Incorporated - Class A | BM80: 6.8 | BN80: Low | BO80: Equity Malaysia Domestic 30% of the fund’s NAV | BP80: Note: Distribution yield simply measures the level of distributions and is Kuala Lumpur Composite Index (prior to 6 July 2009). not a measure of fund performance. FTSE Bursa Malaysia KLCI (w.e.f. 6 July 2009). | BQ80: 1.07 | BR80: 2000-02-18 | BS80: 0.534 | BT80: -50.09 | BU80: 9614
A81: PUBLIC FAR-EAST ALPHA-30 FUND | B81: PFA30F | C81: Conventional | D81: Equity | E81: Capital Growth | F81: 5 | G81: Incidental | H81: 362.86 | I81: 06.04.2010 | J81: Qualified | K81: 60 | L81: 3/5 | M81: Qualified (WA: +0.33%) — YTD✔ 1Y✔ 3Y✘ 5Y✘ 10Y✔ | N81: 0.33 | O81: 14.43 | P81: 12.92 | Q81: 1.51 | R81: 45.54 | S81: 39.58 | T81: 5.96 | U81: 16.49 | V81: 17.82 | W81: -1.33 | X81: 3.09 | Y81: 3.52 | Z81: -0.43 | AA81: 9.36 | AB81: 9.35 | AC81: 0.01 | AD81: =IF(OR(Q81="",BM81="",BM81=0),"",Q81/BM81) | AE81: =IF(OR(T81="",BM81="",BM81=0),"",T81/BM81) | AF81: =IF(OR(W81="",BM81="",BM81=0),"",W81/BM81) | AG81: =IF(OR(Z81="",BM81="",BM81=0),"",Z81/BM81) | AH81: =IF(OR(AC81="",BM81="",BM81=0),"",AC81/BM81) | AJ81: 93.1 | AL81: 6.9 | AO81: 11.2 | AP81: 19.4 | AQ81: 26.2 | AR81: 4.5 | AU81: 29.9 | BA81: 13.7 | BB81: 41.5 | BC81: 3.5 | BD81: 24.6 | BE81: 9.3 | BL81: SK Hynix Incorporated | Samsung Electronics Company Limited | Taiwan Semiconductor Manufacturing Company Limited | Tencent Holdings Limited | Advanced Micro Devices Incorporated | BM81: 18.1 | BN81: Very High | BO81: Equity Asia Pacific Asia | BQ81: 0.795 | BR81: 2026-06-04 | BS81: 0.7652 | BT81: -3.75 | BU81: 11
A82: PUBLIC ISLAMIC SECTOR SELECT FUND | B82: PISSF | C82: Shariah | D82: Equity | E82: Capital Growth | F82: 4 | G82: Incidental | H82: 109.51 | I82: 13.11.2007 | J82: Qualified | K82: 40 | L82: 2/5 | M82: Qualified (WA: +0.29%) — YTD✘ 1Y✘ 3Y✘ 5Y✔ 10Y✔ | N82: 0.29 | O82: 4.34 | P82: 5.14 | Q82: -0.8 | R82: 10.76 | S82: 12.81 | T82: -2.05 | U82: 5.54 | V82: 5.79 | W82: -0.25 | X82: 1.3 | Y82: -0.85 | Z82: 2.15 | AA82: 1.74 | AB82: 0.41 | AC82: 1.33 | AD82: =IF(OR(Q82="",BM82="",BM82=0),"",Q82/BM82) | AE82: =IF(OR(T82="",BM82="",BM82=0),"",T82/BM82) | AF82: =IF(OR(W82="",BM82="",BM82=0),"",W82/BM82) | AG82: =IF(OR(Z82="",BM82="",BM82=0),"",Z82/BM82) | AH82: =IF(OR(AC82="",BM82="",BM82=0),"",AC82/BM82) | AI82: 75.8 | AJ82: 22.3 | AL82: 1.9 | AO82: 10.3 | AP82: 7.6 | AS82: 4.4 | BA82: 24.4 | BD82: 25.5 | BF82: 18 | BG82: 9.5 | BH82: 8.6 | BL82: Sunway Construction Group Berhad | Tenaga Nasional Berhad | Telekom Malaysia Berhad | IHH Healthcare Berhad | Taiwan Semiconductor Manufacturing Company Limited | BM82: 8.4 | BN82: Moderate | BO82: Equity Malaysia Domestic | BP82: Index data are sourced from Lipper. | BQ82: 0.3302 | BR82: 2013-11-19 | BS82: 0.2893 | BT82: -12.39 | BU82: 4591
A83: PB ASIA PACIFIC ENTERPRISES FUND | B83: PBAPENTF | C83: Conventional | D83: Equity | E83: Capital Growth | F83: 5 | G83: Incidental | H83: 63.82 | I83: 08.03.2011 | J83: Qualified | K83: 80 | L83: 4/5 | M83: Qualified (WA: +0.22%) — YTD✔ 1Y✘ 3Y✔ 5Y✔ 10Y✔ | N83: 0.22 | O83: 13.2 | P83: 11.64 | Q83: 1.56 | R83: 31.96 | S83: 33.52 | T83: -1.56 | U83: 13.33 | V83: 12.67 | W83: 0.66 | X83: 3.69 | Y83: 3.68 | Z83: 0.01 | AA83: 8.5 | AB83: 7.74 | AC83: 0.76 | AD83: =IF(OR(Q83="",BM83="",BM83=0),"",Q83/BM83) | AE83: =IF(OR(T83="",BM83="",BM83=0),"",T83/BM83) | AF83: =IF(OR(W83="",BM83="",BM83=0),"",W83/BM83) | AG83: =IF(OR(Z83="",BM83="",BM83=0),"",Z83/BM83) | AH83: =IF(OR(AC83="",BM83="",BM83=0),"",AC83/BM83) | AI83: 0.9 | AJ83: 96 | AL83: 3.1 | AO83: 6.6 | AP83: 27.7 | AQ83: 25.8 | AU83: 27.7 | AV83: 3.4 | BA83: 6.5 | BB83: 48.1 | BC83: 10.4 | BD83: 24.3 | BE83: 5.7 | BL83: Samsung Electronics Company Limited | Taiwan Semiconductor Manufacturing Company Limited | SK Hynix Incorporated | Alibaba Group Holding Limited - W | Tencent Holdings Limited | BM83: 15.1 | BN83: Very High | BO83: Equity Asia Pacific ex- Asia | BP83: Thebenchmark forPBAPENTF isa compositeof 55% S&P Asia50 Index,30% S&P Southeast Asia 40 Index and 15% S&P/ASX 20 Index. UnderlyingindexdataaresourcedfromS&PDowJonesIndices,LLCandLipper and expressed in Ringgit terms. | BQ83: 0.5716 | BR83: 2026-06-04 | BS83: 0.5526 | BT83: -3.32 | BU83: 11
A84: PB DIVIDEND BUILDER EQUITY FUND | B84: PBDBEF | C84: Conventional | D84: Equity | E84: Income | F84: 4 | G84: Annual | H84: 48.32 | I84: 30.06.2015 | J84: Qualified | K84: 40 | L84: 2/5 | M84: Qualified (WA: +0.18%) — YTD✘ 1Y✘ 3Y✔ 5Y✘ 10Y✔ | N84: 0.18 | O84: 2.61 | P84: 3.49 | Q84: -0.88 | R84: 10.54 | S84: 11.41 | T84: -0.87 | U84: 7.97 | V84: 7.22 | W84: 0.75 | X84: 0.88 | Y84: 2.04 | Z84: -1.16 | AA84: 3.59 | AB84: 1.3 | AC84: 2.29 | AD84: =IF(OR(Q84="",BM84="",BM84=0),"",Q84/BM84) | AE84: =IF(OR(T84="",BM84="",BM84=0),"",T84/BM84) | AF84: =IF(OR(W84="",BM84="",BM84=0),"",W84/BM84) | AG84: =IF(OR(Z84="",BM84="",BM84=0),"",Z84/BM84) | AH84: =IF(OR(AC84="",BM84="",BM84=0),"",AC84/BM84) | AI84: 75 | AJ84: 21.7 | AL84: 3.3 | AO84: 17.1 | AS84: 4.6 | BA84: 13.6 | BC84: 31.5 | BD84: 16 | BE84: 14 | BF84: 12 | BL84: Public Bank Berhad | Tenaga Nasional Berhad | Alphabet Incorporated - Class A | Malayan Banking Berhad | Frontken Corporation Berhad | BM84: 7.9 | BN84: Moderate | BO84: Equity Malaysia Income | BP84: ThebenchmarkforPBDBEFisacompositeof90%FTSEBursaMalaysiaTop100 Index (FBM 100) and 10% 3-Month Kuala Lumpur Interbank Offered Rate (KLIBOR). Underlying index data are sourced from Lipper and Bank Negara Malaysia. | BQ84: 0.3051 | BR84: 2021-04-26 | BS84: 0.2869 | BT84: -5.97 | BU84: 1876
A85: PUBLIC e-PIONEER ENTREPRENEUR FUND | B85: PePEF | C85: Conventional | D85: Equity | E85: Capital Growth | F85: 5 | G85: Incidental | H85: 302.94 | I85: 29.07.2021 | J85: Qualified | K85: 33.3 | L85: 1/3 | M85: Qualified (WA: +0.03%) — YTD✘ 1Y✘ 3Y✔ | N85: 0.03 | O85: -0.43 | P85: 6.05 | Q85: -6.48 | R85: 19.35 | S85: 22.13 | T85: -2.78 | U85: 14.94 | V85: 13.05 | W85: 1.89 | AD85: =IF(OR(Q85="",BM85="",BM85=0),"",Q85/BM85) | AE85: =IF(OR(T85="",BM85="",BM85=0),"",T85/BM85) | AF85: =IF(OR(W85="",BM85="",BM85=0),"",W85/BM85) | AG85: =IF(OR(Z85="",BM85="",BM85=0),"",Z85/BM85) | AH85: =IF(OR(AC85="",BM85="",BM85=0),"",AC85/BM85) | AJ85: 80.4 | AL85: 19.6 | AO85: 44 | AP85: 11 | AQ85: 2.8 | AS85: 2.4 | AU85: 19.5 | BB85: 29.1 | BD85: 39.7 | BE85: 11.6 | BL85: Alphabet Incorporated - Class A | Tesla Incorporated | Taiwan Semiconductor Manufacturing Company Limited | Amazon.com Incorporated | Tencent Holdings Limited | BM85: 12.1 | BN85: High | BO85: Equity Global Global | BP85: ThebenchmarkforPePEFisacompositeof50%DowJonesIndustrialAverage, 30% customised index by S&P Dow Jones Indices, LLC based on the top 30 constituentsoftheS&PBMIAsiaEx-JapanIndex,10%TOPIXCore30Indexand 10% 3-Month Kuala Lumpur Interbank Offered Rate (KLIBOR). UnderlyingindexdataaresourcedfromLipper,S&PDowJonesIndices,LLCand Bank Negara Malaysia and expressed in Ringgit terms. | BQ85: 0.3829 | BR85: 2026-06-04 | BS85: 0.3671 | BT85: -4.13 | BU85: 11
A86: PUBLIC ISLAMIC ASIA TACTICAL ALLOCATION FUND | B86: PIATAF | C86: Shariah | D86: Mixed Asset / Balanced | E86: Capital Growth | F86: 5 | G86: Incidental | H86: 3747.6 | I86: 21.08.2007 | J86: Qualified | K86: 100 | L86: 5/5 | M86: Qualified (WA: +30.87%) — YTD✔ 1Y✔ 3Y✔ 5Y✔ 10Y✔ | N86: 30.87 | O86: 62.86 | P86: 21.1 | Q86: 41.76 | R86: 148.26 | S86: 46.82 | T86: 101.44 | U86: 39.75 | V86: 15.57 | W86: 24.18 | X86: 15.34 | Y86: 4.22 | Z86: 11.12 | AA86: 15.62 | AB86: 8.2 | AC86: 7.42 | AD86: =IF(OR(Q86="",BM86="",BM86=0),"",Q86/BM86) | AE86: =IF(OR(T86="",BM86="",BM86=0),"",T86/BM86) | AF86: =IF(OR(W86="",BM86="",BM86=0),"",W86/BM86) | AG86: =IF(OR(Z86="",BM86="",BM86=0),"",Z86/BM86) | AH86: =IF(OR(AC86="",BM86="",BM86=0),"",AC86/BM86) | AJ86: 97.6 | AL86: 2.4 | AP86: 60 | AQ86: 31 | AR86: 1.8 | AU86: 4.8 | BA86: 42.1 | BB86: 47 | BD86: 8.5 | BL86: Unimicron Technology Corporation | Samsung Electronics Company Limited | SK Hynix Incorporated | HD Hyundai Electric Company Limited | Taiwan Semiconductor Manufacturing Company Limited | BM86: 23.8 | BN86: Very High | BO86: Mixed Asset MYR Asia | BP86: The benchmark for PIATAF is a composite of 70% S&P Shariah BMI Asia Ex- JapanIndexand30%3-MonthIslamicInterbankMoneyMarket(IIMM)rate(w.e.f. 12 December 2011). UnderlyingindexdataaresourcedfromS&PDowJonesIndices,LLCandBank Negara Malaysia and expressed in Ringgit terms. | BQ86: 1.3836 | BR86: 2026-06-04 | BS86: 1.3413 | BT86: -3.06 | BU86: 11
A87: PUBLIC TACTICAL ALLOCATION FUND | B87: PTAF | C87: Conventional | D87: Mixed Asset / Balanced | E87: Capital Growth + Income | F87: 5 | G87: Incidental | H87: 613.28 | I87: 23.01.2007 | J87: Qualified | K87: 80 | L87: 4/5 | M87: Qualified (WA: +7.17%) — YTD✔ 1Y✔ 3Y✔ 5Y✘ 10Y✔ | N87: 7.17 | O87: 17.24 | P87: 4.55 | Q87: 12.69 | R87: 38.41 | S87: 18.33 | T87: 20.08 | U87: 18.85 | V87: 10.1 | W87: 8.75 | X87: 0.85 | Y87: 1.52 | Z87: -0.67 | AA87: 7.26 | AB87: 5.99 | AC87: 1.27 | AD87: =IF(OR(Q87="",BM87="",BM87=0),"",Q87/BM87) | AE87: =IF(OR(T87="",BM87="",BM87=0),"",T87/BM87) | AF87: =IF(OR(W87="",BM87="",BM87=0),"",W87/BM87) | AG87: =IF(OR(Z87="",BM87="",BM87=0),"",Z87/BM87) | AH87: =IF(OR(AC87="",BM87="",BM87=0),"",AC87/BM87) | AJ87: 93.3 | AL87: 6.7 | AO87: 24 | AP87: 42 | AQ87: 23.9 | AU87: 3.4 | BA87: 22.5 | BB87: 50.3 | BD87: 14.8 | BE87: 5.7 | BL87: SK Hynix Incorporated | Taiwan Semiconductor Manufacturing Company Limited | Samsung Electronics Company Limited | Alphabet Incorporated - Class A | Tesla Incorporated | BM87: 19.2 | BN87: Very High | BO87: Mixed Asset MYR Flexible Global | BP87: The benchmark for PTAF is a composite of 70% MSCI AC Far-East Ex-Japan Index (prior to 30 April 2021), 70% S&P Pan Asia Ex-Japan, Australia, NewZealand&IndiaLargeCapIndex(30April2021to1January2024),40%S&P UnitedStatesLargeCapIndex,15%customisedindexbyS&PDowJonesIndices, LLCbasedonthetop30constituentsoftheS&PBMIAsiaEx-JapanIndex,15% TOPIX Core 30 Index (w.e.f. 2 January 2024) and 30% 3-Month Kuala Lumpur Interbank Offered Rate (KLIBOR) (w.e.f. 12 December 2011). UnderlyingindexdataaresourcedfromS&PDowJonesIndices,LLC,Lipperand Bank Negara Malaysia and expressed in Ringgit terms. | BQ87: 0.5644 | BR87: 2026-06-04 | BS87: 0.5345 | BT87: -5.3 | BU87: 11
A88: PUBLIC e-FLEXI ALLOCATION FUND | B88: PeFAF | C88: Conventional | D88: Mixed Asset / Balanced | E88: Capital Growth + Income | F88: 5 | G88: Incidental | H88: 137.39 | I88: 14.07.2017 | J88: Qualified | K88: 100 | L88: 4/4 | M88: Qualified (WA: +6.86%) — YTD✔ 1Y✔ 3Y✔ 5Y✔ | N88: 6.86 | O88: 8.03 | P88: 2.11 | Q88: 5.92 | R88: 25.61 | S88: 9.28 | T88: 16.33 | U88: 11.45 | V88: 5.85 | W88: 5.6 | X88: 5.45 | Y88: 2.07 | Z88: 3.38 | AD88: =IF(OR(Q88="",BM88="",BM88=0),"",Q88/BM88) | AE88: =IF(OR(T88="",BM88="",BM88=0),"",T88/BM88) | AF88: =IF(OR(W88="",BM88="",BM88=0),"",W88/BM88) | AG88: =IF(OR(Z88="",BM88="",BM88=0),"",Z88/BM88) | AH88: =IF(OR(AC88="",BM88="",BM88=0),"",AC88/BM88) | AI88: 67.5 | AJ88: 28.8 | AL88: 3.7 | AO88: 14.9 | AP88: 8.1 | AQ88: 5.8 | BA88: 29.8 | BB88: 13.6 | BC88: 16 | BD88: 15.8 | BG88: 9.2 | BL88: Tenaga Nasional Berhad | Malayan Banking Berhad | Taiwan Semiconductor Manufacturing Company Limited | HD Hyundai Electric Company Limited | Press Metal Aluminium Holdings Berhad | BM88: 11 | BN88: High | BO88: Mixed Asset MYR Domestic 30% of the fund’s NAV | BP88: ThebenchmarkforPeFAFisacompositeof70%FTSEBursaMalaysiaKLCIand 30% 3-Month Kuala Lumpur Interbank Offered Rate (KLIBOR). Underlying index data are sourced from Lipper and Bank Negara Malaysia. | BQ88: 0.4799 | BR88: 2026-05-14 | BS88: 0.4705 | BT88: -1.96 | BU88: 32
A89: PUBLIC ISLAMIC MIXED ASSET FUND | B89: PIMXAF | C89: Shariah | D89: Mixed Asset / Balanced | E89: Capital Growth | F89: 4 | G89: Incidental | H89: 1450.07 | I89: 20.09.2005 | J89: Qualified | K89: 80 | L89: 4/5 | M89: Qualified (WA: +5.05%) — YTD✘ 1Y✔ 3Y✔ 5Y✔ 10Y✔ | N89: 5.05 | O89: 3.36 | P89: 3.93 | Q89: -0.57 | R89: 17.87 | S89: 9.96 | T89: 7.91 | U89: 11.62 | V89: 5.23 | W89: 6.39 | X89: 3.91 | Y89: 0.47 | Z89: 3.44 | AA89: 4.54 | AB89: 1.38 | AC89: 3.16 | AD89: =IF(OR(Q89="",BM89="",BM89=0),"",Q89/BM89) | AE89: =IF(OR(T89="",BM89="",BM89=0),"",T89/BM89) | AF89: =IF(OR(W89="",BM89="",BM89=0),"",W89/BM89) | AG89: =IF(OR(Z89="",BM89="",BM89=0),"",Z89/BM89) | AH89: =IF(OR(AC89="",BM89="",BM89=0),"",AC89/BM89) | AI89: 44 | AJ89: 23.2 | AK89: 29.9 | AL89: 2.9 | AO89: 9.1 | AP89: 4.8 | AQ89: 6.5 | AU89: 2.8 | BA89: 21 | BD89: 14.4 | BF89: 8 | BG89: 9.3 | BI89: 7.6 | BL89: Tenaga Nasional Berhad | Press Metal Aluminium Holdings Berhad | HD Hyundai Electric Company Limited | IHH Healthcare Berhad | Telekom Malaysia Berhad | BM89: 7.9 | BN89: Moderate | BO89: Mixed Asset MYR | BP89: ThebenchmarkforPIMXAFisacompositeof70%FTSEBursaMalaysiaEMAS ShariahIndexand30%3-MonthIslamicInterbankMoneyMarket(IIMM)rate(w.e.f. 12 December 2011). Underlying index data are sourced from Lipper and Bank Negara Malaysia. | BQ89: 0.3828 | BR89: 2026-05-08 | BS89: 0.379 | BT89: -0.99 | BU89: 38
A90: PUBLIC e-ISLAMIC FLEXI ALLOCATION FUND | B90: PeIFAF | C90: Shariah | D90: Mixed Asset / Balanced | E90: Capital Growth | F90: 4 | G90: Incidental | H90: 45.89 | I90: 03.04.2018 | J90: Qualified | K90: 75 | L90: 3/4 | M90: Qualified (WA: +4.92%) — YTD✘ 1Y✔ 3Y✔ 5Y✔ | N90: 4.92 | O90: 3.58 | P90: 4.03 | Q90: -0.45 | R90: 19.64 | S90: 10.51 | T90: 9.13 | U90: 11.34 | V90: 5.8 | W90: 5.54 | X90: 3.57 | Y90: 1.09 | Z90: 2.48 | AD90: =IF(OR(Q90="",BM90="",BM90=0),"",Q90/BM90) | AE90: =IF(OR(T90="",BM90="",BM90=0),"",T90/BM90) | AF90: =IF(OR(W90="",BM90="",BM90=0),"",W90/BM90) | AG90: =IF(OR(Z90="",BM90="",BM90=0),"",Z90/BM90) | AH90: =IF(OR(AC90="",BM90="",BM90=0),"",AC90/BM90) | AI90: 67.3 | AJ90: 30.3 | AL90: 2.4 | AO90: 22.3 | AP90: 8 | BA90: 23.2 | BB90: 15.4 | BD90: 25.7 | BE90: 12.1 | BG90: 8.6 | BL90: Tenaga Nasional Berhad | Taiwan Semiconductor Manufacturing Company Limited | Telekom Malaysia Berhad | TIME dotCom Berhad | Alphabet Incorporated - Class A | BM90: 10.2 | BN90: Moderate | BO90: Mixed Asset MYR Domestic | BP90: The benchmark for PeIFAF is a composite of 70% FTSE Bursa Malaysia Hijrah Shariah Index and 30% 3-Month Islamic Interbank Money Market (IIMM) rate. Underlying index data are sourced from Lipper and Bank Negara Malaysia. | BQ90: 0.4263 | BR90: 2026-06-03 | BS90: 0.416 | BT90: -2.42 | BU90: 12
A91: PUBLIC SELECT MIXED ASSET GROWTH FUND | B91: PSMAGF | C91: Conventional | D91: Mixed Asset / Balanced | E91: Capital Growth + Income | F91: 4 | G91: Incidental | H91: 32.27 | I91: 16.10.2014 | J91: Qualified | K91: 100 | L91: 5/5 | M91: Qualified (WA: +4.10%) — YTD✔ 1Y✔ 3Y✔ 5Y✔ 10Y✔ | N91: 4.1 | O91: 6.62 | P91: 2.11 | Q91: 4.51 | R91: 16.3 | S91: 9.28 | T91: 7.02 | U91: 10.21 | V91: 5.85 | W91: 4.36 | X91: 3.76 | Y91: 2.07 | Z91: 1.69 | AA91: 5.64 | AB91: 1.27 | AC91: 4.37 | AD91: =IF(OR(Q91="",BM91="",BM91=0),"",Q91/BM91) | AE91: =IF(OR(T91="",BM91="",BM91=0),"",T91/BM91) | AF91: =IF(OR(W91="",BM91="",BM91=0),"",W91/BM91) | AG91: =IF(OR(Z91="",BM91="",BM91=0),"",Z91/BM91) | AH91: =IF(OR(AC91="",BM91="",BM91=0),"",AC91/BM91) | AI91: 34.6 | AJ91: 29.9 | AK91: 28.8 | AL91: 6.7 | AO91: 12.1 | AP91: 7.6 | AQ91: 6.4 | AU91: 3.8 | BA91: 13.6 | BB91: 12.6 | BC91: 15 | BD91: 9 | BG91: 9.1 | BL91: Malayan Banking Berhad | Tenaga Nasional Berhad | Advanced Micro Devices Incorporated | Hanwha Aerospace Company Limited | Taiwan Semiconductor Manufacturing Company Limited | BM91: 8.4 | BN91: Moderate | BO91: Mixed Asset MYR Domestic 30% of the fund’s NAV | BP91: 2022 1.00 29.4.22 3.4 ThebenchmarkforPSMAGFisacompositeof70% FTSEBursa MalaysiaKLCI Note: Distribution yield simply measures the level of distributions and is and 30% 3-Month Kuala Lumpur Interbank Offered Rate (KLIBOR). not a measure of fund performance. Underlying index data are sourced from Lipper and Bank Negara Malaysia. | BQ91: 0.3977 | BR91: 2026-05-26 | BS91: 0.3926 | BT91: -1.28 | BU91: 20
A92: PUBLIC FAR-EAST BALANCED FUND | B92: PFEBF | C92: Conventional | D92: Mixed Asset / Balanced | E92: Capital Growth + Income | F92: 4 | G92: Incidental | H92: 237.42 | I92: 23.01.2007 | J92: Qualified | K92: 100 | L92: 5/5 | M92: Qualified (WA: +4.01%) — YTD✔ 1Y✔ 3Y✔ 5Y✔ 10Y✔ | N92: 4.01 | O92: 16.93 | P92: 8.77 | Q92: 8.16 | R92: 38.42 | S92: 25.31 | T92: 13.11 | U92: 13.86 | V92: 11.16 | W92: 2.7 | X92: 4.72 | Y92: 3.09 | Z92: 1.63 | AA92: 7.21 | AB92: 6.23 | AC92: 0.98 | AD92: =IF(OR(Q92="",BM92="",BM92=0),"",Q92/BM92) | AE92: =IF(OR(T92="",BM92="",BM92=0),"",T92/BM92) | AF92: =IF(OR(W92="",BM92="",BM92=0),"",W92/BM92) | AG92: =IF(OR(Z92="",BM92="",BM92=0),"",Z92/BM92) | AH92: =IF(OR(AC92="",BM92="",BM92=0),"",AC92/BM92) | AI92: 0.9 | AJ92: 59.6 | AK92: 30.4 | AL92: 9.1 | AO92: 2.9 | AP92: 22.7 | AQ92: 20.7 | AU92: 13.3 | BA92: 15.9 | BB92: 31.1 | BC92: 0.9 | BD92: 11.5 | BE92: 1.1 | BL92: Taiwan Semiconductor Manufacturing Company Limited | Samsung Electronics Company Limited | SK Hynix Incorporated | Alibaba Group Holding Limited - W | HD Hyundai Electric Company Limited | BM92: 11.6 | BN92: High | BO92: Mixed Asset MYR Asia | BQ92: 0.4764 | BR92: 2026-06-04 | BS92: 0.4668 | BT92: -2.02 | BU92: 11
A93: PUBLIC EHSAN MIXED ASSET GROWTH FUND | B93: PESMAGF | C93: Shariah | D93: Mixed Asset / Balanced | E93: Capital Growth | F93: 4 | G93: Incidental | H93: 31.01 | I93: 25.11.2014 | J93: Qualified | K93: 80 | L93: 4/5 | M93: Qualified (WA: +3.07%) — YTD✔ 1Y✔ 3Y✔ 5Y✘ 10Y✔ | N93: 3.07 | O93: 4.39 | P93: 4.03 | Q93: 0.36 | R93: 17.65 | S93: 10.51 | T93: 7.14 | U93: 10.66 | V93: 5.8 | W93: 4.86 | X93: -0.06 | Y93: 1.09 | Z93: -1.15 | AA93: 3.45 | AB93: 1.26 | AC93: 2.19 | AD93: =IF(OR(Q93="",BM93="",BM93=0),"",Q93/BM93) | AE93: =IF(OR(T93="",BM93="",BM93=0),"",T93/BM93) | AF93: =IF(OR(W93="",BM93="",BM93=0),"",W93/BM93) | AG93: =IF(OR(Z93="",BM93="",BM93=0),"",Z93/BM93) | AH93: =IF(OR(AC93="",BM93="",BM93=0),"",AC93/BM93) | AI93: 41.6 | AJ93: 25.6 | AK93: 30.3 | AL93: 2.5 | AO93: 16.8 | AP93: 6.7 | AU93: 2.1 | BA93: 7.3 | BB93: 9.3 | BD93: 19.9 | BF93: 11.1 | BG93: 7.5 | BL93: Alphabet Incorporated - Class A | Tenaga Nasional Berhad | Taiwan Semiconductor Manufacturing Company Limited | Press Metal Aluminium Holdings Berhad | IHH Healthcare Berhad | BM93: 7.2 | BN93: Low | BO93: Mixed Asset MYR Domestic | BP93: 2022 2.00 29.4.22 7.5 ThebenchmarkforPESMAGFisacompositeof70%FTSEBursaMalaysiaHijrah Shariah Index and 30% 3-Month Islamic Interbank Money Market (IIMM) rate. Note: Distribution yield simply measures the level of distributions and is not Underlying index data are sourced from Lipper and Bank Negara Malaysia. a measure of fund performance. | BQ93: 0.4083 | BR93: 2020-08-06 | BS93: 0.3429 | BT93: -16.02 | BU93: 2139
A94: PB DYNAMIC ALLOCATION FUND | B94: PBDYNAF | C94: Conventional | D94: Mixed Asset / Balanced | E94: Capital Growth + Income | F94: 5 | G94: Incidental | H94: 377.95 | I94: 19.06.2012 | J94: Qualified | K94: 100 | L94: 5/5 | M94: Qualified (WA: +3.03%) — YTD✔ 1Y✔ 3Y✔ 5Y✔ 10Y✔ | N94: 3.03 | O94: 10.44 | P94: 10.03 | Q94: 0.41 | R94: 36.18 | S94: 29.24 | T94: 6.94 | U94: 15.61 | V94: 12.36 | W94: 3.25 | X94: 4.1 | Y94: 2.96 | Z94: 1.14 | AA94: 9.2 | AB94: 6.64 | AC94: 2.56 | AD94: =IF(OR(Q94="",BM94="",BM94=0),"",Q94/BM94) | AE94: =IF(OR(T94="",BM94="",BM94=0),"",T94/BM94) | AF94: =IF(OR(W94="",BM94="",BM94=0),"",W94/BM94) | AG94: =IF(OR(Z94="",BM94="",BM94=0),"",Z94/BM94) | AH94: =IF(OR(AC94="",BM94="",BM94=0),"",AC94/BM94) | AJ94: 95.7 | AL94: 4.3 | AO94: 34 | AP94: 24.9 | AQ94: 15.5 | AU94: 19 | BA94: 9.7 | BB94: 51.3 | BC94: 0.7 | BD94: 27.4 | BE94: 6.6 | BL94: Taiwan Semiconductor Manufacturing Company Limited | Alphabet Incorporated - Class A | NVIDIA Corporation | Samsung Electronics Company Limited | SK Hynix Incorporated | BM94: 16.4 | BN94: Very High | BO94: Mixed Asset MYR Global | BQ94: 2.0462 | BR94: 2026-06-04 | BS94: 1.9627 | BT94: -4.08 | BU94: 11
A95: PUBLIC GROWTH BALANCED FUND | B95: PGRBF | C95: Conventional | D95: Mixed Asset / Balanced | E95: Capital Growth | F95: 3 | G95: Incidental | H95: 27.17 | I95: 07.10.2015 | J95: Qualified | K95: 100 | L95: 5/5 | M95: Qualified (WA: +2.54%) — YTD✔ 1Y✔ 3Y✔ 5Y✔ 10Y✔ | N95: 2.54 | O95: 2.46 | P95: 1.97 | Q95: 0.49 | R95: 9.83 | S95: 8.44 | T95: 1.39 | U95: 7.95 | V95: 5.55 | W95: 2.4 | X95: 4.48 | Y95: 2.25 | Z95: 2.23 | AA95: 6.84 | AB95: 1.57 | AC95: 5.27 | AD95: =IF(OR(Q95="",BM95="",BM95=0),"",Q95/BM95) | AE95: =IF(OR(T95="",BM95="",BM95=0),"",T95/BM95) | AF95: =IF(OR(W95="",BM95="",BM95=0),"",W95/BM95) | AG95: =IF(OR(Z95="",BM95="",BM95=0),"",Z95/BM95) | AH95: =IF(OR(AC95="",BM95="",BM95=0),"",AC95/BM95) | AI95: 29.8 | AJ95: 23.8 | AK95: 44.4 | AL95: 2 | AO95: 15.2 | AP95: 6.3 | AU95: 2.3 | BA95: 6.6 | BB95: 15.7 | BD95: 13.6 | BF95: 4.1 | BG95: 8.2 | BL95: Tenaga Nasional Berhad | Taiwan Semiconductor Manufacturing Company Limited | Advanced Micro Devices Incorporated | Frontken Corporation Berhad | TIME dotCom Berhad | BM95: 6.3 | BN95: Low | BO95: Domestic 25% of the fund’s NAV | BP95: ThebenchmarkforPGRBFisacompositeof60%FTSEBursaMalaysiaKLCIand 40% 3-Month Kuala Lumpur Interbank Offered Rate (KLIBOR). Underlying index data are sourced from Lipper and Bank Negara Malaysia. | BQ95: 0.4365 | BR95: 2026-06-03 | BS95: 0.4288 | BT95: -1.76 | BU95: 12
A96: PUBLIC NAVIGATOR GROWTH FUND | B96: PNVGF | C96: Conventional | D96: Mixed Asset / Balanced | E96: Capital Growth + Income | F96: 5 | G96: Incidental | H96: 238.46 | I96: 09.01.2017 | J96: Qualified | K96: 75 | L96: 3/4 | M96: Qualified (WA: +2.34%) — YTD✔ 1Y✔ 3Y✔ 5Y✘ | N96: 2.34 | O96: 8.08 | P96: 2.56 | Q96: 5.52 | R96: 24.18 | S96: 8 | T96: 16.18 | U96: 8.75 | V96: 8 | W96: 0.75 | X96: 3.94 | Y96: 8.01 | Z96: -4.07 | AD96: =IF(OR(Q96="",BM96="",BM96=0),"",Q96/BM96) | AE96: =IF(OR(T96="",BM96="",BM96=0),"",T96/BM96) | AF96: =IF(OR(W96="",BM96="",BM96=0),"",W96/BM96) | AG96: =IF(OR(Z96="",BM96="",BM96=0),"",Z96/BM96) | AH96: =IF(OR(AC96="",BM96="",BM96=0),"",AC96/BM96) | AI96: 1.1 | AJ96: 91.5 | AL96: 7.4 | AO96: 51.4 | AP96: 12.2 | AQ96: 5.3 | AR96: 4.9 | AU96: 7.7 | BA96: 4.4 | BB96: 43.4 | BC96: 2.9 | BD96: 31.5 | BE96: 10.4 | BL96: Taiwan Semiconductor Manufacturing Company Limited | Meta Platforms Incorporated | Advanced Micro Devices Incorporated | Broadcom Incorporated | Alphabet Incorporated - Class A | BM96: 14.3 | BN96: Very High | BO96: Mixed Asset MYR Flexible Global | BQ96: 0.3948 | BR96: 2026-06-03 | BS96: 0.3776 | BT96: -4.36 | BU96: 12
A97: PB BALANCED SEQUEL FUND | B97: PBBSQF | C97: Conventional | D97: Mixed Asset / Balanced | E97: Capital Growth | F97: 3 | G97: Incidental | H97: 37.74 | I97: 10.09.2013 | J97: Qualified | K97: 60 | L97: 3/5 | M97: Qualified (WA: +2.27%) — YTD✘ 1Y✘ 3Y✔ 5Y✔ 10Y✔ | N97: 2.27 | O97: 1.93 | P97: 1.97 | Q97: -0.04 | R97: 8.28 | S97: 8.44 | T97: -0.16 | U97: 8.91 | V97: 5.55 | W97: 3.36 | X97: 4.42 | Y97: 2.25 | Z97: 2.17 | AA97: 4.33 | AB97: 1.57 | AC97: 2.76 | AD97: =IF(OR(Q97="",BM97="",BM97=0),"",Q97/BM97) | AE97: =IF(OR(T97="",BM97="",BM97=0),"",T97/BM97) | AF97: =IF(OR(W97="",BM97="",BM97=0),"",W97/BM97) | AG97: =IF(OR(Z97="",BM97="",BM97=0),"",Z97/BM97) | AH97: =IF(OR(AC97="",BM97="",BM97=0),"",AC97/BM97) | AI97: 35.8 | AJ97: 23.8 | AK97: 35.3 | AL97: 5.1 | AO97: 4.2 | AP97: 9 | AQ97: 5 | AU97: 5.6 | BA97: 11.9 | BB97: 14.8 | BC97: 19.8 | BD97: 2.8 | BG97: 8.5 | BL97: Tenaga Nasional Berhad | Malayan Banking Berhad | LPI Capital Berhad | Unimicron Technology Corporation | Samsung Electronics Company Limited | BM97: 8.2 | BN97: Moderate | BO97: Mixed Asset MYR Domestic | BP97: Public Balanced Equity Index (PBEIX) is a composite of 60% the returns of the FTSE Bursa Malaysia KLCI and 40% the returns on 3-Month Kuala Lumpur Interbank Offered Rate (KLIBOR). The Index is an appropriate performance benchmark for balanced fund. Underlying index data are sourced from Lipper and Bank Negara Malaysia. | BQ97: 0.3774 | BR97: 2026-06-03 | BS97: 0.3699 | BT97: -1.99 | BU97: 12
A98: PUBLIC BALANCED FUND | B98: PBF | C98: Conventional | D98: Mixed Asset / Balanced | E98: Capital Growth + Income | F98: 3 | G98: Incidental | H98: 348 | I98: 07.06.1995 | J98: Qualified | K98: 100 | L98: 5/5 | M98: Qualified (WA: +2.21%) — YTD✔ 1Y✔ 3Y✔ 5Y✔ 10Y✔ | N98: 2.21 | O98: 3.62 | P98: 1.97 | Q98: 1.65 | R98: 14.04 | S98: 8.44 | T98: 5.6 | U98: 6.6 | V98: 5.55 | W98: 1.05 | X98: 4.15 | Y98: 2.25 | Z98: 1.9 | AA98: 4.19 | AB98: 1.57 | AC98: 2.62 | AD98: =IF(OR(Q98="",BM98="",BM98=0),"",Q98/BM98) | AE98: =IF(OR(T98="",BM98="",BM98=0),"",T98/BM98) | AF98: =IF(OR(W98="",BM98="",BM98=0),"",W98/BM98) | AG98: =IF(OR(Z98="",BM98="",BM98=0),"",Z98/BM98) | AH98: =IF(OR(AC98="",BM98="",BM98=0),"",AC98/BM98) | AI98: 35.3 | AJ98: 21.2 | AK98: 35.8 | AL98: 7.7 | AO98: 4.7 | AP98: 4.4 | AQ98: 2.9 | AU98: 9.2 | BA98: 7.4 | BB98: 14.6 | BC98: 18.9 | BD98: 3.6 | BG98: 7.4 | BL98: Tenaga Nasional Berhad | Malayan Banking Berhad | Semiconductor Manufacturing International Corporation | UWC Berhad | Public Bank Berhad | BM98: 7.6 | BN98: Low | BO98: Mixed Asset MYR Domestic 30% of the fund’s NAV | BP98: 2021 2.75 31.5.21 3.9 Public Balanced Equity Index (PBEIX) is a composite of 60% the returns of the Kuala Lumpur Composite Index (prior to 6July2009),60% thereturns ofFTSE 2022 2.75 31.5.22 4.1 BursaMalaysiaKLCI(w.e.f.6July2009)and40% the returns of 3-MonthKuala 2023 1.75 31.5.23 2.6 LumpurInterbankOfferedRate(KLIBOR).TheIndexisanappropriateperformance Note: Distribution yield simply measures the level of distributions and is benchmark for balanced fund. not a measure of fund performance. Underlying index data are sourced from Lipper and Bank Negara Malaysia. | BQ98: 1.0016 | BR98: 2007-05-22 | BS98: 0.8355 | BT98: -16.58 | BU98: 6964
A99: PUBLIC SELECT MIXED ASSET CONSERVATIVE FUND | B99: PSMACF | C99: Conventional | D99: Mixed Asset / Balanced | E99: Capital Growth + Income | F99: 3 | G99: Annual | H99: 156.66 | I99: 16.10.2014 | J99: Qualified | K99: 80 | L99: 4/5 | M99: Qualified (WA: +1.82%) — YTD✘ 1Y✔ 3Y✔ 5Y✔ 10Y✔ | N99: 1.82 | O99: 1.06 | P99: 1.61 | Q99: -0.55 | R99: 8.68 | S99: 6.31 | T99: 2.37 | U99: 6.39 | V99: 4.73 | W99: 1.66 | X99: 4.29 | Y99: 2.66 | Z99: 1.63 | AA99: 5.07 | AB99: 2.28 | AC99: 2.79 | AD99: =IF(OR(Q99="",BM99="",BM99=0),"",Q99/BM99) | AE99: =IF(OR(T99="",BM99="",BM99=0),"",T99/BM99) | AF99: =IF(OR(W99="",BM99="",BM99=0),"",W99/BM99) | AG99: =IF(OR(Z99="",BM99="",BM99=0),"",Z99/BM99) | AH99: =IF(OR(AC99="",BM99="",BM99=0),"",AC99/BM99) | AI99: 10.4 | AJ99: 19.2 | AK99: 60.7 | AL99: 9.7 | AO99: 12.6 | AP99: 3.9 | AU99: 2.7 | BA99: 4.7 | BB99: 6.3 | BD99: 9.9 | BE99: 3 | BG99: 4.9 | BL99: Alphabet Incorporated - Class A | Tenaga Nasional Berhad | Taiwan Semiconductor Manufacturing Company Limited | Tesla Incorporated | Alibaba Group Holding Limited - W | BM99: 5 | BN99: Low | BO99: Mixed Asset MYR Domestic 25% of the fund’s NAV | BP99: The benchmark for PSMACF is a composite of 65% 3-Month Kuala Lumpur Interbank Offered Rate (KLIBOR) and 35% FTSE Bursa Malaysia KLCI. Underlying index data are sourced from Lipper and Bank Negara Malaysia. | BQ99: 0.3199 | BR99: 2025-10-03 | BS99: 0.3152 | BT99: -1.47 | BU99: 255
A100: PUBLIC e-ATARAXIA MIXED ASSET FUND | B100: PeAXMAF | C100: Conventional | D100: Mixed Asset / Balanced | E100: Capital Growth | F100: 3 | G100: Incidental | H100: 700.01 | I100: 23.05.2023 | J100: Qualified | K100: 50 | L100: 1/2 | M100: Qualified (WA: +1.57%) — YTD✘ 1Y✔ | N100: 1.57 | O100: 1.23 | P100: 1.8 | Q100: -0.57 | R100: 10.35 | S100: 8.06 | T100: 2.29 | AD100: =IF(OR(Q100="",BM100="",BM100=0),"",Q100/BM100) | AE100: =IF(OR(T100="",BM100="",BM100=0),"",T100/BM100) | AF100: =IF(OR(W100="",BM100="",BM100=0),"",W100/BM100) | AG100: =IF(OR(Z100="",BM100="",BM100=0),"",Z100/BM100) | AH100: =IF(OR(AC100="",BM100="",BM100=0),"",AC100/BM100) | AI100: 1.1 | AJ100: 28.7 | AK100: 62.9 | AL100: 7.3 | AO100: 11.3 | AP100: 7.4 | AQ100: 1.8 | AU100: 3.5 | AW100: 1.8 | BA100: 3.3 | BB100: 15.3 | BC100: 1.1 | BD100: 5.4 | BE100: 4.7 | BL100: Tesla Incorporated | Unimicron Technology Corporation | Broadcom Incorporated | MediaTek Incorporated | Alphabet Incorporated - Class A | BP100: The benchmark for PeAXMAF is a composite of 70% 3-Month Kuala Lumpur Interbank Offered Rate (KLIBOR) and 30% S&P Global LargeCap Index. Underlying indexdata are sourced from S&P Dow Jones Indices, LLC and Bank Negara Malaysia and expressed in Ringgit terms. | BQ100: 0.3094 | BR100: 2026-06-03 | BS100: 0.3024 | BT100: -2.26 | BU100: 12
...

Sheet Summary
A1: PUBLIC MUTUAL FUND SCREENER — SUMMARY | MFR April 2026
A3: SCREENING RESULTS
A4: Metric | B4: Value
A5: Total PHS files (all UT funds) | B5: 181
A6: Excluded: Class-B funds | B6: 6 | C6: (PeCDF-B, PMMF-B, PBCMF-B, PeICDF-B, PIMMF-B, PBICMF-B)
A7: Excluded: Wholesale funds | B7: 4 | C7: (PBCPF, PWSIF, PIWSIF, PeWS20F)
A8: Retail funds screened | B8: 171
A10: Funds qualified (Weighted Alpha > 0%) | B10: 134
A11: Funds disqualified | B11: 37
A12: Pass rate | B12: 78.4%
A13: Conventional funds qualified | B13: 86
A14: Shariah-compliant funds qualified | B14: 48
A16: Data source | B16: MFR April 2026
A17: Screening criteria | B17: Weighted Alpha > 0% (YTD×5% + 1Y×15% + 3Y×40% + 5Y×25% + 10Y×15%)
A18: Minimum data requirement | B18: ≥2 periods (YTD, 1Y, 3Y, 5Y, 10Y)
A19: Note | B19: Class-B & Wholesale funds excluded — not available to typical retail investors
A21: BREAKDOWN BY FUND TYPE
A22: Fund Type | B22: Qualified | C22: 100% Rate | D22: Shariah | E22: Conventional
A23: Equity | B23: =COUNTIFS(Master!J$4:J$174,"Qualified",Master!D$4:D$174,"Equity") | C23: =COUNTIFS(Master!J$4:J$174,"Qualified",Master!D$4:D$174,"Equity",Master!K$4:K$174,100) | D23: =COUNTIFS(Master!J$4:J$174,"Qualified",Master!D$4:D$174,"Equity",Master!C$4:C$174,"Shariah") | E23: =B23-D23
A24: Mixed Asset / Balanced | B24: =COUNTIFS(Master!J$4:J$174,"Qualified",Master!D$4:D$174,"Mixed Asset / Balanced") | C24: =COUNTIFS(Master!J$4:J$174,"Qualified",Master!D$4:D$174,"Mixed Asset / Balanced",Master!K$4:K$174,100) | D24: =COUNTIFS(Master!J$4:J$174,"Qualified",Master!D$4:D$174,"Mixed Asset / Balanced",Master!C$4:C$174,"Shariah") | E24: =B24-D24
A25: Fixed Income | B25: =COUNTIFS(Master!J$4:J$174,"Qualified",Master!D$4:D$174,"Fixed Income") | C25: =COUNTIFS(Master!J$4:J$174,"Qualified",Master!D$4:D$174,"Fixed Income",Master!K$4:K$174,100) | D25: =COUNTIFS(Master!J$4:J$174,"Qualified",Master!D$4:D$174,"Fixed Income",Master!C$4:C$174,"Shariah") | E25: =B25-D25
A26: Fund of Funds | B26: =COUNTIFS(Master!J$4:J$174,"Qualified",Master!D$4:D$174,"Fund of Funds") | C26: =COUNTIFS(Master!J$4:J$174,"Qualified",Master!D$4:D$174,"Fund of Funds",Master!K$4:K$174,100) | D26: =COUNTIFS(Master!J$4:J$174,"Qualified",Master!D$4:D$174,"Fund of Funds",Master!C$4:C$174,"Shariah") | E26: =B26-D26
A27: Money Market | B27: =COUNTIFS(Master!J$4:J$174,"Qualified",Master!D$4:D$174,"Money Market") | C27: =COUNTIFS(Master!J$4:J$174,"Qualified",Master!D$4:D$174,"Money Market",Master!K$4:K$174,100) | D27: =COUNTIFS(Master!J$4:J$174,"Qualified",Master!D$4:D$174,"Money Market",Master!C$4:C$174,"Shariah") | E27: =B27-D27
A28: TOTAL | B28: =SUM(B23:B27) | C28: =SUM(C23:C27) | D28: =SUM(D23:D27) | E28: =SUM(E23:E27)
A30: EQUITY — MEDIAN STATISTICS
A31: Metric | B31: YTD (%) | C31: 1Y (%) | D31: 3Y Ann. (%) | E31: 5Y Ann. (%) | F31: 10Y Ann. (%) | G31: 3Y Alpha (%) | H31: Beat (%)
A32: Median | B32: =IFERROR(MEDIAN(FILTER(Master!O$4:O$174,(Master!J$4:J$174="Qualified")*(Master!D$4:D$174="Equity"))),"") | C32: =IFERROR(MEDIAN(FILTER(Master!R$4:R$174,(Master!J$4:J$174="Qualified")*(Master!D$4:D$174="Equity"))),"") | D32: =IFERROR(MEDIAN(FILTER(Master!U$4:U$174,(Master!J$4:J$174="Qualified")*(Master!D$4:D$174="Equity"))),"") | E32: =IFERROR(MEDIAN(FILTER(Master!X$4:X$174,(Master!J$4:J$174="Qualified")*(Master!D$4:D$174="Equity"))),"") | F32: =IFERROR(MEDIAN(FILTER(Master!AA$4:AA$174,(Master!J$4:J$174="Qualified")*(Master!D$4:D$174="Equity"))),"") | G32: =IFERROR(MEDIAN(FILTER(Master!W$4:W$174,(Master!J$4:J$174="Qualified")*(Master!D$4:D$174="Equity"))),"") | H32: =IFERROR(MEDIAN(FILTER(Master!K$4:K$174,(Master!J$4:J$174="Qualified")*(Master!D$4:D$174="Equity"))),"")
A34: EQUITY — TOP 5 BY 3Y ANN. FUND RETURN
A35: Fund Name | B35: Abbr | C35: 3Y Fund (%) | D35: 3Y Alpha (%) | E35: Beat (%) | F35: AUM (RM M) | G35: VC
A36: =IFERROR(INDEX(SORT(FILTER({Master!A$4:A$174,Master!B$4:B$174,Master!U$4:U$174,Master!W$4:W$174,Master!K$4:K$174,Master!H$4:H$174,Master!BN$4:BN$174},Master!J$4:J$174="Qualified",Master!D$4:D$174="Equity",Master!U$4:U$174<>""),3,FALSE),1,1),"") | B36: =IFERROR(INDEX(SORT(FILTER({Master!A$4:A$174,Master!B$4:B$174,Master!U$4:U$174,Master!W$4:W$174,Master!K$4:K$174,Master!H$4:H$174,Master!BN$4:BN$174},Master!J$4:J$174="Qualified",Master!D$4:D$174="Equity",Master!U$4:U$174<>""),3,FALSE),1,2),"") | C36: =IFERROR(INDEX(SORT(FILTER({Master!A$4:A$174,Master!B$4:B$174,Master!U$4:U$174,Master!W$4:W$174,Master!K$4:K$174,Master!H$4:H$174,Master!BN$4:BN$174},Master!J$4:J$174="Qualified",Master!D$4:D$174="Equity",Master!U$4:U$174<>""),3,FALSE),1,3),"") | D36: =IFERROR(INDEX(SORT(FILTER({Master!A$4:A$174,Master!B$4:B$174,Master!U$4:U$174,Master!W$4:W$174,Master!K$4:K$174,Master!H$4:H$174,Master!BN$4:BN$174},Master!J$4:J$174="Qualified",Master!D$4:D$174="Equity",Master!U$4:U$174<>""),3,FALSE),1,4),"") | E36: =IFERROR(INDEX(SORT(FILTER({Master!A$4:A$174,Master!B$4:B$174,Master!U$4:U$174,Master!W$4:W$174,Master!K$4:K$174,Master!H$4:H$174,Master!BN$4:BN$174},Master!J$4:J$174="Qualified",Master!D$4:D$174="Equity",Master!U$4:U$174<>""),3,FALSE),1,5),"") | F36: =IFERROR(INDEX(SORT(FILTER({Master!A$4:A$174,Master!B$4:B$174,Master!U$4:U$174,Master!W$4:W$174,Master!K$4:K$174,Master!H$4:H$174,Master!BN$4:BN$174},Master!J$4:J$174="Qualified",Master!D$4:D$174="Equity",Master!U$4:U$174<>""),3,FALSE),1,6),"") | G36: =IFERROR(INDEX(SORT(FILTER({Master!A$4:A$174,Master!B$4:B$174,Master!U$4:U$174,Master!W$4:W$174,Master!K$4:K$174,Master!H$4:H$174,Master!BN$4:BN$174},Master!J$4:J$174="Qualified",Master!D$4:D$174="Equity",Master!U$4:U$174<>""),3,FALSE),1,7),"")
A37: =IFERROR(INDEX(SORT(FILTER({Master!A$4:A$174,Master!B$4:B$174,Master!U$4:U$174,Master!W$4:W$174,Master!K$4:K$174,Master!H$4:H$174,Master!BN$4:BN$174},Master!J$4:J$174="Qualified",Master!D$4:D$174="Equity",Master!U$4:U$174<>""),3,FALSE),2,1),"") | B37: =IFERROR(INDEX(SORT(FILTER({Master!A$4:A$174,Master!B$4:B$174,Master!U$4:U$174,Master!W$4:W$174,Master!K$4:K$174,Master!H$4:H$174,Master!BN$4:BN$174},Master!J$4:J$174="Qualified",Master!D$4:D$174="Equity",Master!U$4:U$174<>""),3,FALSE),2,2),"") | C37: =IFERROR(INDEX(SORT(FILTER({Master!A$4:A$174,Master!B$4:B$174,Master!U$4:U$174,Master!W$4:W$174,Master!K$4:K$174,Master!H$4:H$174,Master!BN$4:BN$174},Master!J$4:J$174="Qualified",Master!D$4:D$174="Equity",Master!U$4:U$174<>""),3,FALSE),2,3),"") | D37: =IFERROR(INDEX(SORT(FILTER({Master!A$4:A$174,Master!B$4:B$174,Master!U$4:U$174,Master!W$4:W$174,Master!K$4:K$174,Master!H$4:H$174,Master!BN$4:BN$174},Master!J$4:J$174="Qualified",Master!D$4:D$174="Equity",Master!U$4:U$174<>""),3,FALSE),2,4),"") | E37: =IFERROR(INDEX(SORT(FILTER({Master!A$4:A$174,Master!B$4:B$174,Master!U$4:U$174,Master!W$4:W$174,Master!K$4:K$174,Master!H$4:H$174,Master!BN$4:BN$174},Master!J$4:J$174="Qualified",Master!D$4:D$174="Equity",Master!U$4:U$174<>""),3,FALSE),2,5),"") | F37: =IFERROR(INDEX(SORT(FILTER({Master!A$4:A$174,Master!B$4:B$174,Master!U$4:U$174,Master!W$4:W$174,Master!K$4:K$174,Master!H$4:H$174,Master!BN$4:BN$174},Master!J$4:J$174="Qualified",Master!D$4:D$174="Equity",Master!U$4:U$174<>""),3,FALSE),2,6),"") | G37: =IFERROR(INDEX(SORT(FILTER({Master!A$4:A$174,Master!B$4:B$174,Master!U$4:U$174,Master!W$4:W$174,Master!K$4:K$174,Master!H$4:H$174,Master!BN$4:BN$174},Master!J$4:J$174="Qualified",Master!D$4:D$174="Equity",Master!U$4:U$174<>""),3,FALSE),2,7),"")
A38: =IFERROR(INDEX(SORT(FILTER({Master!A$4:A$174,Master!B$4:B$174,Master!U$4:U$174,Master!W$4:W$174,Master!K$4:K$174,Master!H$4:H$174,Master!BN$4:BN$174},Master!J$4:J$174="Qualified",Master!D$4:D$174="Equity",Master!U$4:U$174<>""),3,FALSE),3,1),"") | B38: =IFERROR(INDEX(SORT(FILTER({Master!A$4:A$174,Master!B$4:B$174,Master!U$4:U$174,Master!W$4:W$174,Master!K$4:K$174,Master!H$4:H$174,Master!BN$4:BN$174},Master!J$4:J$174="Qualified",Master!D$4:D$174="Equity",Master!U$4:U$174<>""),3,FALSE),3,2),"") | C38: =IFERROR(INDEX(SORT(FILTER({Master!A$4:A$174,Master!B$4:B$174,Master!U$4:U$174,Master!W$4:W$174,Master!K$4:K$174,Master!H$4:H$174,Master!BN$4:BN$174},Master!J$4:J$174="Qualified",Master!D$4:D$174="Equity",Master!U$4:U$174<>""),3,FALSE),3,3),"") | D38: =IFERROR(INDEX(SORT(FILTER({Master!A$4:A$174,Master!B$4:B$174,Master!U$4:U$174,Master!W$4:W$174,Master!K$4:K$174,Master!H$4:H$174,Master!BN$4:BN$174},Master!J$4:J$174="Qualified",Master!D$4:D$174="Equity",Master!U$4:U$174<>""),3,FALSE),3,4),"") | E38: =IFERROR(INDEX(SORT(FILTER({Master!A$4:A$174,Master!B$4:B$174,Master!U$4:U$174,Master!W$4:W$174,Master!K$4:K$174,Master!H$4:H$174,Master!BN$4:BN$174},Master!J$4:J$174="Qualified",Master!D$4:D$174="Equity",Master!U$4:U$174<>""),3,FALSE),3,5),"") | F38: =IFERROR(INDEX(SORT(FILTER({Master!A$4:A$174,Master!B$4:B$174,Master!U$4:U$174,Master!W$4:W$174,Master!K$4:K$174,Master!H$4:H$174,Master!BN$4:BN$174},Master!J$4:J$174="Qualified",Master!D$4:D$174="Equity",Master!U$4:U$174<>""),3,FALSE),3,6),"") | G38: =IFERROR(INDEX(SORT(FILTER({Master!A$4:A$174,Master!B$4:B$174,Master!U$4:U$174,Master!W$4:W$174,Master!K$4:K$174,Master!H$4:H$174,Master!BN$4:BN$174},Master!J$4:J$174="Qualified",Master!D$4:D$174="Equity",Master!U$4:U$174<>""),3,FALSE),3,7),"")
A39: =IFERROR(INDEX(SORT(FILTER({Master!A$4:A$174,Master!B$4:B$174,Master!U$4:U$174,Master!W$4:W$174,Master!K$4:K$174,Master!H$4:H$174,Master!BN$4:BN$174},Master!J$4:J$174="Qualified",Master!D$4:D$174="Equity",Master!U$4:U$174<>""),3,FALSE),4,1),"") | B39: =IFERROR(INDEX(SORT(FILTER({Master!A$4:A$174,Master!B$4:B$174,Master!U$4:U$174,Master!W$4:W$174,Master!K$4:K$174,Master!H$4:H$174,Master!BN$4:BN$174},Master!J$4:J$174="Qualified",Master!D$4:D$174="Equity",Master!U$4:U$174<>""),3,FALSE),4,2),"") | C39: =IFERROR(INDEX(SORT(FILTER({Master!A$4:A$174,Master!B$4:B$174,Master!U$4:U$174,Master!W$4:W$174,Master!K$4:K$174,Master!H$4:H$174,Master!BN$4:BN$174},Master!J$4:J$174="Qualified",Master!D$4:D$174="Equity",Master!U$4:U$174<>""),3,FALSE),4,3),"") | D39: =IFERROR(INDEX(SORT(FILTER({Master!A$4:A$174,Master!B$4:B$174,Master!U$4:U$174,Master!W$4:W$174,Master!K$4:K$174,Master!H$4:H$174,Master!BN$4:BN$174},Master!J$4:J$174="Qualified",Master!D$4:D$174="Equity",Master!U$4:U$174<>""),3,FALSE),4,4),"") | E39: =IFERROR(INDEX(SORT(FILTER({Master!A$4:A$174,Master!B$4:B$174,Master!U$4:U$174,Master!W$4:W$174,Master!K$4:K$174,Master!H$4:H$174,Master!BN$4:BN$174},Master!J$4:J$174="Qualified",Master!D$4:D$174="Equity",Master!U$4:U$174<>""),3,FALSE),4,5),"") | F39: =IFERROR(INDEX(SORT(FILTER({Master!A$4:A$174,Master!B$4:B$174,Master!U$4:U$174,Master!W$4:W$174,Master!K$4:K$174,Master!H$4:H$174,Master!BN$4:BN$174},Master!J$4:J$174="Qualified",Master!D$4:D$174="Equity",Master!U$4:U$174<>""),3,FALSE),4,6),"") | G39: =IFERROR(INDEX(SORT(FILTER({Master!A$4:A$174,Master!B$4:B$174,Master!U$4:U$174,Master!W$4:W$174,Master!K$4:K$174,Master!H$4:H$174,Master!BN$4:BN$174},Master!J$4:J$174="Qualified",Master!D$4:D$174="Equity",Master!U$4:U$174<>""),3,FALSE),4,7),"")
A40: =IFERROR(INDEX(SORT(FILTER({Master!A$4:A$174,Master!B$4:B$174,Master!U$4:U$174,Master!W$4:W$174,Master!K$4:K$174,Master!H$4:H$174,Master!BN$4:BN$174},Master!J$4:J$174="Qualified",Master!D$4:D$174="Equity",Master!U$4:U$174<>""),3,FALSE),5,1),"") | B40: =IFERROR(INDEX(SORT(FILTER({Master!A$4:A$174,Master!B$4:B$174,Master!U$4:U$174,Master!W$4:W$174,Master!K$4:K$174,Master!H$4:H$174,Master!BN$4:BN$174},Master!J$4:J$174="Qualified",Master!D$4:D$174="Equity",Master!U$4:U$174<>""),3,FALSE),5,2),"") | C40: =IFERROR(INDEX(SORT(FILTER({Master!A$4:A$174,Master!B$4:B$174,Master!U$4:U$174,Master!W$4:W$174,Master!K$4:K$174,Master!H$4:H$174,Master!BN$4:BN$174},Master!J$4:J$174="Qualified",Master!D$4:D$174="Equity",Master!U$4:U$174<>""),3,FALSE),5,3),"") | D40: =IFERROR(INDEX(SORT(FILTER({Master!A$4:A$174,Master!B$4:B$174,Master!U$4:U$174,Master!W$4:W$174,Master!K$4:K$174,Master!H$4:H$174,Master!BN$4:BN$174},Master!J$4:J$174="Qualified",Master!D$4:D$174="Equity",Master!U$4:U$174<>""),3,FALSE),5,4),"") | E40: =IFERROR(INDEX(SORT(FILTER({Master!A$4:A$174,Master!B$4:B$174,Master!U$4:U$174,Master!W$4:W$174,Master!K$4:K$174,Master!H$4:H$174,Master!BN$4:BN$174},Master!J$4:J$174="Qualified",Master!D$4:D$174="Equity",Master!U$4:U$174<>""),3,FALSE),5,5),"") | F40: =IFERROR(INDEX(SORT(FILTER({Master!A$4:A$174,Master!B$4:B$174,Master!U$4:U$174,Master!W$4:W$174,Master!K$4:K$174,Master!H$4:H$174,Master!BN$4:BN$174},Master!J$4:J$174="Qualified",Master!D$4:D$174="Equity",Master!U$4:U$174<>""),3,FALSE),5,6),"") | G40: =IFERROR(INDEX(SORT(FILTER({Master!A$4:A$174,Master!B$4:B$174,Master!U$4:U$174,Master!W$4:W$174,Master!K$4:K$174,Master!H$4:H$174,Master!BN$4:BN$174},Master!J$4:J$174="Qualified",Master!D$4:D$174="Equity",Master!U$4:U$174<>""),3,FALSE),5,7),"")
A42: EQUITY — TOP 5 BY 3Y ANN. ALPHA
A43: Fund Name | B43: Abbr | C43: 3Y Fund (%) | D43: 3Y Alpha (%) | E43: Beat (%) | F43: AUM (RM M) | G43: VC
A44: =IFERROR(INDEX(SORT(FILTER({Master!A$4:A$174,Master!B$4:B$174,Master!U$4:U$174,Master!W$4:W$174,Master!K$4:K$174,Master!H$4:H$174,Master!BN$4:BN$174},Master!J$4:J$174="Qualified",Master!D$4:D$174="Equity",Master!W$4:W$174<>""),4,FALSE),1,1),"") | B44: =IFERROR(INDEX(SORT(FILTER({Master!A$4:A$174,Master!B$4:B$174,Master!U$4:U$174,Master!W$4:W$174,Master!K$4:K$174,Master!H$4:H$174,Master!BN$4:BN$174},Master!J$4:J$174="Qualified",Master!D$4:D$174="Equity",Master!W$4:W$174<>""),4,FALSE),1,2),"") | C44: =IFERROR(INDEX(SORT(FILTER({Master!A$4:A$174,Master!B$4:B$174,Master!U$4:U$174,Master!W$4:W$174,Master!K$4:K$174,Master!H$4:H$174,Master!BN$4:BN$174},Master!J$4:J$174="Qualified",Master!D$4:D$174="Equity",Master!W$4:W$174<>""),4,FALSE),1,3),"") | D44: =IFERROR(INDEX(SORT(FILTER({Master!A$4:A$174,Master!B$4:B$174,Master!U$4:U$174,Master!W$4:W$174,Master!K$4:K$174,Master!H$4:H$174,Master!BN$4:BN$174},Master!J$4:J$174="Qualified",Master!D$4:D$174="Equity",Master!W$4:W$174<>""),4,FALSE),1,4),"") | E44: =IFERROR(INDEX(SORT(FILTER({Master!A$4:A$174,Master!B$4:B$174,Master!U$4:U$174,Master!W$4:W$174,Master!K$4:K$174,Master!H$4:H$174,Master!BN$4:BN$174},Master!J$4:J$174="Qualified",Master!D$4:D$174="Equity",Master!W$4:W$174<>""),4,FALSE),1,5),"") | F44: =IFERROR(INDEX(SORT(FILTER({Master!A$4:A$174,Master!B$4:B$174,Master!U$4:U$174,Master!W$4:W$174,Master!K$4:K$174,Master!H$4:H$174,Master!BN$4:BN$174},Master!J$4:J$174="Qualified",Master!D$4:D$174="Equity",Master!W$4:W$174<>""),4,FALSE),1,6),"") | G44: =IFERROR(INDEX(SORT(FILTER({Master!A$4:A$174,Master!B$4:B$174,Master!U$4:U$174,Master!W$4:W$174,Master!K$4:K$174,Master!H$4:H$174,Master!BN$4:BN$174},Master!J$4:J$174="Qualified",Master!D$4:D$174="Equity",Master!W$4:W$174<>""),4,FALSE),1,7),"")
A45: =IFERROR(INDEX(SORT(FILTER({Master!A$4:A$174,Master!B$4:B$174,Master!U$4:U$174,Master!W$4:W$174,Master!K$4:K$174,Master!H$4:H$174,Master!BN$4:BN$174},Master!J$4:J$174="Qualified",Master!D$4:D$174="Equity",Master!W$4:W$174<>""),4,FALSE),2,1),"") | B45: =IFERROR(INDEX(SORT(FILTER({Master!A$4:A$174,Master!B$4:B$174,Master!U$4:U$174,Master!W$4:W$174,Master!K$4:K$174,Master!H$4:H$174,Master!BN$4:BN$174},Master!J$4:J$174="Qualified",Master!D$4:D$174="Equity",Master!W$4:W$174<>""),4,FALSE),2,2),"") | C45: =IFERROR(INDEX(SORT(FILTER({Master!A$4:A$174,Master!B$4:B$174,Master!U$4:U$174,Master!W$4:W$174,Master!K$4:K$174,Master!H$4:H$174,Master!BN$4:BN$174},Master!J$4:J$174="Qualified",Master!D$4:D$174="Equity",Master!W$4:W$174<>""),4,FALSE),2,3),"") | D45: =IFERROR(INDEX(SORT(FILTER({Master!A$4:A$174,Master!B$4:B$174,Master!U$4:U$174,Master!W$4:W$174,Master!K$4:K$174,Master!H$4:H$174,Master!BN$4:BN$174},Master!J$4:J$174="Qualified",Master!D$4:D$174="Equity",Master!W$4:W$174<>""),4,FALSE),2,4),"") | E45: =IFERROR(INDEX(SORT(FILTER({Master!A$4:A$174,Master!B$4:B$174,Master!U$4:U$174,Master!W$4:W$174,Master!K$4:K$174,Master!H$4:H$174,Master!BN$4:BN$174},Master!J$4:J$174="Qualified",Master!D$4:D$174="Equity",Master!W$4:W$174<>""),4,FALSE),2,5),"") | F45: =IFERROR(INDEX(SORT(FILTER({Master!A$4:A$174,Master!B$4:B$174,Master!U$4:U$174,Master!W$4:W$174,Master!K$4:K$174,Master!H$4:H$174,Master!BN$4:BN$174},Master!J$4:J$174="Qualified",Master!D$4:D$174="Equity",Master!W$4:W$174<>""),4,FALSE),2,6),"") | G45: =IFERROR(INDEX(SORT(FILTER({Master!A$4:A$174,Master!B$4:B$174,Master!U$4:U$174,Master!W$4:W$174,Master!K$4:K$174,Master!H$4:H$174,Master!BN$4:BN$174},Master!J$4:J$174="Qualified",Master!D$4:D$174="Equity",Master!W$4:W$174<>""),4,FALSE),2,7),"")
A46: =IFERROR(INDEX(SORT(FILTER({Master!A$4:A$174,Master!B$4:B$174,Master!U$4:U$174,Master!W$4:W$174,Master!K$4:K$174,Master!H$4:H$174,Master!BN$4:BN$174},Master!J$4:J$174="Qualified",Master!D$4:D$174="Equity",Master!W$4:W$174<>""),4,FALSE),3,1),"") | B46: =IFERROR(INDEX(SORT(FILTER({Master!A$4:A$174,Master!B$4:B$174,Master!U$4:U$174,Master!W$4:W$174,Master!K$4:K$174,Master!H$4:H$174,Master!BN$4:BN$174},Master!J$4:J$174="Qualified",Master!D$4:D$174="Equity",Master!W$4:W$174<>""),4,FALSE),3,2),"") | C46: =IFERROR(INDEX(SORT(FILTER({Master!A$4:A$174,Master!B$4:B$174,Master!U$4:U$174,Master!W$4:W$174,Master!K$4:K$174,Master!H$4:H$174,Master!BN$4:BN$174},Master!J$4:J$174="Qualified",Master!D$4:D$174="Equity",Master!W$4:W$174<>""),4,FALSE),3,3),"") | D46: =IFERROR(INDEX(SORT(FILTER({Master!A$4:A$174,Master!B$4:B$174,Master!U$4:U$174,Master!W$4:W$174,Master!K$4:K$174,Master!H$4:H$174,Master!BN$4:BN$174},Master!J$4:J$174="Qualified",Master!D$4:D$174="Equity",Master!W$4:W$174<>""),4,FALSE),3,4),"") | E46: =IFERROR(INDEX(SORT(FILTER({Master!A$4:A$174,Master!B$4:B$174,Master!U$4:U$174,Master!W$4:W$174,Master!K$4:K$174,Master!H$4:H$174,Master!BN$4:BN$174},Master!J$4:J$174="Qualified",Master!D$4:D$174="Equity",Master!W$4:W$174<>""),4,FALSE),3,5),"") | F46: =IFERROR(INDEX(SORT(FILTER({Master!A$4:A$174,Master!B$4:B$174,Master!U$4:U$174,Master!W$4:W$174,Master!K$4:K$174,Master!H$4:H$174,Master!BN$4:BN$174},Master!J$4:J$174="Qualified",Master!D$4:D$174="Equity",Master!W$4:W$174<>""),4,FALSE),3,6),"") | G46: =IFERROR(INDEX(SORT(FILTER({Master!A$4:A$174,Master!B$4:B$174,Master!U$4:U$174,Master!W$4:W$174,Master!K$4:K$174,Master!H$4:H$174,Master!BN$4:BN$174},Master!J$4:J$174="Qualified",Master!D$4:D$174="Equity",Master!W$4:W$174<>""),4,FALSE),3,7),"")
A47: =IFERROR(INDEX(SORT(FILTER({Master!A$4:A$174,Master!B$4:B$174,Master!U$4:U$174,Master!W$4:W$174,Master!K$4:K$174,Master!H$4:H$174,Master!BN$4:BN$174},Master!J$4:J$174="Qualified",Master!D$4:D$174="Equity",Master!W$4:W$174<>""),4,FALSE),4,1),"") | B47: =IFERROR(INDEX(SORT(FILTER({Master!A$4:A$174,Master!B$4:B$174,Master!U$4:U$174,Master!W$4:W$174,Master!K$4:K$174,Master!H$4:H$174,Master!BN$4:BN$174},Master!J$4:J$174="Qualified",Master!D$4:D$174="Equity",Master!W$4:W$174<>""),4,FALSE),4,2),"") | C47: =IFERROR(INDEX(SORT(FILTER({Master!A$4:A$174,Master!B$4:B$174,Master!U$4:U$174,Master!W$4:W$174,Master!K$4:K$174,Master!H$4:H$174,Master!BN$4:BN$174},Master!J$4:J$174="Qualified",Master!D$4:D$174="Equity",Master!W$4:W$174<>""),4,FALSE),4,3),"") | D47: =IFERROR(INDEX(SORT(FILTER({Master!A$4:A$174,Master!B$4:B$174,Master!U$4:U$174,Master!W$4:W$174,Master!K$4:K$174,Master!H$4:H$174,Master!BN$4:BN$174},Master!J$4:J$174="Qualified",Master!D$4:D$174="Equity",Master!W$4:W$174<>""),4,FALSE),4,4),"") | E47: =IFERROR(INDEX(SORT(FILTER({Master!A$4:A$174,Master!B$4:B$174,Master!U$4:U$174,Master!W$4:W$174,Master!K$4:K$174,Master!H$4:H$174,Master!BN$4:BN$174},Master!J$4:J$174="Qualified",Master!D$4:D$174="Equity",Master!W$4:W$174<>""),4,FALSE),4,5),"") | F47: =IFERROR(INDEX(SORT(FILTER({Master!A$4:A$174,Master!B$4:B$174,Master!U$4:U$174,Master!W$4:W$174,Master!K$4:K$174,Master!H$4:H$174,Master!BN$4:BN$174},Master!J$4:J$174="Qualified",Master!D$4:D$174="Equity",Master!W$4:W$174<>""),4,FALSE),4,6),"") | G47: =IFERROR(INDEX(SORT(FILTER({Master!A$4:A$174,Master!B$4:B$174,Master!U$4:U$174,Master!W$4:W$174,Master!K$4:K$174,Master!H$4:H$174,Master!BN$4:BN$174},Master!J$4:J$174="Qualified",Master!D$4:D$174="Equity",Master!W$4:W$174<>""),4,FALSE),4,7),"")
A48: =IFERROR(INDEX(SORT(FILTER({Master!A$4:A$174,Master!B$4:B$174,Master!U$4:U$174,Master!W$4:W$174,Master!K$4:K$174,Master!H$4:H$174,Master!BN$4:BN$174},Master!J$4:J$174="Qualified",Master!D$4:D$174="Equity",Master!W$4:W$174<>""),4,FALSE),5,1),"") | B48: =IFERROR(INDEX(SORT(FILTER({Master!A$4:A$174,Master!B$4:B$174,Master!U$4:U$174,Master!W$4:W$174,Master!K$4:K$174,Master!H$4:H$174,Master!BN$4:BN$174},Master!J$4:J$174="Qualified",Master!D$4:D$174="Equity",Master!W$4:W$174<>""),4,FALSE),5,2),"") | C48: =IFERROR(INDEX(SORT(FILTER({Master!A$4:A$174,Master!B$4:B$174,Master!U$4:U$174,Master!W$4:W$174,Master!K$4:K$174,Master!H$4:H$174,Master!BN$4:BN$174},Master!J$4:J$174="Qualified",Master!D$4:D$174="Equity",Master!W$4:W$174<>""),4,FALSE),5,3),"") | D48: =IFERROR(INDEX(SORT(FILTER({Master!A$4:A$174,Master!B$4:B$174,Master!U$4:U$174,Master!W$4:W$174,Master!K$4:K$174,Master!H$4:H$174,Master!BN$4:BN$174},Master!J$4:J$174="Qualified",Master!D$4:D$174="Equity",Master!W$4:W$174<>""),4,FALSE),5,4),"") | E48: =IFERROR(INDEX(SORT(FILTER({Master!A$4:A$174,Master!B$4:B$174,Master!U$4:U$174,Master!W$4:W$174,Master!K$4:K$174,Master!H$4:H$174,Master!BN$4:BN$174},Master!J$4:J$174="Qualified",Master!D$4:D$174="Equity",Master!W$4:W$174<>""),4,FALSE),5,5),"") | F48: =IFERROR(INDEX(SORT(FILTER({Master!A$4:A$174,Master!B$4:B$174,Master!U$4:U$174,Master!W$4:W$174,Master!K$4:K$174,Master!H$4:H$174,Master!BN$4:BN$174},Master!J$4:J$174="Qualified",Master!D$4:D$174="Equity",Master!W$4:W$174<>""),4,FALSE),5,6),"") | G48: =IFERROR(INDEX(SORT(FILTER({Master!A$4:A$174,Master!B$4:B$174,Master!U$4:U$174,Master!W$4:W$174,Master!K$4:K$174,Master!H$4:H$174,Master!BN$4:BN$174},Master!J$4:J$174="Qualified",Master!D$4:D$174="Equity",Master!W$4:W$174<>""),4,FALSE),5,7),"")
A50: EQUITY — TOP 5 BY ALPHA EFFICIENCY
A51: Fund Name | B51: Abbr | C51: Alpha Eff | D51: 3Y Alpha (%) | E51: Beat (%) | F51: AUM (RM M) | G51: VC
A52: =IFERROR(INDEX(SORT(FILTER({Master!A$4:A$174,Master!B$4:B$174,Master!AF$4:AF$174,Master!W$4:W$174,Master!K$4:K$174,Master!H$4:H$174,Master!BN$4:BN$174},Master!J$4:J$174="Qualified",Master!D$4:D$174="Equity",Master!AF$4:AF$174<>""),3,FALSE),1,1),"") | B52: =IFERROR(INDEX(SORT(FILTER({Master!A$4:A$174,Master!B$4:B$174,Master!AF$4:AF$174,Master!W$4:W$174,Master!K$4:K$174,Master!H$4:H$174,Master!BN$4:BN$174},Master!J$4:J$174="Qualified",Master!D$4:D$174="Equity",Master!AF$4:AF$174<>""),3,FALSE),1,2),"") | C52: =IFERROR(INDEX(SORT(FILTER({Master!A$4:A$174,Master!B$4:B$174,Master!AF$4:AF$174,Master!W$4:W$174,Master!K$4:K$174,Master!H$4:H$174,Master!BN$4:BN$174},Master!J$4:J$174="Qualified",Master!D$4:D$174="Equity",Master!AF$4:AF$174<>""),3,FALSE),1,3),"") | D52: =IFERROR(INDEX(SORT(FILTER({Master!A$4:A$174,Master!B$4:B$174,Master!AF$4:AF$174,Master!W$4:W$174,Master!K$4:K$174,Master!H$4:H$174,Master!BN$4:BN$174},Master!J$4:J$174="Qualified",Master!D$4:D$174="Equity",Master!AF$4:AF$174<>""),3,FALSE),1,4),"") | E52: =IFERROR(INDEX(SORT(FILTER({Master!A$4:A$174,Master!B$4:B$174,Master!AF$4:AF$174,Master!W$4:W$174,Master!K$4:K$174,Master!H$4:H$174,Master!BN$4:BN$174},Master!J$4:J$174="Qualified",Master!D$4:D$174="Equity",Master!AF$4:AF$174<>""),3,FALSE),1,5),"") | F52: =IFERROR(INDEX(SORT(FILTER({Master!A$4:A$174,Master!B$4:B$174,Master!AF$4:AF$174,Master!W$4:W$174,Master!K$4:K$174,Master!H$4:H$174,Master!BN$4:BN$174},Master!J$4:J$174="Qualified",Master!D$4:D$174="Equity",Master!AF$4:AF$174<>""),3,FALSE),1,6),"") | G52: =IFERROR(INDEX(SORT(FILTER({Master!A$4:A$174,Master!B$4:B$174,Master!AF$4:AF$174,Master!W$4:W$174,Master!K$4:K$174,Master!H$4:H$174,Master!BN$4:BN$174},Master!J$4:J$174="Qualified",Master!D$4:D$174="Equity",Master!AF$4:AF$174<>""),3,FALSE),1,7),"")
A53: =IFERROR(INDEX(SORT(FILTER({Master!A$4:A$174,Master!B$4:B$174,Master!AF$4:AF$174,Master!W$4:W$174,Master!K$4:K$174,Master!H$4:H$174,Master!BN$4:BN$174},Master!J$4:J$174="Qualified",Master!D$4:D$174="Equity",Master!AF$4:AF$174<>""),3,FALSE),2,1),"") | B53: =IFERROR(INDEX(SORT(FILTER({Master!A$4:A$174,Master!B$4:B$174,Master!AF$4:AF$174,Master!W$4:W$174,Master!K$4:K$174,Master!H$4:H$174,Master!BN$4:BN$174},Master!J$4:J$174="Qualified",Master!D$4:D$174="Equity",Master!AF$4:AF$174<>""),3,FALSE),2,2),"") | C53: =IFERROR(INDEX(SORT(FILTER({Master!A$4:A$174,Master!B$4:B$174,Master!AF$4:AF$174,Master!W$4:W$174,Master!K$4:K$174,Master!H$4:H$174,Master!BN$4:BN$174},Master!J$4:J$174="Qualified",Master!D$4:D$174="Equity",Master!AF$4:AF$174<>""),3,FALSE),2,3),"") | D53: =IFERROR(INDEX(SORT(FILTER({Master!A$4:A$174,Master!B$4:B$174,Master!AF$4:AF$174,Master!W$4:W$174,Master!K$4:K$174,Master!H$4:H$174,Master!BN$4:BN$174},Master!J$4:J$174="Qualified",Master!D$4:D$174="Equity",Master!AF$4:AF$174<>""),3,FALSE),2,4),"") | E53: =IFERROR(INDEX(SORT(FILTER({Master!A$4:A$174,Master!B$4:B$174,Master!AF$4:AF$174,Master!W$4:W$174,Master!K$4:K$174,Master!H$4:H$174,Master!BN$4:BN$174},Master!J$4:J$174="Qualified",Master!D$4:D$174="Equity",Master!AF$4:AF$174<>""),3,FALSE),2,5),"") | F53: =IFERROR(INDEX(SORT(FILTER({Master!A$4:A$174,Master!B$4:B$174,Master!AF$4:AF$174,Master!W$4:W$174,Master!K$4:K$174,Master!H$4:H$174,Master!BN$4:BN$174},Master!J$4:J$174="Qualified",Master!D$4:D$174="Equity",Master!AF$4:AF$174<>""),3,FALSE),2,6),"") | G53: =IFERROR(INDEX(SORT(FILTER({Master!A$4:A$174,Master!B$4:B$174,Master!AF$4:AF$174,Master!W$4:W$174,Master!K$4:K$174,Master!H$4:H$174,Master!BN$4:BN$174},Master!J$4:J$174="Qualified",Master!D$4:D$174="Equity",Master!AF$4:AF$174<>""),3,FALSE),2,7),"")
A54: =IFERROR(INDEX(SORT(FILTER({Master!A$4:A$174,Master!B$4:B$174,Master!AF$4:AF$174,Master!W$4:W$174,Master!K$4:K$174,Master!H$4:H$174,Master!BN$4:BN$174},Master!J$4:J$174="Qualified",Master!D$4:D$174="Equity",Master!AF$4:AF$174<>""),3,FALSE),3,1),"") | B54: =IFERROR(INDEX(SORT(FILTER({Master!A$4:A$174,Master!B$4:B$174,Master!AF$4:AF$174,Master!W$4:W$174,Master!K$4:K$174,Master!H$4:H$174,Master!BN$4:BN$174},Master!J$4:J$174="Qualified",Master!D$4:D$174="Equity",Master!AF$4:AF$174<>""),3,FALSE),3,2),"") | C54: =IFERROR(INDEX(SORT(FILTER({Master!A$4:A$174,Master!B$4:B$174,Master!AF$4:AF$174,Master!W$4:W$174,Master!K$4:K$174,Master!H$4:H$174,Master!BN$4:BN$174},Master!J$4:J$174="Qualified",Master!D$4:D$174="Equity",Master!AF$4:AF$174<>""),3,FALSE),3,3),"") | D54: =IFERROR(INDEX(SORT(FILTER({Master!A$4:A$174,Master!B$4:B$174,Master!AF$4:AF$174,Master!W$4:W$174,Master!K$4:K$174,Master!H$4:H$174,Master!BN$4:BN$174},Master!J$4:J$174="Qualified",Master!D$4:D$174="Equity",Master!AF$4:AF$174<>""),3,FALSE),3,4),"") | E54: =IFERROR(INDEX(SORT(FILTER({Master!A$4:A$174,Master!B$4:B$174,Master!AF$4:AF$174,Master!W$4:W$174,Master!K$4:K$174,Master!H$4:H$174,Master!BN$4:BN$174},Master!J$4:J$174="Qualified",Master!D$4:D$174="Equity",Master!AF$4:AF$174<>""),3,FALSE),3,5),"") | F54: =IFERROR(INDEX(SORT(FILTER({Master!A$4:A$174,Master!B$4:B$174,Master!AF$4:AF$174,Master!W$4:W$174,Master!K$4:K$174,Master!H$4:H$174,Master!BN$4:BN$174},Master!J$4:J$174="Qualified",Master!D$4:D$174="Equity",Master!AF$4:AF$174<>""),3,FALSE),3,6),"") | G54: =IFERROR(INDEX(SORT(FILTER({Master!A$4:A$174,Master!B$4:B$174,Master!AF$4:AF$174,Master!W$4:W$174,Master!K$4:K$174,Master!H$4:H$174,Master!BN$4:BN$174},Master!J$4:J$174="Qualified",Master!D$4:D$174="Equity",Master!AF$4:AF$174<>""),3,FALSE),3,7),"")
A55: =IFERROR(INDEX(SORT(FILTER({Master!A$4:A$174,Master!B$4:B$174,Master!AF$4:AF$174,Master!W$4:W$174,Master!K$4:K$174,Master!H$4:H$174,Master!BN$4:BN$174},Master!J$4:J$174="Qualified",Master!D$4:D$174="Equity",Master!AF$4:AF$174<>""),3,FALSE),4,1),"") | B55: =IFERROR(INDEX(SORT(FILTER({Master!A$4:A$174,Master!B$4:B$174,Master!AF$4:AF$174,Master!W$4:W$174,Master!K$4:K$174,Master!H$4:H$174,Master!BN$4:BN$174},Master!J$4:J$174="Qualified",Master!D$4:D$174="Equity",Master!AF$4:AF$174<>""),3,FALSE),4,2),"") | C55: =IFERROR(INDEX(SORT(FILTER({Master!A$4:A$174,Master!B$4:B$174,Master!AF$4:AF$174,Master!W$4:W$174,Master!K$4:K$174,Master!H$4:H$174,Master!BN$4:BN$174},Master!J$4:J$174="Qualified",Master!D$4:D$174="Equity",Master!AF$4:AF$174<>""),3,FALSE),4,3),"") | D55: =IFERROR(INDEX(SORT(FILTER({Master!A$4:A$174,Master!B$4:B$174,Master!AF$4:AF$174,Master!W$4:W$174,Master!K$4:K$174,Master!H$4:H$174,Master!BN$4:BN$174},Master!J$4:J$174="Qualified",Master!D$4:D$174="Equity",Master!AF$4:AF$174<>""),3,FALSE),4,4),"") | E55: =IFERROR(INDEX(SORT(FILTER({Master!A$4:A$174,Master!B$4:B$174,Master!AF$4:AF$174,Master!W$4:W$174,Master!K$4:K$174,Master!H$4:H$174,Master!BN$4:BN$174},Master!J$4:J$174="Qualified",Master!D$4:D$174="Equity",Master!AF$4:AF$174<>""),3,FALSE),4,5),"") | F55: =IFERROR(INDEX(SORT(FILTER({Master!A$4:A$174,Master!B$4:B$174,Master!AF$4:AF$174,Master!W$4:W$174,Master!K$4:K$174,Master!H$4:H$174,Master!BN$4:BN$174},Master!J$4:J$174="Qualified",Master!D$4:D$174="Equity",Master!AF$4:AF$174<>""),3,FALSE),4,6),"") | G55: =IFERROR(INDEX(SORT(FILTER({Master!A$4:A$174,Master!B$4:B$174,Master!AF$4:AF$174,Master!W$4:W$174,Master!K$4:K$174,Master!H$4:H$174,Master!BN$4:BN$174},Master!J$4:J$174="Qualified",Master!D$4:D$174="Equity",Master!AF$4:AF$174<>""),3,FALSE),4,7),"")
A56: =IFERROR(INDEX(SORT(FILTER({Master!A$4:A$174,Master!B$4:B$174,Master!AF$4:AF$174,Master!W$4:W$174,Master!K$4:K$174,Master!H$4:H$174,Master!BN$4:BN$174},Master!J$4:J$174="Qualified",Master!D$4:D$174="Equity",Master!AF$4:AF$174<>""),3,FALSE),5,1),"") | B56: =IFERROR(INDEX(SORT(FILTER({Master!A$4:A$174,Master!B$4:B$174,Master!AF$4:AF$174,Master!W$4:W$174,Master!K$4:K$174,Master!H$4:H$174,Master!BN$4:BN$174},Master!J$4:J$174="Qualified",Master!D$4:D$174="Equity",Master!AF$4:AF$174<>""),3,FALSE),5,2),"") | C56: =IFERROR(INDEX(SORT(FILTER({Master!A$4:A$174,Master!B$4:B$174,Master!AF$4:AF$174,Master!W$4:W$174,Master!K$4:K$174,Master!H$4:H$174,Master!BN$4:BN$174},Master!J$4:J$174="Qualified",Master!D$4:D$174="Equity",Master!AF$4:AF$174<>""),3,FALSE),5,3),"") | D56: =IFERROR(INDEX(SORT(FILTER({Master!A$4:A$174,Master!B$4:B$174,Master!AF$4:AF$174,Master!W$4:W$174,Master!K$4:K$174,Master!H$4:H$174,Master!BN$4:BN$174},Master!J$4:J$174="Qualified",Master!D$4:D$174="Equity",Master!AF$4:AF$174<>""),3,FALSE),5,4),"") | E56: =IFERROR(INDEX(SORT(FILTER({Master!A$4:A$174,Master!B$4:B$174,Master!AF$4:AF$174,Master!W$4:W$174,Master!K$4:K$174,Master!H$4:H$174,Master!BN$4:BN$174},Master!J$4:J$174="Qualified",Master!D$4:D$174="Equity",Master!AF$4:AF$174<>""),3,FALSE),5,5),"") | F56: =IFERROR(INDEX(SORT(FILTER({Master!A$4:A$174,Master!B$4:B$174,Master!AF$4:AF$174,Master!W$4:W$174,Master!K$4:K$174,Master!H$4:H$174,Master!BN$4:BN$174},Master!J$4:J$174="Qualified",Master!D$4:D$174="Equity",Master!AF$4:AF$174<>""),3,FALSE),5,6),"") | G56: =IFERROR(INDEX(SORT(FILTER({Master!A$4:A$174,Master!B$4:B$174,Master!AF$4:AF$174,Master!W$4:W$174,Master!K$4:K$174,Master!H$4:H$174,Master!BN$4:BN$174},Master!J$4:J$174="Qualified",Master!D$4:D$174="Equity",Master!AF$4:AF$174<>""),3,FALSE),5,7),"")
A58: EQUITY — TOP 5 BY AUM
A59: Fund Name | B59: Abbr | C59: AUM (RM M) | D59: 3Y Fund (%) | E59: 3Y Alpha (%) | F59: Beat (%) | G59: VC
A60: =IFERROR(INDEX(SORT(FILTER({Master!A$4:A$174,Master!B$4:B$174,Master!H$4:H$174,Master!U$4:U$174,Master!W$4:W$174,Master!K$4:K$174,Master!BN$4:BN$174},Master!J$4:J$174="Qualified",Master!D$4:D$174="Equity",Master!H$4:H$174<>""),3,FALSE),1,1),"") | B60: =IFERROR(INDEX(SORT(FILTER({Master!A$4:A$174,Master!B$4:B$174,Master!H$4:H$174,Master!U$4:U$174,Master!W$4:W$174,Master!K$4:K$174,Master!BN$4:BN$174},Master!J$4:J$174="Qualified",Master!D$4:D$174="Equity",Master!H$4:H$174<>""),3,FALSE),1,2),"") | C60: =IFERROR(INDEX(SORT(FILTER({Master!A$4:A$174,Master!B$4:B$174,Master!H$4:H$174,Master!U$4:U$174,Master!W$4:W$174,Master!K$4:K$174,Master!BN$4:BN$174},Master!J$4:J$174="Qualified",Master!D$4:D$174="Equity",Master!H$4:H$174<>""),3,FALSE),1,3),"") | D60: =IFERROR(INDEX(SORT(FILTER({Master!A$4:A$174,Master!B$4:B$174,Master!H$4:H$174,Master!U$4:U$174,Master!W$4:W$174,Master!K$4:K$174,Master!BN$4:BN$174},Master!J$4:J$174="Qualified",Master!D$4:D$174="Equity",Master!H$4:H$174<>""),3,FALSE),1,4),"") | E60: =IFERROR(INDEX(SORT(FILTER({Master!A$4:A$174,Master!B$4:B$174,Master!H$4:H$174,Master!U$4:U$174,Master!W$4:W$174,Master!K$4:K$174,Master!BN$4:BN$174},Master!J$4:J$174="Qualified",Master!D$4:D$174="Equity",Master!H$4:H$174<>""),3,FALSE),1,5),"") | F60: =IFERROR(INDEX(SORT(FILTER({Master!A$4:A$174,Master!B$4:B$174,Master!H$4:H$174,Master!U$4:U$174,Master!W$4:W$174,Master!K$4:K$174,Master!BN$4:BN$174},Master!J$4:J$174="Qualified",Master!D$4:D$174="Equity",Master!H$4:H$174<>""),3,FALSE),1,6),"") | G60: =IFERROR(INDEX(SORT(FILTER({Master!A$4:A$174,Master!B$4:B$174,Master!H$4:H$174,Master!U$4:U$174,Master!W$4:W$174,Master!K$4:K$174,Master!BN$4:BN$174},Master!J$4:J$174="Qualified",Master!D$4:D$174="Equity",Master!H$4:H$174<>""),3,FALSE),1,7),"")
A61: =IFERROR(INDEX(SORT(FILTER({Master!A$4:A$174,Master!B$4:B$174,Master!H$4:H$174,Master!U$4:U$174,Master!W$4:W$174,Master!K$4:K$174,Master!BN$4:BN$174},Master!J$4:J$174="Qualified",Master!D$4:D$174="Equity",Master!H$4:H$174<>""),3,FALSE),2,1),"") | B61: =IFERROR(INDEX(SORT(FILTER({Master!A$4:A$174,Master!B$4:B$174,Master!H$4:H$174,Master!U$4:U$174,Master!W$4:W$174,Master!K$4:K$174,Master!BN$4:BN$174},Master!J$4:J$174="Qualified",Master!D$4:D$174="Equity",Master!H$4:H$174<>""),3,FALSE),2,2),"") | C61: =IFERROR(INDEX(SORT(FILTER({Master!A$4:A$174,Master!B$4:B$174,Master!H$4:H$174,Master!U$4:U$174,Master!W$4:W$174,Master!K$4:K$174,Master!BN$4:BN$174},Master!J$4:J$174="Qualified",Master!D$4:D$174="Equity",Master!H$4:H$174<>""),3,FALSE),2,3),"") | D61: =IFERROR(INDEX(SORT(FILTER({Master!A$4:A$174,Master!B$4:B$174,Master!H$4:H$174,Master!U$4:U$174,Master!W$4:W$174,Master!K$4:K$174,Master!BN$4:BN$174},Master!J$4:J$174="Qualified",Master!D$4:D$174="Equity",Master!H$4:H$174<>""),3,FALSE),2,4),"") | E61: =IFERROR(INDEX(SORT(FILTER({Master!A$4:A$174,Master!B$4:B$174,Master!H$4:H$174,Master!U$4:U$174,Master!W$4:W$174,Master!K$4:K$174,Master!BN$4:BN$174},Master!J$4:J$174="Qualified",Master!D$4:D$174="Equity",Master!H$4:H$174<>""),3,FALSE),2,5),"") | F61: =IFERROR(INDEX(SORT(FILTER({Master!A$4:A$174,Master!B$4:B$174,Master!H$4:H$174,Master!U$4:U$174,Master!W$4:W$174,Master!K$4:K$174,Master!BN$4:BN$174},Master!J$4:J$174="Qualified",Master!D$4:D$174="Equity",Master!H$4:H$174<>""),3,FALSE),2,6),"") | G61: =IFERROR(INDEX(SORT(FILTER({Master!A$4:A$174,Master!B$4:B$174,Master!H$4:H$174,Master!U$4:U$174,Master!W$4:W$174,Master!K$4:K$174,Master!BN$4:BN$174},Master!J$4:J$174="Qualified",Master!D$4:D$174="Equity",Master!H$4:H$174<>""),3,FALSE),2,7),"")
A62: =IFERROR(INDEX(SORT(FILTER({Master!A$4:A$174,Master!B$4:B$174,Master!H$4:H$174,Master!U$4:U$174,Master!W$4:W$174,Master!K$4:K$174,Master!BN$4:BN$174},Master!J$4:J$174="Qualified",Master!D$4:D$174="Equity",Master!H$4:H$174<>""),3,FALSE),3,1),"") | B62: =IFERROR(INDEX(SORT(FILTER({Master!A$4:A$174,Master!B$4:B$174,Master!H$4:H$174,Master!U$4:U$174,Master!W$4:W$174,Master!K$4:K$174,Master!BN$4:BN$174},Master!J$4:J$174="Qualified",Master!D$4:D$174="Equity",Master!H$4:H$174<>""),3,FALSE),3,2),"") | C62: =IFERROR(INDEX(SORT(FILTER({Master!A$4:A$174,Master!B$4:B$174,Master!H$4:H$174,Master!U$4:U$174,Master!W$4:W$174,Master!K$4:K$174,Master!BN$4:BN$174},Master!J$4:J$174="Qualified",Master!D$4:D$174="Equity",Master!H$4:H$174<>""),3,FALSE),3,3),"") | D62: =IFERROR(INDEX(SORT(FILTER({Master!A$4:A$174,Master!B$4:B$174,Master!H$4:H$174,Master!U$4:U$174,Master!W$4:W$174,Master!K$4:K$174,Master!BN$4:BN$174},Master!J$4:J$174="Qualified",Master!D$4:D$174="Equity",Master!H$4:H$174<>""),3,FALSE),3,4),"") | E62: =IFERROR(INDEX(SORT(FILTER({Master!A$4:A$174,Master!B$4:B$174,Master!H$4:H$174,Master!U$4:U$174,Master!W$4:W$174,Master!K$4:K$174,Master!BN$4:BN$174},Master!J$4:J$174="Qualified",Master!D$4:D$174="Equity",Master!H$4:H$174<>""),3,FALSE),3,5),"") | F62: =IFERROR(INDEX(SORT(FILTER({Master!A$4:A$174,Master!B$4:B$174,Master!H$4:H$174,Master!U$4:U$174,Master!W$4:W$174,Master!K$4:K$174,Master!BN$4:BN$174},Master!J$4:J$174="Qualified",Master!D$4:D$174="Equity",Master!H$4:H$174<>""),3,FALSE),3,6),"") | G62: =IFERROR(INDEX(SORT(FILTER({Master!A$4:A$174,Master!B$4:B$174,Master!H$4:H$174,Master!U$4:U$174,Master!W$4:W$174,Master!K$4:K$174,Master!BN$4:BN$174},Master!J$4:J$174="Qualified",Master!D$4:D$174="Equity",Master!H$4:H$174<>""),3,FALSE),3,7),"")
A63: =IFERROR(INDEX(SORT(FILTER({Master!A$4:A$174,Master!B$4:B$174,Master!H$4:H$174,Master!U$4:U$174,Master!W$4:W$174,Master!K$4:K$174,Master!BN$4:BN$174},Master!J$4:J$174="Qualified",Master!D$4:D$174="Equity",Master!H$4:H$174<>""),3,FALSE),4,1),"") | B63: =IFERROR(INDEX(SORT(FILTER({Master!A$4:A$174,Master!B$4:B$174,Master!H$4:H$174,Master!U$4:U$174,Master!W$4:W$174,Master!K$4:K$174,Master!BN$4:BN$174},Master!J$4:J$174="Qualified",Master!D$4:D$174="Equity",Master!H$4:H$174<>""),3,FALSE),4,2),"") | C63: =IFERROR(INDEX(SORT(FILTER({Master!A$4:A$174,Master!B$4:B$174,Master!H$4:H$174,Master!U$4:U$174,Master!W$4:W$174,Master!K$4:K$174,Master!BN$4:BN$174},Master!J$4:J$174="Qualified",Master!D$4:D$174="Equity",Master!H$4:H$174<>""),3,FALSE),4,3),"") | D63: =IFERROR(INDEX(SORT(FILTER({Master!A$4:A$174,Master!B$4:B$174,Master!H$4:H$174,Master!U$4:U$174,Master!W$4:W$174,Master!K$4:K$174,Master!BN$4:BN$174},Master!J$4:J$174="Qualified",Master!D$4:D$174="Equity",Master!H$4:H$174<>""),3,FALSE),4,4),"") | E63: =IFERROR(INDEX(SORT(FILTER({Master!A$4:A$174,Master!B$4:B$174,Master!H$4:H$174,Master!U$4:U$174,Master!W$4:W$174,Master!K$4:K$174,Master!BN$4:BN$174},Master!J$4:J$174="Qualified",Master!D$4:D$174="Equity",Master!H$4:H$174<>""),3,FALSE),4,5),"") | F63: =IFERROR(INDEX(SORT(FILTER({Master!A$4:A$174,Master!B$4:B$174,Master!H$4:H$174,Master!U$4:U$174,Master!W$4:W$174,Master!K$4:K$174,Master!BN$4:BN$174},Master!J$4:J$174="Qualified",Master!D$4:D$174="Equity",Master!H$4:H$174<>""),3,FALSE),4,6),"") | G63: =IFERROR(INDEX(SORT(FILTER({Master!A$4:A$174,Master!B$4:B$174,Master!H$4:H$174,Master!U$4:U$174,Master!W$4:W$174,Master!K$4:K$174,Master!BN$4:BN$174},Master!J$4:J$174="Qualified",Master!D$4:D$174="Equity",Master!H$4:H$174<>""),3,FALSE),4,7),"")
A64: =IFERROR(INDEX(SORT(FILTER({Master!A$4:A$174,Master!B$4:B$174,Master!H$4:H$174,Master!U$4:U$174,Master!W$4:W$174,Master!K$4:K$174,Master!BN$4:BN$174},Master!J$4:J$174="Qualified",Master!D$4:D$174="Equity",Master!H$4:H$174<>""),3,FALSE),5,1),"") | B64: =IFERROR(INDEX(SORT(FILTER({Master!A$4:A$174,Master!B$4:B$174,Master!H$4:H$174,Master!U$4:U$174,Master!W$4:W$174,Master!K$4:K$174,Master!BN$4:BN$174},Master!J$4:J$174="Qualified",Master!D$4:D$174="Equity",Master!H$4:H$174<>""),3,FALSE),5,2),"") | C64: =IFERROR(INDEX(SORT(FILTER({Master!A$4:A$174,Master!B$4:B$174,Master!H$4:H$174,Master!U$4:U$174,Master!W$4:W$174,Master!K$4:K$174,Master!BN$4:BN$174},Master!J$4:J$174="Qualified",Master!D$4:D$174="Equity",Master!H$4:H$174<>""),3,FALSE),5,3),"") | D64: =IFERROR(INDEX(SORT(FILTER({Master!A$4:A$174,Master!B$4:B$174,Master!H$4:H$174,Master!U$4:U$174,Master!W$4:W$174,Master!K$4:K$174,Master!BN$4:BN$174},Master!J$4:J$174="Qualified",Master!D$4:D$174="Equity",Master!H$4:H$174<>""),3,FALSE),5,4),"") | E64: =IFERROR(INDEX(SORT(FILTER({Master!A$4:A$174,Master!B$4:B$174,Master!H$4:H$174,Master!U$4:U$174,Master!W$4:W$174,Master!K$4:K$174,Master!BN$4:BN$174},Master!J$4:J$174="Qualified",Master!D$4:D$174="Equity",Master!H$4:H$174<>""),3,FALSE),5,5),"") | F64: =IFERROR(INDEX(SORT(FILTER({Master!A$4:A$174,Master!B$4:B$174,Master!H$4:H$174,Master!U$4:U$174,Master!W$4:W$174,Master!K$4:K$174,Master!BN$4:BN$174},Master!J$4:J$174="Qualified",Master!D$4:D$174="Equity",Master!H$4:H$174<>""),3,FALSE),5,6),"") | G64: =IFERROR(INDEX(SORT(FILTER({Master!A$4:A$174,Master!B$4:B$174,Master!H$4:H$174,Master!U$4:U$174,Master!W$4:W$174,Master!K$4:K$174,Master!BN$4:BN$174},Master!J$4:J$174="Qualified",Master!D$4:D$174="Equity",Master!H$4:H$174<>""),3,FALSE),5,7),"")
A66: BALANCED / MIXED ASSET — MEDIAN STATISTICS
A67: Metric | B67: YTD (%) | C67: 1Y (%) | D67: 3Y Ann. (%) | E67: 5Y Ann. (%) | F67: 10Y Ann. (%) | G67: 3Y Alpha (%) | H67: Beat (%)
A68: Median | B68: =IFERROR(MEDIAN(FILTER(Master!O$4:O$174,(Master!J$4:J$174="Qualified")*(Master!D$4:D$174="Mixed Asset / Balanced"))),"") | C68: =IFERROR(MEDIAN(FILTER(Master!R$4:R$174,(Master!J$4:J$174="Qualified")*(Master!D$4:D$174="Mixed Asset / Balanced"))),"") | D68: =IFERROR(MEDIAN(FILTER(Master!U$4:U$174,(Master!J$4:J$174="Qualified")*(Master!D$4:D$174="Mixed Asset / Balanced"))),"") | E68: =IFERROR(MEDIAN(FILTER(Master!X$4:X$174,(Master!J$4:J$174="Qualified")*(Master!D$4:D$174="Mixed Asset / Balanced"))),"") | F68: =IFERROR(MEDIAN(FILTER(Master!AA$4:AA$174,(Master!J$4:J$174="Qualified")*(Master!D$4:D$174="Mixed Asset / Balanced"))),"") | G68: =IFERROR(MEDIAN(FILTER(Master!W$4:W$174,(Master!J$4:J$174="Qualified")*(Master!D$4:D$174="Mixed Asset / Balanced"))),"") | H68: =IFERROR(MEDIAN(FILTER(Master!K$4:K$174,(Master!J$4:J$174="Qualified")*(Master!D$4:D$174="Mixed Asset / Balanced"))),"")
A70: BALANCED / MIXED ASSET — TOP 5 BY 3Y ANN. FUND RETURN
A71: Fund Name | B71: Abbr | C71: 3Y Fund (%) | D71: 3Y Alpha (%) | E71: Beat (%) | F71: AUM (RM M) | G71: VC
A72: =IFERROR(INDEX(SORT(FILTER({Master!A$4:A$174,Master!B$4:B$174,Master!U$4:U$174,Master!W$4:W$174,Master!K$4:K$174,Master!H$4:H$174,Master!BN$4:BN$174},Master!J$4:J$174="Qualified",Master!D$4:D$174="Mixed Asset / Balanced",Master!U$4:U$174<>""),3,FALSE),1,1),"") | B72: =IFERROR(INDEX(SORT(FILTER({Master!A$4:A$174,Master!B$4:B$174,Master!U$4:U$174,Master!W$4:W$174,Master!K$4:K$174,Master!H$4:H$174,Master!BN$4:BN$174},Master!J$4:J$174="Qualified",Master!D$4:D$174="Mixed Asset / Balanced",Master!U$4:U$174<>""),3,FALSE),1,2),"") | C72: =IFERROR(INDEX(SORT(FILTER({Master!A$4:A$174,Master!B$4:B$174,Master!U$4:U$174,Master!W$4:W$174,Master!K$4:K$174,Master!H$4:H$174,Master!BN$4:BN$174},Master!J$4:J$174="Qualified",Master!D$4:D$174="Mixed Asset / Balanced",Master!U$4:U$174<>""),3,FALSE),1,3),"") | D72: =IFERROR(INDEX(SORT(FILTER({Master!A$4:A$174,Master!B$4:B$174,Master!U$4:U$174,Master!W$4:W$174,Master!K$4:K$174,Master!H$4:H$174,Master!BN$4:BN$174},Master!J$4:J$174="Qualified",Master!D$4:D$174="Mixed Asset / Balanced",Master!U$4:U$174<>""),3,FALSE),1,4),"") | E72: =IFERROR(INDEX(SORT(FILTER({Master!A$4:A$174,Master!B$4:B$174,Master!U$4:U$174,Master!W$4:W$174,Master!K$4:K$174,Master!H$4:H$174,Master!BN$4:BN$174},Master!J$4:J$174="Qualified",Master!D$4:D$174="Mixed Asset / Balanced",Master!U$4:U$174<>""),3,FALSE),1,5),"") | F72: =IFERROR(INDEX(SORT(FILTER({Master!A$4:A$174,Master!B$4:B$174,Master!U$4:U$174,Master!W$4:W$174,Master!K$4:K$174,Master!H$4:H$174,Master!BN$4:BN$174},Master!J$4:J$174="Qualified",Master!D$4:D$174="Mixed Asset / Balanced",Master!U$4:U$174<>""),3,FALSE),1,6),"") | G72: =IFERROR(INDEX(SORT(FILTER({Master!A$4:A$174,Master!B$4:B$174,Master!U$4:U$174,Master!W$4:W$174,Master!K$4:K$174,Master!H$4:H$174,Master!BN$4:BN$174},Master!J$4:J$174="Qualified",Master!D$4:D$174="Mixed Asset / Balanced",Master!U$4:U$174<>""),3,FALSE),1,7),"")
A73: =IFERROR(INDEX(SORT(FILTER({Master!A$4:A$174,Master!B$4:B$174,Master!U$4:U$174,Master!W$4:W$174,Master!K$4:K$174,Master!H$4:H$174,Master!BN$4:BN$174},Master!J$4:J$174="Qualified",Master!D$4:D$174="Mixed Asset / Balanced",Master!U$4:U$174<>""),3,FALSE),2,1),"") | B73: =IFERROR(INDEX(SORT(FILTER({Master!A$4:A$174,Master!B$4:B$174,Master!U$4:U$174,Master!W$4:W$174,Master!K$4:K$174,Master!H$4:H$174,Master!BN$4:BN$174},Master!J$4:J$174="Qualified",Master!D$4:D$174="Mixed Asset / Balanced",Master!U$4:U$174<>""),3,FALSE),2,2),"") | C73: =IFERROR(INDEX(SORT(FILTER({Master!A$4:A$174,Master!B$4:B$174,Master!U$4:U$174,Master!W$4:W$174,Master!K$4:K$174,Master!H$4:H$174,Master!BN$4:BN$174},Master!J$4:J$174="Qualified",Master!D$4:D$174="Mixed Asset / Balanced",Master!U$4:U$174<>""),3,FALSE),2,3),"") | D73: =IFERROR(INDEX(SORT(FILTER({Master!A$4:A$174,Master!B$4:B$174,Master!U$4:U$174,Master!W$4:W$174,Master!K$4:K$174,Master!H$4:H$174,Master!BN$4:BN$174},Master!J$4:J$174="Qualified",Master!D$4:D$174="Mixed Asset / Balanced",Master!U$4:U$174<>""),3,FALSE),2,4),"") | E73: =IFERROR(INDEX(SORT(FILTER({Master!A$4:A$174,Master!B$4:B$174,Master!U$4:U$174,Master!W$4:W$174,Master!K$4:K$174,Master!H$4:H$174,Master!BN$4:BN$174},Master!J$4:J$174="Qualified",Master!D$4:D$174="Mixed Asset / Balanced",Master!U$4:U$174<>""),3,FALSE),2,5),"") | F73: =IFERROR(INDEX(SORT(FILTER({Master!A$4:A$174,Master!B$4:B$174,Master!U$4:U$174,Master!W$4:W$174,Master!K$4:K$174,Master!H$4:H$174,Master!BN$4:BN$174},Master!J$4:J$174="Qualified",Master!D$4:D$174="Mixed Asset / Balanced",Master!U$4:U$174<>""),3,FALSE),2,6),"") | G73: =IFERROR(INDEX(SORT(FILTER({Master!A$4:A$174,Master!B$4:B$174,Master!U$4:U$174,Master!W$4:W$174,Master!K$4:K$174,Master!H$4:H$174,Master!BN$4:BN$174},Master!J$4:J$174="Qualified",Master!D$4:D$174="Mixed Asset / Balanced",Master!U$4:U$174<>""),3,FALSE),2,7),"")
A74: =IFERROR(INDEX(SORT(FILTER({Master!A$4:A$174,Master!B$4:B$174,Master!U$4:U$174,Master!W$4:W$174,Master!K$4:K$174,Master!H$4:H$174,Master!BN$4:BN$174},Master!J$4:J$174="Qualified",Master!D$4:D$174="Mixed Asset / Balanced",Master!U$4:U$174<>""),3,FALSE),3,1),"") | B74: =IFERROR(INDEX(SORT(FILTER({Master!A$4:A$174,Master!B$4:B$174,Master!U$4:U$174,Master!W$4:W$174,Master!K$4:K$174,Master!H$4:H$174,Master!BN$4:BN$174},Master!J$4:J$174="Qualified",Master!D$4:D$174="Mixed Asset / Balanced",Master!U$4:U$174<>""),3,FALSE),3,2),"") | C74: =IFERROR(INDEX(SORT(FILTER({Master!A$4:A$174,Master!B$4:B$174,Master!U$4:U$174,Master!W$4:W$174,Master!K$4:K$174,Master!H$4:H$174,Master!BN$4:BN$174},Master!J$4:J$174="Qualified",Master!D$4:D$174="Mixed Asset / Balanced",Master!U$4:U$174<>""),3,FALSE),3,3),"") | D74: =IFERROR(INDEX(SORT(FILTER({Master!A$4:A$174,Master!B$4:B$174,Master!U$4:U$174,Master!W$4:W$174,Master!K$4:K$174,Master!H$4:H$174,Master!BN$4:BN$174},Master!J$4:J$174="Qualified",Master!D$4:D$174="Mixed Asset / Balanced",Master!U$4:U$174<>""),3,FALSE),3,4),"") | E74: =IFERROR(INDEX(SORT(FILTER({Master!A$4:A$174,Master!B$4:B$174,Master!U$4:U$174,Master!W$4:W$174,Master!K$4:K$174,Master!H$4:H$174,Master!BN$4:BN$174},Master!J$4:J$174="Qualified",Master!D$4:D$174="Mixed Asset / Balanced",Master!U$4:U$174<>""),3,FALSE),3,5),"") | F74: =IFERROR(INDEX(SORT(FILTER({Master!A$4:A$174,Master!B$4:B$174,Master!U$4:U$174,Master!W$4:W$174,Master!K$4:K$174,Master!H$4:H$174,Master!BN$4:BN$174},Master!J$4:J$174="Qualified",Master!D$4:D$174="Mixed Asset / Balanced",Master!U$4:U$174<>""),3,FALSE),3,6),"") | G74: =IFERROR(INDEX(SORT(FILTER({Master!A$4:A$174,Master!B$4:B$174,Master!U$4:U$174,Master!W$4:W$174,Master!K$4:K$174,Master!H$4:H$174,Master!BN$4:BN$174},Master!J$4:J$174="Qualified",Master!D$4:D$174="Mixed Asset / Balanced",Master!U$4:U$174<>""),3,FALSE),3,7),"")
A75: =IFERROR(INDEX(SORT(FILTER({Master!A$4:A$174,Master!B$4:B$174,Master!U$4:U$174,Master!W$4:W$174,Master!K$4:K$174,Master!H$4:H$174,Master!BN$4:BN$174},Master!J$4:J$174="Qualified",Master!D$4:D$174="Mixed Asset / Balanced",Master!U$4:U$174<>""),3,FALSE),4,1),"") | B75: =IFERROR(INDEX(SORT(FILTER({Master!A$4:A$174,Master!B$4:B$174,Master!U$4:U$174,Master!W$4:W$174,Master!K$4:K$174,Master!H$4:H$174,Master!BN$4:BN$174},Master!J$4:J$174="Qualified",Master!D$4:D$174="Mixed Asset / Balanced",Master!U$4:U$174<>""),3,FALSE),4,2),"") | C75: =IFERROR(INDEX(SORT(FILTER({Master!A$4:A$174,Master!B$4:B$174,Master!U$4:U$174,Master!W$4:W$174,Master!K$4:K$174,Master!H$4:H$174,Master!BN$4:BN$174},Master!J$4:J$174="Qualified",Master!D$4:D$174="Mixed Asset / Balanced",Master!U$4:U$174<>""),3,FALSE),4,3),"") | D75: =IFERROR(INDEX(SORT(FILTER({Master!A$4:A$174,Master!B$4:B$174,Master!U$4:U$174,Master!W$4:W$174,Master!K$4:K$174,Master!H$4:H$174,Master!BN$4:BN$174},Master!J$4:J$174="Qualified",Master!D$4:D$174="Mixed Asset / Balanced",Master!U$4:U$174<>""),3,FALSE),4,4),"") | E75: =IFERROR(INDEX(SORT(FILTER({Master!A$4:A$174,Master!B$4:B$174,Master!U$4:U$174,Master!W$4:W$174,Master!K$4:K$174,Master!H$4:H$174,Master!BN$4:BN$174},Master!J$4:J$174="Qualified",Master!D$4:D$174="Mixed Asset / Balanced",Master!U$4:U$174<>""),3,FALSE),4,5),"") | F75: =IFERROR(INDEX(SORT(FILTER({Master!A$4:A$174,Master!B$4:B$174,Master!U$4:U$174,Master!W$4:W$174,Master!K$4:K$174,Master!H$4:H$174,Master!BN$4:BN$174},Master!J$4:J$174="Qualified",Master!D$4:D$174="Mixed Asset / Balanced",Master!U$4:U$174<>""),3,FALSE),4,6),"") | G75: =IFERROR(INDEX(SORT(FILTER({Master!A$4:A$174,Master!B$4:B$174,Master!U$4:U$174,Master!W$4:W$174,Master!K$4:K$174,Master!H$4:H$174,Master!BN$4:BN$174},Master!J$4:J$174="Qualified",Master!D$4:D$174="Mixed Asset / Balanced",Master!U$4:U$174<>""),3,FALSE),4,7),"")
A76: =IFERROR(INDEX(SORT(FILTER({Master!A$4:A$174,Master!B$4:B$174,Master!U$4:U$174,Master!W$4:W$174,Master!K$4:K$174,Master!H$4:H$174,Master!BN$4:BN$174},Master!J$4:J$174="Qualified",Master!D$4:D$174="Mixed Asset / Balanced",Master!U$4:U$174<>""),3,FALSE),5,1),"") | B76: =IFERROR(INDEX(SORT(FILTER({Master!A$4:A$174,Master!B$4:B$174,Master!U$4:U$174,Master!W$4:W$174,Master!K$4:K$174,Master!H$4:H$174,Master!BN$4:BN$174},Master!J$4:J$174="Qualified",Master!D$4:D$174="Mixed Asset / Balanced",Master!U$4:U$174<>""),3,FALSE),5,2),"") | C76: =IFERROR(INDEX(SORT(FILTER({Master!A$4:A$174,Master!B$4:B$174,Master!U$4:U$174,Master!W$4:W$174,Master!K$4:K$174,Master!H$4:H$174,Master!BN$4:BN$174},Master!J$4:J$174="Qualified",Master!D$4:D$174="Mixed Asset / Balanced",Master!U$4:U$174<>""),3,FALSE),5,3),"") | D76: =IFERROR(INDEX(SORT(FILTER({Master!A$4:A$174,Master!B$4:B$174,Master!U$4:U$174,Master!W$4:W$174,Master!K$4:K$174,Master!H$4:H$174,Master!BN$4:BN$174},Master!J$4:J$174="Qualified",Master!D$4:D$174="Mixed Asset / Balanced",Master!U$4:U$174<>""),3,FALSE),5,4),"") | E76: =IFERROR(INDEX(SORT(FILTER({Master!A$4:A$174,Master!B$4:B$174,Master!U$4:U$174,Master!W$4:W$174,Master!K$4:K$174,Master!H$4:H$174,Master!BN$4:BN$174},Master!J$4:J$174="Qualified",Master!D$4:D$174="Mixed Asset / Balanced",Master!U$4:U$174<>""),3,FALSE),5,5),"") | F76: =IFERROR(INDEX(SORT(FILTER({Master!A$4:A$174,Master!B$4:B$174,Master!U$4:U$174,Master!W$4:W$174,Master!K$4:K$174,Master!H$4:H$174,Master!BN$4:BN$174},Master!J$4:J$174="Qualified",Master!D$4:D$174="Mixed Asset / Balanced",Master!U$4:U$174<>""),3,FALSE),5,6),"") | G76: =IFERROR(INDEX(SORT(FILTER({Master!A$4:A$174,Master!B$4:B$174,Master!U$4:U$174,Master!W$4:W$174,Master!K$4:K$174,Master!H$4:H$174,Master!BN$4:BN$174},Master!J$4:J$174="Qualified",Master!D$4:D$174="Mixed Asset / Balanced",Master!U$4:U$174<>""),3,FALSE),5,7),"")
A78: BALANCED / MIXED ASSET — TOP 5 BY 3Y ANN. ALPHA
A79: Fund Name | B79: Abbr | C79: 3Y Fund (%) | D79: 3Y Alpha (%) | E79: Beat (%) | F79: AUM (RM M) | G79: VC
A80: =IFERROR(INDEX(SORT(FILTER({Master!A$4:A$174,Master!B$4:B$174,Master!U$4:U$174,Master!W$4:W$174,Master!K$4:K$174,Master!H$4:H$174,Master!BN$4:BN$174},Master!J$4:J$174="Qualified",Master!D$4:D$174="Mixed Asset / Balanced",Master!W$4:W$174<>""),4,FALSE),1,1),"") | B80: =IFERROR(INDEX(SORT(FILTER({Master!A$4:A$174,Master!B$4:B$174,Master!U$4:U$174,Master!W$4:W$174,Master!K$4:K$174,Master!H$4:H$174,Master!BN$4:BN$174},Master!J$4:J$174="Qualified",Master!D$4:D$174="Mixed Asset / Balanced",Master!W$4:W$174<>""),4,FALSE),1,2),"") | C80: =IFERROR(INDEX(SORT(FILTER({Master!A$4:A$174,Master!B$4:B$174,Master!U$4:U$174,Master!W$4:W$174,Master!K$4:K$174,Master!H$4:H$174,Master!BN$4:BN$174},Master!J$4:J$174="Qualified",Master!D$4:D$174="Mixed Asset / Balanced",Master!W$4:W$174<>""),4,FALSE),1,3),"") | D80: =IFERROR(INDEX(SORT(FILTER({Master!A$4:A$174,Master!B$4:B$174,Master!U$4:U$174,Master!W$4:W$174,Master!K$4:K$174,Master!H$4:H$174,Master!BN$4:BN$174},Master!J$4:J$174="Qualified",Master!D$4:D$174="Mixed Asset / Balanced",Master!W$4:W$174<>""),4,FALSE),1,4),"") | E80: =IFERROR(INDEX(SORT(FILTER({Master!A$4:A$174,Master!B$4:B$174,Master!U$4:U$174,Master!W$4:W$174,Master!K$4:K$174,Master!H$4:H$174,Master!BN$4:BN$174},Master!J$4:J$174="Qualified",Master!D$4:D$174="Mixed Asset / Balanced",Master!W$4:W$174<>""),4,FALSE),1,5),"") | F80: =IFERROR(INDEX(SORT(FILTER({Master!A$4:A$174,Master!B$4:B$174,Master!U$4:U$174,Master!W$4:W$174,Master!K$4:K$174,Master!H$4:H$174,Master!BN$4:BN$174},Master!J$4:J$174="Qualified",Master!D$4:D$174="Mixed Asset / Balanced",Master!W$4:W$174<>""),4,FALSE),1,6),"") | G80: =IFERROR(INDEX(SORT(FILTER({Master!A$4:A$174,Master!B$4:B$174,Master!U$4:U$174,Master!W$4:W$174,Master!K$4:K$174,Master!H$4:H$174,Master!BN$4:BN$174},Master!J$4:J$174="Qualified",Master!D$4:D$174="Mixed Asset / Balanced",Master!W$4:W$174<>""),4,FALSE),1,7),"")
A81: =IFERROR(INDEX(SORT(FILTER({Master!A$4:A$174,Master!B$4:B$174,Master!U$4:U$174,Master!W$4:W$174,Master!K$4:K$174,Master!H$4:H$174,Master!BN$4:BN$174},Master!J$4:J$174="Qualified",Master!D$4:D$174="Mixed Asset / Balanced",Master!W$4:W$174<>""),4,FALSE),2,1),"") | B81: =IFERROR(INDEX(SORT(FILTER({Master!A$4:A$174,Master!B$4:B$174,Master!U$4:U$174,Master!W$4:W$174,Master!K$4:K$174,Master!H$4:H$174,Master!BN$4:BN$174},Master!J$4:J$174="Qualified",Master!D$4:D$174="Mixed Asset / Balanced",Master!W$4:W$174<>""),4,FALSE),2,2),"") | C81: =IFERROR(INDEX(SORT(FILTER({Master!A$4:A$174,Master!B$4:B$174,Master!U$4:U$174,Master!W$4:W$174,Master!K$4:K$174,Master!H$4:H$174,Master!BN$4:BN$174},Master!J$4:J$174="Qualified",Master!D$4:D$174="Mixed Asset / Balanced",Master!W$4:W$174<>""),4,FALSE),2,3),"") | D81: =IFERROR(INDEX(SORT(FILTER({Master!A$4:A$174,Master!B$4:B$174,Master!U$4:U$174,Master!W$4:W$174,Master!K$4:K$174,Master!H$4:H$174,Master!BN$4:BN$174},Master!J$4:J$174="Qualified",Master!D$4:D$174="Mixed Asset / Balanced",Master!W$4:W$174<>""),4,FALSE),2,4),"") | E81: =IFERROR(INDEX(SORT(FILTER({Master!A$4:A$174,Master!B$4:B$174,Master!U$4:U$174,Master!W$4:W$174,Master!K$4:K$174,Master!H$4:H$174,Master!BN$4:BN$174},Master!J$4:J$174="Qualified",Master!D$4:D$174="Mixed Asset / Balanced",Master!W$4:W$174<>""),4,FALSE),2,5),"") | F81: =IFERROR(INDEX(SORT(FILTER({Master!A$4:A$174,Master!B$4:B$174,Master!U$4:U$174,Master!W$4:W$174,Master!K$4:K$174,Master!H$4:H$174,Master!BN$4:BN$174},Master!J$4:J$174="Qualified",Master!D$4:D$174="Mixed Asset / Balanced",Master!W$4:W$174<>""),4,FALSE),2,6),"") | G81: =IFERROR(INDEX(SORT(FILTER({Master!A$4:A$174,Master!B$4:B$174,Master!U$4:U$174,Master!W$4:W$174,Master!K$4:K$174,Master!H$4:H$174,Master!BN$4:BN$174},Master!J$4:J$174="Qualified",Master!D$4:D$174="Mixed Asset / Balanced",Master!W$4:W$174<>""),4,FALSE),2,7),"")
A82: =IFERROR(INDEX(SORT(FILTER({Master!A$4:A$174,Master!B$4:B$174,Master!U$4:U$174,Master!W$4:W$174,Master!K$4:K$174,Master!H$4:H$174,Master!BN$4:BN$174},Master!J$4:J$174="Qualified",Master!D$4:D$174="Mixed Asset / Balanced",Master!W$4:W$174<>""),4,FALSE),3,1),"") | B82: =IFERROR(INDEX(SORT(FILTER({Master!A$4:A$174,Master!B$4:B$174,Master!U$4:U$174,Master!W$4:W$174,Master!K$4:K$174,Master!H$4:H$174,Master!BN$4:BN$174},Master!J$4:J$174="Qualified",Master!D$4:D$174="Mixed Asset / Balanced",Master!W$4:W$174<>""),4,FALSE),3,2),"") | C82: =IFERROR(INDEX(SORT(FILTER({Master!A$4:A$174,Master!B$4:B$174,Master!U$4:U$174,Master!W$4:W$174,Master!K$4:K$174,Master!H$4:H$174,Master!BN$4:BN$174},Master!J$4:J$174="Qualified",Master!D$4:D$174="Mixed Asset / Balanced",Master!W$4:W$174<>""),4,FALSE),3,3),"") | D82: =IFERROR(INDEX(SORT(FILTER({Master!A$4:A$174,Master!B$4:B$174,Master!U$4:U$174,Master!W$4:W$174,Master!K$4:K$174,Master!H$4:H$174,Master!BN$4:BN$174},Master!J$4:J$174="Qualified",Master!D$4:D$174="Mixed Asset / Balanced",Master!W$4:W$174<>""),4,FALSE),3,4),"") | E82: =IFERROR(INDEX(SORT(FILTER({Master!A$4:A$174,Master!B$4:B$174,Master!U$4:U$174,Master!W$4:W$174,Master!K$4:K$174,Master!H$4:H$174,Master!BN$4:BN$174},Master!J$4:J$174="Qualified",Master!D$4:D$174="Mixed Asset / Balanced",Master!W$4:W$174<>""),4,FALSE),3,5),"") | F82: =IFERROR(INDEX(SORT(FILTER({Master!A$4:A$174,Master!B$4:B$174,Master!U$4:U$174,Master!W$4:W$174,Master!K$4:K$174,Master!H$4:H$174,Master!BN$4:BN$174},Master!J$4:J$174="Qualified",Master!D$4:D$174="Mixed Asset / Balanced",Master!W$4:W$174<>""),4,FALSE),3,6),"") | G82: =IFERROR(INDEX(SORT(FILTER({Master!A$4:A$174,Master!B$4:B$174,Master!U$4:U$174,Master!W$4:W$174,Master!K$4:K$174,Master!H$4:H$174,Master!BN$4:BN$174},Master!J$4:J$174="Qualified",Master!D$4:D$174="Mixed Asset / Balanced",Master!W$4:W$174<>""),4,FALSE),3,7),"")
A83: =IFERROR(INDEX(SORT(FILTER({Master!A$4:A$174,Master!B$4:B$174,Master!U$4:U$174,Master!W$4:W$174,Master!K$4:K$174,Master!H$4:H$174,Master!BN$4:BN$174},Master!J$4:J$174="Qualified",Master!D$4:D$174="Mixed Asset / Balanced",Master!W$4:W$174<>""),4,FALSE),4,1),"") | B83: =IFERROR(INDEX(SORT(FILTER({Master!A$4:A$174,Master!B$4:B$174,Master!U$4:U$174,Master!W$4:W$174,Master!K$4:K$174,Master!H$4:H$174,Master!BN$4:BN$174},Master!J$4:J$174="Qualified",Master!D$4:D$174="Mixed Asset / Balanced",Master!W$4:W$174<>""),4,FALSE),4,2),"") | C83: =IFERROR(INDEX(SORT(FILTER({Master!A$4:A$174,Master!B$4:B$174,Master!U$4:U$174,Master!W$4:W$174,Master!K$4:K$174,Master!H$4:H$174,Master!BN$4:BN$174},Master!J$4:J$174="Qualified",Master!D$4:D$174="Mixed Asset / Balanced",Master!W$4:W$174<>""),4,FALSE),4,3),"") | D83: =IFERROR(INDEX(SORT(FILTER({Master!A$4:A$174,Master!B$4:B$174,Master!U$4:U$174,Master!W$4:W$174,Master!K$4:K$174,Master!H$4:H$174,Master!BN$4:BN$174},Master!J$4:J$174="Qualified",Master!D$4:D$174="Mixed Asset / Balanced",Master!W$4:W$174<>""),4,FALSE),4,4),"") | E83: =IFERROR(INDEX(SORT(FILTER({Master!A$4:A$174,Master!B$4:B$174,Master!U$4:U$174,Master!W$4:W$174,Master!K$4:K$174,Master!H$4:H$174,Master!BN$4:BN$174},Master!J$4:J$174="Qualified",Master!D$4:D$174="Mixed Asset / Balanced",Master!W$4:W$174<>""),4,FALSE),4,5),"") | F83: =IFERROR(INDEX(SORT(FILTER({Master!A$4:A$174,Master!B$4:B$174,Master!U$4:U$174,Master!W$4:W$174,Master!K$4:K$174,Master!H$4:H$174,Master!BN$4:BN$174},Master!J$4:J$174="Qualified",Master!D$4:D$174="Mixed Asset / Balanced",Master!W$4:W$174<>""),4,FALSE),4,6),"") | G83: =IFERROR(INDEX(SORT(FILTER({Master!A$4:A$174,Master!B$4:B$174,Master!U$4:U$174,Master!W$4:W$174,Master!K$4:K$174,Master!H$4:H$174,Master!BN$4:BN$174},Master!J$4:J$174="Qualified",Master!D$4:D$174="Mixed Asset / Balanced",Master!W$4:W$174<>""),4,FALSE),4,7),"")
A84: =IFERROR(INDEX(SORT(FILTER({Master!A$4:A$174,Master!B$4:B$174,Master!U$4:U$174,Master!W$4:W$174,Master!K$4:K$174,Master!H$4:H$174,Master!BN$4:BN$174},Master!J$4:J$174="Qualified",Master!D$4:D$174="Mixed Asset / Balanced",Master!W$4:W$174<>""),4,FALSE),5,1),"") | B84: =IFERROR(INDEX(SORT(FILTER({Master!A$4:A$174,Master!B$4:B$174,Master!U$4:U$174,Master!W$4:W$174,Master!K$4:K$174,Master!H$4:H$174,Master!BN$4:BN$174},Master!J$4:J$174="Qualified",Master!D$4:D$174="Mixed Asset / Balanced",Master!W$4:W$174<>""),4,FALSE),5,2),"") | C84: =IFERROR(INDEX(SORT(FILTER({Master!A$4:A$174,Master!B$4:B$174,Master!U$4:U$174,Master!W$4:W$174,Master!K$4:K$174,Master!H$4:H$174,Master!BN$4:BN$174},Master!J$4:J$174="Qualified",Master!D$4:D$174="Mixed Asset / Balanced",Master!W$4:W$174<>""),4,FALSE),5,3),"") | D84: =IFERROR(INDEX(SORT(FILTER({Master!A$4:A$174,Master!B$4:B$174,Master!U$4:U$174,Master!W$4:W$174,Master!K$4:K$174,Master!H$4:H$174,Master!BN$4:BN$174},Master!J$4:J$174="Qualified",Master!D$4:D$174="Mixed Asset / Balanced",Master!W$4:W$174<>""),4,FALSE),5,4),"") | E84: =IFERROR(INDEX(SORT(FILTER({Master!A$4:A$174,Master!B$4:B$174,Master!U$4:U$174,Master!W$4:W$174,Master!K$4:K$174,Master!H$4:H$174,Master!BN$4:BN$174},Master!J$4:J$174="Qualified",Master!D$4:D$174="Mixed Asset / Balanced",Master!W$4:W$174<>""),4,FALSE),5,5),"") | F84: =IFERROR(INDEX(SORT(FILTER({Master!A$4:A$174,Master!B$4:B$174,Master!U$4:U$174,Master!W$4:W$174,Master!K$4:K$174,Master!H$4:H$174,Master!BN$4:BN$174},Master!J$4:J$174="Qualified",Master!D$4:D$174="Mixed Asset / Balanced",Master!W$4:W$174<>""),4,FALSE),5,6),"") | G84: =IFERROR(INDEX(SORT(FILTER({Master!A$4:A$174,Master!B$4:B$174,Master!U$4:U$174,Master!W$4:W$174,Master!K$4:K$174,Master!H$4:H$174,Master!BN$4:BN$174},Master!J$4:J$174="Qualified",Master!D$4:D$174="Mixed Asset / Balanced",Master!W$4:W$174<>""),4,FALSE),5,7),"")
A86: BALANCED / MIXED ASSET — TOP 5 BY ALPHA EFFICIENCY
A87: Fund Name | B87: Abbr | C87: Alpha Eff | D87: 3Y Alpha (%) | E87: Beat (%) | F87: AUM (RM M) | G87: VC
A88: =IFERROR(INDEX(SORT(FILTER({Master!A$4:A$174,Master!B$4:B$174,Master!AF$4:AF$174,Master!W$4:W$174,Master!K$4:K$174,Master!H$4:H$174,Master!BN$4:BN$174},Master!J$4:J$174="Qualified",Master!D$4:D$174="Mixed Asset / Balanced",Master!AF$4:AF$174<>""),3,FALSE),1,1),"") | B88: =IFERROR(INDEX(SORT(FILTER({Master!A$4:A$174,Master!B$4:B$174,Master!AF$4:AF$174,Master!W$4:W$174,Master!K$4:K$174,Master!H$4:H$174,Master!BN$4:BN$174},Master!J$4:J$174="Qualified",Master!D$4:D$174="Mixed Asset / Balanced",Master!AF$4:AF$174<>""),3,FALSE),1,2),"") | C88: =IFERROR(INDEX(SORT(FILTER({Master!A$4:A$174,Master!B$4:B$174,Master!AF$4:AF$174,Master!W$4:W$174,Master!K$4:K$174,Master!H$4:H$174,Master!BN$4:BN$174},Master!J$4:J$174="Qualified",Master!D$4:D$174="Mixed Asset / Balanced",Master!AF$4:AF$174<>""),3,FALSE),1,3),"") | D88: =IFERROR(INDEX(SORT(FILTER({Master!A$4:A$174,Master!B$4:B$174,Master!AF$4:AF$174,Master!W$4:W$174,Master!K$4:K$174,Master!H$4:H$174,Master!BN$4:BN$174},Master!J$4:J$174="Qualified",Master!D$4:D$174="Mixed Asset / Balanced",Master!AF$4:AF$174<>""),3,FALSE),1,4),"") | E88: =IFERROR(INDEX(SORT(FILTER({Master!A$4:A$174,Master!B$4:B$174,Master!AF$4:AF$174,Master!W$4:W$174,Master!K$4:K$174,Master!H$4:H$174,Master!BN$4:BN$174},Master!J$4:J$174="Qualified",Master!D$4:D$174="Mixed Asset / Balanced",Master!AF$4:AF$174<>""),3,FALSE),1,5),"") | F88: =IFERROR(INDEX(SORT(FILTER({Master!A$4:A$174,Master!B$4:B$174,Master!AF$4:AF$174,Master!W$4:W$174,Master!K$4:K$174,Master!H$4:H$174,Master!BN$4:BN$174},Master!J$4:J$174="Qualified",Master!D$4:D$174="Mixed Asset / Balanced",Master!AF$4:AF$174<>""),3,FALSE),1,6),"") | G88: =IFERROR(INDEX(SORT(FILTER({Master!A$4:A$174,Master!B$4:B$174,Master!AF$4:AF$174,Master!W$4:W$174,Master!K$4:K$174,Master!H$4:H$174,Master!BN$4:BN$174},Master!J$4:J$174="Qualified",Master!D$4:D$174="Mixed Asset / Balanced",Master!AF$4:AF$174<>""),3,FALSE),1,7),"")
A89: =IFERROR(INDEX(SORT(FILTER({Master!A$4:A$174,Master!B$4:B$174,Master!AF$4:AF$174,Master!W$4:W$174,Master!K$4:K$174,Master!H$4:H$174,Master!BN$4:BN$174},Master!J$4:J$174="Qualified",Master!D$4:D$174="Mixed Asset / Balanced",Master!AF$4:AF$174<>""),3,FALSE),2,1),"") | B89: =IFERROR(INDEX(SORT(FILTER({Master!A$4:A$174,Master!B$4:B$174,Master!AF$4:AF$174,Master!W$4:W$174,Master!K$4:K$174,Master!H$4:H$174,Master!BN$4:BN$174},Master!J$4:J$174="Qualified",Master!D$4:D$174="Mixed Asset / Balanced",Master!AF$4:AF$174<>""),3,FALSE),2,2),"") | C89: =IFERROR(INDEX(SORT(FILTER({Master!A$4:A$174,Master!B$4:B$174,Master!AF$4:AF$174,Master!W$4:W$174,Master!K$4:K$174,Master!H$4:H$174,Master!BN$4:BN$174},Master!J$4:J$174="Qualified",Master!D$4:D$174="Mixed Asset / Balanced",Master!AF$4:AF$174<>""),3,FALSE),2,3),"") | D89: =IFERROR(INDEX(SORT(FILTER({Master!A$4:A$174,Master!B$4:B$174,Master!AF$4:AF$174,Master!W$4:W$174,Master!K$4:K$174,Master!H$4:H$174,Master!BN$4:BN$174},Master!J$4:J$174="Qualified",Master!D$4:D$174="Mixed Asset / Balanced",Master!AF$4:AF$174<>""),3,FALSE),2,4),"") | E89: =IFERROR(INDEX(SORT(FILTER({Master!A$4:A$174,Master!B$4:B$174,Master!AF$4:AF$174,Master!W$4:W$174,Master!K$4:K$174,Master!H$4:H$174,Master!BN$4:BN$174},Master!J$4:J$174="Qualified",Master!D$4:D$174="Mixed Asset / Balanced",Master!AF$4:AF$174<>""),3,FALSE),2,5),"") | F89: =IFERROR(INDEX(SORT(FILTER({Master!A$4:A$174,Master!B$4:B$174,Master!AF$4:AF$174,Master!W$4:W$174,Master!K$4:K$174,Master!H$4:H$174,Master!BN$4:BN$174},Master!J$4:J$174="Qualified",Master!D$4:D$174="Mixed Asset / Balanced",Master!AF$4:AF$174<>""),3,FALSE),2,6),"") | G89: =IFERROR(INDEX(SORT(FILTER({Master!A$4:A$174,Master!B$4:B$174,Master!AF$4:AF$174,Master!W$4:W$174,Master!K$4:K$174,Master!H$4:H$174,Master!BN$4:BN$174},Master!J$4:J$174="Qualified",Master!D$4:D$174="Mixed Asset / Balanced",Master!AF$4:AF$174<>""),3,FALSE),2,7),"")
A90: =IFERROR(INDEX(SORT(FILTER({Master!A$4:A$174,Master!B$4:B$174,Master!AF$4:AF$174,Master!W$4:W$174,Master!K$4:K$174,Master!H$4:H$174,Master!BN$4:BN$174},Master!J$4:J$174="Qualified",Master!D$4:D$174="Mixed Asset / Balanced",Master!AF$4:AF$174<>""),3,FALSE),3,1),"") | B90: =IFERROR(INDEX(SORT(FILTER({Master!A$4:A$174,Master!B$4:B$174,Master!AF$4:AF$174,Master!W$4:W$174,Master!K$4:K$174,Master!H$4:H$174,Master!BN$4:BN$174},Master!J$4:J$174="Qualified",Master!D$4:D$174="Mixed Asset / Balanced",Master!AF$4:AF$174<>""),3,FALSE),3,2),"") | C90: =IFERROR(INDEX(SORT(FILTER({Master!A$4:A$174,Master!B$4:B$174,Master!AF$4:AF$174,Master!W$4:W$174,Master!K$4:K$174,Master!H$4:H$174,Master!BN$4:BN$174},Master!J$4:J$174="Qualified",Master!D$4:D$174="Mixed Asset / Balanced",Master!AF$4:AF$174<>""),3,FALSE),3,3),"") | D90: =IFERROR(INDEX(SORT(FILTER({Master!A$4:A$174,Master!B$4:B$174,Master!AF$4:AF$174,Master!W$4:W$174,Master!K$4:K$174,Master!H$4:H$174,Master!BN$4:BN$174},Master!J$4:J$174="Qualified",Master!D$4:D$174="Mixed Asset / Balanced",Master!AF$4:AF$174<>""),3,FALSE),3,4),"") | E90: =IFERROR(INDEX(SORT(FILTER({Master!A$4:A$174,Master!B$4:B$174,Master!AF$4:AF$174,Master!W$4:W$174,Master!K$4:K$174,Master!H$4:H$174,Master!BN$4:BN$174},Master!J$4:J$174="Qualified",Master!D$4:D$174="Mixed Asset / Balanced",Master!AF$4:AF$174<>""),3,FALSE),3,5),"") | F90: =IFERROR(INDEX(SORT(FILTER({Master!A$4:A$174,Master!B$4:B$174,Master!AF$4:AF$174,Master!W$4:W$174,Master!K$4:K$174,Master!H$4:H$174,Master!BN$4:BN$174},Master!J$4:J$174="Qualified",Master!D$4:D$174="Mixed Asset / Balanced",Master!AF$4:AF$174<>""),3,FALSE),3,6),"") | G90: =IFERROR(INDEX(SORT(FILTER({Master!A$4:A$174,Master!B$4:B$174,Master!AF$4:AF$174,Master!W$4:W$174,Master!K$4:K$174,Master!H$4:H$174,Master!BN$4:BN$174},Master!J$4:J$174="Qualified",Master!D$4:D$174="Mixed Asset / Balanced",Master!AF$4:AF$174<>""),3,FALSE),3,7),"")
A91: =IFERROR(INDEX(SORT(FILTER({Master!A$4:A$174,Master!B$4:B$174,Master!AF$4:AF$174,Master!W$4:W$174,Master!K$4:K$174,Master!H$4:H$174,Master!BN$4:BN$174},Master!J$4:J$174="Qualified",Master!D$4:D$174="Mixed Asset / Balanced",Master!AF$4:AF$174<>""),3,FALSE),4,1),"") | B91: =IFERROR(INDEX(SORT(FILTER({Master!A$4:A$174,Master!B$4:B$174,Master!AF$4:AF$174,Master!W$4:W$174,Master!K$4:K$174,Master!H$4:H$174,Master!BN$4:BN$174},Master!J$4:J$174="Qualified",Master!D$4:D$174="Mixed Asset / Balanced",Master!AF$4:AF$174<>""),3,FALSE),4,2),"") | C91: =IFERROR(INDEX(SORT(FILTER({Master!A$4:A$174,Master!B$4:B$174,Master!AF$4:AF$174,Master!W$4:W$174,Master!K$4:K$174,Master!H$4:H$174,Master!BN$4:BN$174},Master!J$4:J$174="Qualified",Master!D$4:D$174="Mixed Asset / Balanced",Master!AF$4:AF$174<>""),3,FALSE),4,3),"") | D91: =IFERROR(INDEX(SORT(FILTER({Master!A$4:A$174,Master!B$4:B$174,Master!AF$4:AF$174,Master!W$4:W$174,Master!K$4:K$174,Master!H$4:H$174,Master!BN$4:BN$174},Master!J$4:J$174="Qualified",Master!D$4:D$174="Mixed Asset / Balanced",Master!AF$4:AF$174<>""),3,FALSE),4,4),"") | E91: =IFERROR(INDEX(SORT(FILTER({Master!A$4:A$174,Master!B$4:B$174,Master!AF$4:AF$174,Master!W$4:W$174,Master!K$4:K$174,Master!H$4:H$174,Master!BN$4:BN$174},Master!J$4:J$174="Qualified",Master!D$4:D$174="Mixed Asset / Balanced",Master!AF$4:AF$174<>""),3,FALSE),4,5),"") | F91: =IFERROR(INDEX(SORT(FILTER({Master!A$4:A$174,Master!B$4:B$174,Master!AF$4:AF$174,Master!W$4:W$174,Master!K$4:K$174,Master!H$4:H$174,Master!BN$4:BN$174},Master!J$4:J$174="Qualified",Master!D$4:D$174="Mixed Asset / Balanced",Master!AF$4:AF$174<>""),3,FALSE),4,6),"") | G91: =IFERROR(INDEX(SORT(FILTER({Master!A$4:A$174,Master!B$4:B$174,Master!AF$4:AF$174,Master!W$4:W$174,Master!K$4:K$174,Master!H$4:H$174,Master!BN$4:BN$174},Master!J$4:J$174="Qualified",Master!D$4:D$174="Mixed Asset / Balanced",Master!AF$4:AF$174<>""),3,FALSE),4,7),"")
